// 
// Decompiled by Procyon v0.5.36
// 

package kotlin.collections;

import java.util.Set;
import java.util.List;
import java.util.Collection;
import kotlin.sequences.Sequence;
import kotlin.jvm.JvmName;
import java.util.Iterator;
import kotlin.jvm.internal.TypeIntrinsics;
import kotlin.jvm.functions.Function0;
import kotlin.ExperimentalStdlibApi;
import kotlin.WasExperimental;
import kotlin.BuilderInference;
import kotlin.Unit;
import kotlin.jvm.functions.Function1;
import java.util.HashMap;
import kotlin.SinceKotlin;
import kotlin.internal.InlineOnly;
import java.util.LinkedHashMap;
import kotlin.Pair;
import org.jetbrains.annotations.NotNull;
import kotlin.jvm.internal.Intrinsics;
import java.util.Map;
import kotlin.Metadata;

@Metadata(mv = { 1, 7, 1 }, k = 5, xi = 49, d1 = { "\u0000~\n\u0000\n\u0002\u0010$\n\u0002\b\u0003\n\u0002\u0010\b\n\u0000\n\u0002\u0018\u0002\n\u0002\u0010%\n\u0002\u0010\u0002\n\u0002\u0018\u0002\n\u0002\b\u0002\n\u0002\u0018\u0002\n\u0002\u0018\u0002\n\u0000\n\u0002\u0010\u0011\n\u0002\u0018\u0002\n\u0002\b\u0002\n\u0002\u0018\u0002\n\u0002\u0018\u0002\n\u0002\b\u0005\n\u0002\u0010&\n\u0002\b\u0003\n\u0002\u0010\u000b\n\u0002\u0018\u0002\n\u0002\b\u0013\n\u0002\u0018\u0002\n\u0002\b\n\n\u0002\u0010(\n\u0002\u0010)\n\u0002\u0010'\n\u0002\b\n\n\u0002\u0010\u001c\n\u0002\u0018\u0002\n\u0002\b\u0017\u001a`\u0010\u0000\u001a\u000e\u0012\u0004\u0012\u0002H\u0002\u0012\u0004\u0012\u0002H\u00030\u0001\"\u0004\b\u0000\u0010\u0002\"\u0004\b\u0001\u0010\u00032\u0006\u0010\u0004\u001a\u00020\u00052%\b\u0001\u0010\u0006\u001a\u001f\u0012\u0010\u0012\u000e\u0012\u0004\u0012\u0002H\u0002\u0012\u0004\u0012\u0002H\u00030\b\u0012\u0004\u0012\u00020\t0\u0007¢\u0006\u0002\b\nH\u0087\b\u00f8\u0001\u0000\u0082\u0002\n\n\b\b\u0001\u0012\u0002\u0010\u0002 \u0001\u001aX\u0010\u0000\u001a\u000e\u0012\u0004\u0012\u0002H\u0002\u0012\u0004\u0012\u0002H\u00030\u0001\"\u0004\b\u0000\u0010\u0002\"\u0004\b\u0001\u0010\u00032%\b\u0001\u0010\u0006\u001a\u001f\u0012\u0010\u0012\u000e\u0012\u0004\u0012\u0002H\u0002\u0012\u0004\u0012\u0002H\u00030\b\u0012\u0004\u0012\u00020\t0\u0007¢\u0006\u0002\b\nH\u0087\b\u00f8\u0001\u0000\u0082\u0002\n\n\b\b\u0001\u0012\u0002\u0010\u0001 \u0001\u001a\u001e\u0010\u000b\u001a\u000e\u0012\u0004\u0012\u0002H\u0002\u0012\u0004\u0012\u0002H\u00030\u0001\"\u0004\b\u0000\u0010\u0002\"\u0004\b\u0001\u0010\u0003\u001a1\u0010\f\u001a\u001e\u0012\u0004\u0012\u0002H\u0002\u0012\u0004\u0012\u0002H\u00030\rj\u000e\u0012\u0004\u0012\u0002H\u0002\u0012\u0004\u0012\u0002H\u0003`\u000e\"\u0004\b\u0000\u0010\u0002\"\u0004\b\u0001\u0010\u0003H\u0087\b\u001a_\u0010\f\u001a\u001e\u0012\u0004\u0012\u0002H\u0002\u0012\u0004\u0012\u0002H\u00030\rj\u000e\u0012\u0004\u0012\u0002H\u0002\u0012\u0004\u0012\u0002H\u0003`\u000e\"\u0004\b\u0000\u0010\u0002\"\u0004\b\u0001\u0010\u00032*\u0010\u000f\u001a\u0016\u0012\u0012\b\u0001\u0012\u000e\u0012\u0004\u0012\u0002H\u0002\u0012\u0004\u0012\u0002H\u00030\u00110\u0010\"\u000e\u0012\u0004\u0012\u0002H\u0002\u0012\u0004\u0012\u0002H\u00030\u0011¢\u0006\u0002\u0010\u0012\u001a1\u0010\u0013\u001a\u001e\u0012\u0004\u0012\u0002H\u0002\u0012\u0004\u0012\u0002H\u00030\u0014j\u000e\u0012\u0004\u0012\u0002H\u0002\u0012\u0004\u0012\u0002H\u0003`\u0015\"\u0004\b\u0000\u0010\u0002\"\u0004\b\u0001\u0010\u0003H\u0087\b\u001a_\u0010\u0013\u001a\u001e\u0012\u0004\u0012\u0002H\u0002\u0012\u0004\u0012\u0002H\u00030\u0014j\u000e\u0012\u0004\u0012\u0002H\u0002\u0012\u0004\u0012\u0002H\u0003`\u0015\"\u0004\b\u0000\u0010\u0002\"\u0004\b\u0001\u0010\u00032*\u0010\u000f\u001a\u0016\u0012\u0012\b\u0001\u0012\u000e\u0012\u0004\u0012\u0002H\u0002\u0012\u0004\u0012\u0002H\u00030\u00110\u0010\"\u000e\u0012\u0004\u0012\u0002H\u0002\u0012\u0004\u0012\u0002H\u00030\u0011¢\u0006\u0002\u0010\u0016\u001a!\u0010\u0017\u001a\u000e\u0012\u0004\u0012\u0002H\u0002\u0012\u0004\u0012\u0002H\u00030\u0001\"\u0004\b\u0000\u0010\u0002\"\u0004\b\u0001\u0010\u0003H\u0087\b\u001aO\u0010\u0017\u001a\u000e\u0012\u0004\u0012\u0002H\u0002\u0012\u0004\u0012\u0002H\u00030\u0001\"\u0004\b\u0000\u0010\u0002\"\u0004\b\u0001\u0010\u00032*\u0010\u000f\u001a\u0016\u0012\u0012\b\u0001\u0012\u000e\u0012\u0004\u0012\u0002H\u0002\u0012\u0004\u0012\u0002H\u00030\u00110\u0010\"\u000e\u0012\u0004\u0012\u0002H\u0002\u0012\u0004\u0012\u0002H\u00030\u0011¢\u0006\u0002\u0010\u0018\u001a!\u0010\u0019\u001a\u000e\u0012\u0004\u0012\u0002H\u0002\u0012\u0004\u0012\u0002H\u00030\b\"\u0004\b\u0000\u0010\u0002\"\u0004\b\u0001\u0010\u0003H\u0087\b\u001aO\u0010\u0019\u001a\u000e\u0012\u0004\u0012\u0002H\u0002\u0012\u0004\u0012\u0002H\u00030\b\"\u0004\b\u0000\u0010\u0002\"\u0004\b\u0001\u0010\u00032*\u0010\u000f\u001a\u0016\u0012\u0012\b\u0001\u0012\u000e\u0012\u0004\u0012\u0002H\u0002\u0012\u0004\u0012\u0002H\u00030\u00110\u0010\"\u000e\u0012\u0004\u0012\u0002H\u0002\u0012\u0004\u0012\u0002H\u00030\u0011¢\u0006\u0002\u0010\u0018\u001a*\u0010\u001a\u001a\u0002H\u0002\"\u0004\b\u0000\u0010\u0002\"\u0004\b\u0001\u0010\u0003*\u000e\u0012\u0004\u0012\u0002H\u0002\u0012\u0004\u0012\u0002H\u00030\u001bH\u0087\n¢\u0006\u0002\u0010\u001c\u001a*\u0010\u001d\u001a\u0002H\u0003\"\u0004\b\u0000\u0010\u0002\"\u0004\b\u0001\u0010\u0003*\u000e\u0012\u0004\u0012\u0002H\u0002\u0012\u0004\u0012\u0002H\u00030\u001bH\u0087\n¢\u0006\u0002\u0010\u001c\u001a9\u0010\u001e\u001a\u00020\u001f\"\t\b\u0000\u0010\u0002¢\u0006\u0002\b \"\u0004\b\u0001\u0010\u0003*\u0010\u0012\u0006\b\u0001\u0012\u0002H\u0002\u0012\u0004\u0012\u0002H\u00030\u00012\u0006\u0010!\u001a\u0002H\u0002H\u0087\n¢\u0006\u0002\u0010\"\u001a1\u0010#\u001a\u00020\u001f\"\t\b\u0000\u0010\u0002¢\u0006\u0002\b *\u000e\u0012\u0006\b\u0001\u0012\u0002H\u0002\u0012\u0002\b\u00030\u00012\u0006\u0010!\u001a\u0002H\u0002H\u0087\b¢\u0006\u0002\u0010\"\u001a7\u0010$\u001a\u00020\u001f\"\u0004\b\u0000\u0010\u0002\"\t\b\u0001\u0010\u0003¢\u0006\u0002\b *\u000e\u0012\u0004\u0012\u0002H\u0002\u0012\u0004\u0012\u0002H\u00030\u00012\u0006\u0010%\u001a\u0002H\u0003H\u0087\b¢\u0006\u0002\u0010\"\u001aV\u0010&\u001a\u000e\u0012\u0004\u0012\u0002H\u0002\u0012\u0004\u0012\u0002H\u00030\u0001\"\u0004\b\u0000\u0010\u0002\"\u0004\b\u0001\u0010\u0003*\u0010\u0012\u0006\b\u0001\u0012\u0002H\u0002\u0012\u0004\u0012\u0002H\u00030\u00012\u001e\u0010'\u001a\u001a\u0012\u0010\u0012\u000e\u0012\u0004\u0012\u0002H\u0002\u0012\u0004\u0012\u0002H\u00030\u001b\u0012\u0004\u0012\u00020\u001f0\u0007H\u0086\b\u00f8\u0001\u0000\u001aJ\u0010(\u001a\u000e\u0012\u0004\u0012\u0002H\u0002\u0012\u0004\u0012\u0002H\u00030\u0001\"\u0004\b\u0000\u0010\u0002\"\u0004\b\u0001\u0010\u0003*\u0010\u0012\u0006\b\u0001\u0012\u0002H\u0002\u0012\u0004\u0012\u0002H\u00030\u00012\u0012\u0010'\u001a\u000e\u0012\u0004\u0012\u0002H\u0002\u0012\u0004\u0012\u00020\u001f0\u0007H\u0086\b\u00f8\u0001\u0000\u001aV\u0010)\u001a\u000e\u0012\u0004\u0012\u0002H\u0002\u0012\u0004\u0012\u0002H\u00030\u0001\"\u0004\b\u0000\u0010\u0002\"\u0004\b\u0001\u0010\u0003*\u0010\u0012\u0006\b\u0001\u0012\u0002H\u0002\u0012\u0004\u0012\u0002H\u00030\u00012\u001e\u0010'\u001a\u001a\u0012\u0010\u0012\u000e\u0012\u0004\u0012\u0002H\u0002\u0012\u0004\u0012\u0002H\u00030\u001b\u0012\u0004\u0012\u00020\u001f0\u0007H\u0086\b\u00f8\u0001\u0000\u001aq\u0010*\u001a\u0002H+\"\u0004\b\u0000\u0010\u0002\"\u0004\b\u0001\u0010\u0003\"\u0018\b\u0002\u0010+*\u0012\u0012\u0006\b\u0000\u0012\u0002H\u0002\u0012\u0006\b\u0000\u0012\u0002H\u00030\b*\u0010\u0012\u0006\b\u0001\u0012\u0002H\u0002\u0012\u0004\u0012\u0002H\u00030\u00012\u0006\u0010,\u001a\u0002H+2\u001e\u0010'\u001a\u001a\u0012\u0010\u0012\u000e\u0012\u0004\u0012\u0002H\u0002\u0012\u0004\u0012\u0002H\u00030\u001b\u0012\u0004\u0012\u00020\u001f0\u0007H\u0086\b\u00f8\u0001\u0000¢\u0006\u0002\u0010-\u001aq\u0010.\u001a\u0002H+\"\u0004\b\u0000\u0010\u0002\"\u0004\b\u0001\u0010\u0003\"\u0018\b\u0002\u0010+*\u0012\u0012\u0006\b\u0000\u0012\u0002H\u0002\u0012\u0006\b\u0000\u0012\u0002H\u00030\b*\u0010\u0012\u0006\b\u0001\u0012\u0002H\u0002\u0012\u0004\u0012\u0002H\u00030\u00012\u0006\u0010,\u001a\u0002H+2\u001e\u0010'\u001a\u001a\u0012\u0010\u0012\u000e\u0012\u0004\u0012\u0002H\u0002\u0012\u0004\u0012\u0002H\u00030\u001b\u0012\u0004\u0012\u00020\u001f0\u0007H\u0086\b\u00f8\u0001\u0000¢\u0006\u0002\u0010-\u001aJ\u0010/\u001a\u000e\u0012\u0004\u0012\u0002H\u0002\u0012\u0004\u0012\u0002H\u00030\u0001\"\u0004\b\u0000\u0010\u0002\"\u0004\b\u0001\u0010\u0003*\u0010\u0012\u0006\b\u0001\u0012\u0002H\u0002\u0012\u0004\u0012\u0002H\u00030\u00012\u0012\u0010'\u001a\u000e\u0012\u0004\u0012\u0002H\u0003\u0012\u0004\u0012\u00020\u001f0\u0007H\u0086\b\u00f8\u0001\u0000\u001a;\u00100\u001a\u0004\u0018\u0001H\u0003\"\t\b\u0000\u0010\u0002¢\u0006\u0002\b \"\u0004\b\u0001\u0010\u0003*\u0010\u0012\u0006\b\u0001\u0012\u0002H\u0002\u0012\u0004\u0012\u0002H\u00030\u00012\u0006\u0010!\u001a\u0002H\u0002H\u0087\n¢\u0006\u0002\u00101\u001aC\u00102\u001a\u0002H\u0003\"\u0004\b\u0000\u0010\u0002\"\u0004\b\u0001\u0010\u0003*\u000e\u0012\u0004\u0012\u0002H\u0002\u0012\u0004\u0012\u0002H\u00030\u00012\u0006\u0010!\u001a\u0002H\u00022\f\u00103\u001a\b\u0012\u0004\u0012\u0002H\u000304H\u0087\b\u00f8\u0001\u0000¢\u0006\u0002\u00105\u001aC\u00106\u001a\u0002H\u0003\"\u0004\b\u0000\u0010\u0002\"\u0004\b\u0001\u0010\u0003*\u000e\u0012\u0004\u0012\u0002H\u0002\u0012\u0004\u0012\u0002H\u00030\u00012\u0006\u0010!\u001a\u0002H\u00022\f\u00103\u001a\b\u0012\u0004\u0012\u0002H\u000304H\u0080\b\u00f8\u0001\u0000¢\u0006\u0002\u00105\u001aC\u00107\u001a\u0002H\u0003\"\u0004\b\u0000\u0010\u0002\"\u0004\b\u0001\u0010\u0003*\u000e\u0012\u0004\u0012\u0002H\u0002\u0012\u0004\u0012\u0002H\u00030\b2\u0006\u0010!\u001a\u0002H\u00022\f\u00103\u001a\b\u0012\u0004\u0012\u0002H\u000304H\u0086\b\u00f8\u0001\u0000¢\u0006\u0002\u00105\u001a1\u00108\u001a\u0002H\u0003\"\u0004\b\u0000\u0010\u0002\"\u0004\b\u0001\u0010\u0003*\u000e\u0012\u0004\u0012\u0002H\u0002\u0012\u0004\u0012\u0002H\u00030\u00012\u0006\u0010!\u001a\u0002H\u0002H\u0007¢\u0006\u0002\u00101\u001a?\u00109\u001a\u0002H:\"\u0014\b\u0000\u0010+*\n\u0012\u0002\b\u0003\u0012\u0002\b\u00030\u0001*\u0002H:\"\u0004\b\u0001\u0010:*\u0002H+2\f\u00103\u001a\b\u0012\u0004\u0012\u0002H:04H\u0087\b\u00f8\u0001\u0000¢\u0006\u0002\u0010;\u001a'\u0010<\u001a\u00020\u001f\"\u0004\b\u0000\u0010\u0002\"\u0004\b\u0001\u0010\u0003*\u0010\u0012\u0006\b\u0001\u0012\u0002H\u0002\u0012\u0004\u0012\u0002H\u00030\u0001H\u0087\b\u001a:\u0010=\u001a\u00020\u001f\"\u0004\b\u0000\u0010\u0002\"\u0004\b\u0001\u0010\u0003*\u0012\u0012\u0006\b\u0001\u0012\u0002H\u0002\u0012\u0004\u0012\u0002H\u0003\u0018\u00010\u0001H\u0087\b\u0082\u0002\u000e\n\f\b\u0000\u0012\u0002\u0018\u0001\u001a\u0004\b\u0003\u0010\u0000\u001a9\u0010>\u001a\u0014\u0012\u0010\u0012\u000e\u0012\u0004\u0012\u0002H\u0002\u0012\u0004\u0012\u0002H\u00030\u001b0?\"\u0004\b\u0000\u0010\u0002\"\u0004\b\u0001\u0010\u0003*\u0010\u0012\u0006\b\u0001\u0012\u0002H\u0002\u0012\u0004\u0012\u0002H\u00030\u0001H\u0087\n\u001a<\u0010>\u001a\u0014\u0012\u0010\u0012\u000e\u0012\u0004\u0012\u0002H\u0002\u0012\u0004\u0012\u0002H\u00030A0@\"\u0004\b\u0000\u0010\u0002\"\u0004\b\u0001\u0010\u0003*\u000e\u0012\u0004\u0012\u0002H\u0002\u0012\u0004\u0012\u0002H\u00030\bH\u0087\n¢\u0006\u0002\bB\u001a\\\u0010C\u001a\u000e\u0012\u0004\u0012\u0002H:\u0012\u0004\u0012\u0002H\u00030\u0001\"\u0004\b\u0000\u0010\u0002\"\u0004\b\u0001\u0010\u0003\"\u0004\b\u0002\u0010:*\u0010\u0012\u0006\b\u0001\u0012\u0002H\u0002\u0012\u0004\u0012\u0002H\u00030\u00012\u001e\u0010D\u001a\u001a\u0012\u0010\u0012\u000e\u0012\u0004\u0012\u0002H\u0002\u0012\u0004\u0012\u0002H\u00030\u001b\u0012\u0004\u0012\u0002H:0\u0007H\u0086\b\u00f8\u0001\u0000\u001aw\u0010E\u001a\u0002H+\"\u0004\b\u0000\u0010\u0002\"\u0004\b\u0001\u0010\u0003\"\u0004\b\u0002\u0010:\"\u0018\b\u0003\u0010+*\u0012\u0012\u0006\b\u0000\u0012\u0002H:\u0012\u0006\b\u0000\u0012\u0002H\u00030\b*\u0010\u0012\u0006\b\u0001\u0012\u0002H\u0002\u0012\u0004\u0012\u0002H\u00030\u00012\u0006\u0010,\u001a\u0002H+2\u001e\u0010D\u001a\u001a\u0012\u0010\u0012\u000e\u0012\u0004\u0012\u0002H\u0002\u0012\u0004\u0012\u0002H\u00030\u001b\u0012\u0004\u0012\u0002H:0\u0007H\u0086\b\u00f8\u0001\u0000¢\u0006\u0002\u0010-\u001a\\\u0010F\u001a\u000e\u0012\u0004\u0012\u0002H\u0002\u0012\u0004\u0012\u0002H:0\u0001\"\u0004\b\u0000\u0010\u0002\"\u0004\b\u0001\u0010\u0003\"\u0004\b\u0002\u0010:*\u0010\u0012\u0006\b\u0001\u0012\u0002H\u0002\u0012\u0004\u0012\u0002H\u00030\u00012\u001e\u0010D\u001a\u001a\u0012\u0010\u0012\u000e\u0012\u0004\u0012\u0002H\u0002\u0012\u0004\u0012\u0002H\u00030\u001b\u0012\u0004\u0012\u0002H:0\u0007H\u0086\b\u00f8\u0001\u0000\u001aw\u0010G\u001a\u0002H+\"\u0004\b\u0000\u0010\u0002\"\u0004\b\u0001\u0010\u0003\"\u0004\b\u0002\u0010:\"\u0018\b\u0003\u0010+*\u0012\u0012\u0006\b\u0000\u0012\u0002H\u0002\u0012\u0006\b\u0000\u0012\u0002H:0\b*\u0010\u0012\u0006\b\u0001\u0012\u0002H\u0002\u0012\u0004\u0012\u0002H\u00030\u00012\u0006\u0010,\u001a\u0002H+2\u001e\u0010D\u001a\u001a\u0012\u0010\u0012\u000e\u0012\u0004\u0012\u0002H\u0002\u0012\u0004\u0012\u0002H\u00030\u001b\u0012\u0004\u0012\u0002H:0\u0007H\u0086\b\u00f8\u0001\u0000¢\u0006\u0002\u0010-\u001a@\u0010H\u001a\u000e\u0012\u0004\u0012\u0002H\u0002\u0012\u0004\u0012\u0002H\u00030\u0001\"\u0004\b\u0000\u0010\u0002\"\u0004\b\u0001\u0010\u0003*\u0010\u0012\u0006\b\u0001\u0012\u0002H\u0002\u0012\u0004\u0012\u0002H\u00030\u00012\u0006\u0010!\u001a\u0002H\u0002H\u0087\u0002¢\u0006\u0002\u0010I\u001aH\u0010H\u001a\u000e\u0012\u0004\u0012\u0002H\u0002\u0012\u0004\u0012\u0002H\u00030\u0001\"\u0004\b\u0000\u0010\u0002\"\u0004\b\u0001\u0010\u0003*\u0010\u0012\u0006\b\u0001\u0012\u0002H\u0002\u0012\u0004\u0012\u0002H\u00030\u00012\u000e\u0010J\u001a\n\u0012\u0006\b\u0001\u0012\u0002H\u00020\u0010H\u0087\u0002¢\u0006\u0002\u0010K\u001aA\u0010H\u001a\u000e\u0012\u0004\u0012\u0002H\u0002\u0012\u0004\u0012\u0002H\u00030\u0001\"\u0004\b\u0000\u0010\u0002\"\u0004\b\u0001\u0010\u0003*\u0010\u0012\u0006\b\u0001\u0012\u0002H\u0002\u0012\u0004\u0012\u0002H\u00030\u00012\f\u0010J\u001a\b\u0012\u0004\u0012\u0002H\u00020LH\u0087\u0002\u001aA\u0010H\u001a\u000e\u0012\u0004\u0012\u0002H\u0002\u0012\u0004\u0012\u0002H\u00030\u0001\"\u0004\b\u0000\u0010\u0002\"\u0004\b\u0001\u0010\u0003*\u0010\u0012\u0006\b\u0001\u0012\u0002H\u0002\u0012\u0004\u0012\u0002H\u00030\u00012\f\u0010J\u001a\b\u0012\u0004\u0012\u0002H\u00020MH\u0087\u0002\u001a2\u0010N\u001a\u00020\t\"\u0004\b\u0000\u0010\u0002\"\u0004\b\u0001\u0010\u0003*\u000e\u0012\u0004\u0012\u0002H\u0002\u0012\u0004\u0012\u0002H\u00030\b2\u0006\u0010!\u001a\u0002H\u0002H\u0087\n¢\u0006\u0002\u0010O\u001a:\u0010N\u001a\u00020\t\"\u0004\b\u0000\u0010\u0002\"\u0004\b\u0001\u0010\u0003*\u000e\u0012\u0004\u0012\u0002H\u0002\u0012\u0004\u0012\u0002H\u00030\b2\u000e\u0010J\u001a\n\u0012\u0006\b\u0001\u0012\u0002H\u00020\u0010H\u0087\n¢\u0006\u0002\u0010P\u001a3\u0010N\u001a\u00020\t\"\u0004\b\u0000\u0010\u0002\"\u0004\b\u0001\u0010\u0003*\u000e\u0012\u0004\u0012\u0002H\u0002\u0012\u0004\u0012\u0002H\u00030\b2\f\u0010J\u001a\b\u0012\u0004\u0012\u0002H\u00020LH\u0087\n\u001a3\u0010N\u001a\u00020\t\"\u0004\b\u0000\u0010\u0002\"\u0004\b\u0001\u0010\u0003*\u000e\u0012\u0004\u0012\u0002H\u0002\u0012\u0004\u0012\u0002H\u00030\b2\f\u0010J\u001a\b\u0012\u0004\u0012\u0002H\u00020MH\u0087\n\u001a0\u0010Q\u001a\u000e\u0012\u0004\u0012\u0002H\u0002\u0012\u0004\u0012\u0002H\u00030\u0001\"\u0004\b\u0000\u0010\u0002\"\u0004\b\u0001\u0010\u0003*\u000e\u0012\u0004\u0012\u0002H\u0002\u0012\u0004\u0012\u0002H\u00030\u0001H\u0000\u001a3\u0010R\u001a\u000e\u0012\u0004\u0012\u0002H\u0002\u0012\u0004\u0012\u0002H\u00030\u0001\"\u0004\b\u0000\u0010\u0002\"\u0004\b\u0001\u0010\u0003*\u0010\u0012\u0004\u0012\u0002H\u0002\u0012\u0004\u0012\u0002H\u0003\u0018\u00010\u0001H\u0087\b\u001aT\u0010S\u001a\u000e\u0012\u0004\u0012\u0002H\u0002\u0012\u0004\u0012\u0002H\u00030\u0001\"\u0004\b\u0000\u0010\u0002\"\u0004\b\u0001\u0010\u0003*\u0010\u0012\u0006\b\u0001\u0012\u0002H\u0002\u0012\u0004\u0012\u0002H\u00030\u00012\u001a\u0010\u000f\u001a\u0016\u0012\u0012\b\u0001\u0012\u000e\u0012\u0004\u0012\u0002H\u0002\u0012\u0004\u0012\u0002H\u00030\u00110\u0010H\u0086\u0002¢\u0006\u0002\u0010T\u001aG\u0010S\u001a\u000e\u0012\u0004\u0012\u0002H\u0002\u0012\u0004\u0012\u0002H\u00030\u0001\"\u0004\b\u0000\u0010\u0002\"\u0004\b\u0001\u0010\u0003*\u0010\u0012\u0006\b\u0001\u0012\u0002H\u0002\u0012\u0004\u0012\u0002H\u00030\u00012\u0012\u0010U\u001a\u000e\u0012\u0004\u0012\u0002H\u0002\u0012\u0004\u0012\u0002H\u00030\u0011H\u0086\u0002\u001aM\u0010S\u001a\u000e\u0012\u0004\u0012\u0002H\u0002\u0012\u0004\u0012\u0002H\u00030\u0001\"\u0004\b\u0000\u0010\u0002\"\u0004\b\u0001\u0010\u0003*\u0010\u0012\u0006\b\u0001\u0012\u0002H\u0002\u0012\u0004\u0012\u0002H\u00030\u00012\u0018\u0010\u000f\u001a\u0014\u0012\u0010\u0012\u000e\u0012\u0004\u0012\u0002H\u0002\u0012\u0004\u0012\u0002H\u00030\u00110LH\u0086\u0002\u001aI\u0010S\u001a\u000e\u0012\u0004\u0012\u0002H\u0002\u0012\u0004\u0012\u0002H\u00030\u0001\"\u0004\b\u0000\u0010\u0002\"\u0004\b\u0001\u0010\u0003*\u0010\u0012\u0006\b\u0001\u0012\u0002H\u0002\u0012\u0004\u0012\u0002H\u00030\u00012\u0014\u0010V\u001a\u0010\u0012\u0006\b\u0001\u0012\u0002H\u0002\u0012\u0004\u0012\u0002H\u00030\u0001H\u0086\u0002\u001aM\u0010S\u001a\u000e\u0012\u0004\u0012\u0002H\u0002\u0012\u0004\u0012\u0002H\u00030\u0001\"\u0004\b\u0000\u0010\u0002\"\u0004\b\u0001\u0010\u0003*\u0010\u0012\u0006\b\u0001\u0012\u0002H\u0002\u0012\u0004\u0012\u0002H\u00030\u00012\u0018\u0010\u000f\u001a\u0014\u0012\u0010\u0012\u000e\u0012\u0004\u0012\u0002H\u0002\u0012\u0004\u0012\u0002H\u00030\u00110MH\u0086\u0002\u001aJ\u0010W\u001a\u00020\t\"\u0004\b\u0000\u0010\u0002\"\u0004\b\u0001\u0010\u0003*\u0012\u0012\u0006\b\u0000\u0012\u0002H\u0002\u0012\u0006\b\u0000\u0012\u0002H\u00030\b2\u001a\u0010\u000f\u001a\u0016\u0012\u0012\b\u0001\u0012\u000e\u0012\u0004\u0012\u0002H\u0002\u0012\u0004\u0012\u0002H\u00030\u00110\u0010H\u0087\n¢\u0006\u0002\u0010X\u001a=\u0010W\u001a\u00020\t\"\u0004\b\u0000\u0010\u0002\"\u0004\b\u0001\u0010\u0003*\u0012\u0012\u0006\b\u0000\u0012\u0002H\u0002\u0012\u0006\b\u0000\u0012\u0002H\u00030\b2\u0012\u0010U\u001a\u000e\u0012\u0004\u0012\u0002H\u0002\u0012\u0004\u0012\u0002H\u00030\u0011H\u0087\n\u001aC\u0010W\u001a\u00020\t\"\u0004\b\u0000\u0010\u0002\"\u0004\b\u0001\u0010\u0003*\u0012\u0012\u0006\b\u0000\u0012\u0002H\u0002\u0012\u0006\b\u0000\u0012\u0002H\u00030\b2\u0018\u0010\u000f\u001a\u0014\u0012\u0010\u0012\u000e\u0012\u0004\u0012\u0002H\u0002\u0012\u0004\u0012\u0002H\u00030\u00110LH\u0087\n\u001a=\u0010W\u001a\u00020\t\"\u0004\b\u0000\u0010\u0002\"\u0004\b\u0001\u0010\u0003*\u0012\u0012\u0006\b\u0000\u0012\u0002H\u0002\u0012\u0006\b\u0000\u0012\u0002H\u00030\b2\u0012\u0010V\u001a\u000e\u0012\u0004\u0012\u0002H\u0002\u0012\u0004\u0012\u0002H\u00030\u0001H\u0087\n\u001aC\u0010W\u001a\u00020\t\"\u0004\b\u0000\u0010\u0002\"\u0004\b\u0001\u0010\u0003*\u0012\u0012\u0006\b\u0000\u0012\u0002H\u0002\u0012\u0006\b\u0000\u0012\u0002H\u00030\b2\u0018\u0010\u000f\u001a\u0014\u0012\u0010\u0012\u000e\u0012\u0004\u0012\u0002H\u0002\u0012\u0004\u0012\u0002H\u00030\u00110MH\u0087\n\u001aG\u0010Y\u001a\u00020\t\"\u0004\b\u0000\u0010\u0002\"\u0004\b\u0001\u0010\u0003*\u0012\u0012\u0006\b\u0000\u0012\u0002H\u0002\u0012\u0006\b\u0000\u0012\u0002H\u00030\b2\u001a\u0010\u000f\u001a\u0016\u0012\u0012\b\u0001\u0012\u000e\u0012\u0004\u0012\u0002H\u0002\u0012\u0004\u0012\u0002H\u00030\u00110\u0010¢\u0006\u0002\u0010X\u001a@\u0010Y\u001a\u00020\t\"\u0004\b\u0000\u0010\u0002\"\u0004\b\u0001\u0010\u0003*\u0012\u0012\u0006\b\u0000\u0012\u0002H\u0002\u0012\u0006\b\u0000\u0012\u0002H\u00030\b2\u0018\u0010\u000f\u001a\u0014\u0012\u0010\u0012\u000e\u0012\u0004\u0012\u0002H\u0002\u0012\u0004\u0012\u0002H\u00030\u00110L\u001a@\u0010Y\u001a\u00020\t\"\u0004\b\u0000\u0010\u0002\"\u0004\b\u0001\u0010\u0003*\u0012\u0012\u0006\b\u0000\u0012\u0002H\u0002\u0012\u0006\b\u0000\u0012\u0002H\u00030\b2\u0018\u0010\u000f\u001a\u0014\u0012\u0010\u0012\u000e\u0012\u0004\u0012\u0002H\u0002\u0012\u0004\u0012\u0002H\u00030\u00110M\u001a;\u0010Z\u001a\u0004\u0018\u0001H\u0003\"\t\b\u0000\u0010\u0002¢\u0006\u0002\b \"\u0004\b\u0001\u0010\u0003*\u0010\u0012\u0006\b\u0001\u0012\u0002H\u0002\u0012\u0004\u0012\u0002H\u00030\b2\u0006\u0010!\u001a\u0002H\u0002H\u0087\b¢\u0006\u0002\u00101\u001a:\u0010[\u001a\u00020\t\"\u0004\b\u0000\u0010\u0002\"\u0004\b\u0001\u0010\u0003*\u000e\u0012\u0004\u0012\u0002H\u0002\u0012\u0004\u0012\u0002H\u00030\b2\u0006\u0010!\u001a\u0002H\u00022\u0006\u0010%\u001a\u0002H\u0003H\u0087\n¢\u0006\u0002\u0010\\\u001a;\u0010]\u001a\u000e\u0012\u0004\u0012\u0002H\u0002\u0012\u0004\u0012\u0002H\u00030\u0001\"\u0004\b\u0000\u0010\u0002\"\u0004\b\u0001\u0010\u0003*\u0016\u0012\u0012\b\u0001\u0012\u000e\u0012\u0004\u0012\u0002H\u0002\u0012\u0004\u0012\u0002H\u00030\u00110\u0010¢\u0006\u0002\u0010\u0018\u001aQ\u0010]\u001a\u0002H+\"\u0004\b\u0000\u0010\u0002\"\u0004\b\u0001\u0010\u0003\"\u0018\b\u0002\u0010+*\u0012\u0012\u0006\b\u0000\u0012\u0002H\u0002\u0012\u0006\b\u0000\u0012\u0002H\u00030\b*\u0016\u0012\u0012\b\u0001\u0012\u000e\u0012\u0004\u0012\u0002H\u0002\u0012\u0004\u0012\u0002H\u00030\u00110\u00102\u0006\u0010,\u001a\u0002H+¢\u0006\u0002\u0010^\u001a4\u0010]\u001a\u000e\u0012\u0004\u0012\u0002H\u0002\u0012\u0004\u0012\u0002H\u00030\u0001\"\u0004\b\u0000\u0010\u0002\"\u0004\b\u0001\u0010\u0003*\u0014\u0012\u0010\u0012\u000e\u0012\u0004\u0012\u0002H\u0002\u0012\u0004\u0012\u0002H\u00030\u00110L\u001aO\u0010]\u001a\u0002H+\"\u0004\b\u0000\u0010\u0002\"\u0004\b\u0001\u0010\u0003\"\u0018\b\u0002\u0010+*\u0012\u0012\u0006\b\u0000\u0012\u0002H\u0002\u0012\u0006\b\u0000\u0012\u0002H\u00030\b*\u0014\u0012\u0010\u0012\u000e\u0012\u0004\u0012\u0002H\u0002\u0012\u0004\u0012\u0002H\u00030\u00110L2\u0006\u0010,\u001a\u0002H+¢\u0006\u0002\u0010_\u001a2\u0010]\u001a\u000e\u0012\u0004\u0012\u0002H\u0002\u0012\u0004\u0012\u0002H\u00030\u0001\"\u0004\b\u0000\u0010\u0002\"\u0004\b\u0001\u0010\u0003*\u0010\u0012\u0006\b\u0001\u0012\u0002H\u0002\u0012\u0004\u0012\u0002H\u00030\u0001H\u0007\u001aM\u0010]\u001a\u0002H+\"\u0004\b\u0000\u0010\u0002\"\u0004\b\u0001\u0010\u0003\"\u0018\b\u0002\u0010+*\u0012\u0012\u0006\b\u0000\u0012\u0002H\u0002\u0012\u0006\b\u0000\u0012\u0002H\u00030\b*\u0010\u0012\u0006\b\u0001\u0012\u0002H\u0002\u0012\u0004\u0012\u0002H\u00030\u00012\u0006\u0010,\u001a\u0002H+H\u0007¢\u0006\u0002\u0010`\u001a4\u0010]\u001a\u000e\u0012\u0004\u0012\u0002H\u0002\u0012\u0004\u0012\u0002H\u00030\u0001\"\u0004\b\u0000\u0010\u0002\"\u0004\b\u0001\u0010\u0003*\u0014\u0012\u0010\u0012\u000e\u0012\u0004\u0012\u0002H\u0002\u0012\u0004\u0012\u0002H\u00030\u00110M\u001aO\u0010]\u001a\u0002H+\"\u0004\b\u0000\u0010\u0002\"\u0004\b\u0001\u0010\u0003\"\u0018\b\u0002\u0010+*\u0012\u0012\u0006\b\u0000\u0012\u0002H\u0002\u0012\u0006\b\u0000\u0012\u0002H\u00030\b*\u0014\u0012\u0010\u0012\u000e\u0012\u0004\u0012\u0002H\u0002\u0012\u0004\u0012\u0002H\u00030\u00110M2\u0006\u0010,\u001a\u0002H+¢\u0006\u0002\u0010a\u001a2\u0010b\u001a\u000e\u0012\u0004\u0012\u0002H\u0002\u0012\u0004\u0012\u0002H\u00030\b\"\u0004\b\u0000\u0010\u0002\"\u0004\b\u0001\u0010\u0003*\u0010\u0012\u0006\b\u0001\u0012\u0002H\u0002\u0012\u0004\u0012\u0002H\u00030\u0001H\u0007\u001a1\u0010c\u001a\u000e\u0012\u0004\u0012\u0002H\u0002\u0012\u0004\u0012\u0002H\u00030\u0011\"\u0004\b\u0000\u0010\u0002\"\u0004\b\u0001\u0010\u0003*\u000e\u0012\u0004\u0012\u0002H\u0002\u0012\u0004\u0012\u0002H\u00030\u001bH\u0087\b\u0082\u0002\u0007\n\u0005\b\u009920\u0001¨\u0006d" }, d2 = { "buildMap", "", "K", "V", "capacity", "", "builderAction", "Lkotlin/Function1;", "", "", "Lkotlin/ExtensionFunctionType;", "emptyMap", "hashMapOf", "Ljava/util/HashMap;", "Lkotlin/collections/HashMap;", "pairs", "", "Lkotlin/Pair;", "([Lkotlin/Pair;)Ljava/util/HashMap;", "linkedMapOf", "Ljava/util/LinkedHashMap;", "Lkotlin/collections/LinkedHashMap;", "([Lkotlin/Pair;)Ljava/util/LinkedHashMap;", "mapOf", "([Lkotlin/Pair;)Ljava/util/Map;", "mutableMapOf", "component1", "", "(Ljava/util/Map$Entry;)Ljava/lang/Object;", "component2", "contains", "", "Lkotlin/internal/OnlyInputTypes;", "key", "(Ljava/util/Map;Ljava/lang/Object;)Z", "containsKey", "containsValue", "value", "filter", "predicate", "filterKeys", "filterNot", "filterNotTo", "M", "destination", "(Ljava/util/Map;Ljava/util/Map;Lkotlin/jvm/functions/Function1;)Ljava/util/Map;", "filterTo", "filterValues", "get", "(Ljava/util/Map;Ljava/lang/Object;)Ljava/lang/Object;", "getOrElse", "defaultValue", "Lkotlin/Function0;", "(Ljava/util/Map;Ljava/lang/Object;Lkotlin/jvm/functions/Function0;)Ljava/lang/Object;", "getOrElseNullable", "getOrPut", "getValue", "ifEmpty", "R", "(Ljava/util/Map;Lkotlin/jvm/functions/Function0;)Ljava/lang/Object;", "isNotEmpty", "isNullOrEmpty", "iterator", "", "", "", "mutableIterator", "mapKeys", "transform", "mapKeysTo", "mapValues", "mapValuesTo", "minus", "(Ljava/util/Map;Ljava/lang/Object;)Ljava/util/Map;", "keys", "(Ljava/util/Map;[Ljava/lang/Object;)Ljava/util/Map;", "", "Lkotlin/sequences/Sequence;", "minusAssign", "(Ljava/util/Map;Ljava/lang/Object;)V", "(Ljava/util/Map;[Ljava/lang/Object;)V", "optimizeReadOnlyMap", "orEmpty", "plus", "(Ljava/util/Map;[Lkotlin/Pair;)Ljava/util/Map;", "pair", "map", "plusAssign", "(Ljava/util/Map;[Lkotlin/Pair;)V", "putAll", "remove", "set", "(Ljava/util/Map;Ljava/lang/Object;Ljava/lang/Object;)V", "toMap", "([Lkotlin/Pair;Ljava/util/Map;)Ljava/util/Map;", "(Ljava/lang/Iterable;Ljava/util/Map;)Ljava/util/Map;", "(Ljava/util/Map;Ljava/util/Map;)Ljava/util/Map;", "(Lkotlin/sequences/Sequence;Ljava/util/Map;)Ljava/util/Map;", "toMutableMap", "toPair", "kotlin-stdlib" }, xs = "kotlin/collections/MapsKt")
class MapsKt__MapsKt extends MapsKt__MapsJVMKt
{
    @NotNull
    public static final <K, V> Map<K, V> emptyMap() {
        final EmptyMap instance = EmptyMap.INSTANCE;
        Intrinsics.checkNotNull(instance, "null cannot be cast to non-null type kotlin.collections.Map<K of kotlin.collections.MapsKt__MapsKt.emptyMap, V of kotlin.collections.MapsKt__MapsKt.emptyMap>");
        return (Map<K, V>)instance;
    }
    
    @NotNull
    public static final <K, V> Map<K, V> mapOf(@NotNull final Pair<? extends K, ? extends V>... pairs) {
        Intrinsics.checkNotNullParameter(pairs, "pairs");
        return (((Pair<? extends K, ? extends V>[])pairs).length > 0) ? toMap((Pair<?, ?>[])pairs, (LinkedHashMap)new LinkedHashMap(MapsKt__MapsJVMKt.mapCapacity(((Pair<? extends K, ? extends V>[])pairs).length))) : emptyMap();
    }
    
    @InlineOnly
    private static final <K, V> Map<K, V> mapOf() {
        return (Map<K, V>)emptyMap();
    }
    
    @SinceKotlin(version = "1.1")
    @InlineOnly
    private static final <K, V> Map<K, V> mutableMapOf() {
        return new LinkedHashMap<K, V>();
    }
    
    @NotNull
    public static final <K, V> Map<K, V> mutableMapOf(@NotNull final Pair<? extends K, ? extends V>... pairs) {
        Intrinsics.checkNotNullParameter(pairs, "pairs");
        final LinkedHashMap $this$mutableMapOf_u24lambda_u240;
        final LinkedHashMap linkedHashMap = $this$mutableMapOf_u24lambda_u240 = new LinkedHashMap(MapsKt__MapsJVMKt.mapCapacity(pairs.length));
        final int n = 0;
        putAll((Map<? super Object, ? super Object>)$this$mutableMapOf_u24lambda_u240, (Pair<?, ?>[])pairs);
        return (LinkedHashMap<K, V>)linkedHashMap;
    }
    
    @SinceKotlin(version = "1.1")
    @InlineOnly
    private static final <K, V> HashMap<K, V> hashMapOf() {
        return new HashMap<K, V>();
    }
    
    @NotNull
    public static final <K, V> HashMap<K, V> hashMapOf(@NotNull final Pair<? extends K, ? extends V>... pairs) {
        Intrinsics.checkNotNullParameter(pairs, "pairs");
        final HashMap $this$hashMapOf_u24lambda_u241;
        final HashMap hashMap = $this$hashMapOf_u24lambda_u241 = new HashMap(MapsKt__MapsJVMKt.mapCapacity(pairs.length));
        final int n = 0;
        putAll((Map<? super Object, ? super Object>)$this$hashMapOf_u24lambda_u241, (Pair<?, ?>[])pairs);
        return (HashMap<K, V>)hashMap;
    }
    
    @SinceKotlin(version = "1.1")
    @InlineOnly
    private static final <K, V> LinkedHashMap<K, V> linkedMapOf() {
        return new LinkedHashMap<K, V>();
    }
    
    @NotNull
    public static final <K, V> LinkedHashMap<K, V> linkedMapOf(@NotNull final Pair<? extends K, ? extends V>... pairs) {
        Intrinsics.checkNotNullParameter(pairs, "pairs");
        return toMap((Pair<?, ?>[])pairs, (LinkedHashMap<K, V>)new LinkedHashMap<Object, Object>(MapsKt__MapsJVMKt.mapCapacity(((Pair<? extends K, ? extends V>[])pairs).length)));
    }
    
    @SinceKotlin(version = "1.6")
    @WasExperimental(markerClass = { ExperimentalStdlibApi.class })
    @InlineOnly
    private static final <K, V> Map<K, V> buildMap(@BuilderInference final Function1<? super Map<K, V>, Unit> builderAction) {
        Intrinsics.checkNotNullParameter(builderAction, "builderAction");
        final Map<K, V> mapBuilder = MapsKt__MapsJVMKt.createMapBuilder();
        builderAction.invoke(mapBuilder);
        return MapsKt__MapsJVMKt.build(mapBuilder);
    }
    
    @SinceKotlin(version = "1.6")
    @WasExperimental(markerClass = { ExperimentalStdlibApi.class })
    @InlineOnly
    private static final <K, V> Map<K, V> buildMap(final int capacity, @BuilderInference final Function1<? super Map<K, V>, Unit> builderAction) {
        Intrinsics.checkNotNullParameter(builderAction, "builderAction");
        final Map<K, V> mapBuilder = MapsKt__MapsJVMKt.createMapBuilder(capacity);
        builderAction.invoke(mapBuilder);
        return MapsKt__MapsJVMKt.build(mapBuilder);
    }
    
    @InlineOnly
    private static final <K, V> boolean isNotEmpty(final Map<? extends K, ? extends V> $this$isNotEmpty) {
        Intrinsics.checkNotNullParameter($this$isNotEmpty, "<this>");
        return !$this$isNotEmpty.isEmpty();
    }
    
    @SinceKotlin(version = "1.3")
    @InlineOnly
    private static final <K, V> boolean isNullOrEmpty(final Map<? extends K, ? extends V> $this$isNullOrEmpty) {
        return $this$isNullOrEmpty == null || $this$isNullOrEmpty.isEmpty();
    }
    
    @InlineOnly
    private static final <K, V> Map<K, V> orEmpty(final Map<K, ? extends V> $this$orEmpty) {
        Map<K, V> emptyMap = (Map<K, V>)$this$orEmpty;
        if ($this$orEmpty == null) {
            emptyMap = emptyMap();
        }
        return emptyMap;
    }
    
    @SinceKotlin(version = "1.3")
    @InlineOnly
    private static final <M extends java.util.Map, R> R ifEmpty(final M $this$ifEmpty, final Function0<? extends R> defaultValue) {
        // 
        // This method could not be decompiled.
        // 
        // Original Bytecode:
        // 
        //     1: ldc             "defaultValue"
        //     3: invokestatic    kotlin/jvm/internal/Intrinsics.checkNotNullParameter:(Ljava/lang/Object;Ljava/lang/String;)V
        //     6: aload_0         /* $this$ifEmpty */
        //     7: invokeinterface java/util/Map.isEmpty:()Z
        //    12: ifeq            24
        //    15: aload_1         /* defaultValue */
        //    16: invokeinterface kotlin/jvm/functions/Function0.invoke:()Ljava/lang/Object;
        //    21: goto            25
        //    24: aload_0         /* $this$ifEmpty */
        //    25: areturn        
        //    Signature:
        //  <M::Ljava/util/Map<**>;:TR;R:Ljava/lang/Object;>(TM;Lkotlin/jvm/functions/Function0<+TR;>;)TR;
        //    StackMapTable: 00 02 18 40 07 00 91
        // 
        // The error that occurred was:
        // 
        // java.lang.StackOverflowError
        //     at com.strobel.assembler.metadata.MetadataHelper.isSubType(MetadataHelper.java:1283)
        //     at com.strobel.assembler.metadata.MetadataHelper.isSubType(MetadataHelper.java:1283)
        //     at com.strobel.assembler.metadata.MetadataHelper.isSubType(MetadataHelper.java:1283)
        //     at com.strobel.assembler.metadata.MetadataHelper.isSubType(MetadataHelper.java:1283)
        //     at com.strobel.assembler.metadata.MetadataHelper.isSubType(MetadataHelper.java:1283)
        //     at com.strobel.assembler.metadata.MetadataHelper.isSubType(MetadataHelper.java:1283)
        //     at com.strobel.assembler.metadata.MetadataHelper.isSubType(MetadataHelper.java:1283)
        //     at com.strobel.assembler.metadata.MetadataHelper.isSubType(MetadataHelper.java:1283)
        //     at com.strobel.assembler.metadata.MetadataHelper.isSubType(MetadataHelper.java:1283)
        //     at com.strobel.assembler.metadata.MetadataHelper.isSubType(MetadataHelper.java:1283)
        //     at com.strobel.assembler.metadata.MetadataHelper.isSubType(MetadataHelper.java:1283)
        //     at com.strobel.assembler.metadata.MetadataHelper.isSubType(MetadataHelper.java:1283)
        //     at com.strobel.assembler.metadata.MetadataHelper.isSubType(MetadataHelper.java:1283)
        //     at com.strobel.assembler.metadata.MetadataHelper.isSubType(MetadataHelper.java:1283)
        //     at com.strobel.assembler.metadata.MetadataHelper.isSubType(MetadataHelper.java:1283)
        //     at com.strobel.assembler.metadata.MetadataHelper.isSubType(MetadataHelper.java:1283)
        //     at com.strobel.assembler.metadata.MetadataHelper.isSubType(MetadataHelper.java:1283)
        //     at com.strobel.assembler.metadata.MetadataHelper.isSubType(MetadataHelper.java:1283)
        //     at com.strobel.assembler.metadata.MetadataHelper.isSubType(MetadataHelper.java:1283)
        //     at com.strobel.assembler.metadata.MetadataHelper.isSubType(MetadataHelper.java:1283)
        //     at com.strobel.assembler.metadata.MetadataHelper.isSubType(MetadataHelper.java:1283)
        //     at com.strobel.assembler.metadata.MetadataHelper.isSubType(MetadataHelper.java:1283)
        //     at com.strobel.assembler.metadata.MetadataHelper.isSubType(MetadataHelper.java:1283)
        //     at com.strobel.assembler.metadata.MetadataHelper.isSubType(MetadataHelper.java:1283)
        //     at com.strobel.assembler.metadata.MetadataHelper.isSubType(MetadataHelper.java:1283)
        //     at com.strobel.assembler.metadata.MetadataHelper.isSubType(MetadataHelper.java:1283)
        //     at com.strobel.assembler.metadata.MetadataHelper.isSubType(MetadataHelper.java:1283)
        //     at com.strobel.assembler.metadata.MetadataHelper.isSubType(MetadataHelper.java:1283)
        //     at com.strobel.assembler.metadata.MetadataHelper.isSubType(MetadataHelper.java:1283)
        //     at com.strobel.assembler.metadata.MetadataHelper.isSubType(MetadataHelper.java:1283)
        //     at com.strobel.assembler.metadata.MetadataHelper.isSubType(MetadataHelper.java:1283)
        //     at com.strobel.assembler.metadata.MetadataHelper.isSubType(MetadataHelper.java:1283)
        //     at com.strobel.assembler.metadata.MetadataHelper.isSubType(MetadataHelper.java:1283)
        //     at com.strobel.assembler.metadata.MetadataHelper.isSubType(MetadataHelper.java:1283)
        //     at com.strobel.assembler.metadata.MetadataHelper.isSubType(MetadataHelper.java:1283)
        //     at com.strobel.assembler.metadata.MetadataHelper.isSubType(MetadataHelper.java:1283)
        //     at com.strobel.assembler.metadata.MetadataHelper.isSubType(MetadataHelper.java:1283)
        //     at com.strobel.assembler.metadata.MetadataHelper.isSubType(MetadataHelper.java:1283)
        //     at com.strobel.assembler.metadata.MetadataHelper.isSubType(MetadataHelper.java:1283)
        //     at com.strobel.assembler.metadata.MetadataHelper.isSubType(MetadataHelper.java:1283)
        //     at com.strobel.assembler.metadata.MetadataHelper.isSubType(MetadataHelper.java:1283)
        //     at com.strobel.assembler.metadata.MetadataHelper.isSubType(MetadataHelper.java:1283)
        //     at com.strobel.assembler.metadata.MetadataHelper.isSubType(MetadataHelper.java:1283)
        //     at com.strobel.assembler.metadata.MetadataHelper.isSubType(MetadataHelper.java:1283)
        //     at com.strobel.assembler.metadata.MetadataHelper.isSubType(MetadataHelper.java:1283)
        //     at com.strobel.assembler.metadata.MetadataHelper.isSubType(MetadataHelper.java:1283)
        //     at com.strobel.assembler.metadata.MetadataHelper.isSubType(MetadataHelper.java:1283)
        //     at com.strobel.assembler.metadata.MetadataHelper.isSubType(MetadataHelper.java:1283)
        //     at com.strobel.assembler.metadata.MetadataHelper.isSubType(MetadataHelper.java:1283)
        //     at com.strobel.assembler.metadata.MetadataHelper.isSubType(MetadataHelper.java:1283)
        //     at com.strobel.assembler.metadata.MetadataHelper.isSubType(MetadataHelper.java:1283)
        //     at com.strobel.assembler.metadata.MetadataHelper.isSubType(MetadataHelper.java:1283)
        //     at com.strobel.assembler.metadata.MetadataHelper.isSubType(MetadataHelper.java:1283)
        //     at com.strobel.assembler.metadata.MetadataHelper.isSubType(MetadataHelper.java:1283)
        //     at com.strobel.assembler.metadata.MetadataHelper.isSubType(MetadataHelper.java:1283)
        //     at com.strobel.assembler.metadata.MetadataHelper.isSubType(MetadataHelper.java:1283)
        //     at com.strobel.assembler.metadata.MetadataHelper.isSubType(MetadataHelper.java:1283)
        //     at com.strobel.assembler.metadata.MetadataHelper.isSubType(MetadataHelper.java:1283)
        //     at com.strobel.assembler.metadata.MetadataHelper.isSubType(MetadataHelper.java:1283)
        //     at com.strobel.assembler.metadata.MetadataHelper.isSubType(MetadataHelper.java:1283)
        //     at com.strobel.assembler.metadata.MetadataHelper.isSubType(MetadataHelper.java:1283)
        //     at com.strobel.assembler.metadata.MetadataHelper.isSubType(MetadataHelper.java:1283)
        //     at com.strobel.assembler.metadata.MetadataHelper.isSubType(MetadataHelper.java:1283)
        //     at com.strobel.assembler.metadata.MetadataHelper.isSubType(MetadataHelper.java:1283)
        //     at com.strobel.assembler.metadata.MetadataHelper.isSubType(MetadataHelper.java:1283)
        //     at com.strobel.assembler.metadata.MetadataHelper.isSubType(MetadataHelper.java:1283)
        //     at com.strobel.assembler.metadata.MetadataHelper.isSubType(MetadataHelper.java:1283)
        //     at com.strobel.assembler.metadata.MetadataHelper.isSubType(MetadataHelper.java:1283)
        //     at com.strobel.assembler.metadata.MetadataHelper.isSubType(MetadataHelper.java:1283)
        //     at com.strobel.assembler.metadata.MetadataHelper.isSubType(MetadataHelper.java:1283)
        //     at com.strobel.assembler.metadata.MetadataHelper.isSubType(MetadataHelper.java:1283)
        //     at com.strobel.assembler.metadata.MetadataHelper.isSubType(MetadataHelper.java:1283)
        //     at com.strobel.assembler.metadata.MetadataHelper.isSubType(MetadataHelper.java:1283)
        //     at com.strobel.assembler.metadata.MetadataHelper.isSubType(MetadataHelper.java:1283)
        //     at com.strobel.assembler.metadata.MetadataHelper.isSubType(MetadataHelper.java:1283)
        //     at com.strobel.assembler.metadata.MetadataHelper.isSubType(MetadataHelper.java:1283)
        //     at com.strobel.assembler.metadata.MetadataHelper.isSubType(MetadataHelper.java:1283)
        //     at com.strobel.assembler.metadata.MetadataHelper.isSubType(MetadataHelper.java:1283)
        //     at com.strobel.assembler.metadata.MetadataHelper.isSubType(MetadataHelper.java:1283)
        //     at com.strobel.assembler.metadata.MetadataHelper.isSubType(MetadataHelper.java:1283)
        //     at com.strobel.assembler.metadata.MetadataHelper.isSubType(MetadataHelper.java:1283)
        //     at com.strobel.assembler.metadata.MetadataHelper.isSubType(MetadataHelper.java:1283)
        //     at com.strobel.assembler.metadata.MetadataHelper.isSubType(MetadataHelper.java:1283)
        //     at com.strobel.assembler.metadata.MetadataHelper.isSubType(MetadataHelper.java:1283)
        //     at com.strobel.assembler.metadata.MetadataHelper.isSubType(MetadataHelper.java:1283)
        //     at com.strobel.assembler.metadata.MetadataHelper.isSubType(MetadataHelper.java:1283)
        //     at com.strobel.assembler.metadata.MetadataHelper.isSubType(MetadataHelper.java:1283)
        //     at com.strobel.assembler.metadata.MetadataHelper.isSubType(MetadataHelper.java:1283)
        //     at com.strobel.assembler.metadata.MetadataHelper.isSubType(MetadataHelper.java:1283)
        //     at com.strobel.assembler.metadata.MetadataHelper.isSubType(MetadataHelper.java:1283)
        //     at com.strobel.assembler.metadata.MetadataHelper.isSubType(MetadataHelper.java:1283)
        //     at com.strobel.assembler.metadata.MetadataHelper.isSubType(MetadataHelper.java:1283)
        //     at com.strobel.assembler.metadata.MetadataHelper.isSubType(MetadataHelper.java:1283)
        //     at com.strobel.assembler.metadata.MetadataHelper.isSubType(MetadataHelper.java:1283)
        //     at com.strobel.assembler.metadata.MetadataHelper.isSubType(MetadataHelper.java:1283)
        //     at com.strobel.assembler.metadata.MetadataHelper.isSubType(MetadataHelper.java:1283)
        //     at com.strobel.assembler.metadata.MetadataHelper.isSubType(MetadataHelper.java:1283)
        //     at com.strobel.assembler.metadata.MetadataHelper.isSubType(MetadataHelper.java:1283)
        //     at com.strobel.assembler.metadata.MetadataHelper.isSubType(MetadataHelper.java:1283)
        //     at com.strobel.assembler.metadata.MetadataHelper.isSubType(MetadataHelper.java:1283)
        //     at com.strobel.assembler.metadata.MetadataHelper.isSubType(MetadataHelper.java:1283)
        //     at com.strobel.assembler.metadata.MetadataHelper.isSubType(MetadataHelper.java:1283)
        //     at com.strobel.assembler.metadata.MetadataHelper.isSubType(MetadataHelper.java:1283)
        //     at com.strobel.assembler.metadata.MetadataHelper.isSubType(MetadataHelper.java:1283)
        //     at com.strobel.assembler.metadata.MetadataHelper.isSubType(MetadataHelper.java:1283)
        //     at com.strobel.assembler.metadata.MetadataHelper.isSubType(MetadataHelper.java:1283)
        //     at com.strobel.assembler.metadata.MetadataHelper.isSubType(MetadataHelper.java:1283)
        //     at com.strobel.assembler.metadata.MetadataHelper.isSubType(MetadataHelper.java:1283)
        //     at com.strobel.assembler.metadata.MetadataHelper.isSubType(MetadataHelper.java:1283)
        //     at com.strobel.assembler.metadata.MetadataHelper.isSubType(MetadataHelper.java:1283)
        //     at com.strobel.assembler.metadata.MetadataHelper.isSubType(MetadataHelper.java:1283)
        //     at com.strobel.assembler.metadata.MetadataHelper.isSubType(MetadataHelper.java:1283)
        //     at com.strobel.assembler.metadata.MetadataHelper.isSubType(MetadataHelper.java:1283)
        //     at com.strobel.assembler.metadata.MetadataHelper.isSubType(MetadataHelper.java:1283)
        //     at com.strobel.assembler.metadata.MetadataHelper.isSubType(MetadataHelper.java:1283)
        //     at com.strobel.assembler.metadata.MetadataHelper.isSubType(MetadataHelper.java:1283)
        //     at com.strobel.assembler.metadata.MetadataHelper.isSubType(MetadataHelper.java:1283)
        //     at com.strobel.assembler.metadata.MetadataHelper.isSubType(MetadataHelper.java:1283)
        //     at com.strobel.assembler.metadata.MetadataHelper.isSubType(MetadataHelper.java:1283)
        //     at com.strobel.assembler.metadata.MetadataHelper.isSubType(MetadataHelper.java:1283)
        //     at com.strobel.assembler.metadata.MetadataHelper.isSubType(MetadataHelper.java:1283)
        //     at com.strobel.assembler.metadata.MetadataHelper.isSubType(MetadataHelper.java:1283)
        //     at com.strobel.assembler.metadata.MetadataHelper.isSubType(MetadataHelper.java:1283)
        //     at com.strobel.assembler.metadata.MetadataHelper.isSubType(MetadataHelper.java:1283)
        //     at com.strobel.assembler.metadata.MetadataHelper.isSubType(MetadataHelper.java:1283)
        //     at com.strobel.assembler.metadata.MetadataHelper.isSubType(MetadataHelper.java:1283)
        //     at com.strobel.assembler.metadata.MetadataHelper.isSubType(MetadataHelper.java:1283)
        //     at com.strobel.assembler.metadata.MetadataHelper.isSubType(MetadataHelper.java:1283)
        //     at com.strobel.assembler.metadata.MetadataHelper.isSubType(MetadataHelper.java:1283)
        //     at com.strobel.assembler.metadata.MetadataHelper.isSubType(MetadataHelper.java:1283)
        //     at com.strobel.assembler.metadata.MetadataHelper.isSubType(MetadataHelper.java:1283)
        //     at com.strobel.assembler.metadata.MetadataHelper.isSubType(MetadataHelper.java:1283)
        //     at com.strobel.assembler.metadata.MetadataHelper.isSubType(MetadataHelper.java:1283)
        //     at com.strobel.assembler.metadata.MetadataHelper.isSubType(MetadataHelper.java:1283)
        //     at com.strobel.assembler.metadata.MetadataHelper.isSubType(MetadataHelper.java:1283)
        //     at com.strobel.assembler.metadata.MetadataHelper.isSubType(MetadataHelper.java:1283)
        //     at com.strobel.assembler.metadata.MetadataHelper.isSubType(MetadataHelper.java:1283)
        //     at com.strobel.assembler.metadata.MetadataHelper.isSubType(MetadataHelper.java:1283)
        //     at com.strobel.assembler.metadata.MetadataHelper.isSubType(MetadataHelper.java:1283)
        //     at com.strobel.assembler.metadata.MetadataHelper.isSubType(MetadataHelper.java:1283)
        //     at com.strobel.assembler.metadata.MetadataHelper.isSubType(MetadataHelper.java:1283)
        //     at com.strobel.assembler.metadata.MetadataHelper.isSubType(MetadataHelper.java:1283)
        //     at com.strobel.assembler.metadata.MetadataHelper.isSubType(MetadataHelper.java:1283)
        //     at com.strobel.assembler.metadata.MetadataHelper.isSubType(MetadataHelper.java:1283)
        //     at com.strobel.assembler.metadata.MetadataHelper.isSubType(MetadataHelper.java:1283)
        //     at com.strobel.assembler.metadata.MetadataHelper.isSubType(MetadataHelper.java:1283)
        //     at com.strobel.assembler.metadata.MetadataHelper.isSubType(MetadataHelper.java:1283)
        //     at com.strobel.assembler.metadata.MetadataHelper.isSubType(MetadataHelper.java:1283)
        //     at com.strobel.assembler.metadata.MetadataHelper.isSubType(MetadataHelper.java:1283)
        //     at com.strobel.assembler.metadata.MetadataHelper.isSubType(MetadataHelper.java:1283)
        //     at com.strobel.assembler.metadata.MetadataHelper.isSubType(MetadataHelper.java:1283)
        //     at com.strobel.assembler.metadata.MetadataHelper.isSubType(MetadataHelper.java:1283)
        //     at com.strobel.assembler.metadata.MetadataHelper.isSubType(MetadataHelper.java:1283)
        //     at com.strobel.assembler.metadata.MetadataHelper.isSubType(MetadataHelper.java:1283)
        //     at com.strobel.assembler.metadata.MetadataHelper.isSubType(MetadataHelper.java:1283)
        //     at com.strobel.assembler.metadata.MetadataHelper.isSubType(MetadataHelper.java:1283)
        //     at com.strobel.assembler.metadata.MetadataHelper.isSubType(MetadataHelper.java:1283)
        //     at com.strobel.assembler.metadata.MetadataHelper.isSubType(MetadataHelper.java:1283)
        //     at com.strobel.assembler.metadata.MetadataHelper.isSubType(MetadataHelper.java:1283)
        //     at com.strobel.assembler.metadata.MetadataHelper.isSubType(MetadataHelper.java:1283)
        //     at com.strobel.assembler.metadata.MetadataHelper.isSubType(MetadataHelper.java:1283)
        //     at com.strobel.assembler.metadata.MetadataHelper.isSubType(MetadataHelper.java:1283)
        //     at com.strobel.assembler.metadata.MetadataHelper.isSubType(MetadataHelper.java:1283)
        //     at com.strobel.assembler.metadata.MetadataHelper.isSubType(MetadataHelper.java:1283)
        //     at com.strobel.assembler.metadata.MetadataHelper.isSubType(MetadataHelper.java:1283)
        //     at com.strobel.assembler.metadata.MetadataHelper.isSubType(MetadataHelper.java:1283)
        //     at com.strobel.assembler.metadata.MetadataHelper.isSubType(MetadataHelper.java:1283)
        //     at com.strobel.assembler.metadata.MetadataHelper.isSubType(MetadataHelper.java:1283)
        //     at com.strobel.assembler.metadata.MetadataHelper.isSubType(MetadataHelper.java:1283)
        //     at com.strobel.assembler.metadata.MetadataHelper.isSubType(MetadataHelper.java:1283)
        //     at com.strobel.assembler.metadata.MetadataHelper.isSubType(MetadataHelper.java:1283)
        //     at com.strobel.assembler.metadata.MetadataHelper.isSubType(MetadataHelper.java:1283)
        //     at com.strobel.assembler.metadata.MetadataHelper.isSubType(MetadataHelper.java:1283)
        //     at com.strobel.assembler.metadata.MetadataHelper.isSubType(MetadataHelper.java:1283)
        //     at com.strobel.assembler.metadata.MetadataHelper.isSubType(MetadataHelper.java:1283)
        //     at com.strobel.assembler.metadata.MetadataHelper.isSubType(MetadataHelper.java:1283)
        //     at com.strobel.assembler.metadata.MetadataHelper.isSubType(MetadataHelper.java:1283)
        //     at com.strobel.assembler.metadata.MetadataHelper.isSubType(MetadataHelper.java:1283)
        //     at com.strobel.assembler.metadata.MetadataHelper.isSubType(MetadataHelper.java:1283)
        //     at com.strobel.assembler.metadata.MetadataHelper.isSubType(MetadataHelper.java:1283)
        //     at com.strobel.assembler.metadata.MetadataHelper.isSubType(MetadataHelper.java:1283)
        //     at com.strobel.assembler.metadata.MetadataHelper.isSubType(MetadataHelper.java:1283)
        //     at com.strobel.assembler.metadata.MetadataHelper.isSubType(MetadataHelper.java:1283)
        //     at com.strobel.assembler.metadata.MetadataHelper.isSubType(MetadataHelper.java:1283)
        //     at com.strobel.assembler.metadata.MetadataHelper.isSubType(MetadataHelper.java:1283)
        //     at com.strobel.assembler.metadata.MetadataHelper.isSubType(MetadataHelper.java:1283)
        //     at com.strobel.assembler.metadata.MetadataHelper.isSubType(MetadataHelper.java:1283)
        //     at com.strobel.assembler.metadata.MetadataHelper.isSubType(MetadataHelper.java:1283)
        //     at com.strobel.assembler.metadata.MetadataHelper.isSubType(MetadataHelper.java:1283)
        //     at com.strobel.assembler.metadata.MetadataHelper.isSubType(MetadataHelper.java:1283)
        //     at com.strobel.assembler.metadata.MetadataHelper.isSubType(MetadataHelper.java:1283)
        //     at com.strobel.assembler.metadata.MetadataHelper.isSubType(MetadataHelper.java:1283)
        //     at com.strobel.assembler.metadata.MetadataHelper.isSubType(MetadataHelper.java:1283)
        //     at com.strobel.assembler.metadata.MetadataHelper.isSubType(MetadataHelper.java:1283)
        //     at com.strobel.assembler.metadata.MetadataHelper.isSubType(MetadataHelper.java:1283)
        //     at com.strobel.assembler.metadata.MetadataHelper.isSubType(MetadataHelper.java:1283)
        //     at com.strobel.assembler.metadata.MetadataHelper.isSubType(MetadataHelper.java:1283)
        //     at com.strobel.assembler.metadata.MetadataHelper.isSubType(MetadataHelper.java:1283)
        //     at com.strobel.assembler.metadata.MetadataHelper.isSubType(MetadataHelper.java:1283)
        //     at com.strobel.assembler.metadata.MetadataHelper.isSubType(MetadataHelper.java:1283)
        //     at com.strobel.assembler.metadata.MetadataHelper.isSubType(MetadataHelper.java:1283)
        //     at com.strobel.assembler.metadata.MetadataHelper.isSubType(MetadataHelper.java:1283)
        //     at com.strobel.assembler.metadata.MetadataHelper.isSubType(MetadataHelper.java:1283)
        //     at com.strobel.assembler.metadata.MetadataHelper.isSubType(MetadataHelper.java:1283)
        //     at com.strobel.assembler.metadata.MetadataHelper.isSubType(MetadataHelper.java:1283)
        //     at com.strobel.assembler.metadata.MetadataHelper.isSubType(MetadataHelper.java:1283)
        //     at com.strobel.assembler.metadata.MetadataHelper.isSubType(MetadataHelper.java:1283)
        //     at com.strobel.assembler.metadata.MetadataHelper.isSubType(MetadataHelper.java:1283)
        //     at com.strobel.assembler.metadata.MetadataHelper.isSubType(MetadataHelper.java:1283)
        //     at com.strobel.assembler.metadata.MetadataHelper.isSubType(MetadataHelper.java:1283)
        //     at com.strobel.assembler.metadata.MetadataHelper.isSubType(MetadataHelper.java:1283)
        //     at com.strobel.assembler.metadata.MetadataHelper.isSubType(MetadataHelper.java:1283)
        //     at com.strobel.assembler.metadata.MetadataHelper.isSubType(MetadataHelper.java:1283)
        //     at com.strobel.assembler.metadata.MetadataHelper.isSubType(MetadataHelper.java:1283)
        //     at com.strobel.assembler.metadata.MetadataHelper.isSubType(MetadataHelper.java:1283)
        //     at com.strobel.assembler.metadata.MetadataHelper.isSubType(MetadataHelper.java:1283)
        //     at com.strobel.assembler.metadata.MetadataHelper.isSubType(MetadataHelper.java:1283)
        //     at com.strobel.assembler.metadata.MetadataHelper.isSubType(MetadataHelper.java:1283)
        //     at com.strobel.assembler.metadata.MetadataHelper.isSubType(MetadataHelper.java:1283)
        //     at com.strobel.assembler.metadata.MetadataHelper.isSubType(MetadataHelper.java:1283)
        //     at com.strobel.assembler.metadata.MetadataHelper.isSubType(MetadataHelper.java:1283)
        //     at com.strobel.assembler.metadata.MetadataHelper.isSubType(MetadataHelper.java:1283)
        //     at com.strobel.assembler.metadata.MetadataHelper.isSubType(MetadataHelper.java:1283)
        //     at com.strobel.assembler.metadata.MetadataHelper.isSubType(MetadataHelper.java:1283)
        //     at com.strobel.assembler.metadata.MetadataHelper.isSubType(MetadataHelper.java:1283)
        //     at com.strobel.assembler.metadata.MetadataHelper.isSubType(MetadataHelper.java:1283)
        //     at com.strobel.assembler.metadata.MetadataHelper.isSubType(MetadataHelper.java:1283)
        //     at com.strobel.assembler.metadata.MetadataHelper.isSubType(MetadataHelper.java:1283)
        //     at com.strobel.assembler.metadata.MetadataHelper.isSubType(MetadataHelper.java:1283)
        //     at com.strobel.assembler.metadata.MetadataHelper.isSubType(MetadataHelper.java:1283)
        //     at com.strobel.assembler.metadata.MetadataHelper.isSubType(MetadataHelper.java:1283)
        //     at com.strobel.assembler.metadata.MetadataHelper.isSubType(MetadataHelper.java:1283)
        //     at com.strobel.assembler.metadata.MetadataHelper.isSubType(MetadataHelper.java:1283)
        //     at com.strobel.assembler.metadata.MetadataHelper.isSubType(MetadataHelper.java:1283)
        //     at com.strobel.assembler.metadata.MetadataHelper.isSubType(MetadataHelper.java:1283)
        //     at com.strobel.assembler.metadata.MetadataHelper.isSubType(MetadataHelper.java:1283)
        //     at com.strobel.assembler.metadata.MetadataHelper.isSubType(MetadataHelper.java:1283)
        //     at com.strobel.assembler.metadata.MetadataHelper.isSubType(MetadataHelper.java:1283)
        //     at com.strobel.assembler.metadata.MetadataHelper.isSubType(MetadataHelper.java:1283)
        //     at com.strobel.assembler.metadata.MetadataHelper.isSubType(MetadataHelper.java:1283)
        //     at com.strobel.assembler.metadata.MetadataHelper.isSubType(MetadataHelper.java:1283)
        //     at com.strobel.assembler.metadata.MetadataHelper.isSubType(MetadataHelper.java:1283)
        //     at com.strobel.assembler.metadata.MetadataHelper.isSubType(MetadataHelper.java:1283)
        //     at com.strobel.assembler.metadata.MetadataHelper.isSubType(MetadataHelper.java:1283)
        //     at com.strobel.assembler.metadata.MetadataHelper.isSubType(MetadataHelper.java:1283)
        //     at com.strobel.assembler.metadata.MetadataHelper.isSubType(MetadataHelper.java:1283)
        //     at com.strobel.assembler.metadata.MetadataHelper.isSubType(MetadataHelper.java:1283)
        //     at com.strobel.assembler.metadata.MetadataHelper.isSubType(MetadataHelper.java:1283)
        //     at com.strobel.assembler.metadata.MetadataHelper.isSubType(MetadataHelper.java:1283)
        //     at com.strobel.assembler.metadata.MetadataHelper.isSubType(MetadataHelper.java:1283)
        //     at com.strobel.assembler.metadata.MetadataHelper.isSubType(MetadataHelper.java:1283)
        //     at com.strobel.assembler.metadata.MetadataHelper.isSubType(MetadataHelper.java:1283)
        //     at com.strobel.assembler.metadata.MetadataHelper.isSubType(MetadataHelper.java:1283)
        //     at com.strobel.assembler.metadata.MetadataHelper.isSubType(MetadataHelper.java:1283)
        //     at com.strobel.assembler.metadata.MetadataHelper.isSubType(MetadataHelper.java:1283)
        //     at com.strobel.assembler.metadata.MetadataHelper.isSubType(MetadataHelper.java:1283)
        //     at com.strobel.assembler.metadata.MetadataHelper.isSubType(MetadataHelper.java:1283)
        //     at com.strobel.assembler.metadata.MetadataHelper.isSubType(MetadataHelper.java:1283)
        //     at com.strobel.assembler.metadata.MetadataHelper.isSubType(MetadataHelper.java:1283)
        //     at com.strobel.assembler.metadata.MetadataHelper.isSubType(MetadataHelper.java:1283)
        //     at com.strobel.assembler.metadata.MetadataHelper.isSubType(MetadataHelper.java:1283)
        //     at com.strobel.assembler.metadata.MetadataHelper.isSubType(MetadataHelper.java:1283)
        //     at com.strobel.assembler.metadata.MetadataHelper.isSubType(MetadataHelper.java:1283)
        //     at com.strobel.assembler.metadata.MetadataHelper.isSubType(MetadataHelper.java:1283)
        //     at com.strobel.assembler.metadata.MetadataHelper.isSubType(MetadataHelper.java:1283)
        //     at com.strobel.assembler.metadata.MetadataHelper.isSubType(MetadataHelper.java:1283)
        //     at com.strobel.assembler.metadata.MetadataHelper.isSubType(MetadataHelper.java:1283)
        //     at com.strobel.assembler.metadata.MetadataHelper.isSubType(MetadataHelper.java:1283)
        //     at com.strobel.assembler.metadata.MetadataHelper.isSubType(MetadataHelper.java:1283)
        //     at com.strobel.assembler.metadata.MetadataHelper.isSubType(MetadataHelper.java:1283)
        //     at com.strobel.assembler.metadata.MetadataHelper.isSubType(MetadataHelper.java:1283)
        //     at com.strobel.assembler.metadata.MetadataHelper.isSubType(MetadataHelper.java:1283)
        //     at com.strobel.assembler.metadata.MetadataHelper.isSubType(MetadataHelper.java:1283)
        //     at com.strobel.assembler.metadata.MetadataHelper.isSubType(MetadataHelper.java:1283)
        //     at com.strobel.assembler.metadata.MetadataHelper.isSubType(MetadataHelper.java:1283)
        //     at com.strobel.assembler.metadata.MetadataHelper.isSubType(MetadataHelper.java:1283)
        //     at com.strobel.assembler.metadata.MetadataHelper.isSubType(MetadataHelper.java:1283)
        //     at com.strobel.assembler.metadata.MetadataHelper.isSubType(MetadataHelper.java:1283)
        //     at com.strobel.assembler.metadata.MetadataHelper.isSubType(MetadataHelper.java:1283)
        //     at com.strobel.assembler.metadata.MetadataHelper.isSubType(MetadataHelper.java:1283)
        //     at com.strobel.assembler.metadata.MetadataHelper.isSubType(MetadataHelper.java:1283)
        //     at com.strobel.assembler.metadata.MetadataHelper.isSubType(MetadataHelper.java:1283)
        //     at com.strobel.assembler.metadata.MetadataHelper.isSubType(MetadataHelper.java:1283)
        //     at com.strobel.assembler.metadata.MetadataHelper.isSubType(MetadataHelper.java:1283)
        //     at com.strobel.assembler.metadata.MetadataHelper.isSubType(MetadataHelper.java:1283)
        //     at com.strobel.assembler.metadata.MetadataHelper.isSubType(MetadataHelper.java:1283)
        //     at com.strobel.assembler.metadata.MetadataHelper.isSubType(MetadataHelper.java:1283)
        //     at com.strobel.assembler.metadata.MetadataHelper.isSubType(MetadataHelper.java:1283)
        //     at com.strobel.assembler.metadata.MetadataHelper.isSubType(MetadataHelper.java:1283)
        //     at com.strobel.assembler.metadata.MetadataHelper.isSubType(MetadataHelper.java:1283)
        //     at com.strobel.assembler.metadata.MetadataHelper.isSubType(MetadataHelper.java:1283)
        //     at com.strobel.assembler.metadata.MetadataHelper.isSubType(MetadataHelper.java:1283)
        //     at com.strobel.assembler.metadata.MetadataHelper.isSubType(MetadataHelper.java:1283)
        //     at com.strobel.assembler.metadata.MetadataHelper.isSubType(MetadataHelper.java:1283)
        //     at com.strobel.assembler.metadata.MetadataHelper.isSubType(MetadataHelper.java:1283)
        //     at com.strobel.assembler.metadata.MetadataHelper.isSubType(MetadataHelper.java:1283)
        //     at com.strobel.assembler.metadata.MetadataHelper.isSubType(MetadataHelper.java:1283)
        //     at com.strobel.assembler.metadata.MetadataHelper.isSubType(MetadataHelper.java:1283)
        //     at com.strobel.assembler.metadata.MetadataHelper.isSubType(MetadataHelper.java:1283)
        //     at com.strobel.assembler.metadata.MetadataHelper.isSubType(MetadataHelper.java:1283)
        //     at com.strobel.assembler.metadata.MetadataHelper.isSubType(MetadataHelper.java:1283)
        //     at com.strobel.assembler.metadata.MetadataHelper.isSubType(MetadataHelper.java:1283)
        //     at com.strobel.assembler.metadata.MetadataHelper.isSubType(MetadataHelper.java:1283)
        //     at com.strobel.assembler.metadata.MetadataHelper.isSubType(MetadataHelper.java:1283)
        //     at com.strobel.assembler.metadata.MetadataHelper.isSubType(MetadataHelper.java:1283)
        //     at com.strobel.assembler.metadata.MetadataHelper.isSubType(MetadataHelper.java:1283)
        //     at com.strobel.assembler.metadata.MetadataHelper.isSubType(MetadataHelper.java:1283)
        //     at com.strobel.assembler.metadata.MetadataHelper.isSubType(MetadataHelper.java:1283)
        //     at com.strobel.assembler.metadata.MetadataHelper.isSubType(MetadataHelper.java:1283)
        //     at com.strobel.assembler.metadata.MetadataHelper.isSubType(MetadataHelper.java:1283)
        //     at com.strobel.assembler.metadata.MetadataHelper.isSubType(MetadataHelper.java:1283)
        //     at com.strobel.assembler.metadata.MetadataHelper.isSubType(MetadataHelper.java:1283)
        //     at com.strobel.assembler.metadata.MetadataHelper.isSubType(MetadataHelper.java:1283)
        //     at com.strobel.assembler.metadata.MetadataHelper.isSubType(MetadataHelper.java:1283)
        //     at com.strobel.assembler.metadata.MetadataHelper.isSubType(MetadataHelper.java:1283)
        //     at com.strobel.assembler.metadata.MetadataHelper.isSubType(MetadataHelper.java:1283)
        //     at com.strobel.assembler.metadata.MetadataHelper.isSubType(MetadataHelper.java:1283)
        //     at com.strobel.assembler.metadata.MetadataHelper.isSubType(MetadataHelper.java:1283)
        //     at com.strobel.assembler.metadata.MetadataHelper.isSubType(MetadataHelper.java:1283)
        //     at com.strobel.assembler.metadata.MetadataHelper.isSubType(MetadataHelper.java:1283)
        //     at com.strobel.assembler.metadata.MetadataHelper.isSubType(MetadataHelper.java:1283)
        //     at com.strobel.assembler.metadata.MetadataHelper.isSubType(MetadataHelper.java:1283)
        //     at com.strobel.assembler.metadata.MetadataHelper.isSubType(MetadataHelper.java:1283)
        //     at com.strobel.assembler.metadata.MetadataHelper.isSubType(MetadataHelper.java:1283)
        //     at com.strobel.assembler.metadata.MetadataHelper.isSubType(MetadataHelper.java:1283)
        //     at com.strobel.assembler.metadata.MetadataHelper.isSubType(MetadataHelper.java:1283)
        //     at com.strobel.assembler.metadata.MetadataHelper.isSubType(MetadataHelper.java:1283)
        //     at com.strobel.assembler.metadata.MetadataHelper.isSubType(MetadataHelper.java:1283)
        //     at com.strobel.assembler.metadata.MetadataHelper.isSubType(MetadataHelper.java:1283)
        //     at com.strobel.assembler.metadata.MetadataHelper.isSubType(MetadataHelper.java:1283)
        //     at com.strobel.assembler.metadata.MetadataHelper.isSubType(MetadataHelper.java:1283)
        //     at com.strobel.assembler.metadata.MetadataHelper.isSubType(MetadataHelper.java:1283)
        //     at com.strobel.assembler.metadata.MetadataHelper.isSubType(MetadataHelper.java:1283)
        //     at com.strobel.assembler.metadata.MetadataHelper.isSubType(MetadataHelper.java:1283)
        //     at com.strobel.assembler.metadata.MetadataHelper.isSubType(MetadataHelper.java:1283)
        //     at com.strobel.assembler.metadata.MetadataHelper.isSubType(MetadataHelper.java:1283)
        //     at com.strobel.assembler.metadata.MetadataHelper.isSubType(MetadataHelper.java:1283)
        //     at com.strobel.assembler.metadata.MetadataHelper.isSubType(MetadataHelper.java:1283)
        //     at com.strobel.assembler.metadata.MetadataHelper.isSubType(MetadataHelper.java:1283)
        //     at com.strobel.assembler.metadata.MetadataHelper.isSubType(MetadataHelper.java:1283)
        //     at com.strobel.assembler.metadata.MetadataHelper.isSubType(MetadataHelper.java:1283)
        //     at com.strobel.assembler.metadata.MetadataHelper.isSubType(MetadataHelper.java:1283)
        //     at com.strobel.assembler.metadata.MetadataHelper.isSubType(MetadataHelper.java:1283)
        //     at com.strobel.assembler.metadata.MetadataHelper.isSubType(MetadataHelper.java:1283)
        //     at com.strobel.assembler.metadata.MetadataHelper.isSubType(MetadataHelper.java:1283)
        //     at com.strobel.assembler.metadata.MetadataHelper.isSubType(MetadataHelper.java:1283)
        //     at com.strobel.assembler.metadata.MetadataHelper.isSubType(MetadataHelper.java:1283)
        //     at com.strobel.assembler.metadata.MetadataHelper.isSubType(MetadataHelper.java:1283)
        //     at com.strobel.assembler.metadata.MetadataHelper.isSubType(MetadataHelper.java:1283)
        //     at com.strobel.assembler.metadata.MetadataHelper.isSubType(MetadataHelper.java:1283)
        //     at com.strobel.assembler.metadata.MetadataHelper.isSubType(MetadataHelper.java:1283)
        //     at com.strobel.assembler.metadata.MetadataHelper.isSubType(MetadataHelper.java:1283)
        //     at com.strobel.assembler.metadata.MetadataHelper.isSubType(MetadataHelper.java:1283)
        //     at com.strobel.assembler.metadata.MetadataHelper.isSubType(MetadataHelper.java:1283)
        //     at com.strobel.assembler.metadata.MetadataHelper.isSubType(MetadataHelper.java:1283)
        //     at com.strobel.assembler.metadata.MetadataHelper.isSubType(MetadataHelper.java:1283)
        //     at com.strobel.assembler.metadata.MetadataHelper.isSubType(MetadataHelper.java:1283)
        //     at com.strobel.assembler.metadata.MetadataHelper.isSubType(MetadataHelper.java:1283)
        //     at com.strobel.assembler.metadata.MetadataHelper.isSubType(MetadataHelper.java:1283)
        //     at com.strobel.assembler.metadata.MetadataHelper.isSubType(MetadataHelper.java:1283)
        //     at com.strobel.assembler.metadata.MetadataHelper.isSubType(MetadataHelper.java:1283)
        //     at com.strobel.assembler.metadata.MetadataHelper.isSubType(MetadataHelper.java:1283)
        //     at com.strobel.assembler.metadata.MetadataHelper.isSubType(MetadataHelper.java:1283)
        //     at com.strobel.assembler.metadata.MetadataHelper.isSubType(MetadataHelper.java:1283)
        //     at com.strobel.assembler.metadata.MetadataHelper.isSubType(MetadataHelper.java:1283)
        //     at com.strobel.assembler.metadata.MetadataHelper.isSubType(MetadataHelper.java:1283)
        //     at com.strobel.assembler.metadata.MetadataHelper.isSubType(MetadataHelper.java:1283)
        //     at com.strobel.assembler.metadata.MetadataHelper.isSubType(MetadataHelper.java:1283)
        //     at com.strobel.assembler.metadata.MetadataHelper.isSubType(MetadataHelper.java:1283)
        //     at com.strobel.assembler.metadata.MetadataHelper.isSubType(MetadataHelper.java:1283)
        //     at com.strobel.assembler.metadata.MetadataHelper.isSubType(MetadataHelper.java:1283)
        //     at com.strobel.assembler.metadata.MetadataHelper.isSubType(MetadataHelper.java:1283)
        //     at com.strobel.assembler.metadata.MetadataHelper.isSubType(MetadataHelper.java:1283)
        //     at com.strobel.assembler.metadata.MetadataHelper.isSubType(MetadataHelper.java:1283)
        //     at com.strobel.assembler.metadata.MetadataHelper.isSubType(MetadataHelper.java:1283)
        //     at com.strobel.assembler.metadata.MetadataHelper.isSubType(MetadataHelper.java:1283)
        //     at com.strobel.assembler.metadata.MetadataHelper.isSubType(MetadataHelper.java:1283)
        //     at com.strobel.assembler.metadata.MetadataHelper.isSubType(MetadataHelper.java:1283)
        //     at com.strobel.assembler.metadata.MetadataHelper.isSubType(MetadataHelper.java:1283)
        //     at com.strobel.assembler.metadata.MetadataHelper.isSubType(MetadataHelper.java:1283)
        //     at com.strobel.assembler.metadata.MetadataHelper.isSubType(MetadataHelper.java:1283)
        //     at com.strobel.assembler.metadata.MetadataHelper.isSubType(MetadataHelper.java:1283)
        //     at com.strobel.assembler.metadata.MetadataHelper.isSubType(MetadataHelper.java:1283)
        //     at com.strobel.assembler.metadata.MetadataHelper.isSubType(MetadataHelper.java:1283)
        //     at com.strobel.assembler.metadata.MetadataHelper.isSubType(MetadataHelper.java:1283)
        //     at com.strobel.assembler.metadata.MetadataHelper.isSubType(MetadataHelper.java:1283)
        //     at com.strobel.assembler.metadata.MetadataHelper.isSubType(MetadataHelper.java:1283)
        //     at com.strobel.assembler.metadata.MetadataHelper.isSubType(MetadataHelper.java:1283)
        //     at com.strobel.assembler.metadata.MetadataHelper.isSubType(MetadataHelper.java:1283)
        //     at com.strobel.assembler.metadata.MetadataHelper.isSubType(MetadataHelper.java:1283)
        //     at com.strobel.assembler.metadata.MetadataHelper.isSubType(MetadataHelper.java:1283)
        //     at com.strobel.assembler.metadata.MetadataHelper.isSubType(MetadataHelper.java:1283)
        //     at com.strobel.assembler.metadata.MetadataHelper.isSubType(MetadataHelper.java:1283)
        //     at com.strobel.assembler.metadata.MetadataHelper.isSubType(MetadataHelper.java:1283)
        //     at com.strobel.assembler.metadata.MetadataHelper.isSubType(MetadataHelper.java:1283)
        //     at com.strobel.assembler.metadata.MetadataHelper.isSubType(MetadataHelper.java:1283)
        //     at com.strobel.assembler.metadata.MetadataHelper.isSubType(MetadataHelper.java:1283)
        //     at com.strobel.assembler.metadata.MetadataHelper.isSubType(MetadataHelper.java:1283)
        //     at com.strobel.assembler.metadata.MetadataHelper.isSubType(MetadataHelper.java:1283)
        //     at com.strobel.assembler.metadata.MetadataHelper.isSubType(MetadataHelper.java:1283)
        //     at com.strobel.assembler.metadata.MetadataHelper.isSubType(MetadataHelper.java:1283)
        //     at com.strobel.assembler.metadata.MetadataHelper.isSubType(MetadataHelper.java:1283)
        //     at com.strobel.assembler.metadata.MetadataHelper.isSubType(MetadataHelper.java:1283)
        //     at com.strobel.assembler.metadata.MetadataHelper.isSubType(MetadataHelper.java:1283)
        //     at com.strobel.assembler.metadata.MetadataHelper.isSubType(MetadataHelper.java:1283)
        //     at com.strobel.assembler.metadata.MetadataHelper.isSubType(MetadataHelper.java:1283)
        //     at com.strobel.assembler.metadata.MetadataHelper.isSubType(MetadataHelper.java:1283)
        //     at com.strobel.assembler.metadata.MetadataHelper.isSubType(MetadataHelper.java:1283)
        //     at com.strobel.assembler.metadata.MetadataHelper.isSubType(MetadataHelper.java:1283)
        //     at com.strobel.assembler.metadata.MetadataHelper.isSubType(MetadataHelper.java:1283)
        //     at com.strobel.assembler.metadata.MetadataHelper.isSubType(MetadataHelper.java:1283)
        //     at com.strobel.assembler.metadata.MetadataHelper.isSubType(MetadataHelper.java:1283)
        //     at com.strobel.assembler.metadata.MetadataHelper.isSubType(MetadataHelper.java:1283)
        //     at com.strobel.assembler.metadata.MetadataHelper.isSubType(MetadataHelper.java:1283)
        //     at com.strobel.assembler.metadata.MetadataHelper.isSubType(MetadataHelper.java:1283)
        //     at com.strobel.assembler.metadata.MetadataHelper.isSubType(MetadataHelper.java:1283)
        //     at com.strobel.assembler.metadata.MetadataHelper.isSubType(MetadataHelper.java:1283)
        //     at com.strobel.assembler.metadata.MetadataHelper.isSubType(MetadataHelper.java:1283)
        //     at com.strobel.assembler.metadata.MetadataHelper.isSubType(MetadataHelper.java:1283)
        //     at com.strobel.assembler.metadata.MetadataHelper.isSubType(MetadataHelper.java:1283)
        //     at com.strobel.assembler.metadata.MetadataHelper.isSubType(MetadataHelper.java:1283)
        //     at com.strobel.assembler.metadata.MetadataHelper.isSubType(MetadataHelper.java:1283)
        //     at com.strobel.assembler.metadata.MetadataHelper.isSubType(MetadataHelper.java:1283)
        //     at com.strobel.assembler.metadata.MetadataHelper.isSubType(MetadataHelper.java:1283)
        //     at com.strobel.assembler.metadata.MetadataHelper.isSubType(MetadataHelper.java:1283)
        //     at com.strobel.assembler.metadata.MetadataHelper.isSubType(MetadataHelper.java:1283)
        //     at com.strobel.assembler.metadata.MetadataHelper.isSubType(MetadataHelper.java:1283)
        //     at com.strobel.assembler.metadata.MetadataHelper.isSubType(MetadataHelper.java:1283)
        //     at com.strobel.assembler.metadata.MetadataHelper.isSubType(MetadataHelper.java:1283)
        //     at com.strobel.assembler.metadata.MetadataHelper.isSubType(MetadataHelper.java:1283)
        //     at com.strobel.assembler.metadata.MetadataHelper.isSubType(MetadataHelper.java:1283)
        //     at com.strobel.assembler.metadata.MetadataHelper.isSubType(MetadataHelper.java:1283)
        //     at com.strobel.assembler.metadata.MetadataHelper.isSubType(MetadataHelper.java:1283)
        //     at com.strobel.assembler.metadata.MetadataHelper.isSubType(MetadataHelper.java:1283)
        //     at com.strobel.assembler.metadata.MetadataHelper.isSubType(MetadataHelper.java:1283)
        //     at com.strobel.assembler.metadata.MetadataHelper.isSubType(MetadataHelper.java:1283)
        //     at com.strobel.assembler.metadata.MetadataHelper.isSubType(MetadataHelper.java:1283)
        //     at com.strobel.assembler.metadata.MetadataHelper.isSubType(MetadataHelper.java:1283)
        //     at com.strobel.assembler.metadata.MetadataHelper.isSubType(MetadataHelper.java:1283)
        //     at com.strobel.assembler.metadata.MetadataHelper.isSubType(MetadataHelper.java:1283)
        //     at com.strobel.assembler.metadata.MetadataHelper.isSubType(MetadataHelper.java:1283)
        //     at com.strobel.assembler.metadata.MetadataHelper.isSubType(MetadataHelper.java:1283)
        //     at com.strobel.assembler.metadata.MetadataHelper.isSubType(MetadataHelper.java:1283)
        //     at com.strobel.assembler.metadata.MetadataHelper.isSubType(MetadataHelper.java:1283)
        //     at com.strobel.assembler.metadata.MetadataHelper.isSubType(MetadataHelper.java:1283)
        //     at com.strobel.assembler.metadata.MetadataHelper.isSubType(MetadataHelper.java:1283)
        //     at com.strobel.assembler.metadata.MetadataHelper.isSubType(MetadataHelper.java:1283)
        //     at com.strobel.assembler.metadata.MetadataHelper.isSubType(MetadataHelper.java:1283)
        //     at com.strobel.assembler.metadata.MetadataHelper.isSubType(MetadataHelper.java:1283)
        //     at com.strobel.assembler.metadata.MetadataHelper.isSubType(MetadataHelper.java:1283)
        //     at com.strobel.assembler.metadata.MetadataHelper.isSubType(MetadataHelper.java:1283)
        //     at com.strobel.assembler.metadata.MetadataHelper.isSubType(MetadataHelper.java:1283)
        //     at com.strobel.assembler.metadata.MetadataHelper.isSubType(MetadataHelper.java:1283)
        //     at com.strobel.assembler.metadata.MetadataHelper.isSubType(MetadataHelper.java:1283)
        //     at com.strobel.assembler.metadata.MetadataHelper.isSubType(MetadataHelper.java:1283)
        //     at com.strobel.assembler.metadata.MetadataHelper.isSubType(MetadataHelper.java:1283)
        //     at com.strobel.assembler.metadata.MetadataHelper.isSubType(MetadataHelper.java:1283)
        //     at com.strobel.assembler.metadata.MetadataHelper.isSubType(MetadataHelper.java:1283)
        //     at com.strobel.assembler.metadata.MetadataHelper.isSubType(MetadataHelper.java:1283)
        //     at com.strobel.assembler.metadata.MetadataHelper.isSubType(MetadataHelper.java:1283)
        //     at com.strobel.assembler.metadata.MetadataHelper.isSubType(MetadataHelper.java:1283)
        //     at com.strobel.assembler.metadata.MetadataHelper.isSubType(MetadataHelper.java:1283)
        //     at com.strobel.assembler.metadata.MetadataHelper.isSubType(MetadataHelper.java:1283)
        //     at com.strobel.assembler.metadata.MetadataHelper.isSubType(MetadataHelper.java:1283)
        //     at com.strobel.assembler.metadata.MetadataHelper.isSubType(MetadataHelper.java:1283)
        //     at com.strobel.assembler.metadata.MetadataHelper.isSubType(MetadataHelper.java:1283)
        //     at com.strobel.assembler.metadata.MetadataHelper.isSubType(MetadataHelper.java:1283)
        //     at com.strobel.assembler.metadata.MetadataHelper.isSubType(MetadataHelper.java:1283)
        //     at com.strobel.assembler.metadata.MetadataHelper.isSubType(MetadataHelper.java:1283)
        //     at com.strobel.assembler.metadata.MetadataHelper.isSubType(MetadataHelper.java:1283)
        //     at com.strobel.assembler.metadata.MetadataHelper.isSubType(MetadataHelper.java:1283)
        //     at com.strobel.assembler.metadata.MetadataHelper.isSubType(MetadataHelper.java:1283)
        //     at com.strobel.assembler.metadata.MetadataHelper.isSubType(MetadataHelper.java:1283)
        //     at com.strobel.assembler.metadata.MetadataHelper.isSubType(MetadataHelper.java:1283)
        //     at com.strobel.assembler.metadata.MetadataHelper.isSubType(MetadataHelper.java:1283)
        //     at com.strobel.assembler.metadata.MetadataHelper.isSubType(MetadataHelper.java:1283)
        //     at com.strobel.assembler.metadata.MetadataHelper.isSubType(MetadataHelper.java:1283)
        //     at com.strobel.assembler.metadata.MetadataHelper.isSubType(MetadataHelper.java:1283)
        //     at com.strobel.assembler.metadata.MetadataHelper.isSubType(MetadataHelper.java:1283)
        //     at com.strobel.assembler.metadata.MetadataHelper.isSubType(MetadataHelper.java:1283)
        //     at com.strobel.assembler.metadata.MetadataHelper.isSubType(MetadataHelper.java:1283)
        //     at com.strobel.assembler.metadata.MetadataHelper.isSubType(MetadataHelper.java:1283)
        //     at com.strobel.assembler.metadata.MetadataHelper.isSubType(MetadataHelper.java:1283)
        //     at com.strobel.assembler.metadata.MetadataHelper.isSubType(MetadataHelper.java:1283)
        //     at com.strobel.assembler.metadata.MetadataHelper.isSubType(MetadataHelper.java:1283)
        //     at com.strobel.assembler.metadata.MetadataHelper.isSubType(MetadataHelper.java:1283)
        //     at com.strobel.assembler.metadata.MetadataHelper.isSubType(MetadataHelper.java:1283)
        //     at com.strobel.assembler.metadata.MetadataHelper.isSubType(MetadataHelper.java:1283)
        //     at com.strobel.assembler.metadata.MetadataHelper.isSubType(MetadataHelper.java:1283)
        //     at com.strobel.assembler.metadata.MetadataHelper.isSubType(MetadataHelper.java:1283)
        //     at com.strobel.assembler.metadata.MetadataHelper.isSubType(MetadataHelper.java:1283)
        //     at com.strobel.assembler.metadata.MetadataHelper.isSubType(MetadataHelper.java:1283)
        //     at com.strobel.assembler.metadata.MetadataHelper.isSubType(MetadataHelper.java:1283)
        //     at com.strobel.assembler.metadata.MetadataHelper.isSubType(MetadataHelper.java:1283)
        //     at com.strobel.assembler.metadata.MetadataHelper.isSubType(MetadataHelper.java:1283)
        //     at com.strobel.assembler.metadata.MetadataHelper.isSubType(MetadataHelper.java:1283)
        //     at com.strobel.assembler.metadata.MetadataHelper.isSubType(MetadataHelper.java:1283)
        //     at com.strobel.assembler.metadata.MetadataHelper.isSubType(MetadataHelper.java:1283)
        //     at com.strobel.assembler.metadata.MetadataHelper.isSubType(MetadataHelper.java:1283)
        //     at com.strobel.assembler.metadata.MetadataHelper.isSubType(MetadataHelper.java:1283)
        //     at com.strobel.assembler.metadata.MetadataHelper.isSubType(MetadataHelper.java:1283)
        //     at com.strobel.assembler.metadata.MetadataHelper.isSubType(MetadataHelper.java:1283)
        //     at com.strobel.assembler.metadata.MetadataHelper.isSubType(MetadataHelper.java:1283)
        //     at com.strobel.assembler.metadata.MetadataHelper.isSubType(MetadataHelper.java:1283)
        //     at com.strobel.assembler.metadata.MetadataHelper.isSubType(MetadataHelper.java:1283)
        //     at com.strobel.assembler.metadata.MetadataHelper.isSubType(MetadataHelper.java:1283)
        //     at com.strobel.assembler.metadata.MetadataHelper.isSubType(MetadataHelper.java:1283)
        //     at com.strobel.assembler.metadata.MetadataHelper.isSubType(MetadataHelper.java:1283)
        //     at com.strobel.assembler.metadata.MetadataHelper.isSubType(MetadataHelper.java:1283)
        //     at com.strobel.assembler.metadata.MetadataHelper.isSubType(MetadataHelper.java:1283)
        //     at com.strobel.assembler.metadata.MetadataHelper.isSubType(MetadataHelper.java:1283)
        //     at com.strobel.assembler.metadata.MetadataHelper.isSubType(MetadataHelper.java:1283)
        //     at com.strobel.assembler.metadata.MetadataHelper.isSubType(MetadataHelper.java:1283)
        //     at com.strobel.assembler.metadata.MetadataHelper.isSubType(MetadataHelper.java:1283)
        //     at com.strobel.assembler.metadata.MetadataHelper.isSubType(MetadataHelper.java:1283)
        //     at com.strobel.assembler.metadata.MetadataHelper.isSubType(MetadataHelper.java:1283)
        //     at com.strobel.assembler.metadata.MetadataHelper.isSubType(MetadataHelper.java:1283)
        //     at com.strobel.assembler.metadata.MetadataHelper.isSubType(MetadataHelper.java:1283)
        //     at com.strobel.assembler.metadata.MetadataHelper.isSubType(MetadataHelper.java:1283)
        //     at com.strobel.assembler.metadata.MetadataHelper.isSubType(MetadataHelper.java:1283)
        //     at com.strobel.assembler.metadata.MetadataHelper.isSubType(MetadataHelper.java:1283)
        //     at com.strobel.assembler.metadata.MetadataHelper.isSubType(MetadataHelper.java:1283)
        //     at com.strobel.assembler.metadata.MetadataHelper.isSubType(MetadataHelper.java:1283)
        //     at com.strobel.assembler.metadata.MetadataHelper.isSubType(MetadataHelper.java:1283)
        //     at com.strobel.assembler.metadata.MetadataHelper.isSubType(MetadataHelper.java:1283)
        //     at com.strobel.assembler.metadata.MetadataHelper.isSubType(MetadataHelper.java:1283)
        //     at com.strobel.assembler.metadata.MetadataHelper.isSubType(MetadataHelper.java:1283)
        //     at com.strobel.assembler.metadata.MetadataHelper.isSubType(MetadataHelper.java:1283)
        //     at com.strobel.assembler.metadata.MetadataHelper.isSubType(MetadataHelper.java:1283)
        //     at com.strobel.assembler.metadata.MetadataHelper.isSubType(MetadataHelper.java:1283)
        //     at com.strobel.assembler.metadata.MetadataHelper.isSubType(MetadataHelper.java:1283)
        //     at com.strobel.assembler.metadata.MetadataHelper.isSubType(MetadataHelper.java:1283)
        //     at com.strobel.assembler.metadata.MetadataHelper.isSubType(MetadataHelper.java:1283)
        //     at com.strobel.assembler.metadata.MetadataHelper.isSubType(MetadataHelper.java:1283)
        //     at com.strobel.assembler.metadata.MetadataHelper.isSubType(MetadataHelper.java:1283)
        //     at com.strobel.assembler.metadata.MetadataHelper.isSubType(MetadataHelper.java:1283)
        //     at com.strobel.assembler.metadata.MetadataHelper.isSubType(MetadataHelper.java:1283)
        //     at com.strobel.assembler.metadata.MetadataHelper.isSubType(MetadataHelper.java:1283)
        //     at com.strobel.assembler.metadata.MetadataHelper.isSubType(MetadataHelper.java:1283)
        //     at com.strobel.assembler.metadata.MetadataHelper.isSubType(MetadataHelper.java:1283)
        //     at com.strobel.assembler.metadata.MetadataHelper.isSubType(MetadataHelper.java:1283)
        //     at com.strobel.assembler.metadata.MetadataHelper.isSubType(MetadataHelper.java:1283)
        //     at com.strobel.assembler.metadata.MetadataHelper.isSubType(MetadataHelper.java:1283)
        //     at com.strobel.assembler.metadata.MetadataHelper.isSubType(MetadataHelper.java:1283)
        //     at com.strobel.assembler.metadata.MetadataHelper.isSubType(MetadataHelper.java:1283)
        //     at com.strobel.assembler.metadata.MetadataHelper.isSubType(MetadataHelper.java:1283)
        //     at com.strobel.assembler.metadata.MetadataHelper.isSubType(MetadataHelper.java:1283)
        //     at com.strobel.assembler.metadata.MetadataHelper.isSubType(MetadataHelper.java:1283)
        //     at com.strobel.assembler.metadata.MetadataHelper.isSubType(MetadataHelper.java:1283)
        //     at com.strobel.assembler.metadata.MetadataHelper.isSubType(MetadataHelper.java:1283)
        //     at com.strobel.assembler.metadata.MetadataHelper.isSubType(MetadataHelper.java:1283)
        //     at com.strobel.assembler.metadata.MetadataHelper.isSubType(MetadataHelper.java:1283)
        //     at com.strobel.assembler.metadata.MetadataHelper.isSubType(MetadataHelper.java:1283)
        //     at com.strobel.assembler.metadata.MetadataHelper.isSubType(MetadataHelper.java:1283)
        //     at com.strobel.assembler.metadata.MetadataHelper.isSubType(MetadataHelper.java:1283)
        //     at com.strobel.assembler.metadata.MetadataHelper.isSubType(MetadataHelper.java:1283)
        //     at com.strobel.assembler.metadata.MetadataHelper.isSubType(MetadataHelper.java:1283)
        //     at com.strobel.assembler.metadata.MetadataHelper.isSubType(MetadataHelper.java:1283)
        //     at com.strobel.assembler.metadata.MetadataHelper.isSubType(MetadataHelper.java:1283)
        //     at com.strobel.assembler.metadata.MetadataHelper.isSubType(MetadataHelper.java:1283)
        //     at com.strobel.assembler.metadata.MetadataHelper.isSubType(MetadataHelper.java:1283)
        //     at com.strobel.assembler.metadata.MetadataHelper.isSubType(MetadataHelper.java:1283)
        //     at com.strobel.assembler.metadata.MetadataHelper.isSubType(MetadataHelper.java:1283)
        //     at com.strobel.assembler.metadata.MetadataHelper.isSubType(MetadataHelper.java:1283)
        //     at com.strobel.assembler.metadata.MetadataHelper.isSubType(MetadataHelper.java:1283)
        //     at com.strobel.assembler.metadata.MetadataHelper.isSubType(MetadataHelper.java:1283)
        //     at com.strobel.assembler.metadata.MetadataHelper.isSubType(MetadataHelper.java:1283)
        //     at com.strobel.assembler.metadata.MetadataHelper.isSubType(MetadataHelper.java:1283)
        //     at com.strobel.assembler.metadata.MetadataHelper.isSubType(MetadataHelper.java:1283)
        //     at com.strobel.assembler.metadata.MetadataHelper.isSubType(MetadataHelper.java:1283)
        //     at com.strobel.assembler.metadata.MetadataHelper.isSubType(MetadataHelper.java:1283)
        //     at com.strobel.assembler.metadata.MetadataHelper.isSubType(MetadataHelper.java:1283)
        //     at com.strobel.assembler.metadata.MetadataHelper.isSubType(MetadataHelper.java:1283)
        //     at com.strobel.assembler.metadata.MetadataHelper.isSubType(MetadataHelper.java:1283)
        //     at com.strobel.assembler.metadata.MetadataHelper.isSubType(MetadataHelper.java:1283)
        //     at com.strobel.assembler.metadata.MetadataHelper.isSubType(MetadataHelper.java:1283)
        //     at com.strobel.assembler.metadata.MetadataHelper.isSubType(MetadataHelper.java:1283)
        //     at com.strobel.assembler.metadata.MetadataHelper.isSubType(MetadataHelper.java:1283)
        //     at com.strobel.assembler.metadata.MetadataHelper.isSubType(MetadataHelper.java:1283)
        //     at com.strobel.assembler.metadata.MetadataHelper.isSubType(MetadataHelper.java:1283)
        //     at com.strobel.assembler.metadata.MetadataHelper.isSubType(MetadataHelper.java:1283)
        //     at com.strobel.assembler.metadata.MetadataHelper.isSubType(MetadataHelper.java:1283)
        //     at com.strobel.assembler.metadata.MetadataHelper.isSubType(MetadataHelper.java:1283)
        //     at com.strobel.assembler.metadata.MetadataHelper.isSubType(MetadataHelper.java:1283)
        //     at com.strobel.assembler.metadata.MetadataHelper.isSubType(MetadataHelper.java:1283)
        //     at com.strobel.assembler.metadata.MetadataHelper.isSubType(MetadataHelper.java:1283)
        //     at com.strobel.assembler.metadata.MetadataHelper.isSubType(MetadataHelper.java:1283)
        //     at com.strobel.assembler.metadata.MetadataHelper.isSubType(MetadataHelper.java:1283)
        //     at com.strobel.assembler.metadata.MetadataHelper.isSubType(MetadataHelper.java:1283)
        //     at com.strobel.assembler.metadata.MetadataHelper.isSubType(MetadataHelper.java:1283)
        //     at com.strobel.assembler.metadata.MetadataHelper.isSubType(MetadataHelper.java:1283)
        //     at com.strobel.assembler.metadata.MetadataHelper.isSubType(MetadataHelper.java:1283)
        //     at com.strobel.assembler.metadata.MetadataHelper.isSubType(MetadataHelper.java:1283)
        //     at com.strobel.assembler.metadata.MetadataHelper.isSubType(MetadataHelper.java:1283)
        //     at com.strobel.assembler.metadata.MetadataHelper.isSubType(MetadataHelper.java:1283)
        //     at com.strobel.assembler.metadata.MetadataHelper.isSubType(MetadataHelper.java:1283)
        //     at com.strobel.assembler.metadata.MetadataHelper.isSubType(MetadataHelper.java:1283)
        //     at com.strobel.assembler.metadata.MetadataHelper.isSubType(MetadataHelper.java:1283)
        //     at com.strobel.assembler.metadata.MetadataHelper.isSubType(MetadataHelper.java:1283)
        //     at com.strobel.assembler.metadata.MetadataHelper.isSubType(MetadataHelper.java:1283)
        //     at com.strobel.assembler.metadata.MetadataHelper.isSubType(MetadataHelper.java:1283)
        //     at com.strobel.assembler.metadata.MetadataHelper.isSubType(MetadataHelper.java:1283)
        //     at com.strobel.assembler.metadata.MetadataHelper.isSubType(MetadataHelper.java:1283)
        //     at com.strobel.assembler.metadata.MetadataHelper.isSubType(MetadataHelper.java:1283)
        //     at com.strobel.assembler.metadata.MetadataHelper.isSubType(MetadataHelper.java:1283)
        //     at com.strobel.assembler.metadata.MetadataHelper.isSubType(MetadataHelper.java:1283)
        //     at com.strobel.assembler.metadata.MetadataHelper.isSubType(MetadataHelper.java:1283)
        //     at com.strobel.assembler.metadata.MetadataHelper.isSubType(MetadataHelper.java:1283)
        //     at com.strobel.assembler.metadata.MetadataHelper.isSubType(MetadataHelper.java:1283)
        //     at com.strobel.assembler.metadata.MetadataHelper.isSubType(MetadataHelper.java:1283)
        //     at com.strobel.assembler.metadata.MetadataHelper.isSubType(MetadataHelper.java:1283)
        //     at com.strobel.assembler.metadata.MetadataHelper.isSubType(MetadataHelper.java:1283)
        //     at com.strobel.assembler.metadata.MetadataHelper.isSubType(MetadataHelper.java:1283)
        //     at com.strobel.assembler.metadata.MetadataHelper.isSubType(MetadataHelper.java:1283)
        //     at com.strobel.assembler.metadata.MetadataHelper.isSubType(MetadataHelper.java:1283)
        //     at com.strobel.assembler.metadata.MetadataHelper.isSubType(MetadataHelper.java:1283)
        //     at com.strobel.assembler.metadata.MetadataHelper.isSubType(MetadataHelper.java:1283)
        //     at com.strobel.assembler.metadata.MetadataHelper.isSubType(MetadataHelper.java:1283)
        //     at com.strobel.assembler.metadata.MetadataHelper.isSubType(MetadataHelper.java:1283)
        //     at com.strobel.assembler.metadata.MetadataHelper.isSubType(MetadataHelper.java:1283)
        //     at com.strobel.assembler.metadata.MetadataHelper.isSubType(MetadataHelper.java:1283)
        //     at com.strobel.assembler.metadata.MetadataHelper.isSubType(MetadataHelper.java:1283)
        //     at com.strobel.assembler.metadata.MetadataHelper.isSubType(MetadataHelper.java:1283)
        //     at com.strobel.assembler.metadata.MetadataHelper.isSubType(MetadataHelper.java:1283)
        //     at com.strobel.assembler.metadata.MetadataHelper.isSubType(MetadataHelper.java:1283)
        //     at com.strobel.assembler.metadata.MetadataHelper.isSubType(MetadataHelper.java:1283)
        //     at com.strobel.assembler.metadata.MetadataHelper.isSubType(MetadataHelper.java:1283)
        //     at com.strobel.assembler.metadata.MetadataHelper.isSubType(MetadataHelper.java:1283)
        //     at com.strobel.assembler.metadata.MetadataHelper.isSubType(MetadataHelper.java:1283)
        //     at com.strobel.assembler.metadata.MetadataHelper.isSubType(MetadataHelper.java:1283)
        //     at com.strobel.assembler.metadata.MetadataHelper.isSubType(MetadataHelper.java:1283)
        //     at com.strobel.assembler.metadata.MetadataHelper.isSubType(MetadataHelper.java:1283)
        //     at com.strobel.assembler.metadata.MetadataHelper.isSubType(MetadataHelper.java:1283)
        //     at com.strobel.assembler.metadata.MetadataHelper.isSubType(MetadataHelper.java:1283)
        //     at com.strobel.assembler.metadata.MetadataHelper.isSubType(MetadataHelper.java:1283)
        //     at com.strobel.assembler.metadata.MetadataHelper.isSubType(MetadataHelper.java:1283)
        //     at com.strobel.assembler.metadata.MetadataHelper.isSubType(MetadataHelper.java:1283)
        //     at com.strobel.assembler.metadata.MetadataHelper.isSubType(MetadataHelper.java:1283)
        //     at com.strobel.assembler.metadata.MetadataHelper.isSubType(MetadataHelper.java:1283)
        //     at com.strobel.assembler.metadata.MetadataHelper.isSubType(MetadataHelper.java:1283)
        //     at com.strobel.assembler.metadata.MetadataHelper.isSubType(MetadataHelper.java:1283)
        //     at com.strobel.assembler.metadata.MetadataHelper.isSubType(MetadataHelper.java:1283)
        //     at com.strobel.assembler.metadata.MetadataHelper.isSubType(MetadataHelper.java:1283)
        //     at com.strobel.assembler.metadata.MetadataHelper.isSubType(MetadataHelper.java:1283)
        //     at com.strobel.assembler.metadata.MetadataHelper.isSubType(MetadataHelper.java:1283)
        //     at com.strobel.assembler.metadata.MetadataHelper.isSubType(MetadataHelper.java:1283)
        //     at com.strobel.assembler.metadata.MetadataHelper.isSubType(MetadataHelper.java:1283)
        //     at com.strobel.assembler.metadata.MetadataHelper.isSubType(MetadataHelper.java:1283)
        //     at com.strobel.assembler.metadata.MetadataHelper.isSubType(MetadataHelper.java:1283)
        //     at com.strobel.assembler.metadata.MetadataHelper.isSubType(MetadataHelper.java:1283)
        //     at com.strobel.assembler.metadata.MetadataHelper.isSubType(MetadataHelper.java:1283)
        //     at com.strobel.assembler.metadata.MetadataHelper.isSubType(MetadataHelper.java:1283)
        //     at com.strobel.assembler.metadata.MetadataHelper.isSubType(MetadataHelper.java:1283)
        //     at com.strobel.assembler.metadata.MetadataHelper.isSubType(MetadataHelper.java:1283)
        //     at com.strobel.assembler.metadata.MetadataHelper.isSubType(MetadataHelper.java:1283)
        //     at com.strobel.assembler.metadata.MetadataHelper.isSubType(MetadataHelper.java:1283)
        //     at com.strobel.assembler.metadata.MetadataHelper.isSubType(MetadataHelper.java:1283)
        //     at com.strobel.assembler.metadata.MetadataHelper.isSubType(MetadataHelper.java:1283)
        //     at com.strobel.assembler.metadata.MetadataHelper.isSubType(MetadataHelper.java:1283)
        //     at com.strobel.assembler.metadata.MetadataHelper.isSubType(MetadataHelper.java:1283)
        //     at com.strobel.assembler.metadata.MetadataHelper.isSubType(MetadataHelper.java:1283)
        //     at com.strobel.assembler.metadata.MetadataHelper.isSubType(MetadataHelper.java:1283)
        //     at com.strobel.assembler.metadata.MetadataHelper.isSubType(MetadataHelper.java:1283)
        //     at com.strobel.assembler.metadata.MetadataHelper.isSubType(MetadataHelper.java:1283)
        //     at com.strobel.assembler.metadata.MetadataHelper.isSubType(MetadataHelper.java:1283)
        //     at com.strobel.assembler.metadata.MetadataHelper.isSubType(MetadataHelper.java:1283)
        //     at com.strobel.assembler.metadata.MetadataHelper.isSubType(MetadataHelper.java:1283)
        //     at com.strobel.assembler.metadata.MetadataHelper.isSubType(MetadataHelper.java:1283)
        //     at com.strobel.assembler.metadata.MetadataHelper.isSubType(MetadataHelper.java:1283)
        //     at com.strobel.assembler.metadata.MetadataHelper.isSubType(MetadataHelper.java:1283)
        //     at com.strobel.assembler.metadata.MetadataHelper.isSubType(MetadataHelper.java:1283)
        //     at com.strobel.assembler.metadata.MetadataHelper.isSubType(MetadataHelper.java:1283)
        //     at com.strobel.assembler.metadata.MetadataHelper.isSubType(MetadataHelper.java:1283)
        //     at com.strobel.assembler.metadata.MetadataHelper.isSubType(MetadataHelper.java:1283)
        //     at com.strobel.assembler.metadata.MetadataHelper.isSubType(MetadataHelper.java:1283)
        //     at com.strobel.assembler.metadata.MetadataHelper.isSubType(MetadataHelper.java:1283)
        //     at com.strobel.assembler.metadata.MetadataHelper.isSubType(MetadataHelper.java:1283)
        //     at com.strobel.assembler.metadata.MetadataHelper.isSubType(MetadataHelper.java:1283)
        //     at com.strobel.assembler.metadata.MetadataHelper.isSubType(MetadataHelper.java:1283)
        //     at com.strobel.assembler.metadata.MetadataHelper.isSubType(MetadataHelper.java:1283)
        //     at com.strobel.assembler.metadata.MetadataHelper.isSubType(MetadataHelper.java:1283)
        //     at com.strobel.assembler.metadata.MetadataHelper.isSubType(MetadataHelper.java:1283)
        //     at com.strobel.assembler.metadata.MetadataHelper.isSubType(MetadataHelper.java:1283)
        //     at com.strobel.assembler.metadata.MetadataHelper.isSubType(MetadataHelper.java:1283)
        //     at com.strobel.assembler.metadata.MetadataHelper.isSubType(MetadataHelper.java:1283)
        //     at com.strobel.assembler.metadata.MetadataHelper.isSubType(MetadataHelper.java:1283)
        //     at com.strobel.assembler.metadata.MetadataHelper.isSubType(MetadataHelper.java:1283)
        //     at com.strobel.assembler.metadata.MetadataHelper.isSubType(MetadataHelper.java:1283)
        //     at com.strobel.assembler.metadata.MetadataHelper.isSubType(MetadataHelper.java:1283)
        //     at com.strobel.assembler.metadata.MetadataHelper.isSubType(MetadataHelper.java:1283)
        //     at com.strobel.assembler.metadata.MetadataHelper.isSubType(MetadataHelper.java:1283)
        //     at com.strobel.assembler.metadata.MetadataHelper.isSubType(MetadataHelper.java:1283)
        //     at com.strobel.assembler.metadata.MetadataHelper.isSubType(MetadataHelper.java:1283)
        //     at com.strobel.assembler.metadata.MetadataHelper.isSubType(MetadataHelper.java:1283)
        //     at com.strobel.assembler.metadata.MetadataHelper.isSubType(MetadataHelper.java:1283)
        //     at com.strobel.assembler.metadata.MetadataHelper.isSubType(MetadataHelper.java:1283)
        //     at com.strobel.assembler.metadata.MetadataHelper.isSubType(MetadataHelper.java:1283)
        //     at com.strobel.assembler.metadata.MetadataHelper.isSubType(MetadataHelper.java:1283)
        //     at com.strobel.assembler.metadata.MetadataHelper.isSubType(MetadataHelper.java:1283)
        //     at com.strobel.assembler.metadata.MetadataHelper.isSubType(MetadataHelper.java:1283)
        //     at com.strobel.assembler.metadata.MetadataHelper.isSubType(MetadataHelper.java:1283)
        //     at com.strobel.assembler.metadata.MetadataHelper.isSubType(MetadataHelper.java:1283)
        //     at com.strobel.assembler.metadata.MetadataHelper.isSubType(MetadataHelper.java:1283)
        //     at com.strobel.assembler.metadata.MetadataHelper.isSubType(MetadataHelper.java:1283)
        //     at com.strobel.assembler.metadata.MetadataHelper.isSubType(MetadataHelper.java:1283)
        //     at com.strobel.assembler.metadata.MetadataHelper.isSubType(MetadataHelper.java:1283)
        //     at com.strobel.assembler.metadata.MetadataHelper.isSubType(MetadataHelper.java:1283)
        //     at com.strobel.assembler.metadata.MetadataHelper.isSubType(MetadataHelper.java:1283)
        //     at com.strobel.assembler.metadata.MetadataHelper.isSubType(MetadataHelper.java:1283)
        //     at com.strobel.assembler.metadata.MetadataHelper.isSubType(MetadataHelper.java:1283)
        //     at com.strobel.assembler.metadata.MetadataHelper.isSubType(MetadataHelper.java:1283)
        //     at com.strobel.assembler.metadata.MetadataHelper.isSubType(MetadataHelper.java:1283)
        //     at com.strobel.assembler.metadata.MetadataHelper.isSubType(MetadataHelper.java:1283)
        //     at com.strobel.assembler.metadata.MetadataHelper.isSubType(MetadataHelper.java:1283)
        //     at com.strobel.assembler.metadata.MetadataHelper.isSubType(MetadataHelper.java:1283)
        //     at com.strobel.assembler.metadata.MetadataHelper.isSubType(MetadataHelper.java:1283)
        //     at com.strobel.assembler.metadata.MetadataHelper.isSubType(MetadataHelper.java:1283)
        //     at com.strobel.assembler.metadata.MetadataHelper.isSubType(MetadataHelper.java:1283)
        //     at com.strobel.assembler.metadata.MetadataHelper.isSubType(MetadataHelper.java:1283)
        //     at com.strobel.assembler.metadata.MetadataHelper.isSubType(MetadataHelper.java:1283)
        //     at com.strobel.assembler.metadata.MetadataHelper.isSubType(MetadataHelper.java:1283)
        //     at com.strobel.assembler.metadata.MetadataHelper.isSubType(MetadataHelper.java:1283)
        //     at com.strobel.assembler.metadata.MetadataHelper.isSubType(MetadataHelper.java:1283)
        //     at com.strobel.assembler.metadata.MetadataHelper.isSubType(MetadataHelper.java:1283)
        //     at com.strobel.assembler.metadata.MetadataHelper.isSubType(MetadataHelper.java:1283)
        //     at com.strobel.assembler.metadata.MetadataHelper.isSubType(MetadataHelper.java:1283)
        //     at com.strobel.assembler.metadata.MetadataHelper.isSubType(MetadataHelper.java:1283)
        //     at com.strobel.assembler.metadata.MetadataHelper.isSubType(MetadataHelper.java:1283)
        //     at com.strobel.assembler.metadata.MetadataHelper.isSubType(MetadataHelper.java:1283)
        //     at com.strobel.assembler.metadata.MetadataHelper.isSubType(MetadataHelper.java:1283)
        //     at com.strobel.assembler.metadata.MetadataHelper.isSubType(MetadataHelper.java:1283)
        //     at com.strobel.assembler.metadata.MetadataHelper.isSubType(MetadataHelper.java:1283)
        //     at com.strobel.assembler.metadata.MetadataHelper.isSubType(MetadataHelper.java:1283)
        //     at com.strobel.assembler.metadata.MetadataHelper.isSubType(MetadataHelper.java:1283)
        //     at com.strobel.assembler.metadata.MetadataHelper.isSubType(MetadataHelper.java:1283)
        //     at com.strobel.assembler.metadata.MetadataHelper.isSubType(MetadataHelper.java:1283)
        //     at com.strobel.assembler.metadata.MetadataHelper.isSubType(MetadataHelper.java:1283)
        //     at com.strobel.assembler.metadata.MetadataHelper.isSubType(MetadataHelper.java:1283)
        //     at com.strobel.assembler.metadata.MetadataHelper.isSubType(MetadataHelper.java:1283)
        //     at com.strobel.assembler.metadata.MetadataHelper.isSubType(MetadataHelper.java:1283)
        //     at com.strobel.assembler.metadata.MetadataHelper.isSubType(MetadataHelper.java:1283)
        //     at com.strobel.assembler.metadata.MetadataHelper.isSubType(MetadataHelper.java:1283)
        //     at com.strobel.assembler.metadata.MetadataHelper.isSubType(MetadataHelper.java:1283)
        //     at com.strobel.assembler.metadata.MetadataHelper.isSubType(MetadataHelper.java:1283)
        //     at com.strobel.assembler.metadata.MetadataHelper.isSubType(MetadataHelper.java:1283)
        //     at com.strobel.assembler.metadata.MetadataHelper.isSubType(MetadataHelper.java:1283)
        //     at com.strobel.assembler.metadata.MetadataHelper.isSubType(MetadataHelper.java:1283)
        //     at com.strobel.assembler.metadata.MetadataHelper.isSubType(MetadataHelper.java:1283)
        //     at com.strobel.assembler.metadata.MetadataHelper.isSubType(MetadataHelper.java:1283)
        //     at com.strobel.assembler.metadata.MetadataHelper.isSubType(MetadataHelper.java:1283)
        //     at com.strobel.assembler.metadata.MetadataHelper.isSubType(MetadataHelper.java:1283)
        //     at com.strobel.assembler.metadata.MetadataHelper.isSubType(MetadataHelper.java:1283)
        //     at com.strobel.assembler.metadata.MetadataHelper.isSubType(MetadataHelper.java:1283)
        //     at com.strobel.assembler.metadata.MetadataHelper.isSubType(MetadataHelper.java:1283)
        //     at com.strobel.assembler.metadata.MetadataHelper.isSubType(MetadataHelper.java:1283)
        //     at com.strobel.assembler.metadata.MetadataHelper.isSubType(MetadataHelper.java:1283)
        //     at com.strobel.assembler.metadata.MetadataHelper.isSubType(MetadataHelper.java:1283)
        //     at com.strobel.assembler.metadata.MetadataHelper.isSubType(MetadataHelper.java:1283)
        //     at com.strobel.assembler.metadata.MetadataHelper.isSubType(MetadataHelper.java:1283)
        //     at com.strobel.assembler.metadata.MetadataHelper.isSubType(MetadataHelper.java:1283)
        //     at com.strobel.assembler.metadata.MetadataHelper.isSubType(MetadataHelper.java:1283)
        //     at com.strobel.assembler.metadata.MetadataHelper.isSubType(MetadataHelper.java:1283)
        //     at com.strobel.assembler.metadata.MetadataHelper.isSubType(MetadataHelper.java:1283)
        //     at com.strobel.assembler.metadata.MetadataHelper.isSubType(MetadataHelper.java:1283)
        //     at com.strobel.assembler.metadata.MetadataHelper.isSubType(MetadataHelper.java:1283)
        //     at com.strobel.assembler.metadata.MetadataHelper.isSubType(MetadataHelper.java:1283)
        //     at com.strobel.assembler.metadata.MetadataHelper.isSubType(MetadataHelper.java:1283)
        //     at com.strobel.assembler.metadata.MetadataHelper.isSubType(MetadataHelper.java:1283)
        //     at com.strobel.assembler.metadata.MetadataHelper.isSubType(MetadataHelper.java:1283)
        //     at com.strobel.assembler.metadata.MetadataHelper.isSubType(MetadataHelper.java:1283)
        //     at com.strobel.assembler.metadata.MetadataHelper.isSubType(MetadataHelper.java:1283)
        //     at com.strobel.assembler.metadata.MetadataHelper.isSubType(MetadataHelper.java:1283)
        //     at com.strobel.assembler.metadata.MetadataHelper.isSubType(MetadataHelper.java:1283)
        //     at com.strobel.assembler.metadata.MetadataHelper.isSubType(MetadataHelper.java:1283)
        //     at com.strobel.assembler.metadata.MetadataHelper.isSubType(MetadataHelper.java:1283)
        //     at com.strobel.assembler.metadata.MetadataHelper.isSubType(MetadataHelper.java:1283)
        //     at com.strobel.assembler.metadata.MetadataHelper.isSubType(MetadataHelper.java:1283)
        //     at com.strobel.assembler.metadata.MetadataHelper.isSubType(MetadataHelper.java:1283)
        //     at com.strobel.assembler.metadata.MetadataHelper.isSubType(MetadataHelper.java:1283)
        //     at com.strobel.assembler.metadata.MetadataHelper.isSubType(MetadataHelper.java:1283)
        //     at com.strobel.assembler.metadata.MetadataHelper.isSubType(MetadataHelper.java:1283)
        //     at com.strobel.assembler.metadata.MetadataHelper.isSubType(MetadataHelper.java:1283)
        //     at com.strobel.assembler.metadata.MetadataHelper.isSubType(MetadataHelper.java:1283)
        //     at com.strobel.assembler.metadata.MetadataHelper.isSubType(MetadataHelper.java:1283)
        //     at com.strobel.assembler.metadata.MetadataHelper.isSubType(MetadataHelper.java:1283)
        //     at com.strobel.assembler.metadata.MetadataHelper.isSubType(MetadataHelper.java:1283)
        //     at com.strobel.assembler.metadata.MetadataHelper.isSubType(MetadataHelper.java:1283)
        //     at com.strobel.assembler.metadata.MetadataHelper.isSubType(MetadataHelper.java:1283)
        //     at com.strobel.assembler.metadata.MetadataHelper.isSubType(MetadataHelper.java:1283)
        //     at com.strobel.assembler.metadata.MetadataHelper.isSubType(MetadataHelper.java:1283)
        //     at com.strobel.assembler.metadata.MetadataHelper.isSubType(MetadataHelper.java:1283)
        //     at com.strobel.assembler.metadata.MetadataHelper.isSubType(MetadataHelper.java:1283)
        //     at com.strobel.assembler.metadata.MetadataHelper.isSubType(MetadataHelper.java:1283)
        //     at com.strobel.assembler.metadata.MetadataHelper.isSubType(MetadataHelper.java:1283)
        //     at com.strobel.assembler.metadata.MetadataHelper.isSubType(MetadataHelper.java:1283)
        //     at com.strobel.assembler.metadata.MetadataHelper.isSubType(MetadataHelper.java:1283)
        //     at com.strobel.assembler.metadata.MetadataHelper.isSubType(MetadataHelper.java:1283)
        //     at com.strobel.assembler.metadata.MetadataHelper.isSubType(MetadataHelper.java:1283)
        //     at com.strobel.assembler.metadata.MetadataHelper.isSubType(MetadataHelper.java:1283)
        //     at com.strobel.assembler.metadata.MetadataHelper.isSubType(MetadataHelper.java:1283)
        //     at com.strobel.assembler.metadata.MetadataHelper.isSubType(MetadataHelper.java:1283)
        //     at com.strobel.assembler.metadata.MetadataHelper.isSubType(MetadataHelper.java:1283)
        //     at com.strobel.assembler.metadata.MetadataHelper.isSubType(MetadataHelper.java:1283)
        //     at com.strobel.assembler.metadata.MetadataHelper.isSubType(MetadataHelper.java:1283)
        //     at com.strobel.assembler.metadata.MetadataHelper.isSubType(MetadataHelper.java:1283)
        //     at com.strobel.assembler.metadata.MetadataHelper.isSubType(MetadataHelper.java:1283)
        //     at com.strobel.assembler.metadata.MetadataHelper.isSubType(MetadataHelper.java:1283)
        //     at com.strobel.assembler.metadata.MetadataHelper.isSubType(MetadataHelper.java:1283)
        //     at com.strobel.assembler.metadata.MetadataHelper.isSubType(MetadataHelper.java:1283)
        //     at com.strobel.assembler.metadata.MetadataHelper.isSubType(MetadataHelper.java:1283)
        //     at com.strobel.assembler.metadata.MetadataHelper.isSubType(MetadataHelper.java:1283)
        //     at com.strobel.assembler.metadata.MetadataHelper.isSubType(MetadataHelper.java:1283)
        //     at com.strobel.assembler.metadata.MetadataHelper.isSubType(MetadataHelper.java:1283)
        //     at com.strobel.assembler.metadata.MetadataHelper.isSubType(MetadataHelper.java:1283)
        //     at com.strobel.assembler.metadata.MetadataHelper.isSubType(MetadataHelper.java:1283)
        //     at com.strobel.assembler.metadata.MetadataHelper.isSubType(MetadataHelper.java:1283)
        //     at com.strobel.assembler.metadata.MetadataHelper.isSubType(MetadataHelper.java:1283)
        //     at com.strobel.assembler.metadata.MetadataHelper.isSubType(MetadataHelper.java:1283)
        //     at com.strobel.assembler.metadata.MetadataHelper.isSubType(MetadataHelper.java:1283)
        //     at com.strobel.assembler.metadata.MetadataHelper.isSubType(MetadataHelper.java:1283)
        //     at com.strobel.assembler.metadata.MetadataHelper.isSubType(MetadataHelper.java:1283)
        //     at com.strobel.assembler.metadata.MetadataHelper.isSubType(MetadataHelper.java:1283)
        //     at com.strobel.assembler.metadata.MetadataHelper.isSubType(MetadataHelper.java:1283)
        //     at com.strobel.assembler.metadata.MetadataHelper.isSubType(MetadataHelper.java:1283)
        //     at com.strobel.assembler.metadata.MetadataHelper.isSubType(MetadataHelper.java:1283)
        //     at com.strobel.assembler.metadata.MetadataHelper.isSubType(MetadataHelper.java:1283)
        //     at com.strobel.assembler.metadata.MetadataHelper.isSubType(MetadataHelper.java:1283)
        //     at com.strobel.assembler.metadata.MetadataHelper.isSubType(MetadataHelper.java:1283)
        //     at com.strobel.assembler.metadata.MetadataHelper.isSubType(MetadataHelper.java:1283)
        //     at com.strobel.assembler.metadata.MetadataHelper.isSubType(MetadataHelper.java:1283)
        //     at com.strobel.assembler.metadata.MetadataHelper.isSubType(MetadataHelper.java:1283)
        //     at com.strobel.assembler.metadata.MetadataHelper.isSubType(MetadataHelper.java:1283)
        //     at com.strobel.assembler.metadata.MetadataHelper.isSubType(MetadataHelper.java:1283)
        //     at com.strobel.assembler.metadata.MetadataHelper.isSubType(MetadataHelper.java:1283)
        //     at com.strobel.assembler.metadata.MetadataHelper.isSubType(MetadataHelper.java:1283)
        //     at com.strobel.assembler.metadata.MetadataHelper.isSubType(MetadataHelper.java:1283)
        //     at com.strobel.assembler.metadata.MetadataHelper.isSubType(MetadataHelper.java:1283)
        //     at com.strobel.assembler.metadata.MetadataHelper.isSubType(MetadataHelper.java:1283)
        //     at com.strobel.assembler.metadata.MetadataHelper.isSubType(MetadataHelper.java:1283)
        //     at com.strobel.assembler.metadata.MetadataHelper.isSubType(MetadataHelper.java:1283)
        //     at com.strobel.assembler.metadata.MetadataHelper.isSubType(MetadataHelper.java:1283)
        //     at com.strobel.assembler.metadata.MetadataHelper.isSubType(MetadataHelper.java:1283)
        //     at com.strobel.assembler.metadata.MetadataHelper.isSubType(MetadataHelper.java:1283)
        //     at com.strobel.assembler.metadata.MetadataHelper.isSubType(MetadataHelper.java:1283)
        //     at com.strobel.assembler.metadata.MetadataHelper.isSubType(MetadataHelper.java:1283)
        //     at com.strobel.assembler.metadata.MetadataHelper.isSubType(MetadataHelper.java:1283)
        //     at com.strobel.assembler.metadata.MetadataHelper.isSubType(MetadataHelper.java:1283)
        //     at com.strobel.assembler.metadata.MetadataHelper.isSubType(MetadataHelper.java:1283)
        //     at com.strobel.assembler.metadata.MetadataHelper.isSubType(MetadataHelper.java:1283)
        //     at com.strobel.assembler.metadata.MetadataHelper.isSubType(MetadataHelper.java:1283)
        //     at com.strobel.assembler.metadata.MetadataHelper.isSubType(MetadataHelper.java:1283)
        //     at com.strobel.assembler.metadata.MetadataHelper.isSubType(MetadataHelper.java:1283)
        //     at com.strobel.assembler.metadata.MetadataHelper.isSubType(MetadataHelper.java:1283)
        //     at com.strobel.assembler.metadata.MetadataHelper.isSubType(MetadataHelper.java:1283)
        //     at com.strobel.assembler.metadata.MetadataHelper.isSubType(MetadataHelper.java:1283)
        //     at com.strobel.assembler.metadata.MetadataHelper.isSubType(MetadataHelper.java:1283)
        //     at com.strobel.assembler.metadata.MetadataHelper.isSubType(MetadataHelper.java:1283)
        //     at com.strobel.assembler.metadata.MetadataHelper.isSubType(MetadataHelper.java:1283)
        //     at com.strobel.assembler.metadata.MetadataHelper.isSubType(MetadataHelper.java:1283)
        //     at com.strobel.assembler.metadata.MetadataHelper.isSubType(MetadataHelper.java:1283)
        //     at com.strobel.assembler.metadata.MetadataHelper.isSubType(MetadataHelper.java:1283)
        //     at com.strobel.assembler.metadata.MetadataHelper.isSubType(MetadataHelper.java:1283)
        //     at com.strobel.assembler.metadata.MetadataHelper.isSubType(MetadataHelper.java:1283)
        //     at com.strobel.assembler.metadata.MetadataHelper.isSubType(MetadataHelper.java:1283)
        //     at com.strobel.assembler.metadata.MetadataHelper.isSubType(MetadataHelper.java:1283)
        //     at com.strobel.assembler.metadata.MetadataHelper.isSubType(MetadataHelper.java:1283)
        //     at com.strobel.assembler.metadata.MetadataHelper.isSubType(MetadataHelper.java:1283)
        //     at com.strobel.assembler.metadata.MetadataHelper.isSubType(MetadataHelper.java:1283)
        //     at com.strobel.assembler.metadata.MetadataHelper.isSubType(MetadataHelper.java:1283)
        //     at com.strobel.assembler.metadata.MetadataHelper.isSubType(MetadataHelper.java:1283)
        //     at com.strobel.assembler.metadata.MetadataHelper.isSubType(MetadataHelper.java:1283)
        //     at com.strobel.assembler.metadata.MetadataHelper.isSubType(MetadataHelper.java:1283)
        //     at com.strobel.assembler.metadata.MetadataHelper.isSubType(MetadataHelper.java:1283)
        //     at com.strobel.assembler.metadata.MetadataHelper.isSubType(MetadataHelper.java:1283)
        //     at com.strobel.assembler.metadata.MetadataHelper.isSubType(MetadataHelper.java:1283)
        //     at com.strobel.assembler.metadata.MetadataHelper.isSubType(MetadataHelper.java:1283)
        //     at com.strobel.assembler.metadata.MetadataHelper.isSubType(MetadataHelper.java:1283)
        //     at com.strobel.assembler.metadata.MetadataHelper.isSubType(MetadataHelper.java:1283)
        //     at com.strobel.assembler.metadata.MetadataHelper.isSubType(MetadataHelper.java:1283)
        //     at com.strobel.assembler.metadata.MetadataHelper.isSubType(MetadataHelper.java:1283)
        //     at com.strobel.assembler.metadata.MetadataHelper.isSubType(MetadataHelper.java:1283)
        //     at com.strobel.assembler.metadata.MetadataHelper.isSubType(MetadataHelper.java:1283)
        //     at com.strobel.assembler.metadata.MetadataHelper.isSubType(MetadataHelper.java:1283)
        //     at com.strobel.assembler.metadata.MetadataHelper.isSubType(MetadataHelper.java:1283)
        //     at com.strobel.assembler.metadata.MetadataHelper.isSubType(MetadataHelper.java:1283)
        //     at com.strobel.assembler.metadata.MetadataHelper.isSubType(MetadataHelper.java:1283)
        //     at com.strobel.assembler.metadata.MetadataHelper.isSubType(MetadataHelper.java:1283)
        //     at com.strobel.assembler.metadata.MetadataHelper.isSubType(MetadataHelper.java:1283)
        //     at com.strobel.assembler.metadata.MetadataHelper.isSubType(MetadataHelper.java:1283)
        //     at com.strobel.assembler.metadata.MetadataHelper.isSubType(MetadataHelper.java:1283)
        //     at com.strobel.assembler.metadata.MetadataHelper.isSubType(MetadataHelper.java:1283)
        //     at com.strobel.assembler.metadata.MetadataHelper.isSubType(MetadataHelper.java:1283)
        //     at com.strobel.assembler.metadata.MetadataHelper.isSubType(MetadataHelper.java:1283)
        //     at com.strobel.assembler.metadata.MetadataHelper.isSubType(MetadataHelper.java:1283)
        //     at com.strobel.assembler.metadata.MetadataHelper.isSubType(MetadataHelper.java:1283)
        //     at com.strobel.assembler.metadata.MetadataHelper.isSubType(MetadataHelper.java:1283)
        //     at com.strobel.assembler.metadata.MetadataHelper.isSubType(MetadataHelper.java:1283)
        //     at com.strobel.assembler.metadata.MetadataHelper.isSubType(MetadataHelper.java:1283)
        //     at com.strobel.assembler.metadata.MetadataHelper.isSubType(MetadataHelper.java:1283)
        //     at com.strobel.assembler.metadata.MetadataHelper.isSubType(MetadataHelper.java:1283)
        //     at com.strobel.assembler.metadata.MetadataHelper.isSubType(MetadataHelper.java:1283)
        //     at com.strobel.assembler.metadata.MetadataHelper.isSubType(MetadataHelper.java:1283)
        //     at com.strobel.assembler.metadata.MetadataHelper.isSubType(MetadataHelper.java:1283)
        //     at com.strobel.assembler.metadata.MetadataHelper.isSubType(MetadataHelper.java:1283)
        //     at com.strobel.assembler.metadata.MetadataHelper.isSubType(MetadataHelper.java:1283)
        //     at com.strobel.assembler.metadata.MetadataHelper.isSubType(MetadataHelper.java:1283)
        //     at com.strobel.assembler.metadata.MetadataHelper.isSubType(MetadataHelper.java:1283)
        //     at com.strobel.assembler.metadata.MetadataHelper.isSubType(MetadataHelper.java:1283)
        //     at com.strobel.assembler.metadata.MetadataHelper.isSubType(MetadataHelper.java:1283)
        //     at com.strobel.assembler.metadata.MetadataHelper.isSubType(MetadataHelper.java:1283)
        //     at com.strobel.assembler.metadata.MetadataHelper.isSubType(MetadataHelper.java:1283)
        //     at com.strobel.assembler.metadata.MetadataHelper.isSubType(MetadataHelper.java:1283)
        //     at com.strobel.assembler.metadata.MetadataHelper.isSubType(MetadataHelper.java:1283)
        //     at com.strobel.assembler.metadata.MetadataHelper.isSubType(MetadataHelper.java:1283)
        //     at com.strobel.assembler.metadata.MetadataHelper.isSubType(MetadataHelper.java:1283)
        //     at com.strobel.assembler.metadata.MetadataHelper.isSubType(MetadataHelper.java:1283)
        //     at com.strobel.assembler.metadata.MetadataHelper.isSubType(MetadataHelper.java:1283)
        //     at com.strobel.assembler.metadata.MetadataHelper.isSubType(MetadataHelper.java:1283)
        //     at com.strobel.assembler.metadata.MetadataHelper.isSubType(MetadataHelper.java:1283)
        //     at com.strobel.assembler.metadata.MetadataHelper.isSubType(MetadataHelper.java:1283)
        //     at com.strobel.assembler.metadata.MetadataHelper.isSubType(MetadataHelper.java:1283)
        //     at com.strobel.assembler.metadata.MetadataHelper.isSubType(MetadataHelper.java:1283)
        //     at com.strobel.assembler.metadata.MetadataHelper.isSubType(MetadataHelper.java:1283)
        //     at com.strobel.assembler.metadata.MetadataHelper.isSubType(MetadataHelper.java:1283)
        //     at com.strobel.assembler.metadata.MetadataHelper.isSubType(MetadataHelper.java:1283)
        //     at com.strobel.assembler.metadata.MetadataHelper.isSubType(MetadataHelper.java:1283)
        //     at com.strobel.assembler.metadata.MetadataHelper.isSubType(MetadataHelper.java:1283)
        //     at com.strobel.assembler.metadata.MetadataHelper.isSubType(MetadataHelper.java:1283)
        //     at com.strobel.assembler.metadata.MetadataHelper.isSubType(MetadataHelper.java:1283)
        //     at com.strobel.assembler.metadata.MetadataHelper.isSubType(MetadataHelper.java:1283)
        //     at com.strobel.assembler.metadata.MetadataHelper.isSubType(MetadataHelper.java:1283)
        //     at com.strobel.assembler.metadata.MetadataHelper.isSubType(MetadataHelper.java:1283)
        //     at com.strobel.assembler.metadata.MetadataHelper.isSubType(MetadataHelper.java:1283)
        //     at com.strobel.assembler.metadata.MetadataHelper.isSubType(MetadataHelper.java:1283)
        //     at com.strobel.assembler.metadata.MetadataHelper.isSubType(MetadataHelper.java:1283)
        //     at com.strobel.assembler.metadata.MetadataHelper.isSubType(MetadataHelper.java:1283)
        //     at com.strobel.assembler.metadata.MetadataHelper.isSubType(MetadataHelper.java:1283)
        //     at com.strobel.assembler.metadata.MetadataHelper.isSubType(MetadataHelper.java:1283)
        //     at com.strobel.assembler.metadata.MetadataHelper.isSubType(MetadataHelper.java:1283)
        //     at com.strobel.assembler.metadata.MetadataHelper.isSubType(MetadataHelper.java:1283)
        //     at com.strobel.assembler.metadata.MetadataHelper.isSubType(MetadataHelper.java:1283)
        //     at com.strobel.assembler.metadata.MetadataHelper.isSubType(MetadataHelper.java:1283)
        //     at com.strobel.assembler.metadata.MetadataHelper.isSubType(MetadataHelper.java:1283)
        //     at com.strobel.assembler.metadata.MetadataHelper.isSubType(MetadataHelper.java:1283)
        //     at com.strobel.assembler.metadata.MetadataHelper.isSubType(MetadataHelper.java:1283)
        //     at com.strobel.assembler.metadata.MetadataHelper.isSubType(MetadataHelper.java:1283)
        //     at com.strobel.assembler.metadata.MetadataHelper.isSubType(MetadataHelper.java:1283)
        //     at com.strobel.assembler.metadata.MetadataHelper.isSubType(MetadataHelper.java:1283)
        //     at com.strobel.assembler.metadata.MetadataHelper.isSubType(MetadataHelper.java:1283)
        //     at com.strobel.assembler.metadata.MetadataHelper.isSubType(MetadataHelper.java:1283)
        //     at com.strobel.assembler.metadata.MetadataHelper.isSubType(MetadataHelper.java:1283)
        //     at com.strobel.assembler.metadata.MetadataHelper.isSubType(MetadataHelper.java:1283)
        //     at com.strobel.assembler.metadata.MetadataHelper.isSubType(MetadataHelper.java:1283)
        //     at com.strobel.assembler.metadata.MetadataHelper.isSubType(MetadataHelper.java:1283)
        //     at com.strobel.assembler.metadata.MetadataHelper.isSubType(MetadataHelper.java:1283)
        //     at com.strobel.assembler.metadata.MetadataHelper.isSubType(MetadataHelper.java:1283)
        //     at com.strobel.assembler.metadata.MetadataHelper.isSubType(MetadataHelper.java:1283)
        //     at com.strobel.assembler.metadata.MetadataHelper.isSubType(MetadataHelper.java:1283)
        //     at com.strobel.assembler.metadata.MetadataHelper.isSubType(MetadataHelper.java:1283)
        //     at com.strobel.assembler.metadata.MetadataHelper.isSubType(MetadataHelper.java:1283)
        //     at com.strobel.assembler.metadata.MetadataHelper.isSubType(MetadataHelper.java:1283)
        //     at com.strobel.assembler.metadata.MetadataHelper.isSubType(MetadataHelper.java:1283)
        //     at com.strobel.assembler.metadata.MetadataHelper.isSubType(MetadataHelper.java:1283)
        //     at com.strobel.assembler.metadata.MetadataHelper.isSubType(MetadataHelper.java:1283)
        //     at com.strobel.assembler.metadata.MetadataHelper.isSubType(MetadataHelper.java:1283)
        //     at com.strobel.assembler.metadata.MetadataHelper.isSubType(MetadataHelper.java:1283)
        //     at com.strobel.assembler.metadata.MetadataHelper.isSubType(MetadataHelper.java:1283)
        //     at com.strobel.assembler.metadata.MetadataHelper.isSubType(MetadataHelper.java:1283)
        //     at com.strobel.assembler.metadata.MetadataHelper.isSubType(MetadataHelper.java:1283)
        //     at com.strobel.assembler.metadata.MetadataHelper.isSubType(MetadataHelper.java:1283)
        //     at com.strobel.assembler.metadata.MetadataHelper.isSubType(MetadataHelper.java:1283)
        //     at com.strobel.assembler.metadata.MetadataHelper.isSubType(MetadataHelper.java:1283)
        //     at com.strobel.assembler.metadata.MetadataHelper.isSubType(MetadataHelper.java:1283)
        //     at com.strobel.assembler.metadata.MetadataHelper.isSubType(MetadataHelper.java:1283)
        //     at com.strobel.assembler.metadata.MetadataHelper.isSubType(MetadataHelper.java:1283)
        //     at com.strobel.assembler.metadata.MetadataHelper.isSubType(MetadataHelper.java:1283)
        //     at com.strobel.assembler.metadata.MetadataHelper.isSubType(MetadataHelper.java:1283)
        //     at com.strobel.assembler.metadata.MetadataHelper.isSubType(MetadataHelper.java:1283)
        //     at com.strobel.assembler.metadata.MetadataHelper.isSubType(MetadataHelper.java:1283)
        //     at com.strobel.assembler.metadata.MetadataHelper.isSubType(MetadataHelper.java:1283)
        //     at com.strobel.assembler.metadata.MetadataHelper.isSubType(MetadataHelper.java:1283)
        //     at com.strobel.assembler.metadata.MetadataHelper.isSubType(MetadataHelper.java:1283)
        //     at com.strobel.assembler.metadata.MetadataHelper.isSubType(MetadataHelper.java:1283)
        //     at com.strobel.assembler.metadata.MetadataHelper.isSubType(MetadataHelper.java:1283)
        //     at com.strobel.assembler.metadata.MetadataHelper.isSubType(MetadataHelper.java:1283)
        //     at com.strobel.assembler.metadata.MetadataHelper.isSubType(MetadataHelper.java:1283)
        //     at com.strobel.assembler.metadata.MetadataHelper.isSubType(MetadataHelper.java:1283)
        //     at com.strobel.assembler.metadata.MetadataHelper.isSubType(MetadataHelper.java:1283)
        //     at com.strobel.assembler.metadata.MetadataHelper.isSubType(MetadataHelper.java:1283)
        //     at com.strobel.assembler.metadata.MetadataHelper.isSubType(MetadataHelper.java:1283)
        //     at com.strobel.assembler.metadata.MetadataHelper.isSubType(MetadataHelper.java:1283)
        //     at com.strobel.assembler.metadata.MetadataHelper.isSubType(MetadataHelper.java:1283)
        //     at com.strobel.assembler.metadata.MetadataHelper.isSubType(MetadataHelper.java:1283)
        //     at com.strobel.assembler.metadata.MetadataHelper.isSubType(MetadataHelper.java:1283)
        //     at com.strobel.assembler.metadata.MetadataHelper.isSubType(MetadataHelper.java:1283)
        //     at com.strobel.assembler.metadata.MetadataHelper.isSubType(MetadataHelper.java:1283)
        //     at com.strobel.assembler.metadata.MetadataHelper.isSubType(MetadataHelper.java:1283)
        //     at com.strobel.assembler.metadata.MetadataHelper.isSubType(MetadataHelper.java:1283)
        //     at com.strobel.assembler.metadata.MetadataHelper.isSubType(MetadataHelper.java:1283)
        //     at com.strobel.assembler.metadata.MetadataHelper.isSubType(MetadataHelper.java:1283)
        //     at com.strobel.assembler.metadata.MetadataHelper.isSubType(MetadataHelper.java:1283)
        //     at com.strobel.assembler.metadata.MetadataHelper.isSubType(MetadataHelper.java:1283)
        //     at com.strobel.assembler.metadata.MetadataHelper.isSubType(MetadataHelper.java:1283)
        //     at com.strobel.assembler.metadata.MetadataHelper.isSubType(MetadataHelper.java:1283)
        //     at com.strobel.assembler.metadata.MetadataHelper.isSubType(MetadataHelper.java:1283)
        //     at com.strobel.assembler.metadata.MetadataHelper.isSubType(MetadataHelper.java:1283)
        //     at com.strobel.assembler.metadata.MetadataHelper.isSubType(MetadataHelper.java:1283)
        //     at com.strobel.assembler.metadata.MetadataHelper.isSubType(MetadataHelper.java:1283)
        //     at com.strobel.assembler.metadata.MetadataHelper.isSubType(MetadataHelper.java:1283)
        //     at com.strobel.assembler.metadata.MetadataHelper.isSubType(MetadataHelper.java:1283)
        //     at com.strobel.assembler.metadata.MetadataHelper.isSubType(MetadataHelper.java:1283)
        //     at com.strobel.assembler.metadata.MetadataHelper.isSubType(MetadataHelper.java:1283)
        //     at com.strobel.assembler.metadata.MetadataHelper.isSubType(MetadataHelper.java:1283)
        //     at com.strobel.assembler.metadata.MetadataHelper.isSubType(MetadataHelper.java:1283)
        //     at com.strobel.assembler.metadata.MetadataHelper.isSubType(MetadataHelper.java:1283)
        //     at com.strobel.assembler.metadata.MetadataHelper.isSubType(MetadataHelper.java:1283)
        //     at com.strobel.assembler.metadata.MetadataHelper.isSubType(MetadataHelper.java:1283)
        //     at com.strobel.assembler.metadata.MetadataHelper.isSubType(MetadataHelper.java:1283)
        //     at com.strobel.assembler.metadata.MetadataHelper.isSubType(MetadataHelper.java:1283)
        //     at com.strobel.assembler.metadata.MetadataHelper.isSubType(MetadataHelper.java:1283)
        //     at com.strobel.assembler.metadata.MetadataHelper.isSubType(MetadataHelper.java:1283)
        //     at com.strobel.assembler.metadata.MetadataHelper.isSubType(MetadataHelper.java:1283)
        //     at com.strobel.assembler.metadata.MetadataHelper.isSubType(MetadataHelper.java:1283)
        //     at com.strobel.assembler.metadata.MetadataHelper.isSubType(MetadataHelper.java:1283)
        // 
        throw new IllegalStateException("An error occurred while decompiling this method.");
    }
    
    @InlineOnly
    private static final <K, V> boolean contains(final Map<? extends K, ? extends V> $this$contains, final K key) {
        Intrinsics.checkNotNullParameter($this$contains, "<this>");
        return $this$contains.containsKey(key);
    }
    
    @InlineOnly
    private static final <K, V> V get(final Map<? extends K, ? extends V> $this$get, final K key) {
        Intrinsics.checkNotNullParameter($this$get, "<this>");
        return (V)$this$get.get(key);
    }
    
    @InlineOnly
    private static final <K, V> void set(final Map<K, V> $this$set, final K key, final V value) {
        Intrinsics.checkNotNullParameter($this$set, "<this>");
        $this$set.put(key, value);
    }
    
    @InlineOnly
    private static final <K> boolean containsKey(final Map<? extends K, ?> $this$containsKey, final K key) {
        Intrinsics.checkNotNullParameter($this$containsKey, "<this>");
        return $this$containsKey.containsKey(key);
    }
    
    @InlineOnly
    private static final <K, V> boolean containsValue(final Map<K, ? extends V> $this$containsValue, final V value) {
        Intrinsics.checkNotNullParameter($this$containsValue, "<this>");
        return $this$containsValue.containsValue(value);
    }
    
    @InlineOnly
    private static final <K, V> V remove(final Map<? extends K, V> $this$remove, final K key) {
        Intrinsics.checkNotNullParameter($this$remove, "<this>");
        return TypeIntrinsics.asMutableMap($this$remove).remove(key);
    }
    
    @InlineOnly
    private static final <K, V> K component1(final Map.Entry<? extends K, ? extends V> $this$component1) {
        Intrinsics.checkNotNullParameter($this$component1, "<this>");
        return (K)$this$component1.getKey();
    }
    
    @InlineOnly
    private static final <K, V> V component2(final Map.Entry<? extends K, ? extends V> $this$component2) {
        Intrinsics.checkNotNullParameter($this$component2, "<this>");
        return (V)$this$component2.getValue();
    }
    
    @InlineOnly
    private static final <K, V> Pair<K, V> toPair(final Map.Entry<? extends K, ? extends V> $this$toPair) {
        Intrinsics.checkNotNullParameter($this$toPair, "<this>");
        return new Pair<K, V>((K)$this$toPair.getKey(), (V)$this$toPair.getValue());
    }
    
    @InlineOnly
    private static final <K, V> V getOrElse(final Map<K, ? extends V> $this$getOrElse, final K key, final Function0<? extends V> defaultValue) {
        Intrinsics.checkNotNullParameter($this$getOrElse, "<this>");
        Intrinsics.checkNotNullParameter(defaultValue, "defaultValue");
        V v;
        if ((v = (V)$this$getOrElse.get(key)) == null) {
            v = (V)defaultValue.invoke();
        }
        return v;
    }
    
    public static final <K, V> V getOrElseNullable(@NotNull final Map<K, ? extends V> $this$getOrElseNullable, final K key, @NotNull final Function0<? extends V> defaultValue) {
        Intrinsics.checkNotNullParameter($this$getOrElseNullable, "<this>");
        Intrinsics.checkNotNullParameter(defaultValue, "defaultValue");
        final int $i$f$getOrElseNullable = 0;
        final Object value = $this$getOrElseNullable.get(key);
        if (value == null && !$this$getOrElseNullable.containsKey(key)) {
            return (V)defaultValue.invoke();
        }
        return (V)value;
    }
    
    @SinceKotlin(version = "1.1")
    public static final <K, V> V getValue(@NotNull final Map<K, ? extends V> $this$getValue, final K key) {
        Intrinsics.checkNotNullParameter($this$getValue, "<this>");
        return MapsKt__MapWithDefaultKt.getOrImplicitDefaultNullable($this$getValue, key);
    }
    
    public static final <K, V> V getOrPut(@NotNull final Map<K, V> $this$getOrPut, final K key, @NotNull final Function0<? extends V> defaultValue) {
        Intrinsics.checkNotNullParameter($this$getOrPut, "<this>");
        Intrinsics.checkNotNullParameter(defaultValue, "defaultValue");
        final int $i$f$getOrPut = 0;
        final Object value = $this$getOrPut.get(key);
        Object o;
        if (value == null) {
            final Object answer = defaultValue.invoke();
            $this$getOrPut.put(key, (V)answer);
            o = answer;
        }
        else {
            o = value;
        }
        return (V)o;
    }
    
    @InlineOnly
    private static final <K, V> Iterator<Map.Entry<K, V>> iterator(final Map<? extends K, ? extends V> $this$iterator) {
        Intrinsics.checkNotNullParameter($this$iterator, "<this>");
        return (Iterator<Map.Entry<K, V>>)$this$iterator.entrySet().iterator();
    }
    
    @JvmName(name = "mutableIterator")
    @InlineOnly
    private static final <K, V> Iterator<Map.Entry<K, V>> mutableIterator(final Map<K, V> $this$iterator) {
        Intrinsics.checkNotNullParameter($this$iterator, "<this>");
        return $this$iterator.entrySet().iterator();
    }
    
    @NotNull
    public static final <K, V, R, M extends Map<? super K, ? super R>> M mapValuesTo(@NotNull final Map<? extends K, ? extends V> $this$mapValuesTo, @NotNull final M destination, @NotNull final Function1<? super Map.Entry<? extends K, ? extends V>, ? extends R> transform) {
        // 
        // This method could not be decompiled.
        // 
        // Original Bytecode:
        // 
        //     1: ldc             "<this>"
        //     3: invokestatic    kotlin/jvm/internal/Intrinsics.checkNotNullParameter:(Ljava/lang/Object;Ljava/lang/String;)V
        //     6: aload_1         /* destination */
        //     7: ldc             "destination"
        //     9: invokestatic    kotlin/jvm/internal/Intrinsics.checkNotNullParameter:(Ljava/lang/Object;Ljava/lang/String;)V
        //    12: aload_2         /* transform */
        //    13: ldc             "transform"
        //    15: invokestatic    kotlin/jvm/internal/Intrinsics.checkNotNullParameter:(Ljava/lang/Object;Ljava/lang/String;)V
        //    18: iconst_0       
        //    19: istore_3        /* $i$f$mapValuesTo */
        //    20: aload_0         /* $this$mapValuesTo */
        //    21: invokeinterface java/util/Map.entrySet:()Ljava/util/Set;
        //    26: checkcast       Ljava/lang/Iterable;
        //    29: astore          $this$associateByTo$iv
        //    31: iconst_0       
        //    32: istore          $i$f$associateByTo
        //    34: aload           $this$associateByTo$iv
        //    36: invokeinterface java/lang/Iterable.iterator:()Ljava/util/Iterator;
        //    41: astore          6
        //    43: aload           6
        //    45: invokeinterface java/util/Iterator.hasNext:()Z
        //    50: ifeq            102
        //    53: aload           6
        //    55: invokeinterface java/util/Iterator.next:()Ljava/lang/Object;
        //    60: astore          element$iv
        //    62: aload_1         /* destination */
        //    63: aload           element$iv
        //    65: checkcast       Ljava/util/Map$Entry;
        //    68: astore          8
        //    70: astore          10
        //    72: iconst_0       
        //    73: istore          $i$a$-associateByTo-MapsKt__MapsKt$mapValuesTo$1
        //    75: aload           it
        //    77: invokeinterface java/util/Map$Entry.getKey:()Ljava/lang/Object;
        //    82: aload           10
        //    84: swap           
        //    85: aload_2         /* transform */
        //    86: aload           element$iv
        //    88: invokeinterface kotlin/jvm/functions/Function1.invoke:(Ljava/lang/Object;)Ljava/lang/Object;
        //    93: invokeinterface java/util/Map.put:(Ljava/lang/Object;Ljava/lang/Object;)Ljava/lang/Object;
        //    98: pop            
        //    99: goto            43
        //   102: aload_1         /* destination */
        //   103: areturn        
        //    Signature:
        //  <K:Ljava/lang/Object;V:Ljava/lang/Object;R:Ljava/lang/Object;M::Ljava/util/Map<-TK;-TR;>;>(Ljava/util/Map<+TK;+TV;>;TM;Lkotlin/jvm/functions/Function1<-Ljava/util/Map$Entry<+TK;+TV;>;+TR;>;)TM;
        //    StackMapTable: 00 02 FF 00 2B 00 07 07 00 18 07 00 18 07 00 63 01 07 01 00 01 07 01 03 00 00 3A
        // 
        // The error that occurred was:
        // 
        // java.lang.NullPointerException
        // 
        throw new IllegalStateException("An error occurred while decompiling this method.");
    }
    
    @NotNull
    public static final <K, V, R, M extends Map<? super R, ? super V>> M mapKeysTo(@NotNull final Map<? extends K, ? extends V> $this$mapKeysTo, @NotNull final M destination, @NotNull final Function1<? super Map.Entry<? extends K, ? extends V>, ? extends R> transform) {
        // 
        // This method could not be decompiled.
        // 
        // Original Bytecode:
        // 
        //     1: ldc             "<this>"
        //     3: invokestatic    kotlin/jvm/internal/Intrinsics.checkNotNullParameter:(Ljava/lang/Object;Ljava/lang/String;)V
        //     6: aload_1         /* destination */
        //     7: ldc             "destination"
        //     9: invokestatic    kotlin/jvm/internal/Intrinsics.checkNotNullParameter:(Ljava/lang/Object;Ljava/lang/String;)V
        //    12: aload_2         /* transform */
        //    13: ldc             "transform"
        //    15: invokestatic    kotlin/jvm/internal/Intrinsics.checkNotNullParameter:(Ljava/lang/Object;Ljava/lang/String;)V
        //    18: iconst_0       
        //    19: istore_3        /* $i$f$mapKeysTo */
        //    20: aload_0         /* $this$mapKeysTo */
        //    21: invokeinterface java/util/Map.entrySet:()Ljava/util/Set;
        //    26: checkcast       Ljava/lang/Iterable;
        //    29: astore          $this$associateByTo$iv
        //    31: iconst_0       
        //    32: istore          $i$f$associateByTo
        //    34: aload           $this$associateByTo$iv
        //    36: invokeinterface java/lang/Iterable.iterator:()Ljava/util/Iterator;
        //    41: astore          6
        //    43: aload           6
        //    45: invokeinterface java/util/Iterator.hasNext:()Z
        //    50: ifeq            109
        //    53: aload           6
        //    55: invokeinterface java/util/Iterator.next:()Ljava/lang/Object;
        //    60: astore          element$iv
        //    62: aload_1         /* destination */
        //    63: aload_2         /* transform */
        //    64: aload           element$iv
        //    66: invokeinterface kotlin/jvm/functions/Function1.invoke:(Ljava/lang/Object;)Ljava/lang/Object;
        //    71: aload           element$iv
        //    73: checkcast       Ljava/util/Map$Entry;
        //    76: astore          8
        //    78: astore          11
        //    80: astore          10
        //    82: iconst_0       
        //    83: istore          $i$a$-associateByTo-MapsKt__MapsKt$mapKeysTo$1
        //    85: aload           it
        //    87: invokeinterface java/util/Map$Entry.getValue:()Ljava/lang/Object;
        //    92: astore          12
        //    94: aload           10
        //    96: aload           11
        //    98: aload           12
        //   100: invokeinterface java/util/Map.put:(Ljava/lang/Object;Ljava/lang/Object;)Ljava/lang/Object;
        //   105: pop            
        //   106: goto            43
        //   109: aload_1         /* destination */
        //   110: areturn        
        //    Signature:
        //  <K:Ljava/lang/Object;V:Ljava/lang/Object;R:Ljava/lang/Object;M::Ljava/util/Map<-TR;-TV;>;>(Ljava/util/Map<+TK;+TV;>;TM;Lkotlin/jvm/functions/Function1<-Ljava/util/Map$Entry<+TK;+TV;>;+TR;>;)TM;
        //    StackMapTable: 00 02 FF 00 2B 00 07 07 00 18 07 00 18 07 00 63 01 07 01 00 01 07 01 03 00 00 FB 00 41
        // 
        // The error that occurred was:
        // 
        // java.lang.NullPointerException
        // 
        throw new IllegalStateException("An error occurred while decompiling this method.");
    }
    
    public static final <K, V> void putAll(@NotNull final Map<? super K, ? super V> $this$putAll, @NotNull final Pair<? extends K, ? extends V>[] pairs) {
        Intrinsics.checkNotNullParameter($this$putAll, "<this>");
        Intrinsics.checkNotNullParameter(pairs, "pairs");
        for (int i = 0; i < pairs.length; ++i) {
            final Pair<? extends K, ? extends V> pair = pairs[i];
            final Object key = pair.component1();
            final Object value = pair.component2();
            $this$putAll.put((Object)key, (Object)value);
        }
    }
    
    public static final <K, V> void putAll(@NotNull final Map<? super K, ? super V> $this$putAll, @NotNull final Iterable<? extends Pair<? extends K, ? extends V>> pairs) {
        Intrinsics.checkNotNullParameter($this$putAll, "<this>");
        Intrinsics.checkNotNullParameter(pairs, "pairs");
        for (final Pair<Object, B> pair : pairs) {
            final Object key = pair.component1();
            final Object value = pair.component2();
            $this$putAll.put((Object)key, (Object)value);
        }
    }
    
    public static final <K, V> void putAll(@NotNull final Map<? super K, ? super V> $this$putAll, @NotNull final Sequence<? extends Pair<? extends K, ? extends V>> pairs) {
        Intrinsics.checkNotNullParameter($this$putAll, "<this>");
        Intrinsics.checkNotNullParameter(pairs, "pairs");
        for (final Pair<Object, B> pair : pairs) {
            final Object key = pair.component1();
            final Object value = pair.component2();
            $this$putAll.put((Object)key, (Object)value);
        }
    }
    
    @NotNull
    public static final <K, V, R> Map<K, R> mapValues(@NotNull final Map<? extends K, ? extends V> $this$mapValues, @NotNull final Function1<? super Map.Entry<? extends K, ? extends V>, ? extends R> transform) {
        // 
        // This method could not be decompiled.
        // 
        // Original Bytecode:
        // 
        //     1: ldc             "<this>"
        //     3: invokestatic    kotlin/jvm/internal/Intrinsics.checkNotNullParameter:(Ljava/lang/Object;Ljava/lang/String;)V
        //     6: aload_1         /* transform */
        //     7: ldc             "transform"
        //     9: invokestatic    kotlin/jvm/internal/Intrinsics.checkNotNullParameter:(Ljava/lang/Object;Ljava/lang/String;)V
        //    12: iconst_0       
        //    13: istore_2        /* $i$f$mapValues */
        //    14: aload_0         /* $this$mapValues */
        //    15: astore_3       
        //    16: new             Ljava/util/LinkedHashMap;
        //    19: dup            
        //    20: aload_0         /* $this$mapValues */
        //    21: invokeinterface java/util/Map.size:()I
        //    26: invokestatic    kotlin/collections/MapsKt.mapCapacity:(I)I
        //    29: invokespecial   java/util/LinkedHashMap.<init>:(I)V
        //    32: checkcast       Ljava/util/Map;
        //    35: astore          destination$iv
        //    37: iconst_0       
        //    38: istore          $i$f$mapValuesTo
        //    40: aload_3         /* $this$mapValuesTo$iv */
        //    41: invokeinterface java/util/Map.entrySet:()Ljava/util/Set;
        //    46: checkcast       Ljava/lang/Iterable;
        //    49: astore          $this$associateByTo$iv$iv
        //    51: iconst_0       
        //    52: istore          $i$f$associateByTo
        //    54: aload           $this$associateByTo$iv$iv
        //    56: invokeinterface java/lang/Iterable.iterator:()Ljava/util/Iterator;
        //    61: astore          8
        //    63: aload           8
        //    65: invokeinterface java/util/Iterator.hasNext:()Z
        //    70: ifeq            123
        //    73: aload           8
        //    75: invokeinterface java/util/Iterator.next:()Ljava/lang/Object;
        //    80: astore          element$iv$iv
        //    82: aload           destination$iv
        //    84: aload           element$iv$iv
        //    86: checkcast       Ljava/util/Map$Entry;
        //    89: astore          10
        //    91: astore          11
        //    93: iconst_0       
        //    94: istore          $i$a$-associateByTo-MapsKt__MapsKt$mapValuesTo$1$iv
        //    96: aload           it$iv
        //    98: invokeinterface java/util/Map$Entry.getKey:()Ljava/lang/Object;
        //   103: aload           11
        //   105: swap           
        //   106: aload_1         /* transform */
        //   107: aload           element$iv$iv
        //   109: invokeinterface kotlin/jvm/functions/Function1.invoke:(Ljava/lang/Object;)Ljava/lang/Object;
        //   114: invokeinterface java/util/Map.put:(Ljava/lang/Object;Ljava/lang/Object;)Ljava/lang/Object;
        //   119: pop            
        //   120: goto            63
        //   123: aload           destination$iv
        //   125: nop            
        //   126: areturn        
        //    Signature:
        //  <K:Ljava/lang/Object;V:Ljava/lang/Object;R:Ljava/lang/Object;>(Ljava/util/Map<+TK;+TV;>;Lkotlin/jvm/functions/Function1<-Ljava/util/Map$Entry<+TK;+TV;>;+TR;>;)Ljava/util/Map<TK;TR;>;
        //    StackMapTable: 00 02 FF 00 3F 00 09 07 00 18 07 00 63 01 07 00 18 07 00 18 01 07 01 00 01 07 01 03 00 00 3B
        // 
        // The error that occurred was:
        // 
        // java.lang.NullPointerException
        // 
        throw new IllegalStateException("An error occurred while decompiling this method.");
    }
    
    @NotNull
    public static final <K, V, R> Map<R, V> mapKeys(@NotNull final Map<? extends K, ? extends V> $this$mapKeys, @NotNull final Function1<? super Map.Entry<? extends K, ? extends V>, ? extends R> transform) {
        // 
        // This method could not be decompiled.
        // 
        // Original Bytecode:
        // 
        //     1: ldc             "<this>"
        //     3: invokestatic    kotlin/jvm/internal/Intrinsics.checkNotNullParameter:(Ljava/lang/Object;Ljava/lang/String;)V
        //     6: aload_1         /* transform */
        //     7: ldc             "transform"
        //     9: invokestatic    kotlin/jvm/internal/Intrinsics.checkNotNullParameter:(Ljava/lang/Object;Ljava/lang/String;)V
        //    12: iconst_0       
        //    13: istore_2        /* $i$f$mapKeys */
        //    14: aload_0         /* $this$mapKeys */
        //    15: astore_3       
        //    16: new             Ljava/util/LinkedHashMap;
        //    19: dup            
        //    20: aload_0         /* $this$mapKeys */
        //    21: invokeinterface java/util/Map.size:()I
        //    26: invokestatic    kotlin/collections/MapsKt.mapCapacity:(I)I
        //    29: invokespecial   java/util/LinkedHashMap.<init>:(I)V
        //    32: checkcast       Ljava/util/Map;
        //    35: astore          destination$iv
        //    37: iconst_0       
        //    38: istore          $i$f$mapKeysTo
        //    40: aload_3         /* $this$mapKeysTo$iv */
        //    41: invokeinterface java/util/Map.entrySet:()Ljava/util/Set;
        //    46: checkcast       Ljava/lang/Iterable;
        //    49: astore          $this$associateByTo$iv$iv
        //    51: iconst_0       
        //    52: istore          $i$f$associateByTo
        //    54: aload           $this$associateByTo$iv$iv
        //    56: invokeinterface java/lang/Iterable.iterator:()Ljava/util/Iterator;
        //    61: astore          8
        //    63: aload           8
        //    65: invokeinterface java/util/Iterator.hasNext:()Z
        //    70: ifeq            130
        //    73: aload           8
        //    75: invokeinterface java/util/Iterator.next:()Ljava/lang/Object;
        //    80: astore          element$iv$iv
        //    82: aload           destination$iv
        //    84: aload_1         /* transform */
        //    85: aload           element$iv$iv
        //    87: invokeinterface kotlin/jvm/functions/Function1.invoke:(Ljava/lang/Object;)Ljava/lang/Object;
        //    92: aload           element$iv$iv
        //    94: checkcast       Ljava/util/Map$Entry;
        //    97: astore          10
        //    99: astore          11
        //   101: astore          12
        //   103: iconst_0       
        //   104: istore          $i$a$-associateByTo-MapsKt__MapsKt$mapKeysTo$1$iv
        //   106: aload           it$iv
        //   108: invokeinterface java/util/Map$Entry.getValue:()Ljava/lang/Object;
        //   113: astore          14
        //   115: aload           12
        //   117: aload           11
        //   119: aload           14
        //   121: invokeinterface java/util/Map.put:(Ljava/lang/Object;Ljava/lang/Object;)Ljava/lang/Object;
        //   126: pop            
        //   127: goto            63
        //   130: aload           destination$iv
        //   132: nop            
        //   133: areturn        
        //    Signature:
        //  <K:Ljava/lang/Object;V:Ljava/lang/Object;R:Ljava/lang/Object;>(Ljava/util/Map<+TK;+TV;>;Lkotlin/jvm/functions/Function1<-Ljava/util/Map$Entry<+TK;+TV;>;+TR;>;)Ljava/util/Map<TR;TV;>;
        //    StackMapTable: 00 02 FF 00 3F 00 09 07 00 18 07 00 63 01 07 00 18 07 00 18 01 07 01 00 01 07 01 03 00 00 FB 00 42
        // 
        // The error that occurred was:
        // 
        // java.lang.NullPointerException
        // 
        throw new IllegalStateException("An error occurred while decompiling this method.");
    }
    
    @NotNull
    public static final <K, V> Map<K, V> filterKeys(@NotNull final Map<? extends K, ? extends V> $this$filterKeys, @NotNull final Function1<? super K, Boolean> predicate) {
        Intrinsics.checkNotNullParameter($this$filterKeys, "<this>");
        Intrinsics.checkNotNullParameter(predicate, "predicate");
        final int $i$f$filterKeys = 0;
        final LinkedHashMap result = new LinkedHashMap();
        for (final Map.Entry entry : $this$filterKeys.entrySet()) {
            if (predicate.invoke(entry.getKey())) {
                result.put(entry.getKey(), entry.getValue());
            }
        }
        return (Map<K, V>)result;
    }
    
    @NotNull
    public static final <K, V> Map<K, V> filterValues(@NotNull final Map<? extends K, ? extends V> $this$filterValues, @NotNull final Function1<? super V, Boolean> predicate) {
        Intrinsics.checkNotNullParameter($this$filterValues, "<this>");
        Intrinsics.checkNotNullParameter(predicate, "predicate");
        final int $i$f$filterValues = 0;
        final LinkedHashMap result = new LinkedHashMap();
        for (final Map.Entry entry : $this$filterValues.entrySet()) {
            if (predicate.invoke(entry.getValue())) {
                result.put(entry.getKey(), entry.getValue());
            }
        }
        return (Map<K, V>)result;
    }
    
    @NotNull
    public static final <K, V, M extends Map<? super K, ? super V>> M filterTo(@NotNull final Map<? extends K, ? extends V> $this$filterTo, @NotNull final M destination, @NotNull final Function1<? super Map.Entry<? extends K, ? extends V>, Boolean> predicate) {
        Intrinsics.checkNotNullParameter($this$filterTo, "<this>");
        Intrinsics.checkNotNullParameter(destination, "destination");
        Intrinsics.checkNotNullParameter(predicate, "predicate");
        final int $i$f$filterTo = 0;
        for (final Map.Entry element : $this$filterTo.entrySet()) {
            if (predicate.invoke((Object)element)) {
                destination.put(element.getKey(), element.getValue());
            }
        }
        return destination;
    }
    
    @NotNull
    public static final <K, V> Map<K, V> filter(@NotNull final Map<? extends K, ? extends V> $this$filter, @NotNull final Function1<? super Map.Entry<? extends K, ? extends V>, Boolean> predicate) {
        // 
        // This method could not be decompiled.
        // 
        // Original Bytecode:
        // 
        //     1: ldc             "<this>"
        //     3: invokestatic    kotlin/jvm/internal/Intrinsics.checkNotNullParameter:(Ljava/lang/Object;Ljava/lang/String;)V
        //     6: aload_1         /* predicate */
        //     7: ldc_w           "predicate"
        //    10: invokestatic    kotlin/jvm/internal/Intrinsics.checkNotNullParameter:(Ljava/lang/Object;Ljava/lang/String;)V
        //    13: iconst_0       
        //    14: istore_2        /* $i$f$filter */
        //    15: aload_0         /* $this$filter */
        //    16: astore_3       
        //    17: new             Ljava/util/LinkedHashMap;
        //    20: dup            
        //    21: invokespecial   java/util/LinkedHashMap.<init>:()V
        //    24: checkcast       Ljava/util/Map;
        //    27: astore          destination$iv
        //    29: iconst_0       
        //    30: istore          $i$f$filterTo
        //    32: aload_3         /* $this$filterTo$iv */
        //    33: invokeinterface java/util/Map.entrySet:()Ljava/util/Set;
        //    38: invokeinterface java/util/Set.iterator:()Ljava/util/Iterator;
        //    43: astore          6
        //    45: aload           6
        //    47: invokeinterface java/util/Iterator.hasNext:()Z
        //    52: ifeq            109
        //    55: aload           6
        //    57: invokeinterface java/util/Iterator.next:()Ljava/lang/Object;
        //    62: checkcast       Ljava/util/Map$Entry;
        //    65: astore          element$iv
        //    67: aload_1         /* predicate */
        //    68: aload           element$iv
        //    70: invokeinterface kotlin/jvm/functions/Function1.invoke:(Ljava/lang/Object;)Ljava/lang/Object;
        //    75: checkcast       Ljava/lang/Boolean;
        //    78: invokevirtual   java/lang/Boolean.booleanValue:()Z
        //    81: ifeq            45
        //    84: aload           destination$iv
        //    86: aload           element$iv
        //    88: invokeinterface java/util/Map$Entry.getKey:()Ljava/lang/Object;
        //    93: aload           element$iv
        //    95: invokeinterface java/util/Map$Entry.getValue:()Ljava/lang/Object;
        //   100: invokeinterface java/util/Map.put:(Ljava/lang/Object;Ljava/lang/Object;)Ljava/lang/Object;
        //   105: pop            
        //   106: goto            45
        //   109: aload           destination$iv
        //   111: areturn        
        //    Signature:
        //  <K:Ljava/lang/Object;V:Ljava/lang/Object;>(Ljava/util/Map<+TK;+TV;>;Lkotlin/jvm/functions/Function1<-Ljava/util/Map$Entry<+TK;+TV;>;Ljava/lang/Boolean;>;)Ljava/util/Map<TK;TV;>;
        //    StackMapTable: 00 02 FF 00 2D 00 07 07 00 18 07 00 63 01 07 00 18 07 00 18 01 07 01 03 00 00 3F
        // 
        // The error that occurred was:
        // 
        // java.lang.NullPointerException
        // 
        throw new IllegalStateException("An error occurred while decompiling this method.");
    }
    
    @NotNull
    public static final <K, V, M extends Map<? super K, ? super V>> M filterNotTo(@NotNull final Map<? extends K, ? extends V> $this$filterNotTo, @NotNull final M destination, @NotNull final Function1<? super Map.Entry<? extends K, ? extends V>, Boolean> predicate) {
        Intrinsics.checkNotNullParameter($this$filterNotTo, "<this>");
        Intrinsics.checkNotNullParameter(destination, "destination");
        Intrinsics.checkNotNullParameter(predicate, "predicate");
        final int $i$f$filterNotTo = 0;
        for (final Map.Entry element : $this$filterNotTo.entrySet()) {
            if (!predicate.invoke((Object)element)) {
                destination.put(element.getKey(), element.getValue());
            }
        }
        return destination;
    }
    
    @NotNull
    public static final <K, V> Map<K, V> filterNot(@NotNull final Map<? extends K, ? extends V> $this$filterNot, @NotNull final Function1<? super Map.Entry<? extends K, ? extends V>, Boolean> predicate) {
        // 
        // This method could not be decompiled.
        // 
        // Original Bytecode:
        // 
        //     1: ldc             "<this>"
        //     3: invokestatic    kotlin/jvm/internal/Intrinsics.checkNotNullParameter:(Ljava/lang/Object;Ljava/lang/String;)V
        //     6: aload_1         /* predicate */
        //     7: ldc_w           "predicate"
        //    10: invokestatic    kotlin/jvm/internal/Intrinsics.checkNotNullParameter:(Ljava/lang/Object;Ljava/lang/String;)V
        //    13: iconst_0       
        //    14: istore_2        /* $i$f$filterNot */
        //    15: aload_0         /* $this$filterNot */
        //    16: astore_3       
        //    17: new             Ljava/util/LinkedHashMap;
        //    20: dup            
        //    21: invokespecial   java/util/LinkedHashMap.<init>:()V
        //    24: checkcast       Ljava/util/Map;
        //    27: astore          destination$iv
        //    29: iconst_0       
        //    30: istore          $i$f$filterNotTo
        //    32: aload_3         /* $this$filterNotTo$iv */
        //    33: invokeinterface java/util/Map.entrySet:()Ljava/util/Set;
        //    38: invokeinterface java/util/Set.iterator:()Ljava/util/Iterator;
        //    43: astore          6
        //    45: aload           6
        //    47: invokeinterface java/util/Iterator.hasNext:()Z
        //    52: ifeq            109
        //    55: aload           6
        //    57: invokeinterface java/util/Iterator.next:()Ljava/lang/Object;
        //    62: checkcast       Ljava/util/Map$Entry;
        //    65: astore          element$iv
        //    67: aload_1         /* predicate */
        //    68: aload           element$iv
        //    70: invokeinterface kotlin/jvm/functions/Function1.invoke:(Ljava/lang/Object;)Ljava/lang/Object;
        //    75: checkcast       Ljava/lang/Boolean;
        //    78: invokevirtual   java/lang/Boolean.booleanValue:()Z
        //    81: ifne            45
        //    84: aload           destination$iv
        //    86: aload           element$iv
        //    88: invokeinterface java/util/Map$Entry.getKey:()Ljava/lang/Object;
        //    93: aload           element$iv
        //    95: invokeinterface java/util/Map$Entry.getValue:()Ljava/lang/Object;
        //   100: invokeinterface java/util/Map.put:(Ljava/lang/Object;Ljava/lang/Object;)Ljava/lang/Object;
        //   105: pop            
        //   106: goto            45
        //   109: aload           destination$iv
        //   111: areturn        
        //    Signature:
        //  <K:Ljava/lang/Object;V:Ljava/lang/Object;>(Ljava/util/Map<+TK;+TV;>;Lkotlin/jvm/functions/Function1<-Ljava/util/Map$Entry<+TK;+TV;>;Ljava/lang/Boolean;>;)Ljava/util/Map<TK;TV;>;
        //    StackMapTable: 00 02 FF 00 2D 00 07 07 00 18 07 00 63 01 07 00 18 07 00 18 01 07 01 03 00 00 3F
        // 
        // The error that occurred was:
        // 
        // java.lang.NullPointerException
        // 
        throw new IllegalStateException("An error occurred while decompiling this method.");
    }
    
    @NotNull
    public static final <K, V> Map<K, V> toMap(@NotNull final Iterable<? extends Pair<? extends K, ? extends V>> $this$toMap) {
        Intrinsics.checkNotNullParameter($this$toMap, "<this>");
        if ($this$toMap instanceof Collection) {
            Map<K, V> map = null;
            switch (((Collection)$this$toMap).size()) {
                case 0: {
                    map = emptyMap();
                    break;
                }
                case 1: {
                    map = MapsKt__MapsJVMKt.mapOf((Pair<? extends K, ? extends V>)(($this$toMap instanceof List) ? ((List<Pair>)$this$toMap).get(0) : $this$toMap.iterator().next()));
                    break;
                }
                default: {
                    map = (Map<K, V>)toMap((Iterable<? extends Pair<?, ?>>)$this$toMap, (LinkedHashMap)new LinkedHashMap(MapsKt__MapsJVMKt.mapCapacity(((List<Pair>)$this$toMap).size())));
                    break;
                }
            }
            return map;
        }
        return optimizeReadOnlyMap((Map<K, ? extends V>)toMap((Iterable<? extends Pair<?, ?>>)$this$toMap, (LinkedHashMap<K, ? extends V>)new LinkedHashMap<Object, Object>()));
    }
    
    @NotNull
    public static final <K, V, M extends Map<? super K, ? super V>> M toMap(@NotNull final Iterable<? extends Pair<? extends K, ? extends V>> $this$toMap, @NotNull final M destination) {
        Intrinsics.checkNotNullParameter($this$toMap, "<this>");
        Intrinsics.checkNotNullParameter(destination, "destination");
        final Map $this$toMap_u24lambda_u247 = destination;
        final int n = 0;
        putAll((Map<? super Object, ? super Object>)$this$toMap_u24lambda_u247, (Iterable<? extends Pair<?, ?>>)$this$toMap);
        return destination;
    }
    
    @NotNull
    public static final <K, V> Map<K, V> toMap(@NotNull final Pair<? extends K, ? extends V>[] $this$toMap) {
        Intrinsics.checkNotNullParameter($this$toMap, "<this>");
        Map<K, V> map = null;
        switch (((Pair<? extends K, ? extends V>[])$this$toMap).length) {
            case 0: {
                map = emptyMap();
                break;
            }
            case 1: {
                map = MapsKt__MapsJVMKt.mapOf($this$toMap[0]);
                break;
            }
            default: {
                map = (Map<K, V>)toMap((Pair<?, ?>[])$this$toMap, (LinkedHashMap)new LinkedHashMap(MapsKt__MapsJVMKt.mapCapacity(((Pair<? extends K, ? extends V>[])$this$toMap).length)));
                break;
            }
        }
        return map;
    }
    
    @NotNull
    public static final <K, V, M extends Map<? super K, ? super V>> M toMap(@NotNull final Pair<? extends K, ? extends V>[] $this$toMap, @NotNull final M destination) {
        Intrinsics.checkNotNullParameter($this$toMap, "<this>");
        Intrinsics.checkNotNullParameter(destination, "destination");
        final Map $this$toMap_u24lambda_u248 = destination;
        final int n = 0;
        putAll((Map<? super Object, ? super Object>)$this$toMap_u24lambda_u248, (Pair<?, ?>[])$this$toMap);
        return destination;
    }
    
    @NotNull
    public static final <K, V> Map<K, V> toMap(@NotNull final Sequence<? extends Pair<? extends K, ? extends V>> $this$toMap) {
        Intrinsics.checkNotNullParameter($this$toMap, "<this>");
        return optimizeReadOnlyMap((Map<K, ? extends V>)toMap((Sequence<? extends Pair<?, ?>>)$this$toMap, (LinkedHashMap<K, ? extends V>)new LinkedHashMap<Object, Object>()));
    }
    
    @NotNull
    public static final <K, V, M extends Map<? super K, ? super V>> M toMap(@NotNull final Sequence<? extends Pair<? extends K, ? extends V>> $this$toMap, @NotNull final M destination) {
        Intrinsics.checkNotNullParameter($this$toMap, "<this>");
        Intrinsics.checkNotNullParameter(destination, "destination");
        final Map $this$toMap_u24lambda_u249 = destination;
        final int n = 0;
        putAll((Map<? super Object, ? super Object>)$this$toMap_u24lambda_u249, (Sequence<? extends Pair<?, ?>>)$this$toMap);
        return destination;
    }
    
    @SinceKotlin(version = "1.1")
    @NotNull
    public static final <K, V> Map<K, V> toMap(@NotNull final Map<? extends K, ? extends V> $this$toMap) {
        Intrinsics.checkNotNullParameter($this$toMap, "<this>");
        Object o = null;
        switch ($this$toMap.size()) {
            case 0: {
                o = emptyMap();
                break;
            }
            case 1: {
                o = MapsKt__MapsJVMKt.toSingletonMap((Map<?, ?>)$this$toMap);
                break;
            }
            default: {
                o = toMutableMap((Map<?, ?>)$this$toMap);
                break;
            }
        }
        return (Map<K, V>)o;
    }
    
    @SinceKotlin(version = "1.1")
    @NotNull
    public static final <K, V> Map<K, V> toMutableMap(@NotNull final Map<? extends K, ? extends V> $this$toMutableMap) {
        Intrinsics.checkNotNullParameter($this$toMutableMap, "<this>");
        return new LinkedHashMap<K, V>($this$toMutableMap);
    }
    
    @SinceKotlin(version = "1.1")
    @NotNull
    public static final <K, V, M extends Map<? super K, ? super V>> M toMap(@NotNull final Map<? extends K, ? extends V> $this$toMap, @NotNull final M destination) {
        Intrinsics.checkNotNullParameter($this$toMap, "<this>");
        Intrinsics.checkNotNullParameter(destination, "destination");
        final Map $this$toMap_u24lambda_u2410 = destination;
        final int n = 0;
        $this$toMap_u24lambda_u2410.putAll($this$toMap);
        return destination;
    }
    
    @NotNull
    public static final <K, V> Map<K, V> plus(@NotNull final Map<? extends K, ? extends V> $this$plus, @NotNull final Pair<? extends K, ? extends V> pair) {
        Intrinsics.checkNotNullParameter($this$plus, "<this>");
        Intrinsics.checkNotNullParameter(pair, "pair");
        Map<K, V> map;
        if ($this$plus.isEmpty()) {
            map = MapsKt__MapsJVMKt.mapOf(pair);
        }
        else {
            final LinkedHashMap $this$plus_u24lambda_u2411;
            final LinkedHashMap linkedHashMap = $this$plus_u24lambda_u2411 = new LinkedHashMap((Map<? extends K, ? extends V>)$this$plus);
            final int n = 0;
            $this$plus_u24lambda_u2411.put(pair.getFirst(), pair.getSecond());
            map = (LinkedHashMap<K, V>)linkedHashMap;
        }
        return map;
    }
    
    @NotNull
    public static final <K, V> Map<K, V> plus(@NotNull final Map<? extends K, ? extends V> $this$plus, @NotNull final Iterable<? extends Pair<? extends K, ? extends V>> pairs) {
        Intrinsics.checkNotNullParameter($this$plus, "<this>");
        Intrinsics.checkNotNullParameter(pairs, "pairs");
        Map<K, V> map;
        if ($this$plus.isEmpty()) {
            map = toMap(pairs);
        }
        else {
            final LinkedHashMap $this$plus_u24lambda_u2412;
            final LinkedHashMap linkedHashMap = $this$plus_u24lambda_u2412 = new LinkedHashMap((Map<? extends K, ? extends V>)$this$plus);
            final int n = 0;
            putAll((Map<? super Object, ? super Object>)$this$plus_u24lambda_u2412, (Iterable<? extends Pair<?, ?>>)pairs);
            map = (LinkedHashMap<K, V>)linkedHashMap;
        }
        return map;
    }
    
    @NotNull
    public static final <K, V> Map<K, V> plus(@NotNull final Map<? extends K, ? extends V> $this$plus, @NotNull final Pair<? extends K, ? extends V>[] pairs) {
        Intrinsics.checkNotNullParameter($this$plus, "<this>");
        Intrinsics.checkNotNullParameter(pairs, "pairs");
        Map<K, V> map;
        if ($this$plus.isEmpty()) {
            map = toMap(pairs);
        }
        else {
            final LinkedHashMap $this$plus_u24lambda_u2413;
            final LinkedHashMap linkedHashMap = $this$plus_u24lambda_u2413 = new LinkedHashMap((Map<? extends K, ? extends V>)$this$plus);
            final int n = 0;
            putAll((Map<? super Object, ? super Object>)$this$plus_u24lambda_u2413, (Pair<?, ?>[])pairs);
            map = (LinkedHashMap<K, V>)linkedHashMap;
        }
        return map;
    }
    
    @NotNull
    public static final <K, V> Map<K, V> plus(@NotNull final Map<? extends K, ? extends V> $this$plus, @NotNull final Sequence<? extends Pair<? extends K, ? extends V>> pairs) {
        Intrinsics.checkNotNullParameter($this$plus, "<this>");
        Intrinsics.checkNotNullParameter(pairs, "pairs");
        final LinkedHashMap $this$plus_u24lambda_u2414;
        final LinkedHashMap linkedHashMap = $this$plus_u24lambda_u2414 = new LinkedHashMap((Map<? extends K, ? extends V>)$this$plus);
        final int n = 0;
        putAll((Map<? super Object, ? super Object>)$this$plus_u24lambda_u2414, (Sequence<? extends Pair<?, ?>>)pairs);
        return (Map<K, V>)optimizeReadOnlyMap((Map<K, ?>)linkedHashMap);
    }
    
    @NotNull
    public static final <K, V> Map<K, V> plus(@NotNull final Map<? extends K, ? extends V> $this$plus, @NotNull final Map<? extends K, ? extends V> map) {
        Intrinsics.checkNotNullParameter($this$plus, "<this>");
        Intrinsics.checkNotNullParameter(map, "map");
        final LinkedHashMap $this$plus_u24lambda_u2415;
        final LinkedHashMap linkedHashMap = $this$plus_u24lambda_u2415 = new LinkedHashMap((Map<? extends K, ? extends V>)$this$plus);
        final int n = 0;
        $this$plus_u24lambda_u2415.putAll(map);
        return (LinkedHashMap<K, V>)linkedHashMap;
    }
    
    @InlineOnly
    private static final <K, V> void plusAssign(final Map<? super K, ? super V> $this$plusAssign, final Pair<? extends K, ? extends V> pair) {
        Intrinsics.checkNotNullParameter($this$plusAssign, "<this>");
        Intrinsics.checkNotNullParameter(pair, "pair");
        $this$plusAssign.put((Object)pair.getFirst(), (Object)pair.getSecond());
    }
    
    @InlineOnly
    private static final <K, V> void plusAssign(final Map<? super K, ? super V> $this$plusAssign, final Iterable<? extends Pair<? extends K, ? extends V>> pairs) {
        Intrinsics.checkNotNullParameter($this$plusAssign, "<this>");
        Intrinsics.checkNotNullParameter(pairs, "pairs");
        putAll((Map<? super Object, ? super Object>)$this$plusAssign, (Iterable<? extends Pair<?, ?>>)pairs);
    }
    
    @InlineOnly
    private static final <K, V> void plusAssign(final Map<? super K, ? super V> $this$plusAssign, final Pair<? extends K, ? extends V>[] pairs) {
        Intrinsics.checkNotNullParameter($this$plusAssign, "<this>");
        Intrinsics.checkNotNullParameter(pairs, "pairs");
        putAll((Map<? super Object, ? super Object>)$this$plusAssign, (Pair<?, ?>[])pairs);
    }
    
    @InlineOnly
    private static final <K, V> void plusAssign(final Map<? super K, ? super V> $this$plusAssign, final Sequence<? extends Pair<? extends K, ? extends V>> pairs) {
        Intrinsics.checkNotNullParameter($this$plusAssign, "<this>");
        Intrinsics.checkNotNullParameter(pairs, "pairs");
        putAll((Map<? super Object, ? super Object>)$this$plusAssign, (Sequence<? extends Pair<?, ?>>)pairs);
    }
    
    @InlineOnly
    private static final <K, V> void plusAssign(final Map<? super K, ? super V> $this$plusAssign, final Map<K, ? extends V> map) {
        Intrinsics.checkNotNullParameter($this$plusAssign, "<this>");
        Intrinsics.checkNotNullParameter(map, "map");
        $this$plusAssign.putAll((Map<? extends K, ? extends V>)map);
    }
    
    @SinceKotlin(version = "1.1")
    @NotNull
    public static final <K, V> Map<K, V> minus(@NotNull final Map<? extends K, ? extends V> $this$minus, final K key) {
        Intrinsics.checkNotNullParameter($this$minus, "<this>");
        final Map $this$minus_u24lambda_u2416;
        final Map $this$optimizeReadOnlyMap = $this$minus_u24lambda_u2416 = toMutableMap((Map<?, ?>)$this$minus);
        final int n = 0;
        $this$minus_u24lambda_u2416.remove(key);
        return optimizeReadOnlyMap((Map<K, ? extends V>)$this$optimizeReadOnlyMap);
    }
    
    @SinceKotlin(version = "1.1")
    @NotNull
    public static final <K, V> Map<K, V> minus(@NotNull final Map<? extends K, ? extends V> $this$minus, @NotNull final Iterable<? extends K> keys) {
        Intrinsics.checkNotNullParameter($this$minus, "<this>");
        Intrinsics.checkNotNullParameter(keys, "keys");
        final Map $this$minus_u24lambda_u2417;
        final Map $this$optimizeReadOnlyMap = $this$minus_u24lambda_u2417 = toMutableMap((Map<?, ?>)$this$minus);
        final int n = 0;
        CollectionsKt__MutableCollectionsKt.removeAll((Collection<? super Object>)$this$minus_u24lambda_u2417.keySet(), (Iterable<?>)keys);
        return optimizeReadOnlyMap((Map<K, ? extends V>)$this$optimizeReadOnlyMap);
    }
    
    @SinceKotlin(version = "1.1")
    @NotNull
    public static final <K, V> Map<K, V> minus(@NotNull final Map<? extends K, ? extends V> $this$minus, @NotNull final K[] keys) {
        Intrinsics.checkNotNullParameter($this$minus, "<this>");
        Intrinsics.checkNotNullParameter(keys, "keys");
        final Map $this$minus_u24lambda_u2418;
        final Map $this$optimizeReadOnlyMap = $this$minus_u24lambda_u2418 = toMutableMap((Map<?, ?>)$this$minus);
        final int n = 0;
        CollectionsKt__MutableCollectionsKt.removeAll($this$minus_u24lambda_u2418.keySet(), keys);
        return optimizeReadOnlyMap((Map<K, ? extends V>)$this$optimizeReadOnlyMap);
    }
    
    @SinceKotlin(version = "1.1")
    @NotNull
    public static final <K, V> Map<K, V> minus(@NotNull final Map<? extends K, ? extends V> $this$minus, @NotNull final Sequence<? extends K> keys) {
        Intrinsics.checkNotNullParameter($this$minus, "<this>");
        Intrinsics.checkNotNullParameter(keys, "keys");
        final Map $this$minus_u24lambda_u2419;
        final Map $this$optimizeReadOnlyMap = $this$minus_u24lambda_u2419 = toMutableMap((Map<?, ?>)$this$minus);
        final int n = 0;
        CollectionsKt__MutableCollectionsKt.removeAll((Collection<? super Object>)$this$minus_u24lambda_u2419.keySet(), (Sequence<?>)keys);
        return optimizeReadOnlyMap((Map<K, ? extends V>)$this$optimizeReadOnlyMap);
    }
    
    @SinceKotlin(version = "1.1")
    @InlineOnly
    private static final <K, V> void minusAssign(final Map<K, V> $this$minusAssign, final K key) {
        Intrinsics.checkNotNullParameter($this$minusAssign, "<this>");
        $this$minusAssign.remove(key);
    }
    
    @SinceKotlin(version = "1.1")
    @InlineOnly
    private static final <K, V> void minusAssign(final Map<K, V> $this$minusAssign, final Iterable<? extends K> keys) {
        Intrinsics.checkNotNullParameter($this$minusAssign, "<this>");
        Intrinsics.checkNotNullParameter(keys, "keys");
        CollectionsKt__MutableCollectionsKt.removeAll((Collection<? super Object>)$this$minusAssign.keySet(), (Iterable<?>)keys);
    }
    
    @SinceKotlin(version = "1.1")
    @InlineOnly
    private static final <K, V> void minusAssign(final Map<K, V> $this$minusAssign, final K[] keys) {
        Intrinsics.checkNotNullParameter($this$minusAssign, "<this>");
        Intrinsics.checkNotNullParameter(keys, "keys");
        CollectionsKt__MutableCollectionsKt.removeAll($this$minusAssign.keySet(), keys);
    }
    
    @SinceKotlin(version = "1.1")
    @InlineOnly
    private static final <K, V> void minusAssign(final Map<K, V> $this$minusAssign, final Sequence<? extends K> keys) {
        Intrinsics.checkNotNullParameter($this$minusAssign, "<this>");
        Intrinsics.checkNotNullParameter(keys, "keys");
        CollectionsKt__MutableCollectionsKt.removeAll((Collection<? super Object>)$this$minusAssign.keySet(), (Sequence<?>)keys);
    }
    
    @NotNull
    public static final <K, V> Map<K, V> optimizeReadOnlyMap(@NotNull final Map<K, ? extends V> $this$optimizeReadOnlyMap) {
        Intrinsics.checkNotNullParameter($this$optimizeReadOnlyMap, "<this>");
        Object o = null;
        switch ($this$optimizeReadOnlyMap.size()) {
            case 0: {
                o = emptyMap();
                break;
            }
            case 1: {
                o = MapsKt__MapsJVMKt.toSingletonMap((Map<?, ?>)$this$optimizeReadOnlyMap);
                break;
            }
            default: {
                o = $this$optimizeReadOnlyMap;
                break;
            }
        }
        return (Map<K, V>)o;
    }
    
    public MapsKt__MapsKt() {
    }
}
