// 
// Decompiled by Procyon v0.5.36
// 

package kotlin.sequences;

import kotlin.jvm.internal.markers.KMappedMarker;
import kotlin.collections.SlidingWindowKt;
import kotlin.ULong;
import kotlin.ExperimentalUnsignedTypes;
import kotlin.UInt;
import kotlin.DeprecatedSinceKotlin;
import kotlin.ReplaceWith;
import kotlin.Deprecated;
import kotlin.coroutines.Continuation;
import kotlin.ExperimentalStdlibApi;
import kotlin.WasExperimental;
import kotlin.Unit;
import kotlin.jvm.functions.Function3;
import kotlin.collections.IndexedValue;
import kotlin.collections.Grouping;
import kotlin.jvm.JvmName;
import kotlin.OverloadResolutionByLambdaReturnType;
import java.util.LinkedHashSet;
import java.util.Set;
import java.util.ArrayList;
import java.util.List;
import java.util.HashSet;
import java.util.LinkedHashMap;
import java.util.Map;
import kotlin.Pair;
import kotlin.comparisons.ComparisonsKt__ComparisonsKt$compareByDescending;
import java.util.Comparator;
import kotlin.comparisons.ComparisonsKt__ComparisonsKt$compareBy;
import java.util.Collection;
import kotlin.jvm.functions.Function2;
import kotlin.collections.CollectionsKt;
import kotlin.SinceKotlin;
import java.util.NoSuchElementException;
import kotlin.internal.InlineOnly;
import org.jetbrains.annotations.Nullable;
import java.util.Iterator;
import kotlin.jvm.functions.Function1;
import kotlin.jvm.internal.Intrinsics;
import org.jetbrains.annotations.NotNull;
import kotlin.Metadata;

@Metadata(mv = { 1, 7, 1 }, k = 5, xi = 49, d1 = { "\u0000\u0098\u0002\n\u0000\n\u0002\u0010\u000b\n\u0000\n\u0002\u0018\u0002\n\u0000\n\u0002\u0018\u0002\n\u0002\b\u0002\n\u0002\u0010\u001c\n\u0002\b\u0002\n\u0002\u0010$\n\u0002\b\u0003\n\u0002\u0018\u0002\n\u0002\b\u0005\n\u0002\u0010%\n\u0002\b\b\n\u0002\u0010\u0006\n\u0002\u0010\u0005\n\u0002\b\u0002\n\u0002\u0010\u0007\n\u0000\n\u0002\u0010\b\n\u0000\n\u0002\u0010\t\n\u0000\n\u0002\u0010\n\n\u0002\b\u0002\n\u0002\u0010 \n\u0002\b\u0003\n\u0002\u0018\u0002\n\u0002\b\u0012\n\u0002\u0018\u0002\n\u0002\u0018\u0002\n\u0002\b\u0003\n\u0002\u0010\u001f\n\u0002\b\u0002\n\u0002\u0018\u0002\n\u0002\b\u0004\n\u0002\u0010\u0000\n\u0002\b\u001c\n\u0002\u0018\u0002\n\u0002\b\u0002\n\u0002\u0010\u0002\n\u0002\b\u0004\n\u0002\u0010!\n\u0000\n\u0002\u0018\u0002\n\u0002\b\u0006\n\u0002\u0018\u0002\n\u0002\u0018\u0002\n\u0002\b\u0002\n\u0002\u0010\r\n\u0002\b\u0006\n\u0002\u0010\u000e\n\u0002\b\f\n\u0002\u0010\u000f\n\u0002\b\f\n\u0002\u0018\u0002\n\u0002\u0018\u0002\n\u0002\b\u0019\n\u0002\u0010\u0011\n\u0002\b)\n\u0002\u0018\u0002\n\u0002\b\u0002\n\u0002\u0018\u0002\n\u0002\b\u0006\n\u0002\u0018\u0002\n\u0002\u0018\u0002\n\u0002\b\u0003\n\u0002\u0010#\n\u0000\n\u0002\u0010\"\n\u0002\b\u0004\n\u0002\u0018\u0002\n\u0002\b\u0006\u001a0\u0010\u0000\u001a\u00020\u0001\"\u0004\b\u0000\u0010\u0002*\b\u0012\u0004\u0012\u0002H\u00020\u00032\u0012\u0010\u0004\u001a\u000e\u0012\u0004\u0012\u0002H\u0002\u0012\u0004\u0012\u00020\u00010\u0005H\u0086\b\u00f8\u0001\u0000\u001a\u0016\u0010\u0006\u001a\u00020\u0001\"\u0004\b\u0000\u0010\u0002*\b\u0012\u0004\u0012\u0002H\u00020\u0003\u001a0\u0010\u0006\u001a\u00020\u0001\"\u0004\b\u0000\u0010\u0002*\b\u0012\u0004\u0012\u0002H\u00020\u00032\u0012\u0010\u0004\u001a\u000e\u0012\u0004\u0012\u0002H\u0002\u0012\u0004\u0012\u00020\u00010\u0005H\u0086\b\u00f8\u0001\u0000\u001a\u001c\u0010\u0007\u001a\b\u0012\u0004\u0012\u0002H\u00020\b\"\u0004\b\u0000\u0010\u0002*\b\u0012\u0004\u0012\u0002H\u00020\u0003\u001a\u001f\u0010\t\u001a\b\u0012\u0004\u0012\u0002H\u00020\u0003\"\u0004\b\u0000\u0010\u0002*\b\u0012\u0004\u0012\u0002H\u00020\u0003H\u0087\b\u001aT\u0010\n\u001a\u000e\u0012\u0004\u0012\u0002H\f\u0012\u0004\u0012\u0002H\r0\u000b\"\u0004\b\u0000\u0010\u0002\"\u0004\b\u0001\u0010\f\"\u0004\b\u0002\u0010\r*\b\u0012\u0004\u0012\u0002H\u00020\u00032\u001e\u0010\u000e\u001a\u001a\u0012\u0004\u0012\u0002H\u0002\u0012\u0010\u0012\u000e\u0012\u0004\u0012\u0002H\f\u0012\u0004\u0012\u0002H\r0\u000f0\u0005H\u0086\b\u00f8\u0001\u0000\u001aB\u0010\u0010\u001a\u000e\u0012\u0004\u0012\u0002H\f\u0012\u0004\u0012\u0002H\u00020\u000b\"\u0004\b\u0000\u0010\u0002\"\u0004\b\u0001\u0010\f*\b\u0012\u0004\u0012\u0002H\u00020\u00032\u0012\u0010\u0011\u001a\u000e\u0012\u0004\u0012\u0002H\u0002\u0012\u0004\u0012\u0002H\f0\u0005H\u0086\b\u00f8\u0001\u0000\u001a\\\u0010\u0010\u001a\u000e\u0012\u0004\u0012\u0002H\f\u0012\u0004\u0012\u0002H\r0\u000b\"\u0004\b\u0000\u0010\u0002\"\u0004\b\u0001\u0010\f\"\u0004\b\u0002\u0010\r*\b\u0012\u0004\u0012\u0002H\u00020\u00032\u0012\u0010\u0011\u001a\u000e\u0012\u0004\u0012\u0002H\u0002\u0012\u0004\u0012\u0002H\f0\u00052\u0012\u0010\u0012\u001a\u000e\u0012\u0004\u0012\u0002H\u0002\u0012\u0004\u0012\u0002H\r0\u0005H\u0086\b\u00f8\u0001\u0000\u001a]\u0010\u0013\u001a\u0002H\u0014\"\u0004\b\u0000\u0010\u0002\"\u0004\b\u0001\u0010\f\"\u0018\b\u0002\u0010\u0014*\u0012\u0012\u0006\b\u0000\u0012\u0002H\f\u0012\u0006\b\u0000\u0012\u0002H\u00020\u0015*\b\u0012\u0004\u0012\u0002H\u00020\u00032\u0006\u0010\u0016\u001a\u0002H\u00142\u0012\u0010\u0011\u001a\u000e\u0012\u0004\u0012\u0002H\u0002\u0012\u0004\u0012\u0002H\f0\u0005H\u0086\b\u00f8\u0001\u0000¢\u0006\u0002\u0010\u0017\u001aw\u0010\u0013\u001a\u0002H\u0014\"\u0004\b\u0000\u0010\u0002\"\u0004\b\u0001\u0010\f\"\u0004\b\u0002\u0010\r\"\u0018\b\u0003\u0010\u0014*\u0012\u0012\u0006\b\u0000\u0012\u0002H\f\u0012\u0006\b\u0000\u0012\u0002H\r0\u0015*\b\u0012\u0004\u0012\u0002H\u00020\u00032\u0006\u0010\u0016\u001a\u0002H\u00142\u0012\u0010\u0011\u001a\u000e\u0012\u0004\u0012\u0002H\u0002\u0012\u0004\u0012\u0002H\f0\u00052\u0012\u0010\u0012\u001a\u000e\u0012\u0004\u0012\u0002H\u0002\u0012\u0004\u0012\u0002H\r0\u0005H\u0086\b\u00f8\u0001\u0000¢\u0006\u0002\u0010\u0018\u001ao\u0010\u0019\u001a\u0002H\u0014\"\u0004\b\u0000\u0010\u0002\"\u0004\b\u0001\u0010\f\"\u0004\b\u0002\u0010\r\"\u0018\b\u0003\u0010\u0014*\u0012\u0012\u0006\b\u0000\u0012\u0002H\f\u0012\u0006\b\u0000\u0012\u0002H\r0\u0015*\b\u0012\u0004\u0012\u0002H\u00020\u00032\u0006\u0010\u0016\u001a\u0002H\u00142\u001e\u0010\u000e\u001a\u001a\u0012\u0004\u0012\u0002H\u0002\u0012\u0010\u0012\u000e\u0012\u0004\u0012\u0002H\f\u0012\u0004\u0012\u0002H\r0\u000f0\u0005H\u0086\b\u00f8\u0001\u0000¢\u0006\u0002\u0010\u0017\u001aB\u0010\u001a\u001a\u000e\u0012\u0004\u0012\u0002H\f\u0012\u0004\u0012\u0002H\r0\u000b\"\u0004\b\u0000\u0010\f\"\u0004\b\u0001\u0010\r*\b\u0012\u0004\u0012\u0002H\f0\u00032\u0012\u0010\u001b\u001a\u000e\u0012\u0004\u0012\u0002H\f\u0012\u0004\u0012\u0002H\r0\u0005H\u0087\b\u00f8\u0001\u0000\u001a]\u0010\u001c\u001a\u0002H\u0014\"\u0004\b\u0000\u0010\f\"\u0004\b\u0001\u0010\r\"\u0018\b\u0002\u0010\u0014*\u0012\u0012\u0006\b\u0000\u0012\u0002H\f\u0012\u0006\b\u0000\u0012\u0002H\r0\u0015*\b\u0012\u0004\u0012\u0002H\f0\u00032\u0006\u0010\u0016\u001a\u0002H\u00142\u0012\u0010\u001b\u001a\u000e\u0012\u0004\u0012\u0002H\f\u0012\u0004\u0012\u0002H\r0\u0005H\u0087\b\u00f8\u0001\u0000¢\u0006\u0002\u0010\u0017\u001a\u0017\u0010\u001d\u001a\u00020\u001e*\b\u0012\u0004\u0012\u00020\u001f0\u0003H\u0007¢\u0006\u0002\b \u001a\u0017\u0010\u001d\u001a\u00020\u001e*\b\u0012\u0004\u0012\u00020\u001e0\u0003H\u0007¢\u0006\u0002\b!\u001a\u0017\u0010\u001d\u001a\u00020\u001e*\b\u0012\u0004\u0012\u00020\"0\u0003H\u0007¢\u0006\u0002\b#\u001a\u0017\u0010\u001d\u001a\u00020\u001e*\b\u0012\u0004\u0012\u00020$0\u0003H\u0007¢\u0006\u0002\b%\u001a\u0017\u0010\u001d\u001a\u00020\u001e*\b\u0012\u0004\u0012\u00020&0\u0003H\u0007¢\u0006\u0002\b'\u001a\u0017\u0010\u001d\u001a\u00020\u001e*\b\u0012\u0004\u0012\u00020(0\u0003H\u0007¢\u0006\u0002\b)\u001a,\u0010*\u001a\u000e\u0012\n\u0012\b\u0012\u0004\u0012\u0002H\u00020+0\u0003\"\u0004\b\u0000\u0010\u0002*\b\u0012\u0004\u0012\u0002H\u00020\u00032\u0006\u0010,\u001a\u00020$H\u0007\u001aF\u0010*\u001a\b\u0012\u0004\u0012\u0002H-0\u0003\"\u0004\b\u0000\u0010\u0002\"\u0004\b\u0001\u0010-*\b\u0012\u0004\u0012\u0002H\u00020\u00032\u0006\u0010,\u001a\u00020$2\u0018\u0010\u000e\u001a\u0014\u0012\n\u0012\b\u0012\u0004\u0012\u0002H\u00020+\u0012\u0004\u0012\u0002H-0\u0005H\u0007\u001a+\u0010.\u001a\u00020\u0001\"\t\b\u0000\u0010\u0002¢\u0006\u0002\b/*\b\u0012\u0004\u0012\u0002H\u00020\u00032\u0006\u00100\u001a\u0002H\u0002H\u0086\u0002¢\u0006\u0002\u00101\u001a\u0016\u00102\u001a\u00020$\"\u0004\b\u0000\u0010\u0002*\b\u0012\u0004\u0012\u0002H\u00020\u0003\u001a0\u00102\u001a\u00020$\"\u0004\b\u0000\u0010\u0002*\b\u0012\u0004\u0012\u0002H\u00020\u00032\u0012\u0010\u0004\u001a\u000e\u0012\u0004\u0012\u0002H\u0002\u0012\u0004\u0012\u00020\u00010\u0005H\u0086\b\u00f8\u0001\u0000\u001a\u001c\u00103\u001a\b\u0012\u0004\u0012\u0002H\u00020\u0003\"\u0004\b\u0000\u0010\u0002*\b\u0012\u0004\u0012\u0002H\u00020\u0003\u001a6\u00104\u001a\b\u0012\u0004\u0012\u0002H\u00020\u0003\"\u0004\b\u0000\u0010\u0002\"\u0004\b\u0001\u0010\f*\b\u0012\u0004\u0012\u0002H\u00020\u00032\u0012\u00105\u001a\u000e\u0012\u0004\u0012\u0002H\u0002\u0012\u0004\u0012\u0002H\f0\u0005\u001a$\u00106\u001a\b\u0012\u0004\u0012\u0002H\u00020\u0003\"\u0004\b\u0000\u0010\u0002*\b\u0012\u0004\u0012\u0002H\u00020\u00032\u0006\u00107\u001a\u00020$\u001a0\u00108\u001a\b\u0012\u0004\u0012\u0002H\u00020\u0003\"\u0004\b\u0000\u0010\u0002*\b\u0012\u0004\u0012\u0002H\u00020\u00032\u0012\u0010\u0004\u001a\u000e\u0012\u0004\u0012\u0002H\u0002\u0012\u0004\u0012\u00020\u00010\u0005\u001a#\u00109\u001a\u0002H\u0002\"\u0004\b\u0000\u0010\u0002*\b\u0012\u0004\u0012\u0002H\u00020\u00032\u0006\u0010:\u001a\u00020$¢\u0006\u0002\u0010;\u001a7\u0010<\u001a\u0002H\u0002\"\u0004\b\u0000\u0010\u0002*\b\u0012\u0004\u0012\u0002H\u00020\u00032\u0006\u0010:\u001a\u00020$2\u0012\u0010=\u001a\u000e\u0012\u0004\u0012\u00020$\u0012\u0004\u0012\u0002H\u00020\u0005¢\u0006\u0002\u0010>\u001a%\u0010?\u001a\u0004\u0018\u0001H\u0002\"\u0004\b\u0000\u0010\u0002*\b\u0012\u0004\u0012\u0002H\u00020\u00032\u0006\u0010:\u001a\u00020$¢\u0006\u0002\u0010;\u001a0\u0010@\u001a\b\u0012\u0004\u0012\u0002H\u00020\u0003\"\u0004\b\u0000\u0010\u0002*\b\u0012\u0004\u0012\u0002H\u00020\u00032\u0012\u0010\u0004\u001a\u000e\u0012\u0004\u0012\u0002H\u0002\u0012\u0004\u0012\u00020\u00010\u0005\u001aE\u0010A\u001a\b\u0012\u0004\u0012\u0002H\u00020\u0003\"\u0004\b\u0000\u0010\u0002*\b\u0012\u0004\u0012\u0002H\u00020\u00032'\u0010\u0004\u001a#\u0012\u0013\u0012\u00110$¢\u0006\f\bC\u0012\b\bD\u0012\u0004\b\b(:\u0012\u0004\u0012\u0002H\u0002\u0012\u0004\u0012\u00020\u00010B\u001ad\u0010E\u001a\u0002HF\"\u0004\b\u0000\u0010\u0002\"\u0010\b\u0001\u0010F*\n\u0012\u0006\b\u0000\u0012\u0002H\u00020G*\b\u0012\u0004\u0012\u0002H\u00020\u00032\u0006\u0010\u0016\u001a\u0002HF2'\u0010\u0004\u001a#\u0012\u0013\u0012\u00110$¢\u0006\f\bC\u0012\b\bD\u0012\u0004\b\b(:\u0012\u0004\u0012\u0002H\u0002\u0012\u0004\u0012\u00020\u00010BH\u0086\b\u00f8\u0001\u0000¢\u0006\u0002\u0010H\u001a$\u0010I\u001a\r\u0012\t\u0012\u0007H-¢\u0006\u0002\bJ0\u0003\"\u0006\b\u0000\u0010-\u0018\u0001*\u0006\u0012\u0002\b\u00030\u0003H\u0086\b\u001a8\u0010K\u001a\u0002HF\"\u0006\b\u0000\u0010-\u0018\u0001\"\u0010\b\u0001\u0010F*\n\u0012\u0006\b\u0000\u0012\u0002H-0G*\u0006\u0012\u0002\b\u00030\u00032\u0006\u0010\u0016\u001a\u0002HFH\u0086\b¢\u0006\u0002\u0010L\u001a0\u0010M\u001a\b\u0012\u0004\u0012\u0002H\u00020\u0003\"\u0004\b\u0000\u0010\u0002*\b\u0012\u0004\u0012\u0002H\u00020\u00032\u0012\u0010\u0004\u001a\u000e\u0012\u0004\u0012\u0002H\u0002\u0012\u0004\u0012\u00020\u00010\u0005\u001a\"\u0010N\u001a\b\u0012\u0004\u0012\u0002H\u00020\u0003\"\b\b\u0000\u0010\u0002*\u00020O*\n\u0012\u0006\u0012\u0004\u0018\u0001H\u00020\u0003\u001a;\u0010P\u001a\u0002HF\"\u0010\b\u0000\u0010F*\n\u0012\u0006\b\u0000\u0012\u0002H\u00020G\"\b\b\u0001\u0010\u0002*\u00020O*\n\u0012\u0006\u0012\u0004\u0018\u0001H\u00020\u00032\u0006\u0010\u0016\u001a\u0002HF¢\u0006\u0002\u0010L\u001aO\u0010Q\u001a\u0002HF\"\u0004\b\u0000\u0010\u0002\"\u0010\b\u0001\u0010F*\n\u0012\u0006\b\u0000\u0012\u0002H\u00020G*\b\u0012\u0004\u0012\u0002H\u00020\u00032\u0006\u0010\u0016\u001a\u0002HF2\u0012\u0010\u0004\u001a\u000e\u0012\u0004\u0012\u0002H\u0002\u0012\u0004\u0012\u00020\u00010\u0005H\u0086\b\u00f8\u0001\u0000¢\u0006\u0002\u0010R\u001aO\u0010S\u001a\u0002HF\"\u0004\b\u0000\u0010\u0002\"\u0010\b\u0001\u0010F*\n\u0012\u0006\b\u0000\u0012\u0002H\u00020G*\b\u0012\u0004\u0012\u0002H\u00020\u00032\u0006\u0010\u0016\u001a\u0002HF2\u0012\u0010\u0004\u001a\u000e\u0012\u0004\u0012\u0002H\u0002\u0012\u0004\u0012\u00020\u00010\u0005H\u0086\b\u00f8\u0001\u0000¢\u0006\u0002\u0010R\u001a7\u0010T\u001a\u0004\u0018\u0001H\u0002\"\u0004\b\u0000\u0010\u0002*\b\u0012\u0004\u0012\u0002H\u00020\u00032\u0012\u0010\u0004\u001a\u000e\u0012\u0004\u0012\u0002H\u0002\u0012\u0004\u0012\u00020\u00010\u0005H\u0087\b\u00f8\u0001\u0000¢\u0006\u0002\u0010U\u001a7\u0010V\u001a\u0004\u0018\u0001H\u0002\"\u0004\b\u0000\u0010\u0002*\b\u0012\u0004\u0012\u0002H\u00020\u00032\u0012\u0010\u0004\u001a\u000e\u0012\u0004\u0012\u0002H\u0002\u0012\u0004\u0012\u00020\u00010\u0005H\u0087\b\u00f8\u0001\u0000¢\u0006\u0002\u0010U\u001a\u001b\u0010W\u001a\u0002H\u0002\"\u0004\b\u0000\u0010\u0002*\b\u0012\u0004\u0012\u0002H\u00020\u0003¢\u0006\u0002\u0010X\u001a5\u0010W\u001a\u0002H\u0002\"\u0004\b\u0000\u0010\u0002*\b\u0012\u0004\u0012\u0002H\u00020\u00032\u0012\u0010\u0004\u001a\u000e\u0012\u0004\u0012\u0002H\u0002\u0012\u0004\u0012\u00020\u00010\u0005H\u0086\b\u00f8\u0001\u0000¢\u0006\u0002\u0010U\u001aA\u0010Y\u001a\u0002H-\"\u0004\b\u0000\u0010\u0002\"\b\b\u0001\u0010-*\u00020O*\b\u0012\u0004\u0012\u0002H\u00020\u00032\u0014\u0010\u000e\u001a\u0010\u0012\u0004\u0012\u0002H\u0002\u0012\u0006\u0012\u0004\u0018\u0001H-0\u0005H\u0087\b\u00f8\u0001\u0000¢\u0006\u0002\u0010U\u001aC\u0010Z\u001a\u0004\u0018\u0001H-\"\u0004\b\u0000\u0010\u0002\"\b\b\u0001\u0010-*\u00020O*\b\u0012\u0004\u0012\u0002H\u00020\u00032\u0014\u0010\u000e\u001a\u0010\u0012\u0004\u0012\u0002H\u0002\u0012\u0006\u0012\u0004\u0018\u0001H-0\u0005H\u0087\b\u00f8\u0001\u0000¢\u0006\u0002\u0010U\u001a\u001d\u0010[\u001a\u0004\u0018\u0001H\u0002\"\u0004\b\u0000\u0010\u0002*\b\u0012\u0004\u0012\u0002H\u00020\u0003¢\u0006\u0002\u0010X\u001a7\u0010[\u001a\u0004\u0018\u0001H\u0002\"\u0004\b\u0000\u0010\u0002*\b\u0012\u0004\u0012\u0002H\u00020\u00032\u0012\u0010\u0004\u001a\u000e\u0012\u0004\u0012\u0002H\u0002\u0012\u0004\u0012\u00020\u00010\u0005H\u0086\b\u00f8\u0001\u0000¢\u0006\u0002\u0010U\u001aC\u0010\\\u001a\b\u0012\u0004\u0012\u0002H-0\u0003\"\u0004\b\u0000\u0010\u0002\"\u0004\b\u0001\u0010-*\b\u0012\u0004\u0012\u0002H\u00020\u00032\u0018\u0010\u000e\u001a\u0014\u0012\u0004\u0012\u0002H\u0002\u0012\n\u0012\b\u0012\u0004\u0012\u0002H-0\b0\u0005H\u0007¢\u0006\u0002\b]\u001a<\u0010\\\u001a\b\u0012\u0004\u0012\u0002H-0\u0003\"\u0004\b\u0000\u0010\u0002\"\u0004\b\u0001\u0010-*\b\u0012\u0004\u0012\u0002H\u00020\u00032\u0018\u0010\u000e\u001a\u0014\u0012\u0004\u0012\u0002H\u0002\u0012\n\u0012\b\u0012\u0004\u0012\u0002H-0\u00030\u0005\u001aX\u0010^\u001a\b\u0012\u0004\u0012\u0002H-0\u0003\"\u0004\b\u0000\u0010\u0002\"\u0004\b\u0001\u0010-*\b\u0012\u0004\u0012\u0002H\u00020\u00032-\u0010\u000e\u001a)\u0012\u0013\u0012\u00110$¢\u0006\f\bC\u0012\b\bD\u0012\u0004\b\b(:\u0012\u0004\u0012\u0002H\u0002\u0012\n\u0012\b\u0012\u0004\u0012\u0002H-0\b0BH\u0007¢\u0006\u0002\b_\u001aX\u0010^\u001a\b\u0012\u0004\u0012\u0002H-0\u0003\"\u0004\b\u0000\u0010\u0002\"\u0004\b\u0001\u0010-*\b\u0012\u0004\u0012\u0002H\u00020\u00032-\u0010\u000e\u001a)\u0012\u0013\u0012\u00110$¢\u0006\f\bC\u0012\b\bD\u0012\u0004\b\b(:\u0012\u0004\u0012\u0002H\u0002\u0012\n\u0012\b\u0012\u0004\u0012\u0002H-0\u00030BH\u0007¢\u0006\u0002\b`\u001ar\u0010a\u001a\u0002HF\"\u0004\b\u0000\u0010\u0002\"\u0004\b\u0001\u0010-\"\u0010\b\u0002\u0010F*\n\u0012\u0006\b\u0000\u0012\u0002H-0G*\b\u0012\u0004\u0012\u0002H\u00020\u00032\u0006\u0010\u0016\u001a\u0002HF2-\u0010\u000e\u001a)\u0012\u0013\u0012\u00110$¢\u0006\f\bC\u0012\b\bD\u0012\u0004\b\b(:\u0012\u0004\u0012\u0002H\u0002\u0012\n\u0012\b\u0012\u0004\u0012\u0002H-0\b0BH\u0087\b\u00f8\u0001\u0000¢\u0006\u0004\bb\u0010H\u001ar\u0010a\u001a\u0002HF\"\u0004\b\u0000\u0010\u0002\"\u0004\b\u0001\u0010-\"\u0010\b\u0002\u0010F*\n\u0012\u0006\b\u0000\u0012\u0002H-0G*\b\u0012\u0004\u0012\u0002H\u00020\u00032\u0006\u0010\u0016\u001a\u0002HF2-\u0010\u000e\u001a)\u0012\u0013\u0012\u00110$¢\u0006\f\bC\u0012\b\bD\u0012\u0004\b\b(:\u0012\u0004\u0012\u0002H\u0002\u0012\n\u0012\b\u0012\u0004\u0012\u0002H-0\u00030BH\u0087\b\u00f8\u0001\u0000¢\u0006\u0004\bc\u0010H\u001a]\u0010d\u001a\u0002HF\"\u0004\b\u0000\u0010\u0002\"\u0004\b\u0001\u0010-\"\u0010\b\u0002\u0010F*\n\u0012\u0006\b\u0000\u0012\u0002H-0G*\b\u0012\u0004\u0012\u0002H\u00020\u00032\u0006\u0010\u0016\u001a\u0002HF2\u0018\u0010\u000e\u001a\u0014\u0012\u0004\u0012\u0002H\u0002\u0012\n\u0012\b\u0012\u0004\u0012\u0002H-0\b0\u0005H\u0087\b\u00f8\u0001\u0000¢\u0006\u0004\be\u0010R\u001a[\u0010d\u001a\u0002HF\"\u0004\b\u0000\u0010\u0002\"\u0004\b\u0001\u0010-\"\u0010\b\u0002\u0010F*\n\u0012\u0006\b\u0000\u0012\u0002H-0G*\b\u0012\u0004\u0012\u0002H\u00020\u00032\u0006\u0010\u0016\u001a\u0002HF2\u0018\u0010\u000e\u001a\u0014\u0012\u0004\u0012\u0002H\u0002\u0012\n\u0012\b\u0012\u0004\u0012\u0002H-0\u00030\u0005H\u0086\b\u00f8\u0001\u0000¢\u0006\u0002\u0010R\u001aX\u0010f\u001a\u0002H-\"\u0004\b\u0000\u0010\u0002\"\u0004\b\u0001\u0010-*\b\u0012\u0004\u0012\u0002H\u00020\u00032\u0006\u0010g\u001a\u0002H-2'\u0010h\u001a#\u0012\u0013\u0012\u0011H-¢\u0006\f\bC\u0012\b\bD\u0012\u0004\b\b(i\u0012\u0004\u0012\u0002H\u0002\u0012\u0004\u0012\u0002H-0BH\u0086\b\u00f8\u0001\u0000¢\u0006\u0002\u0010j\u001am\u0010k\u001a\u0002H-\"\u0004\b\u0000\u0010\u0002\"\u0004\b\u0001\u0010-*\b\u0012\u0004\u0012\u0002H\u00020\u00032\u0006\u0010g\u001a\u0002H-2<\u0010h\u001a8\u0012\u0013\u0012\u00110$¢\u0006\f\bC\u0012\b\bD\u0012\u0004\b\b(:\u0012\u0013\u0012\u0011H-¢\u0006\f\bC\u0012\b\bD\u0012\u0004\b\b(i\u0012\u0004\u0012\u0002H\u0002\u0012\u0004\u0012\u0002H-0lH\u0086\b\u00f8\u0001\u0000¢\u0006\u0002\u0010m\u001a0\u0010n\u001a\u00020o\"\u0004\b\u0000\u0010\u0002*\b\u0012\u0004\u0012\u0002H\u00020\u00032\u0012\u0010p\u001a\u000e\u0012\u0004\u0012\u0002H\u0002\u0012\u0004\u0012\u00020o0\u0005H\u0086\b\u00f8\u0001\u0000\u001aE\u0010q\u001a\u00020o\"\u0004\b\u0000\u0010\u0002*\b\u0012\u0004\u0012\u0002H\u00020\u00032'\u0010p\u001a#\u0012\u0013\u0012\u00110$¢\u0006\f\bC\u0012\b\bD\u0012\u0004\b\b(:\u0012\u0004\u0012\u0002H\u0002\u0012\u0004\u0012\u00020o0BH\u0086\b\u00f8\u0001\u0000\u001aH\u0010r\u001a\u0014\u0012\u0004\u0012\u0002H\f\u0012\n\u0012\b\u0012\u0004\u0012\u0002H\u00020+0\u000b\"\u0004\b\u0000\u0010\u0002\"\u0004\b\u0001\u0010\f*\b\u0012\u0004\u0012\u0002H\u00020\u00032\u0012\u0010\u0011\u001a\u000e\u0012\u0004\u0012\u0002H\u0002\u0012\u0004\u0012\u0002H\f0\u0005H\u0086\b\u00f8\u0001\u0000\u001ab\u0010r\u001a\u0014\u0012\u0004\u0012\u0002H\f\u0012\n\u0012\b\u0012\u0004\u0012\u0002H\r0+0\u000b\"\u0004\b\u0000\u0010\u0002\"\u0004\b\u0001\u0010\f\"\u0004\b\u0002\u0010\r*\b\u0012\u0004\u0012\u0002H\u00020\u00032\u0012\u0010\u0011\u001a\u000e\u0012\u0004\u0012\u0002H\u0002\u0012\u0004\u0012\u0002H\f0\u00052\u0012\u0010\u0012\u001a\u000e\u0012\u0004\u0012\u0002H\u0002\u0012\u0004\u0012\u0002H\r0\u0005H\u0086\b\u00f8\u0001\u0000\u001aa\u0010s\u001a\u0002H\u0014\"\u0004\b\u0000\u0010\u0002\"\u0004\b\u0001\u0010\f\"\u001c\b\u0002\u0010\u0014*\u0016\u0012\u0006\b\u0000\u0012\u0002H\f\u0012\n\u0012\b\u0012\u0004\u0012\u0002H\u00020t0\u0015*\b\u0012\u0004\u0012\u0002H\u00020\u00032\u0006\u0010\u0016\u001a\u0002H\u00142\u0012\u0010\u0011\u001a\u000e\u0012\u0004\u0012\u0002H\u0002\u0012\u0004\u0012\u0002H\f0\u0005H\u0086\b\u00f8\u0001\u0000¢\u0006\u0002\u0010\u0017\u001a{\u0010s\u001a\u0002H\u0014\"\u0004\b\u0000\u0010\u0002\"\u0004\b\u0001\u0010\f\"\u0004\b\u0002\u0010\r\"\u001c\b\u0003\u0010\u0014*\u0016\u0012\u0006\b\u0000\u0012\u0002H\f\u0012\n\u0012\b\u0012\u0004\u0012\u0002H\r0t0\u0015*\b\u0012\u0004\u0012\u0002H\u00020\u00032\u0006\u0010\u0016\u001a\u0002H\u00142\u0012\u0010\u0011\u001a\u000e\u0012\u0004\u0012\u0002H\u0002\u0012\u0004\u0012\u0002H\f0\u00052\u0012\u0010\u0012\u001a\u000e\u0012\u0004\u0012\u0002H\u0002\u0012\u0004\u0012\u0002H\r0\u0005H\u0086\b\u00f8\u0001\u0000¢\u0006\u0002\u0010\u0018\u001aD\u0010u\u001a\u000e\u0012\u0004\u0012\u0002H\u0002\u0012\u0004\u0012\u0002H\f0v\"\u0004\b\u0000\u0010\u0002\"\u0004\b\u0001\u0010\f*\b\u0012\u0004\u0012\u0002H\u00020\u00032\u0014\b\u0004\u0010\u0011\u001a\u000e\u0012\u0004\u0012\u0002H\u0002\u0012\u0004\u0012\u0002H\f0\u0005H\u0087\b\u00f8\u0001\u0000\u001a(\u0010w\u001a\u00020$\"\t\b\u0000\u0010\u0002¢\u0006\u0002\b/*\b\u0012\u0004\u0012\u0002H\u00020\u00032\u0006\u00100\u001a\u0002H\u0002¢\u0006\u0002\u0010x\u001a0\u0010y\u001a\u00020$\"\u0004\b\u0000\u0010\u0002*\b\u0012\u0004\u0012\u0002H\u00020\u00032\u0012\u0010\u0004\u001a\u000e\u0012\u0004\u0012\u0002H\u0002\u0012\u0004\u0012\u00020\u00010\u0005H\u0086\b\u00f8\u0001\u0000\u001a0\u0010z\u001a\u00020$\"\u0004\b\u0000\u0010\u0002*\b\u0012\u0004\u0012\u0002H\u00020\u00032\u0012\u0010\u0004\u001a\u000e\u0012\u0004\u0012\u0002H\u0002\u0012\u0004\u0012\u00020\u00010\u0005H\u0086\b\u00f8\u0001\u0000\u001a\u0086\u0001\u0010{\u001a\u0002H|\"\u0004\b\u0000\u0010\u0002\"\f\b\u0001\u0010|*\u00060}j\u0002`~*\b\u0012\u0004\u0012\u0002H\u00020\u00032\u0006\u0010\u007f\u001a\u0002H|2\n\b\u0002\u0010\u0080\u0001\u001a\u00030\u0081\u00012\n\b\u0002\u0010\u0082\u0001\u001a\u00030\u0081\u00012\n\b\u0002\u0010\u0083\u0001\u001a\u00030\u0081\u00012\t\b\u0002\u0010\u0084\u0001\u001a\u00020$2\n\b\u0002\u0010\u0085\u0001\u001a\u00030\u0081\u00012\u0017\b\u0002\u0010\u000e\u001a\u0011\u0012\u0004\u0012\u0002H\u0002\u0012\u0005\u0012\u00030\u0081\u0001\u0018\u00010\u0005¢\u0006\u0003\u0010\u0086\u0001\u001al\u0010\u0087\u0001\u001a\u00030\u0088\u0001\"\u0004\b\u0000\u0010\u0002*\b\u0012\u0004\u0012\u0002H\u00020\u00032\n\b\u0002\u0010\u0080\u0001\u001a\u00030\u0081\u00012\n\b\u0002\u0010\u0082\u0001\u001a\u00030\u0081\u00012\n\b\u0002\u0010\u0083\u0001\u001a\u00030\u0081\u00012\t\b\u0002\u0010\u0084\u0001\u001a\u00020$2\n\b\u0002\u0010\u0085\u0001\u001a\u00030\u0081\u00012\u0017\b\u0002\u0010\u000e\u001a\u0011\u0012\u0004\u0012\u0002H\u0002\u0012\u0005\u0012\u00030\u0081\u0001\u0018\u00010\u0005\u001a\u001c\u0010\u0089\u0001\u001a\u0002H\u0002\"\u0004\b\u0000\u0010\u0002*\b\u0012\u0004\u0012\u0002H\u00020\u0003¢\u0006\u0002\u0010X\u001a6\u0010\u0089\u0001\u001a\u0002H\u0002\"\u0004\b\u0000\u0010\u0002*\b\u0012\u0004\u0012\u0002H\u00020\u00032\u0012\u0010\u0004\u001a\u000e\u0012\u0004\u0012\u0002H\u0002\u0012\u0004\u0012\u00020\u00010\u0005H\u0086\b\u00f8\u0001\u0000¢\u0006\u0002\u0010U\u001a)\u0010\u008a\u0001\u001a\u00020$\"\t\b\u0000\u0010\u0002¢\u0006\u0002\b/*\b\u0012\u0004\u0012\u0002H\u00020\u00032\u0006\u00100\u001a\u0002H\u0002¢\u0006\u0002\u0010x\u001a\u001e\u0010\u008b\u0001\u001a\u0004\u0018\u0001H\u0002\"\u0004\b\u0000\u0010\u0002*\b\u0012\u0004\u0012\u0002H\u00020\u0003¢\u0006\u0002\u0010X\u001a8\u0010\u008b\u0001\u001a\u0004\u0018\u0001H\u0002\"\u0004\b\u0000\u0010\u0002*\b\u0012\u0004\u0012\u0002H\u00020\u00032\u0012\u0010\u0004\u001a\u000e\u0012\u0004\u0012\u0002H\u0002\u0012\u0004\u0012\u00020\u00010\u0005H\u0086\b\u00f8\u0001\u0000¢\u0006\u0002\u0010U\u001a7\u0010\u008c\u0001\u001a\b\u0012\u0004\u0012\u0002H-0\u0003\"\u0004\b\u0000\u0010\u0002\"\u0004\b\u0001\u0010-*\b\u0012\u0004\u0012\u0002H\u00020\u00032\u0012\u0010\u000e\u001a\u000e\u0012\u0004\u0012\u0002H\u0002\u0012\u0004\u0012\u0002H-0\u0005\u001aL\u0010\u008d\u0001\u001a\b\u0012\u0004\u0012\u0002H-0\u0003\"\u0004\b\u0000\u0010\u0002\"\u0004\b\u0001\u0010-*\b\u0012\u0004\u0012\u0002H\u00020\u00032'\u0010\u000e\u001a#\u0012\u0013\u0012\u00110$¢\u0006\f\bC\u0012\b\bD\u0012\u0004\b\b(:\u0012\u0004\u0012\u0002H\u0002\u0012\u0004\u0012\u0002H-0B\u001aR\u0010\u008e\u0001\u001a\b\u0012\u0004\u0012\u0002H-0\u0003\"\u0004\b\u0000\u0010\u0002\"\b\b\u0001\u0010-*\u00020O*\b\u0012\u0004\u0012\u0002H\u00020\u00032)\u0010\u000e\u001a%\u0012\u0013\u0012\u00110$¢\u0006\f\bC\u0012\b\bD\u0012\u0004\b\b(:\u0012\u0004\u0012\u0002H\u0002\u0012\u0006\u0012\u0004\u0018\u0001H-0B\u001aq\u0010\u008f\u0001\u001a\u0002HF\"\u0004\b\u0000\u0010\u0002\"\b\b\u0001\u0010-*\u00020O\"\u0010\b\u0002\u0010F*\n\u0012\u0006\b\u0000\u0012\u0002H-0G*\b\u0012\u0004\u0012\u0002H\u00020\u00032\u0006\u0010\u0016\u001a\u0002HF2)\u0010\u000e\u001a%\u0012\u0013\u0012\u00110$¢\u0006\f\bC\u0012\b\bD\u0012\u0004\b\b(:\u0012\u0004\u0012\u0002H\u0002\u0012\u0006\u0012\u0004\u0018\u0001H-0BH\u0086\b\u00f8\u0001\u0000¢\u0006\u0002\u0010H\u001ak\u0010\u0090\u0001\u001a\u0002HF\"\u0004\b\u0000\u0010\u0002\"\u0004\b\u0001\u0010-\"\u0010\b\u0002\u0010F*\n\u0012\u0006\b\u0000\u0012\u0002H-0G*\b\u0012\u0004\u0012\u0002H\u00020\u00032\u0006\u0010\u0016\u001a\u0002HF2'\u0010\u000e\u001a#\u0012\u0013\u0012\u00110$¢\u0006\f\bC\u0012\b\bD\u0012\u0004\b\b(:\u0012\u0004\u0012\u0002H\u0002\u0012\u0004\u0012\u0002H-0BH\u0086\b\u00f8\u0001\u0000¢\u0006\u0002\u0010H\u001a=\u0010\u0091\u0001\u001a\b\u0012\u0004\u0012\u0002H-0\u0003\"\u0004\b\u0000\u0010\u0002\"\b\b\u0001\u0010-*\u00020O*\b\u0012\u0004\u0012\u0002H\u00020\u00032\u0014\u0010\u000e\u001a\u0010\u0012\u0004\u0012\u0002H\u0002\u0012\u0006\u0012\u0004\u0018\u0001H-0\u0005\u001a\\\u0010\u0092\u0001\u001a\u0002HF\"\u0004\b\u0000\u0010\u0002\"\b\b\u0001\u0010-*\u00020O\"\u0010\b\u0002\u0010F*\n\u0012\u0006\b\u0000\u0012\u0002H-0G*\b\u0012\u0004\u0012\u0002H\u00020\u00032\u0006\u0010\u0016\u001a\u0002HF2\u0014\u0010\u000e\u001a\u0010\u0012\u0004\u0012\u0002H\u0002\u0012\u0006\u0012\u0004\u0018\u0001H-0\u0005H\u0086\b\u00f8\u0001\u0000¢\u0006\u0002\u0010R\u001aV\u0010\u0093\u0001\u001a\u0002HF\"\u0004\b\u0000\u0010\u0002\"\u0004\b\u0001\u0010-\"\u0010\b\u0002\u0010F*\n\u0012\u0006\b\u0000\u0012\u0002H-0G*\b\u0012\u0004\u0012\u0002H\u00020\u00032\u0006\u0010\u0016\u001a\u0002HF2\u0012\u0010\u000e\u001a\u000e\u0012\u0004\u0012\u0002H\u0002\u0012\u0004\u0012\u0002H-0\u0005H\u0086\b\u00f8\u0001\u0000¢\u0006\u0002\u0010R\u001a-\u0010\u0094\u0001\u001a\u0002H\u0002\"\u000f\b\u0000\u0010\u0002*\t\u0012\u0004\u0012\u0002H\u00020\u0095\u0001*\b\u0012\u0004\u0012\u0002H\u00020\u0003H\u0007¢\u0006\u0006\b\u0096\u0001\u0010\u0097\u0001\u001a\u0019\u0010\u0094\u0001\u001a\u00020\u001e*\b\u0012\u0004\u0012\u00020\u001e0\u0003H\u0007¢\u0006\u0003\b\u0096\u0001\u001a\u0019\u0010\u0094\u0001\u001a\u00020\"*\b\u0012\u0004\u0012\u00020\"0\u0003H\u0007¢\u0006\u0003\b\u0096\u0001\u001aJ\u0010\u0098\u0001\u001a\u0002H\u0002\"\u0004\b\u0000\u0010\u0002\"\u000f\b\u0001\u0010-*\t\u0012\u0004\u0012\u0002H-0\u0095\u0001*\b\u0012\u0004\u0012\u0002H\u00020\u00032\u0012\u00105\u001a\u000e\u0012\u0004\u0012\u0002H\u0002\u0012\u0004\u0012\u0002H-0\u0005H\u0087\b\u00f8\u0001\u0000¢\u0006\u0005\b\u0099\u0001\u0010U\u001aI\u0010\u009a\u0001\u001a\u0004\u0018\u0001H\u0002\"\u0004\b\u0000\u0010\u0002\"\u000f\b\u0001\u0010-*\t\u0012\u0004\u0012\u0002H-0\u0095\u0001*\b\u0012\u0004\u0012\u0002H\u00020\u00032\u0012\u00105\u001a\u000e\u0012\u0004\u0012\u0002H\u0002\u0012\u0004\u0012\u0002H-0\u0005H\u0087\b\u00f8\u0001\u0000¢\u0006\u0002\u0010U\u001aH\u0010\u009b\u0001\u001a\u0002H-\"\u0004\b\u0000\u0010\u0002\"\u000f\b\u0001\u0010-*\t\u0012\u0004\u0012\u0002H-0\u0095\u0001*\b\u0012\u0004\u0012\u0002H\u00020\u00032\u0012\u00105\u001a\u000e\u0012\u0004\u0012\u0002H\u0002\u0012\u0004\u0012\u0002H-0\u0005H\u0087\b\u00f8\u0001\u0000¢\u0006\u0003\u0010\u009c\u0001\u001a1\u0010\u009b\u0001\u001a\u00020\u001e\"\u0004\b\u0000\u0010\u0002*\b\u0012\u0004\u0012\u0002H\u00020\u00032\u0012\u00105\u001a\u000e\u0012\u0004\u0012\u0002H\u0002\u0012\u0004\u0012\u00020\u001e0\u0005H\u0087\b\u00f8\u0001\u0000\u001a1\u0010\u009b\u0001\u001a\u00020\"\"\u0004\b\u0000\u0010\u0002*\b\u0012\u0004\u0012\u0002H\u00020\u00032\u0012\u00105\u001a\u000e\u0012\u0004\u0012\u0002H\u0002\u0012\u0004\u0012\u00020\"0\u0005H\u0087\b\u00f8\u0001\u0000\u001aJ\u0010\u009d\u0001\u001a\u0004\u0018\u0001H-\"\u0004\b\u0000\u0010\u0002\"\u000f\b\u0001\u0010-*\t\u0012\u0004\u0012\u0002H-0\u0095\u0001*\b\u0012\u0004\u0012\u0002H\u00020\u00032\u0012\u00105\u001a\u000e\u0012\u0004\u0012\u0002H\u0002\u0012\u0004\u0012\u0002H-0\u0005H\u0087\b\u00f8\u0001\u0000¢\u0006\u0003\u0010\u009c\u0001\u001a9\u0010\u009d\u0001\u001a\u0004\u0018\u00010\u001e\"\u0004\b\u0000\u0010\u0002*\b\u0012\u0004\u0012\u0002H\u00020\u00032\u0012\u00105\u001a\u000e\u0012\u0004\u0012\u0002H\u0002\u0012\u0004\u0012\u00020\u001e0\u0005H\u0087\b\u00f8\u0001\u0000¢\u0006\u0003\u0010\u009e\u0001\u001a9\u0010\u009d\u0001\u001a\u0004\u0018\u00010\"\"\u0004\b\u0000\u0010\u0002*\b\u0012\u0004\u0012\u0002H\u00020\u00032\u0012\u00105\u001a\u000e\u0012\u0004\u0012\u0002H\u0002\u0012\u0004\u0012\u00020\"0\u0005H\u0087\b\u00f8\u0001\u0000¢\u0006\u0003\u0010\u009f\u0001\u001a\\\u0010 \u0001\u001a\u0002H-\"\u0004\b\u0000\u0010\u0002\"\u0004\b\u0001\u0010-*\b\u0012\u0004\u0012\u0002H\u00020\u00032\u001d\u0010¡\u0001\u001a\u0018\u0012\u0006\b\u0000\u0012\u0002H-0¢\u0001j\u000b\u0012\u0006\b\u0000\u0012\u0002H-`£\u00012\u0012\u00105\u001a\u000e\u0012\u0004\u0012\u0002H\u0002\u0012\u0004\u0012\u0002H-0\u0005H\u0087\b\u00f8\u0001\u0000¢\u0006\u0003\u0010¤\u0001\u001a^\u0010¥\u0001\u001a\u0004\u0018\u0001H-\"\u0004\b\u0000\u0010\u0002\"\u0004\b\u0001\u0010-*\b\u0012\u0004\u0012\u0002H\u00020\u00032\u001d\u0010¡\u0001\u001a\u0018\u0012\u0006\b\u0000\u0012\u0002H-0¢\u0001j\u000b\u0012\u0006\b\u0000\u0012\u0002H-`£\u00012\u0012\u00105\u001a\u000e\u0012\u0004\u0012\u0002H\u0002\u0012\u0004\u0012\u0002H-0\u0005H\u0087\b\u00f8\u0001\u0000¢\u0006\u0003\u0010¤\u0001\u001a,\u0010¦\u0001\u001a\u0004\u0018\u0001H\u0002\"\u000f\b\u0000\u0010\u0002*\t\u0012\u0004\u0012\u0002H\u00020\u0095\u0001*\b\u0012\u0004\u0012\u0002H\u00020\u0003H\u0007¢\u0006\u0003\u0010\u0097\u0001\u001a\u001b\u0010¦\u0001\u001a\u0004\u0018\u00010\u001e*\b\u0012\u0004\u0012\u00020\u001e0\u0003H\u0007¢\u0006\u0003\u0010§\u0001\u001a\u001b\u0010¦\u0001\u001a\u0004\u0018\u00010\"*\b\u0012\u0004\u0012\u00020\"0\u0003H\u0007¢\u0006\u0003\u0010¨\u0001\u001aA\u0010©\u0001\u001a\u0002H\u0002\"\u0004\b\u0000\u0010\u0002*\b\u0012\u0004\u0012\u0002H\u00020\u00032\u001d\u0010¡\u0001\u001a\u0018\u0012\u0006\b\u0000\u0012\u0002H\u00020¢\u0001j\u000b\u0012\u0006\b\u0000\u0012\u0002H\u0002`£\u0001H\u0007¢\u0006\u0006\bª\u0001\u0010«\u0001\u001a@\u0010¬\u0001\u001a\u0004\u0018\u0001H\u0002\"\u0004\b\u0000\u0010\u0002*\b\u0012\u0004\u0012\u0002H\u00020\u00032\u001d\u0010¡\u0001\u001a\u0018\u0012\u0006\b\u0000\u0012\u0002H\u00020¢\u0001j\u000b\u0012\u0006\b\u0000\u0012\u0002H\u0002`£\u0001H\u0007¢\u0006\u0003\u0010«\u0001\u001a-\u0010\u00ad\u0001\u001a\u0002H\u0002\"\u000f\b\u0000\u0010\u0002*\t\u0012\u0004\u0012\u0002H\u00020\u0095\u0001*\b\u0012\u0004\u0012\u0002H\u00020\u0003H\u0007¢\u0006\u0006\b®\u0001\u0010\u0097\u0001\u001a\u0019\u0010\u00ad\u0001\u001a\u00020\u001e*\b\u0012\u0004\u0012\u00020\u001e0\u0003H\u0007¢\u0006\u0003\b®\u0001\u001a\u0019\u0010\u00ad\u0001\u001a\u00020\"*\b\u0012\u0004\u0012\u00020\"0\u0003H\u0007¢\u0006\u0003\b®\u0001\u001aJ\u0010¯\u0001\u001a\u0002H\u0002\"\u0004\b\u0000\u0010\u0002\"\u000f\b\u0001\u0010-*\t\u0012\u0004\u0012\u0002H-0\u0095\u0001*\b\u0012\u0004\u0012\u0002H\u00020\u00032\u0012\u00105\u001a\u000e\u0012\u0004\u0012\u0002H\u0002\u0012\u0004\u0012\u0002H-0\u0005H\u0087\b\u00f8\u0001\u0000¢\u0006\u0005\b°\u0001\u0010U\u001aI\u0010±\u0001\u001a\u0004\u0018\u0001H\u0002\"\u0004\b\u0000\u0010\u0002\"\u000f\b\u0001\u0010-*\t\u0012\u0004\u0012\u0002H-0\u0095\u0001*\b\u0012\u0004\u0012\u0002H\u00020\u00032\u0012\u00105\u001a\u000e\u0012\u0004\u0012\u0002H\u0002\u0012\u0004\u0012\u0002H-0\u0005H\u0087\b\u00f8\u0001\u0000¢\u0006\u0002\u0010U\u001aH\u0010²\u0001\u001a\u0002H-\"\u0004\b\u0000\u0010\u0002\"\u000f\b\u0001\u0010-*\t\u0012\u0004\u0012\u0002H-0\u0095\u0001*\b\u0012\u0004\u0012\u0002H\u00020\u00032\u0012\u00105\u001a\u000e\u0012\u0004\u0012\u0002H\u0002\u0012\u0004\u0012\u0002H-0\u0005H\u0087\b\u00f8\u0001\u0000¢\u0006\u0003\u0010\u009c\u0001\u001a1\u0010²\u0001\u001a\u00020\u001e\"\u0004\b\u0000\u0010\u0002*\b\u0012\u0004\u0012\u0002H\u00020\u00032\u0012\u00105\u001a\u000e\u0012\u0004\u0012\u0002H\u0002\u0012\u0004\u0012\u00020\u001e0\u0005H\u0087\b\u00f8\u0001\u0000\u001a1\u0010²\u0001\u001a\u00020\"\"\u0004\b\u0000\u0010\u0002*\b\u0012\u0004\u0012\u0002H\u00020\u00032\u0012\u00105\u001a\u000e\u0012\u0004\u0012\u0002H\u0002\u0012\u0004\u0012\u00020\"0\u0005H\u0087\b\u00f8\u0001\u0000\u001aJ\u0010³\u0001\u001a\u0004\u0018\u0001H-\"\u0004\b\u0000\u0010\u0002\"\u000f\b\u0001\u0010-*\t\u0012\u0004\u0012\u0002H-0\u0095\u0001*\b\u0012\u0004\u0012\u0002H\u00020\u00032\u0012\u00105\u001a\u000e\u0012\u0004\u0012\u0002H\u0002\u0012\u0004\u0012\u0002H-0\u0005H\u0087\b\u00f8\u0001\u0000¢\u0006\u0003\u0010\u009c\u0001\u001a9\u0010³\u0001\u001a\u0004\u0018\u00010\u001e\"\u0004\b\u0000\u0010\u0002*\b\u0012\u0004\u0012\u0002H\u00020\u00032\u0012\u00105\u001a\u000e\u0012\u0004\u0012\u0002H\u0002\u0012\u0004\u0012\u00020\u001e0\u0005H\u0087\b\u00f8\u0001\u0000¢\u0006\u0003\u0010\u009e\u0001\u001a9\u0010³\u0001\u001a\u0004\u0018\u00010\"\"\u0004\b\u0000\u0010\u0002*\b\u0012\u0004\u0012\u0002H\u00020\u00032\u0012\u00105\u001a\u000e\u0012\u0004\u0012\u0002H\u0002\u0012\u0004\u0012\u00020\"0\u0005H\u0087\b\u00f8\u0001\u0000¢\u0006\u0003\u0010\u009f\u0001\u001a\\\u0010´\u0001\u001a\u0002H-\"\u0004\b\u0000\u0010\u0002\"\u0004\b\u0001\u0010-*\b\u0012\u0004\u0012\u0002H\u00020\u00032\u001d\u0010¡\u0001\u001a\u0018\u0012\u0006\b\u0000\u0012\u0002H-0¢\u0001j\u000b\u0012\u0006\b\u0000\u0012\u0002H-`£\u00012\u0012\u00105\u001a\u000e\u0012\u0004\u0012\u0002H\u0002\u0012\u0004\u0012\u0002H-0\u0005H\u0087\b\u00f8\u0001\u0000¢\u0006\u0003\u0010¤\u0001\u001a^\u0010µ\u0001\u001a\u0004\u0018\u0001H-\"\u0004\b\u0000\u0010\u0002\"\u0004\b\u0001\u0010-*\b\u0012\u0004\u0012\u0002H\u00020\u00032\u001d\u0010¡\u0001\u001a\u0018\u0012\u0006\b\u0000\u0012\u0002H-0¢\u0001j\u000b\u0012\u0006\b\u0000\u0012\u0002H-`£\u00012\u0012\u00105\u001a\u000e\u0012\u0004\u0012\u0002H\u0002\u0012\u0004\u0012\u0002H-0\u0005H\u0087\b\u00f8\u0001\u0000¢\u0006\u0003\u0010¤\u0001\u001a,\u0010¶\u0001\u001a\u0004\u0018\u0001H\u0002\"\u000f\b\u0000\u0010\u0002*\t\u0012\u0004\u0012\u0002H\u00020\u0095\u0001*\b\u0012\u0004\u0012\u0002H\u00020\u0003H\u0007¢\u0006\u0003\u0010\u0097\u0001\u001a\u001b\u0010¶\u0001\u001a\u0004\u0018\u00010\u001e*\b\u0012\u0004\u0012\u00020\u001e0\u0003H\u0007¢\u0006\u0003\u0010§\u0001\u001a\u001b\u0010¶\u0001\u001a\u0004\u0018\u00010\"*\b\u0012\u0004\u0012\u00020\"0\u0003H\u0007¢\u0006\u0003\u0010¨\u0001\u001aA\u0010·\u0001\u001a\u0002H\u0002\"\u0004\b\u0000\u0010\u0002*\b\u0012\u0004\u0012\u0002H\u00020\u00032\u001d\u0010¡\u0001\u001a\u0018\u0012\u0006\b\u0000\u0012\u0002H\u00020¢\u0001j\u000b\u0012\u0006\b\u0000\u0012\u0002H\u0002`£\u0001H\u0007¢\u0006\u0006\b¸\u0001\u0010«\u0001\u001a@\u0010¹\u0001\u001a\u0004\u0018\u0001H\u0002\"\u0004\b\u0000\u0010\u0002*\b\u0012\u0004\u0012\u0002H\u00020\u00032\u001d\u0010¡\u0001\u001a\u0018\u0012\u0006\b\u0000\u0012\u0002H\u00020¢\u0001j\u000b\u0012\u0006\b\u0000\u0012\u0002H\u0002`£\u0001H\u0007¢\u0006\u0003\u0010«\u0001\u001a.\u0010º\u0001\u001a\b\u0012\u0004\u0012\u0002H\u00020\u0003\"\u0004\b\u0000\u0010\u0002*\b\u0012\u0004\u0012\u0002H\u00020\u00032\u0006\u00100\u001a\u0002H\u0002H\u0086\u0002¢\u0006\u0003\u0010»\u0001\u001a8\u0010º\u0001\u001a\b\u0012\u0004\u0012\u0002H\u00020\u0003\"\u0004\b\u0000\u0010\u0002*\b\u0012\u0004\u0012\u0002H\u00020\u00032\u0010\u0010¼\u0001\u001a\u000b\u0012\u0006\b\u0001\u0012\u0002H\u00020½\u0001H\u0086\u0002¢\u0006\u0003\u0010¾\u0001\u001a/\u0010º\u0001\u001a\b\u0012\u0004\u0012\u0002H\u00020\u0003\"\u0004\b\u0000\u0010\u0002*\b\u0012\u0004\u0012\u0002H\u00020\u00032\r\u0010¼\u0001\u001a\b\u0012\u0004\u0012\u0002H\u00020\bH\u0086\u0002\u001a/\u0010º\u0001\u001a\b\u0012\u0004\u0012\u0002H\u00020\u0003\"\u0004\b\u0000\u0010\u0002*\b\u0012\u0004\u0012\u0002H\u00020\u00032\r\u0010¼\u0001\u001a\b\u0012\u0004\u0012\u0002H\u00020\u0003H\u0086\u0002\u001a.\u0010¿\u0001\u001a\b\u0012\u0004\u0012\u0002H\u00020\u0003\"\u0004\b\u0000\u0010\u0002*\b\u0012\u0004\u0012\u0002H\u00020\u00032\u0006\u00100\u001a\u0002H\u0002H\u0087\b¢\u0006\u0003\u0010»\u0001\u001a\u0017\u0010\u00c0\u0001\u001a\u00020\u0001\"\u0004\b\u0000\u0010\u0002*\b\u0012\u0004\u0012\u0002H\u00020\u0003\u001a1\u0010\u00c0\u0001\u001a\u00020\u0001\"\u0004\b\u0000\u0010\u0002*\b\u0012\u0004\u0012\u0002H\u00020\u00032\u0012\u0010\u0004\u001a\u000e\u0012\u0004\u0012\u0002H\u0002\u0012\u0004\u0012\u00020\u00010\u0005H\u0086\b\u00f8\u0001\u0000\u001a3\u0010\u00c1\u0001\u001a\b\u0012\u0004\u0012\u0002H\u00020\u0003\"\u0004\b\u0000\u0010\u0002*\b\u0012\u0004\u0012\u0002H\u00020\u00032\u0012\u0010p\u001a\u000e\u0012\u0004\u0012\u0002H\u0002\u0012\u0004\u0012\u00020o0\u0005H\u0007\u001aH\u0010\u00c2\u0001\u001a\b\u0012\u0004\u0012\u0002H\u00020\u0003\"\u0004\b\u0000\u0010\u0002*\b\u0012\u0004\u0012\u0002H\u00020\u00032'\u0010p\u001a#\u0012\u0013\u0012\u00110$¢\u0006\f\bC\u0012\b\bD\u0012\u0004\b\b(:\u0012\u0004\u0012\u0002H\u0002\u0012\u0004\u0012\u00020o0BH\u0007\u001aI\u0010\u00c3\u0001\u001a\u001a\u0012\n\u0012\b\u0012\u0004\u0012\u0002H\u00020+\u0012\n\u0012\b\u0012\u0004\u0012\u0002H\u00020+0\u000f\"\u0004\b\u0000\u0010\u0002*\b\u0012\u0004\u0012\u0002H\u00020\u00032\u0012\u0010\u0004\u001a\u000e\u0012\u0004\u0012\u0002H\u0002\u0012\u0004\u0012\u00020\u00010\u0005H\u0086\b\u00f8\u0001\u0000\u001a.\u0010\u00c4\u0001\u001a\b\u0012\u0004\u0012\u0002H\u00020\u0003\"\u0004\b\u0000\u0010\u0002*\b\u0012\u0004\u0012\u0002H\u00020\u00032\u0006\u00100\u001a\u0002H\u0002H\u0086\u0002¢\u0006\u0003\u0010»\u0001\u001a8\u0010\u00c4\u0001\u001a\b\u0012\u0004\u0012\u0002H\u00020\u0003\"\u0004\b\u0000\u0010\u0002*\b\u0012\u0004\u0012\u0002H\u00020\u00032\u0010\u0010¼\u0001\u001a\u000b\u0012\u0006\b\u0001\u0012\u0002H\u00020½\u0001H\u0086\u0002¢\u0006\u0003\u0010¾\u0001\u001a/\u0010\u00c4\u0001\u001a\b\u0012\u0004\u0012\u0002H\u00020\u0003\"\u0004\b\u0000\u0010\u0002*\b\u0012\u0004\u0012\u0002H\u00020\u00032\r\u0010¼\u0001\u001a\b\u0012\u0004\u0012\u0002H\u00020\bH\u0086\u0002\u001a/\u0010\u00c4\u0001\u001a\b\u0012\u0004\u0012\u0002H\u00020\u0003\"\u0004\b\u0000\u0010\u0002*\b\u0012\u0004\u0012\u0002H\u00020\u00032\r\u0010¼\u0001\u001a\b\u0012\u0004\u0012\u0002H\u00020\u0003H\u0086\u0002\u001a.\u0010\u00c5\u0001\u001a\b\u0012\u0004\u0012\u0002H\u00020\u0003\"\u0004\b\u0000\u0010\u0002*\b\u0012\u0004\u0012\u0002H\u00020\u00032\u0006\u00100\u001a\u0002H\u0002H\u0087\b¢\u0006\u0003\u0010»\u0001\u001a[\u0010\u00c6\u0001\u001a\u0003H\u00c7\u0001\"\u0005\b\u0000\u0010\u00c7\u0001\"\t\b\u0001\u0010\u0002*\u0003H\u00c7\u0001*\b\u0012\u0004\u0012\u0002H\u00020\u00032)\u0010h\u001a%\u0012\u0014\u0012\u0012H\u00c7\u0001¢\u0006\f\bC\u0012\b\bD\u0012\u0004\b\b(i\u0012\u0004\u0012\u0002H\u0002\u0012\u0005\u0012\u0003H\u00c7\u00010BH\u0086\b\u00f8\u0001\u0000¢\u0006\u0003\u0010\u00c8\u0001\u001ap\u0010\u00c9\u0001\u001a\u0003H\u00c7\u0001\"\u0005\b\u0000\u0010\u00c7\u0001\"\t\b\u0001\u0010\u0002*\u0003H\u00c7\u0001*\b\u0012\u0004\u0012\u0002H\u00020\u00032>\u0010h\u001a:\u0012\u0013\u0012\u00110$¢\u0006\f\bC\u0012\b\bD\u0012\u0004\b\b(:\u0012\u0014\u0012\u0012H\u00c7\u0001¢\u0006\f\bC\u0012\b\bD\u0012\u0004\b\b(i\u0012\u0004\u0012\u0002H\u0002\u0012\u0005\u0012\u0003H\u00c7\u00010lH\u0086\b\u00f8\u0001\u0000¢\u0006\u0003\u0010\u00ca\u0001\u001ar\u0010\u00cb\u0001\u001a\u0005\u0018\u0001H\u00c7\u0001\"\u0005\b\u0000\u0010\u00c7\u0001\"\t\b\u0001\u0010\u0002*\u0003H\u00c7\u0001*\b\u0012\u0004\u0012\u0002H\u00020\u00032>\u0010h\u001a:\u0012\u0013\u0012\u00110$¢\u0006\f\bC\u0012\b\bD\u0012\u0004\b\b(:\u0012\u0014\u0012\u0012H\u00c7\u0001¢\u0006\f\bC\u0012\b\bD\u0012\u0004\b\b(i\u0012\u0004\u0012\u0002H\u0002\u0012\u0005\u0012\u0003H\u00c7\u00010lH\u0087\b\u00f8\u0001\u0000¢\u0006\u0003\u0010\u00ca\u0001\u001a]\u0010\u00cc\u0001\u001a\u0005\u0018\u0001H\u00c7\u0001\"\u0005\b\u0000\u0010\u00c7\u0001\"\t\b\u0001\u0010\u0002*\u0003H\u00c7\u0001*\b\u0012\u0004\u0012\u0002H\u00020\u00032)\u0010h\u001a%\u0012\u0014\u0012\u0012H\u00c7\u0001¢\u0006\f\bC\u0012\b\bD\u0012\u0004\b\b(i\u0012\u0004\u0012\u0002H\u0002\u0012\u0005\u0012\u0003H\u00c7\u00010BH\u0087\b\u00f8\u0001\u0000¢\u0006\u0003\u0010\u00c8\u0001\u001a#\u0010\u00cd\u0001\u001a\b\u0012\u0004\u0012\u0002H\u00020\u0003\"\b\b\u0000\u0010\u0002*\u00020O*\n\u0012\u0006\u0012\u0004\u0018\u0001H\u00020\u0003\u001a\\\u0010\u00ce\u0001\u001a\b\u0012\u0004\u0012\u0002H-0\u0003\"\u0004\b\u0000\u0010\u0002\"\u0004\b\u0001\u0010-*\b\u0012\u0004\u0012\u0002H\u00020\u00032\u0006\u0010g\u001a\u0002H-2'\u0010h\u001a#\u0012\u0013\u0012\u0011H-¢\u0006\f\bC\u0012\b\bD\u0012\u0004\b\b(i\u0012\u0004\u0012\u0002H\u0002\u0012\u0004\u0012\u0002H-0BH\u0007¢\u0006\u0003\u0010\u00cf\u0001\u001aq\u0010\u00d0\u0001\u001a\b\u0012\u0004\u0012\u0002H-0\u0003\"\u0004\b\u0000\u0010\u0002\"\u0004\b\u0001\u0010-*\b\u0012\u0004\u0012\u0002H\u00020\u00032\u0006\u0010g\u001a\u0002H-2<\u0010h\u001a8\u0012\u0013\u0012\u00110$¢\u0006\f\bC\u0012\b\bD\u0012\u0004\b\b(:\u0012\u0013\u0012\u0011H-¢\u0006\f\bC\u0012\b\bD\u0012\u0004\b\b(i\u0012\u0004\u0012\u0002H\u0002\u0012\u0004\u0012\u0002H-0lH\u0007¢\u0006\u0003\u0010\u00d1\u0001\u001aW\u0010\u00d2\u0001\u001a\t\u0012\u0005\u0012\u0003H\u00c7\u00010\u0003\"\u0005\b\u0000\u0010\u00c7\u0001\"\t\b\u0001\u0010\u0002*\u0003H\u00c7\u0001*\b\u0012\u0004\u0012\u0002H\u00020\u00032)\u0010h\u001a%\u0012\u0014\u0012\u0012H\u00c7\u0001¢\u0006\f\bC\u0012\b\bD\u0012\u0004\b\b(i\u0012\u0004\u0012\u0002H\u0002\u0012\u0005\u0012\u0003H\u00c7\u00010BH\u0007\u001al\u0010\u00d3\u0001\u001a\t\u0012\u0005\u0012\u0003H\u00c7\u00010\u0003\"\u0005\b\u0000\u0010\u00c7\u0001\"\t\b\u0001\u0010\u0002*\u0003H\u00c7\u0001*\b\u0012\u0004\u0012\u0002H\u00020\u00032>\u0010h\u001a:\u0012\u0013\u0012\u00110$¢\u0006\f\bC\u0012\b\bD\u0012\u0004\b\b(:\u0012\u0014\u0012\u0012H\u00c7\u0001¢\u0006\f\bC\u0012\b\bD\u0012\u0004\b\b(i\u0012\u0004\u0012\u0002H\u0002\u0012\u0005\u0012\u0003H\u00c7\u00010lH\u0007\u001a\\\u0010\u00d4\u0001\u001a\b\u0012\u0004\u0012\u0002H-0\u0003\"\u0004\b\u0000\u0010\u0002\"\u0004\b\u0001\u0010-*\b\u0012\u0004\u0012\u0002H\u00020\u00032\u0006\u0010g\u001a\u0002H-2'\u0010h\u001a#\u0012\u0013\u0012\u0011H-¢\u0006\f\bC\u0012\b\bD\u0012\u0004\b\b(i\u0012\u0004\u0012\u0002H\u0002\u0012\u0004\u0012\u0002H-0BH\u0007¢\u0006\u0003\u0010\u00cf\u0001\u001aq\u0010\u00d5\u0001\u001a\b\u0012\u0004\u0012\u0002H-0\u0003\"\u0004\b\u0000\u0010\u0002\"\u0004\b\u0001\u0010-*\b\u0012\u0004\u0012\u0002H\u00020\u00032\u0006\u0010g\u001a\u0002H-2<\u0010h\u001a8\u0012\u0013\u0012\u00110$¢\u0006\f\bC\u0012\b\bD\u0012\u0004\b\b(:\u0012\u0013\u0012\u0011H-¢\u0006\f\bC\u0012\b\bD\u0012\u0004\b\b(i\u0012\u0004\u0012\u0002H\u0002\u0012\u0004\u0012\u0002H-0lH\u0007¢\u0006\u0003\u0010\u00d1\u0001\u001a\u001c\u0010\u00d6\u0001\u001a\u0002H\u0002\"\u0004\b\u0000\u0010\u0002*\b\u0012\u0004\u0012\u0002H\u00020\u0003¢\u0006\u0002\u0010X\u001a6\u0010\u00d6\u0001\u001a\u0002H\u0002\"\u0004\b\u0000\u0010\u0002*\b\u0012\u0004\u0012\u0002H\u00020\u00032\u0012\u0010\u0004\u001a\u000e\u0012\u0004\u0012\u0002H\u0002\u0012\u0004\u0012\u00020\u00010\u0005H\u0086\b\u00f8\u0001\u0000¢\u0006\u0002\u0010U\u001a\u001e\u0010\u00d7\u0001\u001a\u0004\u0018\u0001H\u0002\"\u0004\b\u0000\u0010\u0002*\b\u0012\u0004\u0012\u0002H\u00020\u0003¢\u0006\u0002\u0010X\u001a8\u0010\u00d7\u0001\u001a\u0004\u0018\u0001H\u0002\"\u0004\b\u0000\u0010\u0002*\b\u0012\u0004\u0012\u0002H\u00020\u00032\u0012\u0010\u0004\u001a\u000e\u0012\u0004\u0012\u0002H\u0002\u0012\u0004\u0012\u00020\u00010\u0005H\u0086\b\u00f8\u0001\u0000¢\u0006\u0002\u0010U\u001a(\u0010\u00d8\u0001\u001a\b\u0012\u0004\u0012\u0002H\u00020\u0003\"\u000f\b\u0000\u0010\u0002*\t\u0012\u0004\u0012\u0002H\u00020\u0095\u0001*\b\u0012\u0004\u0012\u0002H\u00020\u0003\u001aL\u0010\u00d9\u0001\u001a\b\u0012\u0004\u0012\u0002H\u00020\u0003\"\u0004\b\u0000\u0010\u0002\"\u000f\b\u0001\u0010-*\t\u0012\u0004\u0012\u0002H-0\u0095\u0001*\b\u0012\u0004\u0012\u0002H\u00020\u00032\u0016\b\u0004\u00105\u001a\u0010\u0012\u0004\u0012\u0002H\u0002\u0012\u0006\u0012\u0004\u0018\u0001H-0\u0005H\u0086\b\u00f8\u0001\u0000\u001aL\u0010\u00da\u0001\u001a\b\u0012\u0004\u0012\u0002H\u00020\u0003\"\u0004\b\u0000\u0010\u0002\"\u000f\b\u0001\u0010-*\t\u0012\u0004\u0012\u0002H-0\u0095\u0001*\b\u0012\u0004\u0012\u0002H\u00020\u00032\u0016\b\u0004\u00105\u001a\u0010\u0012\u0004\u0012\u0002H\u0002\u0012\u0006\u0012\u0004\u0018\u0001H-0\u0005H\u0086\b\u00f8\u0001\u0000\u001a(\u0010\u00db\u0001\u001a\b\u0012\u0004\u0012\u0002H\u00020\u0003\"\u000f\b\u0000\u0010\u0002*\t\u0012\u0004\u0012\u0002H\u00020\u0095\u0001*\b\u0012\u0004\u0012\u0002H\u00020\u0003\u001a<\u0010\u00dc\u0001\u001a\b\u0012\u0004\u0012\u0002H\u00020\u0003\"\u0004\b\u0000\u0010\u0002*\b\u0012\u0004\u0012\u0002H\u00020\u00032\u001d\u0010¡\u0001\u001a\u0018\u0012\u0006\b\u0000\u0012\u0002H\u00020¢\u0001j\u000b\u0012\u0006\b\u0000\u0012\u0002H\u0002`£\u0001\u001a\u0019\u0010\u00dd\u0001\u001a\u00020$*\b\u0012\u0004\u0012\u00020\u001f0\u0003H\u0007¢\u0006\u0003\b\u00de\u0001\u001a\u0019\u0010\u00dd\u0001\u001a\u00020\u001e*\b\u0012\u0004\u0012\u00020\u001e0\u0003H\u0007¢\u0006\u0003\b\u00df\u0001\u001a\u0019\u0010\u00dd\u0001\u001a\u00020\"*\b\u0012\u0004\u0012\u00020\"0\u0003H\u0007¢\u0006\u0003\b\u00e0\u0001\u001a\u0019\u0010\u00dd\u0001\u001a\u00020$*\b\u0012\u0004\u0012\u00020$0\u0003H\u0007¢\u0006\u0003\b\u00e1\u0001\u001a\u0019\u0010\u00dd\u0001\u001a\u00020&*\b\u0012\u0004\u0012\u00020&0\u0003H\u0007¢\u0006\u0003\b\u00e2\u0001\u001a\u0019\u0010\u00dd\u0001\u001a\u00020$*\b\u0012\u0004\u0012\u00020(0\u0003H\u0007¢\u0006\u0003\b\u00e3\u0001\u001a1\u0010\u00e4\u0001\u001a\u00020$\"\u0004\b\u0000\u0010\u0002*\b\u0012\u0004\u0012\u0002H\u00020\u00032\u0012\u00105\u001a\u000e\u0012\u0004\u0012\u0002H\u0002\u0012\u0004\u0012\u00020$0\u0005H\u0087\b\u00f8\u0001\u0000\u001a1\u0010\u00e5\u0001\u001a\u00020\u001e\"\u0004\b\u0000\u0010\u0002*\b\u0012\u0004\u0012\u0002H\u00020\u00032\u0012\u00105\u001a\u000e\u0012\u0004\u0012\u0002H\u0002\u0012\u0004\u0012\u00020\u001e0\u0005H\u0087\b\u00f8\u0001\u0000\u001a7\u0010\u00e6\u0001\u001a\u00020\u001e\"\u0004\b\u0000\u0010\u0002*\b\u0012\u0004\u0012\u0002H\u00020\u00032\u0012\u00105\u001a\u000e\u0012\u0004\u0012\u0002H\u0002\u0012\u0004\u0012\u00020\u001e0\u0005H\u0087\b\u00f8\u0001\u0000¢\u0006\u0003\b\u00df\u0001\u001a7\u0010\u00e6\u0001\u001a\u00020$\"\u0004\b\u0000\u0010\u0002*\b\u0012\u0004\u0012\u0002H\u00020\u00032\u0012\u00105\u001a\u000e\u0012\u0004\u0012\u0002H\u0002\u0012\u0004\u0012\u00020$0\u0005H\u0087\b\u00f8\u0001\u0000¢\u0006\u0003\b\u00e1\u0001\u001a7\u0010\u00e6\u0001\u001a\u00020&\"\u0004\b\u0000\u0010\u0002*\b\u0012\u0004\u0012\u0002H\u00020\u00032\u0012\u00105\u001a\u000e\u0012\u0004\u0012\u0002H\u0002\u0012\u0004\u0012\u00020&0\u0005H\u0087\b\u00f8\u0001\u0000¢\u0006\u0003\b\u00e2\u0001\u001a?\u0010\u00e6\u0001\u001a\u00030\u00e7\u0001\"\u0004\b\u0000\u0010\u0002*\b\u0012\u0004\u0012\u0002H\u00020\u00032\u0013\u00105\u001a\u000f\u0012\u0004\u0012\u0002H\u0002\u0012\u0005\u0012\u00030\u00e7\u00010\u0005H\u0087\b\u00f8\u0001\u0000\u00f8\u0001\u0001¢\u0006\u0006\b\u00e8\u0001\u0010\u00e9\u0001\u001a?\u0010\u00e6\u0001\u001a\u00030\u00ea\u0001\"\u0004\b\u0000\u0010\u0002*\b\u0012\u0004\u0012\u0002H\u00020\u00032\u0013\u00105\u001a\u000f\u0012\u0004\u0012\u0002H\u0002\u0012\u0005\u0012\u00030\u00ea\u00010\u0005H\u0087\b\u00f8\u0001\u0000\u00f8\u0001\u0001¢\u0006\u0006\b\u00eb\u0001\u0010\u00ec\u0001\u001a%\u0010\u00ed\u0001\u001a\b\u0012\u0004\u0012\u0002H\u00020\u0003\"\u0004\b\u0000\u0010\u0002*\b\u0012\u0004\u0012\u0002H\u00020\u00032\u0006\u00107\u001a\u00020$\u001a1\u0010\u00ee\u0001\u001a\b\u0012\u0004\u0012\u0002H\u00020\u0003\"\u0004\b\u0000\u0010\u0002*\b\u0012\u0004\u0012\u0002H\u00020\u00032\u0012\u0010\u0004\u001a\u000e\u0012\u0004\u0012\u0002H\u0002\u0012\u0004\u0012\u00020\u00010\u0005\u001a6\u0010\u00ef\u0001\u001a\u0002HF\"\u0004\b\u0000\u0010\u0002\"\u0010\b\u0001\u0010F*\n\u0012\u0006\b\u0000\u0012\u0002H\u00020G*\b\u0012\u0004\u0012\u0002H\u00020\u00032\u0006\u0010\u0016\u001a\u0002HF¢\u0006\u0002\u0010L\u001a)\u0010\u00f0\u0001\u001a\u0014\u0012\u0004\u0012\u0002H\u00020\u00f1\u0001j\t\u0012\u0004\u0012\u0002H\u0002`\u00f2\u0001\"\u0004\b\u0000\u0010\u0002*\b\u0012\u0004\u0012\u0002H\u00020\u0003\u001a\u001d\u0010\u00f3\u0001\u001a\b\u0012\u0004\u0012\u0002H\u00020+\"\u0004\b\u0000\u0010\u0002*\b\u0012\u0004\u0012\u0002H\u00020\u0003\u001a\u001d\u0010\u00f4\u0001\u001a\b\u0012\u0004\u0012\u0002H\u00020t\"\u0004\b\u0000\u0010\u0002*\b\u0012\u0004\u0012\u0002H\u00020\u0003\u001a\u001e\u0010\u00f5\u0001\u001a\t\u0012\u0004\u0012\u0002H\u00020\u00f6\u0001\"\u0004\b\u0000\u0010\u0002*\b\u0012\u0004\u0012\u0002H\u00020\u0003\u001a\u001e\u0010\u00f7\u0001\u001a\t\u0012\u0004\u0012\u0002H\u00020\u00f8\u0001\"\u0004\b\u0000\u0010\u0002*\b\u0012\u0004\u0012\u0002H\u00020\u0003\u001aC\u0010\u00f9\u0001\u001a\u000e\u0012\n\u0012\b\u0012\u0004\u0012\u0002H\u00020+0\u0003\"\u0004\b\u0000\u0010\u0002*\b\u0012\u0004\u0012\u0002H\u00020\u00032\u0006\u0010,\u001a\u00020$2\t\b\u0002\u0010\u00fa\u0001\u001a\u00020$2\t\b\u0002\u0010\u00fb\u0001\u001a\u00020\u0001H\u0007\u001a]\u0010\u00f9\u0001\u001a\b\u0012\u0004\u0012\u0002H-0\u0003\"\u0004\b\u0000\u0010\u0002\"\u0004\b\u0001\u0010-*\b\u0012\u0004\u0012\u0002H\u00020\u00032\u0006\u0010,\u001a\u00020$2\t\b\u0002\u0010\u00fa\u0001\u001a\u00020$2\t\b\u0002\u0010\u00fb\u0001\u001a\u00020\u00012\u0018\u0010\u000e\u001a\u0014\u0012\n\u0012\b\u0012\u0004\u0012\u0002H\u00020+\u0012\u0004\u0012\u0002H-0\u0005H\u0007\u001a$\u0010\u00fc\u0001\u001a\u000f\u0012\u000b\u0012\t\u0012\u0004\u0012\u0002H\u00020\u00fd\u00010\u0003\"\u0004\b\u0000\u0010\u0002*\b\u0012\u0004\u0012\u0002H\u00020\u0003\u001aA\u0010\u00fe\u0001\u001a\u0014\u0012\u0010\u0012\u000e\u0012\u0004\u0012\u0002H\u0002\u0012\u0004\u0012\u0002H-0\u000f0\u0003\"\u0004\b\u0000\u0010\u0002\"\u0004\b\u0001\u0010-*\b\u0012\u0004\u0012\u0002H\u00020\u00032\r\u0010\u00ff\u0001\u001a\b\u0012\u0004\u0012\u0002H-0\u0003H\u0086\u0004\u001ar\u0010\u00fe\u0001\u001a\b\u0012\u0004\u0012\u0002H\r0\u0003\"\u0004\b\u0000\u0010\u0002\"\u0004\b\u0001\u0010-\"\u0004\b\u0002\u0010\r*\b\u0012\u0004\u0012\u0002H\u00020\u00032\r\u0010\u00ff\u0001\u001a\b\u0012\u0004\u0012\u0002H-0\u000328\u0010\u000e\u001a4\u0012\u0014\u0012\u0012H\u0002¢\u0006\r\bC\u0012\t\bD\u0012\u0005\b\b(\u0080\u0002\u0012\u0014\u0012\u0012H-¢\u0006\r\bC\u0012\t\bD\u0012\u0005\b\b(\u0081\u0002\u0012\u0004\u0012\u0002H\r0B\u001a+\u0010\u0082\u0002\u001a\u0014\u0012\u0010\u0012\u000e\u0012\u0004\u0012\u0002H\u0002\u0012\u0004\u0012\u0002H\u00020\u000f0\u0003\"\u0004\b\u0000\u0010\u0002*\b\u0012\u0004\u0012\u0002H\u00020\u0003H\u0007\u001a_\u0010\u0082\u0002\u001a\b\u0012\u0004\u0012\u0002H-0\u0003\"\u0004\b\u0000\u0010\u0002\"\u0004\b\u0001\u0010-*\b\u0012\u0004\u0012\u0002H\u00020\u000328\u0010\u000e\u001a4\u0012\u0014\u0012\u0012H\u0002¢\u0006\r\bC\u0012\t\bD\u0012\u0005\b\b(\u0080\u0002\u0012\u0014\u0012\u0012H\u0002¢\u0006\r\bC\u0012\t\bD\u0012\u0005\b\b(\u0081\u0002\u0012\u0004\u0012\u0002H-0BH\u0007\u0082\u0002\u000b\n\u0005\b\u009920\u0001\n\u0002\b\u0019¨\u0006\u0083\u0002" }, d2 = { "all", "", "T", "Lkotlin/sequences/Sequence;", "predicate", "Lkotlin/Function1;", "any", "asIterable", "", "asSequence", "associate", "", "K", "V", "transform", "Lkotlin/Pair;", "associateBy", "keySelector", "valueTransform", "associateByTo", "M", "", "destination", "(Lkotlin/sequences/Sequence;Ljava/util/Map;Lkotlin/jvm/functions/Function1;)Ljava/util/Map;", "(Lkotlin/sequences/Sequence;Ljava/util/Map;Lkotlin/jvm/functions/Function1;Lkotlin/jvm/functions/Function1;)Ljava/util/Map;", "associateTo", "associateWith", "valueSelector", "associateWithTo", "average", "", "", "averageOfByte", "averageOfDouble", "", "averageOfFloat", "", "averageOfInt", "", "averageOfLong", "", "averageOfShort", "chunked", "", "size", "R", "contains", "Lkotlin/internal/OnlyInputTypes;", "element", "(Lkotlin/sequences/Sequence;Ljava/lang/Object;)Z", "count", "distinct", "distinctBy", "selector", "drop", "n", "dropWhile", "elementAt", "index", "(Lkotlin/sequences/Sequence;I)Ljava/lang/Object;", "elementAtOrElse", "defaultValue", "(Lkotlin/sequences/Sequence;ILkotlin/jvm/functions/Function1;)Ljava/lang/Object;", "elementAtOrNull", "filter", "filterIndexed", "Lkotlin/Function2;", "Lkotlin/ParameterName;", "name", "filterIndexedTo", "C", "", "(Lkotlin/sequences/Sequence;Ljava/util/Collection;Lkotlin/jvm/functions/Function2;)Ljava/util/Collection;", "filterIsInstance", "Lkotlin/internal/NoInfer;", "filterIsInstanceTo", "(Lkotlin/sequences/Sequence;Ljava/util/Collection;)Ljava/util/Collection;", "filterNot", "filterNotNull", "", "filterNotNullTo", "filterNotTo", "(Lkotlin/sequences/Sequence;Ljava/util/Collection;Lkotlin/jvm/functions/Function1;)Ljava/util/Collection;", "filterTo", "find", "(Lkotlin/sequences/Sequence;Lkotlin/jvm/functions/Function1;)Ljava/lang/Object;", "findLast", "first", "(Lkotlin/sequences/Sequence;)Ljava/lang/Object;", "firstNotNullOf", "firstNotNullOfOrNull", "firstOrNull", "flatMap", "flatMapIterable", "flatMapIndexed", "flatMapIndexedIterable", "flatMapIndexedSequence", "flatMapIndexedTo", "flatMapIndexedIterableTo", "flatMapIndexedSequenceTo", "flatMapTo", "flatMapIterableTo", "fold", "initial", "operation", "acc", "(Lkotlin/sequences/Sequence;Ljava/lang/Object;Lkotlin/jvm/functions/Function2;)Ljava/lang/Object;", "foldIndexed", "Lkotlin/Function3;", "(Lkotlin/sequences/Sequence;Ljava/lang/Object;Lkotlin/jvm/functions/Function3;)Ljava/lang/Object;", "forEach", "", "action", "forEachIndexed", "groupBy", "groupByTo", "", "groupingBy", "Lkotlin/collections/Grouping;", "indexOf", "(Lkotlin/sequences/Sequence;Ljava/lang/Object;)I", "indexOfFirst", "indexOfLast", "joinTo", "A", "Ljava/lang/Appendable;", "Lkotlin/text/Appendable;", "buffer", "separator", "", "prefix", "postfix", "limit", "truncated", "(Lkotlin/sequences/Sequence;Ljava/lang/Appendable;Ljava/lang/CharSequence;Ljava/lang/CharSequence;Ljava/lang/CharSequence;ILjava/lang/CharSequence;Lkotlin/jvm/functions/Function1;)Ljava/lang/Appendable;", "joinToString", "", "last", "lastIndexOf", "lastOrNull", "map", "mapIndexed", "mapIndexedNotNull", "mapIndexedNotNullTo", "mapIndexedTo", "mapNotNull", "mapNotNullTo", "mapTo", "max", "", "maxOrThrow", "(Lkotlin/sequences/Sequence;)Ljava/lang/Comparable;", "maxBy", "maxByOrThrow", "maxByOrNull", "maxOf", "(Lkotlin/sequences/Sequence;Lkotlin/jvm/functions/Function1;)Ljava/lang/Comparable;", "maxOfOrNull", "(Lkotlin/sequences/Sequence;Lkotlin/jvm/functions/Function1;)Ljava/lang/Double;", "(Lkotlin/sequences/Sequence;Lkotlin/jvm/functions/Function1;)Ljava/lang/Float;", "maxOfWith", "comparator", "Ljava/util/Comparator;", "Lkotlin/Comparator;", "(Lkotlin/sequences/Sequence;Ljava/util/Comparator;Lkotlin/jvm/functions/Function1;)Ljava/lang/Object;", "maxOfWithOrNull", "maxOrNull", "(Lkotlin/sequences/Sequence;)Ljava/lang/Double;", "(Lkotlin/sequences/Sequence;)Ljava/lang/Float;", "maxWith", "maxWithOrThrow", "(Lkotlin/sequences/Sequence;Ljava/util/Comparator;)Ljava/lang/Object;", "maxWithOrNull", "min", "minOrThrow", "minBy", "minByOrThrow", "minByOrNull", "minOf", "minOfOrNull", "minOfWith", "minOfWithOrNull", "minOrNull", "minWith", "minWithOrThrow", "minWithOrNull", "minus", "(Lkotlin/sequences/Sequence;Ljava/lang/Object;)Lkotlin/sequences/Sequence;", "elements", "", "(Lkotlin/sequences/Sequence;[Ljava/lang/Object;)Lkotlin/sequences/Sequence;", "minusElement", "none", "onEach", "onEachIndexed", "partition", "plus", "plusElement", "reduce", "S", "(Lkotlin/sequences/Sequence;Lkotlin/jvm/functions/Function2;)Ljava/lang/Object;", "reduceIndexed", "(Lkotlin/sequences/Sequence;Lkotlin/jvm/functions/Function3;)Ljava/lang/Object;", "reduceIndexedOrNull", "reduceOrNull", "requireNoNulls", "runningFold", "(Lkotlin/sequences/Sequence;Ljava/lang/Object;Lkotlin/jvm/functions/Function2;)Lkotlin/sequences/Sequence;", "runningFoldIndexed", "(Lkotlin/sequences/Sequence;Ljava/lang/Object;Lkotlin/jvm/functions/Function3;)Lkotlin/sequences/Sequence;", "runningReduce", "runningReduceIndexed", "scan", "scanIndexed", "single", "singleOrNull", "sorted", "sortedBy", "sortedByDescending", "sortedDescending", "sortedWith", "sum", "sumOfByte", "sumOfDouble", "sumOfFloat", "sumOfInt", "sumOfLong", "sumOfShort", "sumBy", "sumByDouble", "sumOf", "Lkotlin/UInt;", "sumOfUInt", "(Lkotlin/sequences/Sequence;Lkotlin/jvm/functions/Function1;)I", "Lkotlin/ULong;", "sumOfULong", "(Lkotlin/sequences/Sequence;Lkotlin/jvm/functions/Function1;)J", "take", "takeWhile", "toCollection", "toHashSet", "Ljava/util/HashSet;", "Lkotlin/collections/HashSet;", "toList", "toMutableList", "toMutableSet", "", "toSet", "", "windowed", "step", "partialWindows", "withIndex", "Lkotlin/collections/IndexedValue;", "zip", "other", "a", "b", "zipWithNext", "kotlin-stdlib" }, xs = "kotlin/sequences/SequencesKt")
class SequencesKt___SequencesKt extends SequencesKt___SequencesJvmKt
{
    public static final <T> boolean contains(@NotNull final Sequence<? extends T> $this$contains, final T element) {
        Intrinsics.checkNotNullParameter($this$contains, "<this>");
        return indexOf($this$contains, element) >= 0;
    }
    
    public static final <T> T elementAt(@NotNull final Sequence<? extends T> $this$elementAt, final int index) {
        Intrinsics.checkNotNullParameter($this$elementAt, "<this>");
        return elementAtOrElse($this$elementAt, index, (Function1<? super Integer, ? extends T>)new SequencesKt___SequencesKt$elementAt.SequencesKt___SequencesKt$elementAt$1(index));
    }
    
    public static final <T> T elementAtOrElse(@NotNull final Sequence<? extends T> $this$elementAtOrElse, final int index, @NotNull final Function1<? super Integer, ? extends T> defaultValue) {
        Intrinsics.checkNotNullParameter($this$elementAtOrElse, "<this>");
        Intrinsics.checkNotNullParameter(defaultValue, "defaultValue");
        if (index < 0) {
            return (T)defaultValue.invoke(index);
        }
        final Iterator iterator = $this$elementAtOrElse.iterator();
        int count = 0;
        while (iterator.hasNext()) {
            final Object element = iterator.next();
            if (index == count++) {
                return (T)element;
            }
        }
        return (T)defaultValue.invoke(index);
    }
    
    @Nullable
    public static final <T> T elementAtOrNull(@NotNull final Sequence<? extends T> $this$elementAtOrNull, final int index) {
        Intrinsics.checkNotNullParameter($this$elementAtOrNull, "<this>");
        if (index < 0) {
            return null;
        }
        final Iterator iterator = $this$elementAtOrNull.iterator();
        int count = 0;
        while (iterator.hasNext()) {
            final Object element = iterator.next();
            if (index == count++) {
                return (T)element;
            }
        }
        return null;
    }
    
    @InlineOnly
    private static final <T> T find(final Sequence<? extends T> $this$find, final Function1<? super T, Boolean> predicate) {
        Intrinsics.checkNotNullParameter($this$find, "<this>");
        Intrinsics.checkNotNullParameter(predicate, "predicate");
        final Sequence $this$firstOrNull$iv = $this$find;
        final int $i$f$firstOrNull = 0;
        for (final Object element$iv : $this$firstOrNull$iv) {
            if (predicate.invoke((Object)element$iv)) {
                final Object o = element$iv;
                return (T)o;
            }
        }
        final Object o = null;
        return (T)o;
    }
    
    @InlineOnly
    private static final <T> T findLast(final Sequence<? extends T> $this$findLast, final Function1<? super T, Boolean> predicate) {
        Intrinsics.checkNotNullParameter($this$findLast, "<this>");
        Intrinsics.checkNotNullParameter(predicate, "predicate");
        final Sequence $this$lastOrNull$iv = $this$findLast;
        final int $i$f$lastOrNull = 0;
        Object last$iv = null;
        for (final Object element$iv : $this$lastOrNull$iv) {
            if (predicate.invoke((Object)element$iv)) {
                last$iv = element$iv;
            }
        }
        return (T)last$iv;
    }
    
    public static final <T> T first(@NotNull final Sequence<? extends T> $this$first) {
        Intrinsics.checkNotNullParameter($this$first, "<this>");
        final Iterator iterator = $this$first.iterator();
        if (!iterator.hasNext()) {
            throw new NoSuchElementException("Sequence is empty.");
        }
        return iterator.next();
    }
    
    public static final <T> T first(@NotNull final Sequence<? extends T> $this$first, @NotNull final Function1<? super T, Boolean> predicate) {
        Intrinsics.checkNotNullParameter($this$first, "<this>");
        Intrinsics.checkNotNullParameter(predicate, "predicate");
        final int $i$f$first = 0;
        for (final Object element : $this$first) {
            if (predicate.invoke((Object)element)) {
                return (T)element;
            }
        }
        throw new NoSuchElementException("Sequence contains no element matching the predicate.");
    }
    
    @SinceKotlin(version = "1.5")
    @InlineOnly
    private static final <T, R> R firstNotNullOf(final Sequence<? extends T> $this$firstNotNullOf, final Function1<? super T, ? extends R> transform) {
        Intrinsics.checkNotNullParameter($this$firstNotNullOf, "<this>");
        Intrinsics.checkNotNullParameter(transform, "transform");
        final Iterator<? extends T> iterator = $this$firstNotNullOf.iterator();
        while (true) {
            while (iterator.hasNext()) {
                final Object invoke;
                final Object o;
                if ((o = (invoke = transform.invoke((Object)iterator.next()))) == null) {
                    continue;
                }
                if (o == null) {
                    throw new NoSuchElementException("No element of the sequence was transformed to a non-null value.");
                }
                return (R)invoke;
            }
            Object o;
            Object invoke = o = null;
            continue;
        }
    }
    
    @SinceKotlin(version = "1.5")
    @InlineOnly
    private static final <T, R> R firstNotNullOfOrNull(final Sequence<? extends T> $this$firstNotNullOfOrNull, final Function1<? super T, ? extends R> transform) {
        Intrinsics.checkNotNullParameter($this$firstNotNullOfOrNull, "<this>");
        Intrinsics.checkNotNullParameter(transform, "transform");
        for (final Object element : $this$firstNotNullOfOrNull) {
            final Object result = transform.invoke((Object)element);
            if (result != null) {
                return (R)result;
            }
        }
        return null;
    }
    
    @Nullable
    public static final <T> T firstOrNull(@NotNull final Sequence<? extends T> $this$firstOrNull) {
        Intrinsics.checkNotNullParameter($this$firstOrNull, "<this>");
        final Iterator iterator = $this$firstOrNull.iterator();
        if (!iterator.hasNext()) {
            return null;
        }
        return iterator.next();
    }
    
    @Nullable
    public static final <T> T firstOrNull(@NotNull final Sequence<? extends T> $this$firstOrNull, @NotNull final Function1<? super T, Boolean> predicate) {
        Intrinsics.checkNotNullParameter($this$firstOrNull, "<this>");
        Intrinsics.checkNotNullParameter(predicate, "predicate");
        final int $i$f$firstOrNull = 0;
        for (final Object element : $this$firstOrNull) {
            if (predicate.invoke((Object)element)) {
                return (T)element;
            }
        }
        return null;
    }
    
    public static final <T> int indexOf(@NotNull final Sequence<? extends T> $this$indexOf, final T element) {
        Intrinsics.checkNotNullParameter($this$indexOf, "<this>");
        int index = 0;
        for (final Object item : $this$indexOf) {
            if (index < 0) {
                CollectionsKt.throwIndexOverflow();
            }
            if (Intrinsics.areEqual(element, item)) {
                return index;
            }
            ++index;
        }
        return -1;
    }
    
    public static final <T> int indexOfFirst(@NotNull final Sequence<? extends T> $this$indexOfFirst, @NotNull final Function1<? super T, Boolean> predicate) {
        Intrinsics.checkNotNullParameter($this$indexOfFirst, "<this>");
        Intrinsics.checkNotNullParameter(predicate, "predicate");
        final int $i$f$indexOfFirst = 0;
        int index = 0;
        for (final Object item : $this$indexOfFirst) {
            if (index < 0) {
                CollectionsKt.throwIndexOverflow();
            }
            if (predicate.invoke((Object)item)) {
                return index;
            }
            ++index;
        }
        return -1;
    }
    
    public static final <T> int indexOfLast(@NotNull final Sequence<? extends T> $this$indexOfLast, @NotNull final Function1<? super T, Boolean> predicate) {
        Intrinsics.checkNotNullParameter($this$indexOfLast, "<this>");
        Intrinsics.checkNotNullParameter(predicate, "predicate");
        final int $i$f$indexOfLast = 0;
        int lastIndex = -1;
        int index = 0;
        for (final Object item : $this$indexOfLast) {
            if (index < 0) {
                CollectionsKt.throwIndexOverflow();
            }
            if (predicate.invoke((Object)item)) {
                lastIndex = index;
            }
            ++index;
        }
        return lastIndex;
    }
    
    public static final <T> T last(@NotNull final Sequence<? extends T> $this$last) {
        Intrinsics.checkNotNullParameter($this$last, "<this>");
        final Iterator iterator = $this$last.iterator();
        if (!iterator.hasNext()) {
            throw new NoSuchElementException("Sequence is empty.");
        }
        Object last = iterator.next();
        while (iterator.hasNext()) {
            last = iterator.next();
        }
        return (T)last;
    }
    
    public static final <T> T last(@NotNull final Sequence<? extends T> $this$last, @NotNull final Function1<? super T, Boolean> predicate) {
        Intrinsics.checkNotNullParameter($this$last, "<this>");
        Intrinsics.checkNotNullParameter(predicate, "predicate");
        final int $i$f$last = 0;
        Object last = null;
        boolean found = false;
        for (final Object element : $this$last) {
            if (predicate.invoke((Object)element)) {
                last = element;
                found = true;
            }
        }
        if (!found) {
            throw new NoSuchElementException("Sequence contains no element matching the predicate.");
        }
        return (T)last;
    }
    
    public static final <T> int lastIndexOf(@NotNull final Sequence<? extends T> $this$lastIndexOf, final T element) {
        Intrinsics.checkNotNullParameter($this$lastIndexOf, "<this>");
        int lastIndex = -1;
        int index = 0;
        for (final Object item : $this$lastIndexOf) {
            if (index < 0) {
                CollectionsKt.throwIndexOverflow();
            }
            if (Intrinsics.areEqual(element, item)) {
                lastIndex = index;
            }
            ++index;
        }
        return lastIndex;
    }
    
    @Nullable
    public static final <T> T lastOrNull(@NotNull final Sequence<? extends T> $this$lastOrNull) {
        Intrinsics.checkNotNullParameter($this$lastOrNull, "<this>");
        final Iterator iterator = $this$lastOrNull.iterator();
        if (!iterator.hasNext()) {
            return null;
        }
        Object last = iterator.next();
        while (iterator.hasNext()) {
            last = iterator.next();
        }
        return (T)last;
    }
    
    @Nullable
    public static final <T> T lastOrNull(@NotNull final Sequence<? extends T> $this$lastOrNull, @NotNull final Function1<? super T, Boolean> predicate) {
        Intrinsics.checkNotNullParameter($this$lastOrNull, "<this>");
        Intrinsics.checkNotNullParameter(predicate, "predicate");
        final int $i$f$lastOrNull = 0;
        Object last = null;
        for (final Object element : $this$lastOrNull) {
            if (predicate.invoke((Object)element)) {
                last = element;
            }
        }
        return (T)last;
    }
    
    public static final <T> T single(@NotNull final Sequence<? extends T> $this$single) {
        Intrinsics.checkNotNullParameter($this$single, "<this>");
        final Iterator iterator = $this$single.iterator();
        if (!iterator.hasNext()) {
            throw new NoSuchElementException("Sequence is empty.");
        }
        final Object single = iterator.next();
        if (iterator.hasNext()) {
            throw new IllegalArgumentException("Sequence has more than one element.");
        }
        return (T)single;
    }
    
    public static final <T> T single(@NotNull final Sequence<? extends T> $this$single, @NotNull final Function1<? super T, Boolean> predicate) {
        Intrinsics.checkNotNullParameter($this$single, "<this>");
        Intrinsics.checkNotNullParameter(predicate, "predicate");
        final int $i$f$single = 0;
        Object single = null;
        boolean found = false;
        for (final Object element : $this$single) {
            if (predicate.invoke((Object)element)) {
                if (found) {
                    throw new IllegalArgumentException("Sequence contains more than one matching element.");
                }
                single = element;
                found = true;
            }
        }
        if (!found) {
            throw new NoSuchElementException("Sequence contains no element matching the predicate.");
        }
        return (T)single;
    }
    
    @Nullable
    public static final <T> T singleOrNull(@NotNull final Sequence<? extends T> $this$singleOrNull) {
        Intrinsics.checkNotNullParameter($this$singleOrNull, "<this>");
        final Iterator iterator = $this$singleOrNull.iterator();
        if (!iterator.hasNext()) {
            return null;
        }
        final Object single = iterator.next();
        if (iterator.hasNext()) {
            return null;
        }
        return (T)single;
    }
    
    @Nullable
    public static final <T> T singleOrNull(@NotNull final Sequence<? extends T> $this$singleOrNull, @NotNull final Function1<? super T, Boolean> predicate) {
        Intrinsics.checkNotNullParameter($this$singleOrNull, "<this>");
        Intrinsics.checkNotNullParameter(predicate, "predicate");
        final int $i$f$singleOrNull = 0;
        Object single = null;
        boolean found = false;
        for (final Object element : $this$singleOrNull) {
            if (predicate.invoke((Object)element)) {
                if (found) {
                    return null;
                }
                single = element;
                found = true;
            }
        }
        if (!found) {
            return null;
        }
        return (T)single;
    }
    
    @NotNull
    public static final <T> Sequence<T> drop(@NotNull final Sequence<? extends T> $this$drop, final int n) {
        Intrinsics.checkNotNullParameter($this$drop, "<this>");
        if (n < 0) {
            final int n2 = 0;
            throw new IllegalArgumentException(("Requested element count " + n + " is less than zero.").toString());
        }
        return (Sequence<T>)((n == 0) ? $this$drop : (($this$drop instanceof DropTakeSequence) ? ((DropTakeSequence<? extends T>)$this$drop).drop(n) : ((DropSequence<Object>)new DropSequence<Object>($this$drop, n))));
    }
    
    @NotNull
    public static final <T> Sequence<T> dropWhile(@NotNull final Sequence<? extends T> $this$dropWhile, @NotNull final Function1<? super T, Boolean> predicate) {
        Intrinsics.checkNotNullParameter($this$dropWhile, "<this>");
        Intrinsics.checkNotNullParameter(predicate, "predicate");
        return new DropWhileSequence<T>($this$dropWhile, predicate);
    }
    
    @NotNull
    public static final <T> Sequence<T> filter(@NotNull final Sequence<? extends T> $this$filter, @NotNull final Function1<? super T, Boolean> predicate) {
        Intrinsics.checkNotNullParameter($this$filter, "<this>");
        Intrinsics.checkNotNullParameter(predicate, "predicate");
        return new FilteringSequence<T>($this$filter, true, predicate);
    }
    
    @NotNull
    public static final <T> Sequence<T> filterIndexed(@NotNull final Sequence<? extends T> $this$filterIndexed, @NotNull final Function2<? super Integer, ? super T, Boolean> predicate) {
        Intrinsics.checkNotNullParameter($this$filterIndexed, "<this>");
        Intrinsics.checkNotNullParameter(predicate, "predicate");
        return new TransformingSequence<Object, T>(new FilteringSequence<Object>(new IndexingSequence<Object>($this$filterIndexed), true, (Function1<?, Boolean>)new SequencesKt___SequencesKt$filterIndexed.SequencesKt___SequencesKt$filterIndexed$1((Function2)predicate)), (Function1<?, ? extends T>)SequencesKt___SequencesKt$filterIndexed.SequencesKt___SequencesKt$filterIndexed$2.INSTANCE);
    }
    
    @NotNull
    public static final <T, C extends Collection<? super T>> C filterIndexedTo(@NotNull final Sequence<? extends T> $this$filterIndexedTo, @NotNull final C destination, @NotNull final Function2<? super Integer, ? super T, Boolean> predicate) {
        // 
        // This method could not be decompiled.
        // 
        // Original Bytecode:
        // 
        //     1: ldc             "<this>"
        //     3: invokestatic    kotlin/jvm/internal/Intrinsics.checkNotNullParameter:(Ljava/lang/Object;Ljava/lang/String;)V
        //     6: aload_1         /* destination */
        //     7: ldc_w           "destination"
        //    10: invokestatic    kotlin/jvm/internal/Intrinsics.checkNotNullParameter:(Ljava/lang/Object;Ljava/lang/String;)V
        //    13: aload_2         /* predicate */
        //    14: ldc             "predicate"
        //    16: invokestatic    kotlin/jvm/internal/Intrinsics.checkNotNullParameter:(Ljava/lang/Object;Ljava/lang/String;)V
        //    19: iconst_0       
        //    20: istore_3        /* $i$f$filterIndexedTo */
        //    21: aload_0         /* $this$filterIndexedTo */
        //    22: astore          $this$forEachIndexed$iv
        //    24: iconst_0       
        //    25: istore          $i$f$forEachIndexed
        //    27: iconst_0       
        //    28: istore          index$iv
        //    30: aload           $this$forEachIndexed$iv
        //    32: invokeinterface kotlin/sequences/Sequence.iterator:()Ljava/util/Iterator;
        //    37: astore          7
        //    39: aload           7
        //    41: invokeinterface java/util/Iterator.hasNext:()Z
        //    46: ifeq            120
        //    49: aload           7
        //    51: invokeinterface java/util/Iterator.next:()Ljava/lang/Object;
        //    56: astore          item$iv
        //    58: iload           index$iv
        //    60: iinc            index$iv, 1
        //    63: istore          9
        //    65: iload           9
        //    67: ifge            73
        //    70: invokestatic    kotlin/collections/CollectionsKt.throwIndexOverflow:()V
        //    73: iload           9
        //    75: aload           item$iv
        //    77: astore          10
        //    79: istore          index
        //    81: iconst_0       
        //    82: istore          $i$a$-forEachIndexed-SequencesKt___SequencesKt$filterIndexedTo$1
        //    84: aload_2         /* predicate */
        //    85: iload           index
        //    87: invokestatic    java/lang/Integer.valueOf:(I)Ljava/lang/Integer;
        //    90: aload           element
        //    92: invokeinterface kotlin/jvm/functions/Function2.invoke:(Ljava/lang/Object;Ljava/lang/Object;)Ljava/lang/Object;
        //    97: checkcast       Ljava/lang/Boolean;
        //   100: invokevirtual   java/lang/Boolean.booleanValue:()Z
        //   103: ifeq            115
        //   106: aload_1         /* destination */
        //   107: aload           element
        //   109: invokeinterface java/util/Collection.add:(Ljava/lang/Object;)Z
        //   114: pop            
        //   115: nop            
        //   116: nop            
        //   117: goto            39
        //   120: nop            
        //   121: aload_1         /* destination */
        //   122: areturn        
        //    Signature:
        //  <T:Ljava/lang/Object;C::Ljava/util/Collection<-TT;>;>(Lkotlin/sequences/Sequence<+TT;>;TC;Lkotlin/jvm/functions/Function2<-Ljava/lang/Integer;-TT;Ljava/lang/Boolean;>;)TC;
        //    StackMapTable: 00 04 FF 00 27 00 08 07 00 3B 07 01 07 07 01 02 01 07 00 3B 01 01 07 00 41 00 00 FD 00 21 07 00 61 01 FE 00 29 07 00 61 01 01 FF 00 04 00 08 07 00 3B 07 01 07 07 01 02 01 07 00 3B 01 01 07 00 41 00 00
        // 
        // The error that occurred was:
        // 
        // java.lang.NullPointerException
        // 
        throw new IllegalStateException("An error occurred while decompiling this method.");
    }
    
    @NotNull
    public static final <T> Sequence<T> filterNot(@NotNull final Sequence<? extends T> $this$filterNot, @NotNull final Function1<? super T, Boolean> predicate) {
        Intrinsics.checkNotNullParameter($this$filterNot, "<this>");
        Intrinsics.checkNotNullParameter(predicate, "predicate");
        return new FilteringSequence<T>($this$filterNot, false, predicate);
    }
    
    @NotNull
    public static final <T> Sequence<T> filterNotNull(@NotNull final Sequence<? extends T> $this$filterNotNull) {
        Intrinsics.checkNotNullParameter($this$filterNotNull, "<this>");
        final Sequence<Object> filterNot = (Sequence<Object>)filterNot($this$filterNotNull, (Function1<? super T, Boolean>)SequencesKt___SequencesKt$filterNotNull.SequencesKt___SequencesKt$filterNotNull$1.INSTANCE);
        Intrinsics.checkNotNull(filterNot, "null cannot be cast to non-null type kotlin.sequences.Sequence<T of kotlin.sequences.SequencesKt___SequencesKt.filterNotNull>");
        return (Sequence<T>)filterNot;
    }
    
    @NotNull
    public static final <C extends Collection<? super T>, T> C filterNotNullTo(@NotNull final Sequence<? extends T> $this$filterNotNullTo, @NotNull final C destination) {
        Intrinsics.checkNotNullParameter($this$filterNotNullTo, "<this>");
        Intrinsics.checkNotNullParameter(destination, "destination");
        for (final Object element : $this$filterNotNullTo) {
            if (element != null) {
                destination.add((Object)element);
            }
        }
        return destination;
    }
    
    @NotNull
    public static final <T, C extends Collection<? super T>> C filterNotTo(@NotNull final Sequence<? extends T> $this$filterNotTo, @NotNull final C destination, @NotNull final Function1<? super T, Boolean> predicate) {
        Intrinsics.checkNotNullParameter($this$filterNotTo, "<this>");
        Intrinsics.checkNotNullParameter(destination, "destination");
        Intrinsics.checkNotNullParameter(predicate, "predicate");
        final int $i$f$filterNotTo = 0;
        for (final Object element : $this$filterNotTo) {
            if (!predicate.invoke((Object)element)) {
                destination.add((Object)element);
            }
        }
        return destination;
    }
    
    @NotNull
    public static final <T, C extends Collection<? super T>> C filterTo(@NotNull final Sequence<? extends T> $this$filterTo, @NotNull final C destination, @NotNull final Function1<? super T, Boolean> predicate) {
        Intrinsics.checkNotNullParameter($this$filterTo, "<this>");
        Intrinsics.checkNotNullParameter(destination, "destination");
        Intrinsics.checkNotNullParameter(predicate, "predicate");
        final int $i$f$filterTo = 0;
        for (final Object element : $this$filterTo) {
            if (predicate.invoke((Object)element)) {
                destination.add((Object)element);
            }
        }
        return destination;
    }
    
    @NotNull
    public static final <T> Sequence<T> take(@NotNull final Sequence<? extends T> $this$take, final int n) {
        Intrinsics.checkNotNullParameter($this$take, "<this>");
        if (n < 0) {
            final int n2 = 0;
            throw new IllegalArgumentException(("Requested element count " + n + " is less than zero.").toString());
        }
        return (n == 0) ? SequencesKt__SequencesKt.emptySequence() : (($this$take instanceof DropTakeSequence) ? ((DropTakeSequence<T>)$this$take).take(n) : ((TakeSequence<T>)new TakeSequence<T>($this$take, n)));
    }
    
    @NotNull
    public static final <T> Sequence<T> takeWhile(@NotNull final Sequence<? extends T> $this$takeWhile, @NotNull final Function1<? super T, Boolean> predicate) {
        Intrinsics.checkNotNullParameter($this$takeWhile, "<this>");
        Intrinsics.checkNotNullParameter(predicate, "predicate");
        return new TakeWhileSequence<T>($this$takeWhile, predicate);
    }
    
    @NotNull
    public static final <T extends Comparable<? super T>> Sequence<T> sorted(@NotNull final Sequence<? extends T> $this$sorted) {
        Intrinsics.checkNotNullParameter($this$sorted, "<this>");
        return (Sequence<T>)new SequencesKt___SequencesKt$sorted.SequencesKt___SequencesKt$sorted$1((Sequence)$this$sorted);
    }
    
    @NotNull
    public static final <T, R extends Comparable<? super R>> Sequence<T> sortedBy(@NotNull final Sequence<? extends T> $this$sortedBy, @NotNull final Function1<? super T, ? extends R> selector) {
        Intrinsics.checkNotNullParameter($this$sortedBy, "<this>");
        Intrinsics.checkNotNullParameter(selector, "selector");
        final int $i$f$sortedBy = 0;
        return sortedWith($this$sortedBy, (Comparator<? super T>)new Comparator(selector) {
            @Override
            public final int compare(final T a, final T b) {
                final Function1 $selector = this.$selector;
                return ComparisonsKt__ComparisonsKt.compareValues($selector.invoke(a), (Comparable)$selector.invoke(b));
            }
        });
    }
    
    @NotNull
    public static final <T, R extends Comparable<? super R>> Sequence<T> sortedByDescending(@NotNull final Sequence<? extends T> $this$sortedByDescending, @NotNull final Function1<? super T, ? extends R> selector) {
        Intrinsics.checkNotNullParameter($this$sortedByDescending, "<this>");
        Intrinsics.checkNotNullParameter(selector, "selector");
        final int $i$f$sortedByDescending = 0;
        return sortedWith($this$sortedByDescending, (Comparator<? super T>)new Comparator(selector) {
            @Override
            public final int compare(final T a, final T b) {
                final Function1 $selector = this.$selector;
                return ComparisonsKt__ComparisonsKt.compareValues($selector.invoke(b), (Comparable)$selector.invoke(a));
            }
        });
    }
    
    @NotNull
    public static final <T extends Comparable<? super T>> Sequence<T> sortedDescending(@NotNull final Sequence<? extends T> $this$sortedDescending) {
        Intrinsics.checkNotNullParameter($this$sortedDescending, "<this>");
        return sortedWith($this$sortedDescending, ComparisonsKt__ComparisonsKt.reverseOrder());
    }
    
    @NotNull
    public static final <T> Sequence<T> sortedWith(@NotNull final Sequence<? extends T> $this$sortedWith, @NotNull final Comparator<? super T> comparator) {
        Intrinsics.checkNotNullParameter($this$sortedWith, "<this>");
        Intrinsics.checkNotNullParameter(comparator, "comparator");
        return (Sequence<T>)new SequencesKt___SequencesKt$sortedWith.SequencesKt___SequencesKt$sortedWith$1((Sequence)$this$sortedWith, (Comparator)comparator);
    }
    
    @NotNull
    public static final <T, K, V> Map<K, V> associate(@NotNull final Sequence<? extends T> $this$associate, @NotNull final Function1<? super T, ? extends Pair<? extends K, ? extends V>> transform) {
        // 
        // This method could not be decompiled.
        // 
        // Original Bytecode:
        // 
        //     1: ldc             "<this>"
        //     3: invokestatic    kotlin/jvm/internal/Intrinsics.checkNotNullParameter:(Ljava/lang/Object;Ljava/lang/String;)V
        //     6: aload_1         /* transform */
        //     7: ldc             "transform"
        //     9: invokestatic    kotlin/jvm/internal/Intrinsics.checkNotNullParameter:(Ljava/lang/Object;Ljava/lang/String;)V
        //    12: iconst_0       
        //    13: istore_2        /* $i$f$associate */
        //    14: aload_0         /* $this$associate */
        //    15: astore_3       
        //    16: new             Ljava/util/LinkedHashMap;
        //    19: dup            
        //    20: invokespecial   java/util/LinkedHashMap.<init>:()V
        //    23: checkcast       Ljava/util/Map;
        //    26: astore          destination$iv
        //    28: iconst_0       
        //    29: istore          $i$f$associateTo
        //    31: aload_3         /* $this$associateTo$iv */
        //    32: invokeinterface kotlin/sequences/Sequence.iterator:()Ljava/util/Iterator;
        //    37: astore          6
        //    39: aload           6
        //    41: invokeinterface java/util/Iterator.hasNext:()Z
        //    46: ifeq            96
        //    49: aload           6
        //    51: invokeinterface java/util/Iterator.next:()Ljava/lang/Object;
        //    56: astore          element$iv
        //    58: aload           destination$iv
        //    60: astore          8
        //    62: aload_1         /* transform */
        //    63: aload           element$iv
        //    65: invokeinterface kotlin/jvm/functions/Function1.invoke:(Ljava/lang/Object;)Ljava/lang/Object;
        //    70: checkcast       Lkotlin/Pair;
        //    73: astore          9
        //    75: aload           8
        //    77: aload           9
        //    79: invokevirtual   kotlin/Pair.getFirst:()Ljava/lang/Object;
        //    82: aload           9
        //    84: invokevirtual   kotlin/Pair.getSecond:()Ljava/lang/Object;
        //    87: invokeinterface java/util/Map.put:(Ljava/lang/Object;Ljava/lang/Object;)Ljava/lang/Object;
        //    92: pop            
        //    93: goto            39
        //    96: aload           destination$iv
        //    98: areturn        
        //    Signature:
        //  <T:Ljava/lang/Object;K:Ljava/lang/Object;V:Ljava/lang/Object;>(Lkotlin/sequences/Sequence<+TT;>;Lkotlin/jvm/functions/Function1<-TT;+Lkotlin/Pair<+TK;+TV;>;>;)Ljava/util/Map<TK;TV;>;
        //    StackMapTable: 00 02 FF 00 27 00 07 07 00 3B 07 00 25 01 07 00 3B 07 01 93 01 07 00 41 00 00 38
        // 
        // The error that occurred was:
        // 
        // java.lang.NullPointerException
        // 
        throw new IllegalStateException("An error occurred while decompiling this method.");
    }
    
    @NotNull
    public static final <T, K> Map<K, T> associateBy(@NotNull final Sequence<? extends T> $this$associateBy, @NotNull final Function1<? super T, ? extends K> keySelector) {
        // 
        // This method could not be decompiled.
        // 
        // Original Bytecode:
        // 
        //     1: ldc             "<this>"
        //     3: invokestatic    kotlin/jvm/internal/Intrinsics.checkNotNullParameter:(Ljava/lang/Object;Ljava/lang/String;)V
        //     6: aload_1         /* keySelector */
        //     7: ldc_w           "keySelector"
        //    10: invokestatic    kotlin/jvm/internal/Intrinsics.checkNotNullParameter:(Ljava/lang/Object;Ljava/lang/String;)V
        //    13: iconst_0       
        //    14: istore_2        /* $i$f$associateBy */
        //    15: aload_0         /* $this$associateBy */
        //    16: astore_3       
        //    17: new             Ljava/util/LinkedHashMap;
        //    20: dup            
        //    21: invokespecial   java/util/LinkedHashMap.<init>:()V
        //    24: checkcast       Ljava/util/Map;
        //    27: astore          destination$iv
        //    29: iconst_0       
        //    30: istore          $i$f$associateByTo
        //    32: aload_3         /* $this$associateByTo$iv */
        //    33: invokeinterface kotlin/sequences/Sequence.iterator:()Ljava/util/Iterator;
        //    38: astore          6
        //    40: aload           6
        //    42: invokeinterface java/util/Iterator.hasNext:()Z
        //    47: ifeq            80
        //    50: aload           6
        //    52: invokeinterface java/util/Iterator.next:()Ljava/lang/Object;
        //    57: astore          element$iv
        //    59: aload           destination$iv
        //    61: aload_1         /* keySelector */
        //    62: aload           element$iv
        //    64: invokeinterface kotlin/jvm/functions/Function1.invoke:(Ljava/lang/Object;)Ljava/lang/Object;
        //    69: aload           element$iv
        //    71: invokeinterface java/util/Map.put:(Ljava/lang/Object;Ljava/lang/Object;)Ljava/lang/Object;
        //    76: pop            
        //    77: goto            40
        //    80: aload           destination$iv
        //    82: areturn        
        //    Signature:
        //  <T:Ljava/lang/Object;K:Ljava/lang/Object;>(Lkotlin/sequences/Sequence<+TT;>;Lkotlin/jvm/functions/Function1<-TT;+TK;>;)Ljava/util/Map<TK;TT;>;
        //    StackMapTable: 00 02 FF 00 28 00 07 07 00 3B 07 00 25 01 07 00 3B 07 01 93 01 07 00 41 00 00 27
        // 
        // The error that occurred was:
        // 
        // java.lang.NullPointerException
        // 
        throw new IllegalStateException("An error occurred while decompiling this method.");
    }
    
    @NotNull
    public static final <T, K, V> Map<K, V> associateBy(@NotNull final Sequence<? extends T> $this$associateBy, @NotNull final Function1<? super T, ? extends K> keySelector, @NotNull final Function1<? super T, ? extends V> valueTransform) {
        // 
        // This method could not be decompiled.
        // 
        // Original Bytecode:
        // 
        //     1: ldc             "<this>"
        //     3: invokestatic    kotlin/jvm/internal/Intrinsics.checkNotNullParameter:(Ljava/lang/Object;Ljava/lang/String;)V
        //     6: aload_1         /* keySelector */
        //     7: ldc_w           "keySelector"
        //    10: invokestatic    kotlin/jvm/internal/Intrinsics.checkNotNullParameter:(Ljava/lang/Object;Ljava/lang/String;)V
        //    13: aload_2         /* valueTransform */
        //    14: ldc_w           "valueTransform"
        //    17: invokestatic    kotlin/jvm/internal/Intrinsics.checkNotNullParameter:(Ljava/lang/Object;Ljava/lang/String;)V
        //    20: iconst_0       
        //    21: istore_3        /* $i$f$associateBy */
        //    22: aload_0         /* $this$associateBy */
        //    23: astore          4
        //    25: new             Ljava/util/LinkedHashMap;
        //    28: dup            
        //    29: invokespecial   java/util/LinkedHashMap.<init>:()V
        //    32: checkcast       Ljava/util/Map;
        //    35: astore          destination$iv
        //    37: iconst_0       
        //    38: istore          $i$f$associateByTo
        //    40: aload           $this$associateByTo$iv
        //    42: invokeinterface kotlin/sequences/Sequence.iterator:()Ljava/util/Iterator;
        //    47: astore          7
        //    49: aload           7
        //    51: invokeinterface java/util/Iterator.hasNext:()Z
        //    56: ifeq            95
        //    59: aload           7
        //    61: invokeinterface java/util/Iterator.next:()Ljava/lang/Object;
        //    66: astore          element$iv
        //    68: aload           destination$iv
        //    70: aload_1         /* keySelector */
        //    71: aload           element$iv
        //    73: invokeinterface kotlin/jvm/functions/Function1.invoke:(Ljava/lang/Object;)Ljava/lang/Object;
        //    78: aload_2         /* valueTransform */
        //    79: aload           element$iv
        //    81: invokeinterface kotlin/jvm/functions/Function1.invoke:(Ljava/lang/Object;)Ljava/lang/Object;
        //    86: invokeinterface java/util/Map.put:(Ljava/lang/Object;Ljava/lang/Object;)Ljava/lang/Object;
        //    91: pop            
        //    92: goto            49
        //    95: aload           destination$iv
        //    97: areturn        
        //    Signature:
        //  <T:Ljava/lang/Object;K:Ljava/lang/Object;V:Ljava/lang/Object;>(Lkotlin/sequences/Sequence<+TT;>;Lkotlin/jvm/functions/Function1<-TT;+TK;>;Lkotlin/jvm/functions/Function1<-TT;+TV;>;)Ljava/util/Map<TK;TV;>;
        //    StackMapTable: 00 02 FF 00 31 00 08 07 00 3B 07 00 25 07 00 25 01 07 00 3B 07 01 93 01 07 00 41 00 00 2D
        // 
        // The error that occurred was:
        // 
        // java.lang.NullPointerException
        // 
        throw new IllegalStateException("An error occurred while decompiling this method.");
    }
    
    @NotNull
    public static final <T, K, M extends Map<? super K, ? super T>> M associateByTo(@NotNull final Sequence<? extends T> $this$associateByTo, @NotNull final M destination, @NotNull final Function1<? super T, ? extends K> keySelector) {
        Intrinsics.checkNotNullParameter($this$associateByTo, "<this>");
        Intrinsics.checkNotNullParameter(destination, "destination");
        Intrinsics.checkNotNullParameter(keySelector, "keySelector");
        final int $i$f$associateByTo = 0;
        for (final Object element : $this$associateByTo) {
            destination.put((Object)keySelector.invoke((Object)element), (Object)element);
        }
        return destination;
    }
    
    @NotNull
    public static final <T, K, V, M extends Map<? super K, ? super V>> M associateByTo(@NotNull final Sequence<? extends T> $this$associateByTo, @NotNull final M destination, @NotNull final Function1<? super T, ? extends K> keySelector, @NotNull final Function1<? super T, ? extends V> valueTransform) {
        Intrinsics.checkNotNullParameter($this$associateByTo, "<this>");
        Intrinsics.checkNotNullParameter(destination, "destination");
        Intrinsics.checkNotNullParameter(keySelector, "keySelector");
        Intrinsics.checkNotNullParameter(valueTransform, "valueTransform");
        final int $i$f$associateByTo = 0;
        for (final Object element : $this$associateByTo) {
            destination.put((Object)keySelector.invoke((Object)element), (Object)valueTransform.invoke((Object)element));
        }
        return destination;
    }
    
    @NotNull
    public static final <T, K, V, M extends Map<? super K, ? super V>> M associateTo(@NotNull final Sequence<? extends T> $this$associateTo, @NotNull final M destination, @NotNull final Function1<? super T, ? extends Pair<? extends K, ? extends V>> transform) {
        Intrinsics.checkNotNullParameter($this$associateTo, "<this>");
        Intrinsics.checkNotNullParameter(destination, "destination");
        Intrinsics.checkNotNullParameter(transform, "transform");
        final int $i$f$associateTo = 0;
        for (final Object element : $this$associateTo) {
            final Pair pair = (Pair)transform.invoke((Object)element);
            destination.put(pair.getFirst(), (Object)pair.getSecond());
        }
        return destination;
    }
    
    @SinceKotlin(version = "1.3")
    @NotNull
    public static final <K, V> Map<K, V> associateWith(@NotNull final Sequence<? extends K> $this$associateWith, @NotNull final Function1<? super K, ? extends V> valueSelector) {
        Intrinsics.checkNotNullParameter($this$associateWith, "<this>");
        Intrinsics.checkNotNullParameter(valueSelector, "valueSelector");
        final int $i$f$associateWith = 0;
        final LinkedHashMap result = new LinkedHashMap();
        final Sequence $this$associateWithTo$iv = $this$associateWith;
        final int $i$f$associateWithTo = 0;
        for (final Object element$iv : $this$associateWithTo$iv) {
            result.put(element$iv, valueSelector.invoke((Object)element$iv));
        }
        return (Map<K, V>)result;
    }
    
    @SinceKotlin(version = "1.3")
    @NotNull
    public static final <K, V, M extends Map<? super K, ? super V>> M associateWithTo(@NotNull final Sequence<? extends K> $this$associateWithTo, @NotNull final M destination, @NotNull final Function1<? super K, ? extends V> valueSelector) {
        Intrinsics.checkNotNullParameter($this$associateWithTo, "<this>");
        Intrinsics.checkNotNullParameter(destination, "destination");
        Intrinsics.checkNotNullParameter(valueSelector, "valueSelector");
        final int $i$f$associateWithTo = 0;
        for (final Object element : $this$associateWithTo) {
            destination.put((Object)element, (Object)valueSelector.invoke((Object)element));
        }
        return destination;
    }
    
    @NotNull
    public static final <T, C extends Collection<? super T>> C toCollection(@NotNull final Sequence<? extends T> $this$toCollection, @NotNull final C destination) {
        Intrinsics.checkNotNullParameter($this$toCollection, "<this>");
        Intrinsics.checkNotNullParameter(destination, "destination");
        for (final Object item : $this$toCollection) {
            destination.add((Object)item);
        }
        return destination;
    }
    
    @NotNull
    public static final <T> HashSet<T> toHashSet(@NotNull final Sequence<? extends T> $this$toHashSet) {
        Intrinsics.checkNotNullParameter($this$toHashSet, "<this>");
        return toCollection((Sequence<?>)$this$toHashSet, (HashSet<T>)new HashSet<T>());
    }
    
    @NotNull
    public static final <T> List<T> toList(@NotNull final Sequence<? extends T> $this$toList) {
        Intrinsics.checkNotNullParameter($this$toList, "<this>");
        return CollectionsKt__CollectionsKt.optimizeReadOnlyList(toMutableList((Sequence<? extends T>)$this$toList));
    }
    
    @NotNull
    public static final <T> List<T> toMutableList(@NotNull final Sequence<? extends T> $this$toMutableList) {
        Intrinsics.checkNotNullParameter($this$toMutableList, "<this>");
        return toCollection((Sequence<?>)$this$toMutableList, (ArrayList<T>)new ArrayList<T>());
    }
    
    @NotNull
    public static final <T> Set<T> toSet(@NotNull final Sequence<? extends T> $this$toSet) {
        Intrinsics.checkNotNullParameter($this$toSet, "<this>");
        return SetsKt__SetsKt.optimizeReadOnlySet((Set<? extends T>)toCollection((Sequence<?>)$this$toSet, (LinkedHashSet<? extends T>)new LinkedHashSet<Object>()));
    }
    
    @SinceKotlin(version = "1.4")
    @OverloadResolutionByLambdaReturnType
    @JvmName(name = "flatMapIterable")
    @NotNull
    public static final <T, R> Sequence<R> flatMapIterable(@NotNull final Sequence<? extends T> $this$flatMap, @NotNull final Function1<? super T, ? extends Iterable<? extends R>> transform) {
        Intrinsics.checkNotNullParameter($this$flatMap, "<this>");
        Intrinsics.checkNotNullParameter(transform, "transform");
        return new FlatteningSequence<Object, Object, R>($this$flatMap, transform, (Function1<?, ? extends Iterator<? extends R>>)SequencesKt___SequencesKt$flatMap.SequencesKt___SequencesKt$flatMap$1.INSTANCE);
    }
    
    @NotNull
    public static final <T, R> Sequence<R> flatMap(@NotNull final Sequence<? extends T> $this$flatMap, @NotNull final Function1<? super T, ? extends Sequence<? extends R>> transform) {
        Intrinsics.checkNotNullParameter($this$flatMap, "<this>");
        Intrinsics.checkNotNullParameter(transform, "transform");
        return new FlatteningSequence<Object, Object, R>($this$flatMap, transform, (Function1<?, ? extends Iterator<? extends R>>)SequencesKt___SequencesKt$flatMap.SequencesKt___SequencesKt$flatMap$2.INSTANCE);
    }
    
    @SinceKotlin(version = "1.4")
    @OverloadResolutionByLambdaReturnType
    @JvmName(name = "flatMapIndexedIterable")
    @NotNull
    public static final <T, R> Sequence<R> flatMapIndexedIterable(@NotNull final Sequence<? extends T> $this$flatMapIndexed, @NotNull final Function2<? super Integer, ? super T, ? extends Iterable<? extends R>> transform) {
        Intrinsics.checkNotNullParameter($this$flatMapIndexed, "<this>");
        Intrinsics.checkNotNullParameter(transform, "transform");
        return SequencesKt__SequencesKt.flatMapIndexed((Sequence<?>)$this$flatMapIndexed, (Function2<? super Integer, ? super Object, ?>)transform, (Function1<? super Object, ? extends Iterator<? extends R>>)SequencesKt___SequencesKt$flatMapIndexed.SequencesKt___SequencesKt$flatMapIndexed$1.INSTANCE);
    }
    
    @SinceKotlin(version = "1.4")
    @OverloadResolutionByLambdaReturnType
    @JvmName(name = "flatMapIndexedSequence")
    @NotNull
    public static final <T, R> Sequence<R> flatMapIndexedSequence(@NotNull final Sequence<? extends T> $this$flatMapIndexed, @NotNull final Function2<? super Integer, ? super T, ? extends Sequence<? extends R>> transform) {
        Intrinsics.checkNotNullParameter($this$flatMapIndexed, "<this>");
        Intrinsics.checkNotNullParameter(transform, "transform");
        return SequencesKt__SequencesKt.flatMapIndexed((Sequence<?>)$this$flatMapIndexed, (Function2<? super Integer, ? super Object, ?>)transform, (Function1<? super Object, ? extends Iterator<? extends R>>)SequencesKt___SequencesKt$flatMapIndexed.SequencesKt___SequencesKt$flatMapIndexed$2.INSTANCE);
    }
    
    @SinceKotlin(version = "1.4")
    @OverloadResolutionByLambdaReturnType
    @JvmName(name = "flatMapIndexedIterableTo")
    @InlineOnly
    private static final <T, R, C extends Collection<? super R>> C flatMapIndexedIterableTo(final Sequence<? extends T> $this$flatMapIndexedTo, final C destination, final Function2<? super Integer, ? super T, ? extends Iterable<? extends R>> transform) {
        Intrinsics.checkNotNullParameter($this$flatMapIndexedTo, "<this>");
        Intrinsics.checkNotNullParameter(destination, "destination");
        Intrinsics.checkNotNullParameter(transform, "transform");
        int index = 0;
        for (final Object element : $this$flatMapIndexedTo) {
            final int i = index++;
            if (i < 0) {
                CollectionsKt.throwIndexOverflow();
            }
            final Iterable list = (Iterable)transform.invoke(Integer.valueOf(i), (Object)element);
            CollectionsKt__MutableCollectionsKt.addAll((Collection<? super Object>)destination, (Iterable<?>)list);
        }
        return destination;
    }
    
    @SinceKotlin(version = "1.4")
    @OverloadResolutionByLambdaReturnType
    @JvmName(name = "flatMapIndexedSequenceTo")
    @InlineOnly
    private static final <T, R, C extends Collection<? super R>> C flatMapIndexedSequenceTo(final Sequence<? extends T> $this$flatMapIndexedTo, final C destination, final Function2<? super Integer, ? super T, ? extends Sequence<? extends R>> transform) {
        Intrinsics.checkNotNullParameter($this$flatMapIndexedTo, "<this>");
        Intrinsics.checkNotNullParameter(destination, "destination");
        Intrinsics.checkNotNullParameter(transform, "transform");
        int index = 0;
        for (final Object element : $this$flatMapIndexedTo) {
            final int i = index++;
            if (i < 0) {
                CollectionsKt.throwIndexOverflow();
            }
            final Sequence list = (Sequence)transform.invoke(Integer.valueOf(i), (Object)element);
            CollectionsKt__MutableCollectionsKt.addAll((Collection<? super Object>)destination, (Sequence<?>)list);
        }
        return destination;
    }
    
    @SinceKotlin(version = "1.4")
    @OverloadResolutionByLambdaReturnType
    @JvmName(name = "flatMapIterableTo")
    @NotNull
    public static final <T, R, C extends Collection<? super R>> C flatMapIterableTo(@NotNull final Sequence<? extends T> $this$flatMapTo, @NotNull final C destination, @NotNull final Function1<? super T, ? extends Iterable<? extends R>> transform) {
        Intrinsics.checkNotNullParameter($this$flatMapTo, "<this>");
        Intrinsics.checkNotNullParameter(destination, "destination");
        Intrinsics.checkNotNullParameter(transform, "transform");
        final int $i$f$flatMapIterableTo = 0;
        for (final Object element : $this$flatMapTo) {
            final Iterable list = (Iterable)transform.invoke((Object)element);
            CollectionsKt__MutableCollectionsKt.addAll((Collection<? super Object>)destination, (Iterable<?>)list);
        }
        return destination;
    }
    
    @NotNull
    public static final <T, R, C extends Collection<? super R>> C flatMapTo(@NotNull final Sequence<? extends T> $this$flatMapTo, @NotNull final C destination, @NotNull final Function1<? super T, ? extends Sequence<? extends R>> transform) {
        Intrinsics.checkNotNullParameter($this$flatMapTo, "<this>");
        Intrinsics.checkNotNullParameter(destination, "destination");
        Intrinsics.checkNotNullParameter(transform, "transform");
        final int $i$f$flatMapTo = 0;
        for (final Object element : $this$flatMapTo) {
            final Sequence list = (Sequence)transform.invoke((Object)element);
            CollectionsKt__MutableCollectionsKt.addAll((Collection<? super Object>)destination, (Sequence<?>)list);
        }
        return destination;
    }
    
    @NotNull
    public static final <T, K> Map<K, List<T>> groupBy(@NotNull final Sequence<? extends T> $this$groupBy, @NotNull final Function1<? super T, ? extends K> keySelector) {
        // 
        // This method could not be decompiled.
        // 
        // Original Bytecode:
        // 
        //     1: ldc             "<this>"
        //     3: invokestatic    kotlin/jvm/internal/Intrinsics.checkNotNullParameter:(Ljava/lang/Object;Ljava/lang/String;)V
        //     6: aload_1         /* keySelector */
        //     7: ldc_w           "keySelector"
        //    10: invokestatic    kotlin/jvm/internal/Intrinsics.checkNotNullParameter:(Ljava/lang/Object;Ljava/lang/String;)V
        //    13: iconst_0       
        //    14: istore_2        /* $i$f$groupBy */
        //    15: aload_0         /* $this$groupBy */
        //    16: astore_3       
        //    17: new             Ljava/util/LinkedHashMap;
        //    20: dup            
        //    21: invokespecial   java/util/LinkedHashMap.<init>:()V
        //    24: checkcast       Ljava/util/Map;
        //    27: astore          destination$iv
        //    29: iconst_0       
        //    30: istore          $i$f$groupByTo
        //    32: aload_3         /* $this$groupByTo$iv */
        //    33: invokeinterface kotlin/sequences/Sequence.iterator:()Ljava/util/Iterator;
        //    38: astore          6
        //    40: aload           6
        //    42: invokeinterface java/util/Iterator.hasNext:()Z
        //    47: ifeq            145
        //    50: aload           6
        //    52: invokeinterface java/util/Iterator.next:()Ljava/lang/Object;
        //    57: astore          element$iv
        //    59: aload_1         /* keySelector */
        //    60: aload           element$iv
        //    62: invokeinterface kotlin/jvm/functions/Function1.invoke:(Ljava/lang/Object;)Ljava/lang/Object;
        //    67: astore          key$iv
        //    69: aload           destination$iv
        //    71: astore          $this$getOrPut$iv$iv
        //    73: iconst_0       
        //    74: istore          $i$f$getOrPut
        //    76: aload           $this$getOrPut$iv$iv
        //    78: aload           key$iv
        //    80: invokeinterface java/util/Map.get:(Ljava/lang/Object;)Ljava/lang/Object;
        //    85: astore          value$iv$iv
        //    87: aload           value$iv$iv
        //    89: ifnonnull       124
        //    92: iconst_0       
        //    93: istore          $i$a$-getOrPut-SequencesKt___SequencesKt$groupByTo$list$1$iv
        //    95: new             Ljava/util/ArrayList;
        //    98: dup            
        //    99: invokespecial   java/util/ArrayList.<init>:()V
        //   102: checkcast       Ljava/util/List;
        //   105: astore          answer$iv$iv
        //   107: aload           $this$getOrPut$iv$iv
        //   109: aload           key$iv
        //   111: aload           answer$iv$iv
        //   113: invokeinterface java/util/Map.put:(Ljava/lang/Object;Ljava/lang/Object;)Ljava/lang/Object;
        //   118: pop            
        //   119: aload           answer$iv$iv
        //   121: goto            126
        //   124: aload           value$iv$iv
        //   126: nop            
        //   127: checkcast       Ljava/util/List;
        //   130: astore          list$iv
        //   132: aload           list$iv
        //   134: aload           element$iv
        //   136: invokeinterface java/util/List.add:(Ljava/lang/Object;)Z
        //   141: pop            
        //   142: goto            40
        //   145: aload           destination$iv
        //   147: areturn        
        //    Signature:
        //  <T:Ljava/lang/Object;K:Ljava/lang/Object;>(Lkotlin/sequences/Sequence<+TT;>;Lkotlin/jvm/functions/Function1<-TT;+TK;>;)Ljava/util/Map<TK;Ljava/util/List<TT;>;>;
        //    StackMapTable: 00 04 FF 00 28 00 07 07 00 3B 07 00 25 01 07 00 3B 07 01 93 01 07 00 41 00 00 FF 00 53 00 0C 07 00 3B 07 00 25 01 07 00 3B 07 01 93 01 07 00 41 07 00 61 07 00 61 07 01 93 01 07 00 61 00 00 41 07 00 61 FF 00 12 00 07 07 00 3B 07 00 25 01 07 00 3B 07 01 93 01 07 00 41 00 00
        // 
        // The error that occurred was:
        // 
        // java.lang.NullPointerException
        // 
        throw new IllegalStateException("An error occurred while decompiling this method.");
    }
    
    @NotNull
    public static final <T, K, V> Map<K, List<V>> groupBy(@NotNull final Sequence<? extends T> $this$groupBy, @NotNull final Function1<? super T, ? extends K> keySelector, @NotNull final Function1<? super T, ? extends V> valueTransform) {
        // 
        // This method could not be decompiled.
        // 
        // Original Bytecode:
        // 
        //     1: ldc             "<this>"
        //     3: invokestatic    kotlin/jvm/internal/Intrinsics.checkNotNullParameter:(Ljava/lang/Object;Ljava/lang/String;)V
        //     6: aload_1         /* keySelector */
        //     7: ldc_w           "keySelector"
        //    10: invokestatic    kotlin/jvm/internal/Intrinsics.checkNotNullParameter:(Ljava/lang/Object;Ljava/lang/String;)V
        //    13: aload_2         /* valueTransform */
        //    14: ldc_w           "valueTransform"
        //    17: invokestatic    kotlin/jvm/internal/Intrinsics.checkNotNullParameter:(Ljava/lang/Object;Ljava/lang/String;)V
        //    20: iconst_0       
        //    21: istore_3        /* $i$f$groupBy */
        //    22: aload_0         /* $this$groupBy */
        //    23: astore          4
        //    25: new             Ljava/util/LinkedHashMap;
        //    28: dup            
        //    29: invokespecial   java/util/LinkedHashMap.<init>:()V
        //    32: checkcast       Ljava/util/Map;
        //    35: astore          destination$iv
        //    37: iconst_0       
        //    38: istore          $i$f$groupByTo
        //    40: aload           $this$groupByTo$iv
        //    42: invokeinterface kotlin/sequences/Sequence.iterator:()Ljava/util/Iterator;
        //    47: astore          7
        //    49: aload           7
        //    51: invokeinterface java/util/Iterator.hasNext:()Z
        //    56: ifeq            160
        //    59: aload           7
        //    61: invokeinterface java/util/Iterator.next:()Ljava/lang/Object;
        //    66: astore          element$iv
        //    68: aload_1         /* keySelector */
        //    69: aload           element$iv
        //    71: invokeinterface kotlin/jvm/functions/Function1.invoke:(Ljava/lang/Object;)Ljava/lang/Object;
        //    76: astore          key$iv
        //    78: aload           destination$iv
        //    80: astore          $this$getOrPut$iv$iv
        //    82: iconst_0       
        //    83: istore          $i$f$getOrPut
        //    85: aload           $this$getOrPut$iv$iv
        //    87: aload           key$iv
        //    89: invokeinterface java/util/Map.get:(Ljava/lang/Object;)Ljava/lang/Object;
        //    94: astore          value$iv$iv
        //    96: aload           value$iv$iv
        //    98: ifnonnull       133
        //   101: iconst_0       
        //   102: istore          $i$a$-getOrPut-SequencesKt___SequencesKt$groupByTo$list$2$iv
        //   104: new             Ljava/util/ArrayList;
        //   107: dup            
        //   108: invokespecial   java/util/ArrayList.<init>:()V
        //   111: checkcast       Ljava/util/List;
        //   114: astore          answer$iv$iv
        //   116: aload           $this$getOrPut$iv$iv
        //   118: aload           key$iv
        //   120: aload           answer$iv$iv
        //   122: invokeinterface java/util/Map.put:(Ljava/lang/Object;Ljava/lang/Object;)Ljava/lang/Object;
        //   127: pop            
        //   128: aload           answer$iv$iv
        //   130: goto            135
        //   133: aload           value$iv$iv
        //   135: nop            
        //   136: checkcast       Ljava/util/List;
        //   139: astore          list$iv
        //   141: aload           list$iv
        //   143: aload_2         /* valueTransform */
        //   144: aload           element$iv
        //   146: invokeinterface kotlin/jvm/functions/Function1.invoke:(Ljava/lang/Object;)Ljava/lang/Object;
        //   151: invokeinterface java/util/List.add:(Ljava/lang/Object;)Z
        //   156: pop            
        //   157: goto            49
        //   160: aload           destination$iv
        //   162: areturn        
        //    Signature:
        //  <T:Ljava/lang/Object;K:Ljava/lang/Object;V:Ljava/lang/Object;>(Lkotlin/sequences/Sequence<+TT;>;Lkotlin/jvm/functions/Function1<-TT;+TK;>;Lkotlin/jvm/functions/Function1<-TT;+TV;>;)Ljava/util/Map<TK;Ljava/util/List<TV;>;>;
        //    StackMapTable: 00 04 FF 00 31 00 08 07 00 3B 07 00 25 07 00 25 01 07 00 3B 07 01 93 01 07 00 41 00 00 FF 00 53 00 0D 07 00 3B 07 00 25 07 00 25 01 07 00 3B 07 01 93 01 07 00 41 07 00 61 07 00 61 07 01 93 01 07 00 61 00 00 41 07 00 61 FF 00 18 00 08 07 00 3B 07 00 25 07 00 25 01 07 00 3B 07 01 93 01 07 00 41 00 00
        // 
        // The error that occurred was:
        // 
        // java.lang.NullPointerException
        // 
        throw new IllegalStateException("An error occurred while decompiling this method.");
    }
    
    @NotNull
    public static final <T, K, M extends Map<? super K, List<T>>> M groupByTo(@NotNull final Sequence<? extends T> $this$groupByTo, @NotNull final M destination, @NotNull final Function1<? super T, ? extends K> keySelector) {
        Intrinsics.checkNotNullParameter($this$groupByTo, "<this>");
        Intrinsics.checkNotNullParameter(destination, "destination");
        Intrinsics.checkNotNullParameter(keySelector, "keySelector");
        final int $i$f$groupByTo = 0;
        for (final Object element : $this$groupByTo) {
            final Object key = keySelector.invoke((Object)element);
            final Map $this$getOrPut$iv = destination;
            final int $i$f$getOrPut = 0;
            final Object value$iv = $this$getOrPut$iv.get(key);
            Object o;
            if (value$iv == null) {
                final int n = 0;
                final Object answer$iv = new ArrayList<Object>();
                $this$getOrPut$iv.put(key, answer$iv);
                o = answer$iv;
            }
            else {
                o = value$iv;
            }
            final List list = (List)o;
            list.add(element);
        }
        return destination;
    }
    
    @NotNull
    public static final <T, K, V, M extends Map<? super K, List<V>>> M groupByTo(@NotNull final Sequence<? extends T> $this$groupByTo, @NotNull final M destination, @NotNull final Function1<? super T, ? extends K> keySelector, @NotNull final Function1<? super T, ? extends V> valueTransform) {
        Intrinsics.checkNotNullParameter($this$groupByTo, "<this>");
        Intrinsics.checkNotNullParameter(destination, "destination");
        Intrinsics.checkNotNullParameter(keySelector, "keySelector");
        Intrinsics.checkNotNullParameter(valueTransform, "valueTransform");
        final int $i$f$groupByTo = 0;
        for (final Object element : $this$groupByTo) {
            final Object key = keySelector.invoke((Object)element);
            final Map $this$getOrPut$iv = destination;
            final int $i$f$getOrPut = 0;
            final Object value$iv = $this$getOrPut$iv.get(key);
            Object o;
            if (value$iv == null) {
                final int n = 0;
                final Object answer$iv = new ArrayList<Object>();
                $this$getOrPut$iv.put(key, answer$iv);
                o = answer$iv;
            }
            else {
                o = value$iv;
            }
            final List list = (List)o;
            list.add(valueTransform.invoke((Object)element));
        }
        return destination;
    }
    
    @SinceKotlin(version = "1.1")
    @NotNull
    public static final <T, K> Grouping<T, K> groupingBy(@NotNull final Sequence<? extends T> $this$groupingBy, @NotNull final Function1<? super T, ? extends K> keySelector) {
        Intrinsics.checkNotNullParameter($this$groupingBy, "<this>");
        Intrinsics.checkNotNullParameter(keySelector, "keySelector");
        final int $i$f$groupingBy = 0;
        return (Grouping<T, K>)new SequencesKt___SequencesKt$groupingBy.SequencesKt___SequencesKt$groupingBy$1((Sequence)$this$groupingBy, (Function1)keySelector);
    }
    
    @NotNull
    public static final <T, R> Sequence<R> map(@NotNull final Sequence<? extends T> $this$map, @NotNull final Function1<? super T, ? extends R> transform) {
        Intrinsics.checkNotNullParameter($this$map, "<this>");
        Intrinsics.checkNotNullParameter(transform, "transform");
        return new TransformingSequence<Object, R>($this$map, transform);
    }
    
    @NotNull
    public static final <T, R> Sequence<R> mapIndexed(@NotNull final Sequence<? extends T> $this$mapIndexed, @NotNull final Function2<? super Integer, ? super T, ? extends R> transform) {
        Intrinsics.checkNotNullParameter($this$mapIndexed, "<this>");
        Intrinsics.checkNotNullParameter(transform, "transform");
        return new TransformingIndexedSequence<Object, R>($this$mapIndexed, transform);
    }
    
    @NotNull
    public static final <T, R> Sequence<R> mapIndexedNotNull(@NotNull final Sequence<? extends T> $this$mapIndexedNotNull, @NotNull final Function2<? super Integer, ? super T, ? extends R> transform) {
        Intrinsics.checkNotNullParameter($this$mapIndexedNotNull, "<this>");
        Intrinsics.checkNotNullParameter(transform, "transform");
        return filterNotNull((Sequence<? extends R>)new TransformingIndexedSequence<Object, Object>($this$mapIndexedNotNull, (Function2<? super Integer, ? super Object, ?>)transform));
    }
    
    @NotNull
    public static final <T, R, C extends Collection<? super R>> C mapIndexedNotNullTo(@NotNull final Sequence<? extends T> $this$mapIndexedNotNullTo, @NotNull final C destination, @NotNull final Function2<? super Integer, ? super T, ? extends R> transform) {
        // 
        // This method could not be decompiled.
        // 
        // Original Bytecode:
        // 
        //     1: ldc             "<this>"
        //     3: invokestatic    kotlin/jvm/internal/Intrinsics.checkNotNullParameter:(Ljava/lang/Object;Ljava/lang/String;)V
        //     6: aload_1         /* destination */
        //     7: ldc_w           "destination"
        //    10: invokestatic    kotlin/jvm/internal/Intrinsics.checkNotNullParameter:(Ljava/lang/Object;Ljava/lang/String;)V
        //    13: aload_2         /* transform */
        //    14: ldc             "transform"
        //    16: invokestatic    kotlin/jvm/internal/Intrinsics.checkNotNullParameter:(Ljava/lang/Object;Ljava/lang/String;)V
        //    19: iconst_0       
        //    20: istore_3        /* $i$f$mapIndexedNotNullTo */
        //    21: aload_0         /* $this$mapIndexedNotNullTo */
        //    22: astore          $this$forEachIndexed$iv
        //    24: iconst_0       
        //    25: istore          $i$f$forEachIndexed
        //    27: iconst_0       
        //    28: istore          index$iv
        //    30: aload           $this$forEachIndexed$iv
        //    32: invokeinterface kotlin/sequences/Sequence.iterator:()Ljava/util/Iterator;
        //    37: astore          7
        //    39: aload           7
        //    41: invokeinterface java/util/Iterator.hasNext:()Z
        //    46: ifeq            128
        //    49: aload           7
        //    51: invokeinterface java/util/Iterator.next:()Ljava/lang/Object;
        //    56: astore          item$iv
        //    58: iload           index$iv
        //    60: iinc            index$iv, 1
        //    63: istore          9
        //    65: iload           9
        //    67: ifge            73
        //    70: invokestatic    kotlin/collections/CollectionsKt.throwIndexOverflow:()V
        //    73: iload           9
        //    75: aload           item$iv
        //    77: astore          10
        //    79: istore          index
        //    81: iconst_0       
        //    82: istore          $i$a$-forEachIndexed-SequencesKt___SequencesKt$mapIndexedNotNullTo$1
        //    84: aload_2         /* transform */
        //    85: iload           index
        //    87: invokestatic    java/lang/Integer.valueOf:(I)Ljava/lang/Integer;
        //    90: aload           element
        //    92: invokeinterface kotlin/jvm/functions/Function2.invoke:(Ljava/lang/Object;Ljava/lang/Object;)Ljava/lang/Object;
        //    97: dup            
        //    98: ifnull          122
        //   101: astore          13
        //   103: aload           13
        //   105: astore          it
        //   107: iconst_0       
        //   108: istore          $i$a$-let-SequencesKt___SequencesKt$mapIndexedNotNullTo$1$1
        //   110: aload_1         /* destination */
        //   111: aload           it
        //   113: invokeinterface java/util/Collection.add:(Ljava/lang/Object;)Z
        //   118: pop            
        //   119: goto            124
        //   122: pop            
        //   123: nop            
        //   124: nop            
        //   125: goto            39
        //   128: nop            
        //   129: aload_1         /* destination */
        //   130: areturn        
        //    Signature:
        //  <T:Ljava/lang/Object;R:Ljava/lang/Object;C::Ljava/util/Collection<-TR;>;>(Lkotlin/sequences/Sequence<+TT;>;TC;Lkotlin/jvm/functions/Function2<-Ljava/lang/Integer;-TT;+TR;>;)TC;
        //    StackMapTable: 00 05 FF 00 27 00 08 07 00 3B 07 01 07 07 01 02 01 07 00 3B 01 01 07 00 41 00 00 FD 00 21 07 00 61 01 FF 00 30 00 0D 07 00 3B 07 01 07 07 01 02 01 07 00 3B 01 01 07 00 41 07 00 61 01 07 00 61 01 01 00 01 07 00 61 01 FF 00 03 00 08 07 00 3B 07 01 07 07 01 02 01 07 00 3B 01 01 07 00 41 00 00
        // 
        // The error that occurred was:
        // 
        // java.lang.NullPointerException
        // 
        throw new IllegalStateException("An error occurred while decompiling this method.");
    }
    
    @NotNull
    public static final <T, R, C extends Collection<? super R>> C mapIndexedTo(@NotNull final Sequence<? extends T> $this$mapIndexedTo, @NotNull final C destination, @NotNull final Function2<? super Integer, ? super T, ? extends R> transform) {
        Intrinsics.checkNotNullParameter($this$mapIndexedTo, "<this>");
        Intrinsics.checkNotNullParameter(destination, "destination");
        Intrinsics.checkNotNullParameter(transform, "transform");
        final int $i$f$mapIndexedTo = 0;
        int index = 0;
        for (final Object item : $this$mapIndexedTo) {
            final int i = index++;
            if (i < 0) {
                CollectionsKt.throwIndexOverflow();
            }
            destination.add((Object)transform.invoke(Integer.valueOf(i), (Object)item));
        }
        return destination;
    }
    
    @NotNull
    public static final <T, R> Sequence<R> mapNotNull(@NotNull final Sequence<? extends T> $this$mapNotNull, @NotNull final Function1<? super T, ? extends R> transform) {
        Intrinsics.checkNotNullParameter($this$mapNotNull, "<this>");
        Intrinsics.checkNotNullParameter(transform, "transform");
        return filterNotNull((Sequence<? extends R>)new TransformingSequence<Object, Object>($this$mapNotNull, (Function1<? super Object, ?>)transform));
    }
    
    @NotNull
    public static final <T, R, C extends Collection<? super R>> C mapNotNullTo(@NotNull final Sequence<? extends T> $this$mapNotNullTo, @NotNull final C destination, @NotNull final Function1<? super T, ? extends R> transform) {
        Intrinsics.checkNotNullParameter($this$mapNotNullTo, "<this>");
        Intrinsics.checkNotNullParameter(destination, "destination");
        Intrinsics.checkNotNullParameter(transform, "transform");
        final int $i$f$mapNotNullTo = 0;
        final Sequence $this$forEach$iv = $this$mapNotNullTo;
        final int $i$f$forEach = 0;
        for (final Object element : $this$forEach$iv) {
            final Object element$iv = element;
            final int n = 0;
            final R invoke = (R)transform.invoke((Object)element);
            if (invoke != null) {
                final Object it = invoke;
                final int n2 = 0;
                destination.add((Object)it);
            }
        }
        return destination;
    }
    
    @NotNull
    public static final <T, R, C extends Collection<? super R>> C mapTo(@NotNull final Sequence<? extends T> $this$mapTo, @NotNull final C destination, @NotNull final Function1<? super T, ? extends R> transform) {
        Intrinsics.checkNotNullParameter($this$mapTo, "<this>");
        Intrinsics.checkNotNullParameter(destination, "destination");
        Intrinsics.checkNotNullParameter(transform, "transform");
        final int $i$f$mapTo = 0;
        for (final Object item : $this$mapTo) {
            destination.add((Object)transform.invoke((Object)item));
        }
        return destination;
    }
    
    @NotNull
    public static final <T> Sequence<IndexedValue<T>> withIndex(@NotNull final Sequence<? extends T> $this$withIndex) {
        Intrinsics.checkNotNullParameter($this$withIndex, "<this>");
        return (Sequence<IndexedValue<T>>)new IndexingSequence($this$withIndex);
    }
    
    @NotNull
    public static final <T> Sequence<T> distinct(@NotNull final Sequence<? extends T> $this$distinct) {
        Intrinsics.checkNotNullParameter($this$distinct, "<this>");
        return distinctBy($this$distinct, (Function1<? super T, ?>)SequencesKt___SequencesKt$distinct.SequencesKt___SequencesKt$distinct$1.INSTANCE);
    }
    
    @NotNull
    public static final <T, K> Sequence<T> distinctBy(@NotNull final Sequence<? extends T> $this$distinctBy, @NotNull final Function1<? super T, ? extends K> selector) {
        Intrinsics.checkNotNullParameter($this$distinctBy, "<this>");
        Intrinsics.checkNotNullParameter(selector, "selector");
        return new DistinctSequence<T, Object>($this$distinctBy, selector);
    }
    
    @NotNull
    public static final <T> Set<T> toMutableSet(@NotNull final Sequence<? extends T> $this$toMutableSet) {
        Intrinsics.checkNotNullParameter($this$toMutableSet, "<this>");
        final LinkedHashSet set = new LinkedHashSet();
        for (final Object item : $this$toMutableSet) {
            set.add(item);
        }
        return (Set<T>)set;
    }
    
    public static final <T> boolean all(@NotNull final Sequence<? extends T> $this$all, @NotNull final Function1<? super T, Boolean> predicate) {
        Intrinsics.checkNotNullParameter($this$all, "<this>");
        Intrinsics.checkNotNullParameter(predicate, "predicate");
        final int $i$f$all = 0;
        for (final Object element : $this$all) {
            if (!predicate.invoke((Object)element)) {
                return false;
            }
        }
        return true;
    }
    
    public static final <T> boolean any(@NotNull final Sequence<? extends T> $this$any) {
        Intrinsics.checkNotNullParameter($this$any, "<this>");
        return $this$any.iterator().hasNext();
    }
    
    public static final <T> boolean any(@NotNull final Sequence<? extends T> $this$any, @NotNull final Function1<? super T, Boolean> predicate) {
        Intrinsics.checkNotNullParameter($this$any, "<this>");
        Intrinsics.checkNotNullParameter(predicate, "predicate");
        final int $i$f$any = 0;
        for (final Object element : $this$any) {
            if (predicate.invoke((Object)element)) {
                return true;
            }
        }
        return false;
    }
    
    public static final <T> int count(@NotNull final Sequence<? extends T> $this$count) {
        Intrinsics.checkNotNullParameter($this$count, "<this>");
        int count = 0;
        for (final Object element : $this$count) {
            if (++count < 0) {
                CollectionsKt.throwCountOverflow();
            }
        }
        return count;
    }
    
    public static final <T> int count(@NotNull final Sequence<? extends T> $this$count, @NotNull final Function1<? super T, Boolean> predicate) {
        Intrinsics.checkNotNullParameter($this$count, "<this>");
        Intrinsics.checkNotNullParameter(predicate, "predicate");
        final int $i$f$count = 0;
        int count = 0;
        for (final Object element : $this$count) {
            if (predicate.invoke((Object)element) && ++count < 0) {
                CollectionsKt.throwCountOverflow();
            }
        }
        return count;
    }
    
    public static final <T, R> R fold(@NotNull final Sequence<? extends T> $this$fold, final R initial, @NotNull final Function2<? super R, ? super T, ? extends R> operation) {
        Intrinsics.checkNotNullParameter($this$fold, "<this>");
        Intrinsics.checkNotNullParameter(operation, "operation");
        final int $i$f$fold = 0;
        Object accumulator = initial;
        for (final Object element : $this$fold) {
            accumulator = operation.invoke((Object)accumulator, (Object)element);
        }
        return (R)accumulator;
    }
    
    public static final <T, R> R foldIndexed(@NotNull final Sequence<? extends T> $this$foldIndexed, final R initial, @NotNull final Function3<? super Integer, ? super R, ? super T, ? extends R> operation) {
        Intrinsics.checkNotNullParameter($this$foldIndexed, "<this>");
        Intrinsics.checkNotNullParameter(operation, "operation");
        final int $i$f$foldIndexed = 0;
        int index = 0;
        Object accumulator = initial;
        for (final Object element : $this$foldIndexed) {
            final int i = index++;
            if (i < 0) {
                CollectionsKt.throwIndexOverflow();
            }
            accumulator = operation.invoke(Integer.valueOf(i), (Object)accumulator, (Object)element);
        }
        return (R)accumulator;
    }
    
    public static final <T> void forEach(@NotNull final Sequence<? extends T> $this$forEach, @NotNull final Function1<? super T, Unit> action) {
        Intrinsics.checkNotNullParameter($this$forEach, "<this>");
        Intrinsics.checkNotNullParameter(action, "action");
        final int $i$f$forEach = 0;
        for (final Object element : $this$forEach) {
            action.invoke((Object)element);
        }
    }
    
    public static final <T> void forEachIndexed(@NotNull final Sequence<? extends T> $this$forEachIndexed, @NotNull final Function2<? super Integer, ? super T, Unit> action) {
        Intrinsics.checkNotNullParameter($this$forEachIndexed, "<this>");
        Intrinsics.checkNotNullParameter(action, "action");
        final int $i$f$forEachIndexed = 0;
        int index = 0;
        for (final Object item : $this$forEachIndexed) {
            final int i = index++;
            if (i < 0) {
                CollectionsKt.throwIndexOverflow();
            }
            action.invoke(Integer.valueOf(i), (Object)item);
        }
    }
    
    @SinceKotlin(version = "1.7")
    @JvmName(name = "maxOrThrow")
    public static final double maxOrThrow(@NotNull final Sequence<Double> $this$max) {
        Intrinsics.checkNotNullParameter($this$max, "<this>");
        final Iterator iterator = $this$max.iterator();
        if (!iterator.hasNext()) {
            throw new NoSuchElementException();
        }
        double max = iterator.next().doubleValue();
        while (iterator.hasNext()) {
            final double e = iterator.next().doubleValue();
            max = Math.max(max, e);
        }
        return max;
    }
    
    @SinceKotlin(version = "1.7")
    @JvmName(name = "maxOrThrow")
    public static final float maxOrThrow(@NotNull final Sequence<Float> $this$max) {
        Intrinsics.checkNotNullParameter($this$max, "<this>");
        final Iterator iterator = $this$max.iterator();
        if (!iterator.hasNext()) {
            throw new NoSuchElementException();
        }
        float max = iterator.next().floatValue();
        while (iterator.hasNext()) {
            final float e = iterator.next().floatValue();
            max = Math.max(max, e);
        }
        return max;
    }
    
    @SinceKotlin(version = "1.7")
    @JvmName(name = "maxOrThrow")
    @NotNull
    public static final <T extends Comparable<? super T>> T maxOrThrow(@NotNull final Sequence<? extends T> $this$max) {
        Intrinsics.checkNotNullParameter($this$max, "<this>");
        final Iterator iterator = $this$max.iterator();
        if (!iterator.hasNext()) {
            throw new NoSuchElementException();
        }
        Comparable max = iterator.next();
        while (iterator.hasNext()) {
            final Comparable e = iterator.next();
            if (max.compareTo(e) < 0) {
                max = e;
            }
        }
        return (T)max;
    }
    
    @SinceKotlin(version = "1.7")
    @JvmName(name = "maxByOrThrow")
    public static final <T, R extends Comparable<? super R>> T maxByOrThrow(@NotNull final Sequence<? extends T> $this$maxBy, @NotNull final Function1<? super T, ? extends R> selector) {
        Intrinsics.checkNotNullParameter($this$maxBy, "<this>");
        Intrinsics.checkNotNullParameter(selector, "selector");
        final int $i$f$maxByOrThrow = 0;
        final Iterator iterator = $this$maxBy.iterator();
        if (!iterator.hasNext()) {
            throw new NoSuchElementException();
        }
        Object maxElem = iterator.next();
        if (!iterator.hasNext()) {
            return (T)maxElem;
        }
        Comparable maxValue = (Comparable)selector.invoke((Object)maxElem);
        do {
            final Object e = iterator.next();
            final Comparable v = (Comparable)selector.invoke((Object)e);
            if (maxValue.compareTo(v) < 0) {
                maxElem = e;
                maxValue = v;
            }
        } while (iterator.hasNext());
        return (T)maxElem;
    }
    
    @SinceKotlin(version = "1.4")
    @Nullable
    public static final <T, R extends Comparable<? super R>> T maxByOrNull(@NotNull final Sequence<? extends T> $this$maxByOrNull, @NotNull final Function1<? super T, ? extends R> selector) {
        Intrinsics.checkNotNullParameter($this$maxByOrNull, "<this>");
        Intrinsics.checkNotNullParameter(selector, "selector");
        final int $i$f$maxByOrNull = 0;
        final Iterator iterator = $this$maxByOrNull.iterator();
        if (!iterator.hasNext()) {
            return null;
        }
        Object maxElem = iterator.next();
        if (!iterator.hasNext()) {
            return (T)maxElem;
        }
        Comparable maxValue = (Comparable)selector.invoke((Object)maxElem);
        do {
            final Object e = iterator.next();
            final Comparable v = (Comparable)selector.invoke((Object)e);
            if (maxValue.compareTo(v) < 0) {
                maxElem = e;
                maxValue = v;
            }
        } while (iterator.hasNext());
        return (T)maxElem;
    }
    
    @SinceKotlin(version = "1.4")
    @OverloadResolutionByLambdaReturnType
    @InlineOnly
    private static final <T> double maxOf(final Sequence<? extends T> $this$maxOf, final Function1<? super T, Double> selector) {
        Intrinsics.checkNotNullParameter($this$maxOf, "<this>");
        Intrinsics.checkNotNullParameter(selector, "selector");
        final Iterator iterator = $this$maxOf.iterator();
        if (!iterator.hasNext()) {
            throw new NoSuchElementException();
        }
        double maxValue = selector.invoke(iterator.next()).doubleValue();
        while (iterator.hasNext()) {
            final double v = selector.invoke(iterator.next()).doubleValue();
            maxValue = Math.max(maxValue, v);
        }
        return maxValue;
    }
    
    @SinceKotlin(version = "1.4")
    @OverloadResolutionByLambdaReturnType
    @InlineOnly
    private static final <T> float maxOf(final Sequence<? extends T> $this$maxOf, final Function1<? super T, Float> selector) {
        Intrinsics.checkNotNullParameter($this$maxOf, "<this>");
        Intrinsics.checkNotNullParameter(selector, "selector");
        final Iterator iterator = $this$maxOf.iterator();
        if (!iterator.hasNext()) {
            throw new NoSuchElementException();
        }
        float maxValue = selector.invoke(iterator.next()).floatValue();
        while (iterator.hasNext()) {
            final float v = selector.invoke(iterator.next()).floatValue();
            maxValue = Math.max(maxValue, v);
        }
        return maxValue;
    }
    
    @SinceKotlin(version = "1.4")
    @OverloadResolutionByLambdaReturnType
    @InlineOnly
    private static final <T, R extends Comparable<? super R>> R maxOf(final Sequence<? extends T> $this$maxOf, final Function1<? super T, ? extends R> selector) {
        Intrinsics.checkNotNullParameter($this$maxOf, "<this>");
        Intrinsics.checkNotNullParameter(selector, "selector");
        final Iterator iterator = $this$maxOf.iterator();
        if (!iterator.hasNext()) {
            throw new NoSuchElementException();
        }
        Comparable maxValue = (Comparable)selector.invoke(iterator.next());
        while (iterator.hasNext()) {
            final Comparable v = (Comparable)selector.invoke(iterator.next());
            if (maxValue.compareTo(v) < 0) {
                maxValue = v;
            }
        }
        return (R)maxValue;
    }
    
    @SinceKotlin(version = "1.4")
    @OverloadResolutionByLambdaReturnType
    @InlineOnly
    private static final <T> Double maxOfOrNull(final Sequence<? extends T> $this$maxOfOrNull, final Function1<? super T, Double> selector) {
        Intrinsics.checkNotNullParameter($this$maxOfOrNull, "<this>");
        Intrinsics.checkNotNullParameter(selector, "selector");
        final Iterator iterator = $this$maxOfOrNull.iterator();
        if (!iterator.hasNext()) {
            return null;
        }
        double maxValue = selector.invoke(iterator.next()).doubleValue();
        while (iterator.hasNext()) {
            final double v = selector.invoke(iterator.next()).doubleValue();
            maxValue = Math.max(maxValue, v);
        }
        return maxValue;
    }
    
    @SinceKotlin(version = "1.4")
    @OverloadResolutionByLambdaReturnType
    @InlineOnly
    private static final <T> Float maxOfOrNull(final Sequence<? extends T> $this$maxOfOrNull, final Function1<? super T, Float> selector) {
        Intrinsics.checkNotNullParameter($this$maxOfOrNull, "<this>");
        Intrinsics.checkNotNullParameter(selector, "selector");
        final Iterator iterator = $this$maxOfOrNull.iterator();
        if (!iterator.hasNext()) {
            return null;
        }
        float maxValue = selector.invoke(iterator.next()).floatValue();
        while (iterator.hasNext()) {
            final float v = selector.invoke(iterator.next()).floatValue();
            maxValue = Math.max(maxValue, v);
        }
        return maxValue;
    }
    
    @SinceKotlin(version = "1.4")
    @OverloadResolutionByLambdaReturnType
    @InlineOnly
    private static final <T, R extends Comparable<? super R>> R maxOfOrNull(final Sequence<? extends T> $this$maxOfOrNull, final Function1<? super T, ? extends R> selector) {
        Intrinsics.checkNotNullParameter($this$maxOfOrNull, "<this>");
        Intrinsics.checkNotNullParameter(selector, "selector");
        final Iterator iterator = $this$maxOfOrNull.iterator();
        if (!iterator.hasNext()) {
            return null;
        }
        Comparable maxValue = (Comparable)selector.invoke(iterator.next());
        while (iterator.hasNext()) {
            final Comparable v = (Comparable)selector.invoke(iterator.next());
            if (maxValue.compareTo(v) < 0) {
                maxValue = v;
            }
        }
        return (R)maxValue;
    }
    
    @SinceKotlin(version = "1.4")
    @OverloadResolutionByLambdaReturnType
    @InlineOnly
    private static final <T, R> R maxOfWith(final Sequence<? extends T> $this$maxOfWith, final Comparator<? super R> comparator, final Function1<? super T, ? extends R> selector) {
        Intrinsics.checkNotNullParameter($this$maxOfWith, "<this>");
        Intrinsics.checkNotNullParameter(comparator, "comparator");
        Intrinsics.checkNotNullParameter(selector, "selector");
        final Iterator iterator = $this$maxOfWith.iterator();
        if (!iterator.hasNext()) {
            throw new NoSuchElementException();
        }
        Object maxValue = selector.invoke(iterator.next());
        while (iterator.hasNext()) {
            final Object v = selector.invoke(iterator.next());
            if (comparator.compare((Object)maxValue, (Object)v) < 0) {
                maxValue = v;
            }
        }
        return (R)maxValue;
    }
    
    @SinceKotlin(version = "1.4")
    @OverloadResolutionByLambdaReturnType
    @InlineOnly
    private static final <T, R> R maxOfWithOrNull(final Sequence<? extends T> $this$maxOfWithOrNull, final Comparator<? super R> comparator, final Function1<? super T, ? extends R> selector) {
        Intrinsics.checkNotNullParameter($this$maxOfWithOrNull, "<this>");
        Intrinsics.checkNotNullParameter(comparator, "comparator");
        Intrinsics.checkNotNullParameter(selector, "selector");
        final Iterator iterator = $this$maxOfWithOrNull.iterator();
        if (!iterator.hasNext()) {
            return null;
        }
        Object maxValue = selector.invoke(iterator.next());
        while (iterator.hasNext()) {
            final Object v = selector.invoke(iterator.next());
            if (comparator.compare((Object)maxValue, (Object)v) < 0) {
                maxValue = v;
            }
        }
        return (R)maxValue;
    }
    
    @SinceKotlin(version = "1.4")
    @Nullable
    public static final Double maxOrNull(@NotNull final Sequence<Double> $this$maxOrNull) {
        Intrinsics.checkNotNullParameter($this$maxOrNull, "<this>");
        final Iterator iterator = $this$maxOrNull.iterator();
        if (!iterator.hasNext()) {
            return null;
        }
        double max = iterator.next().doubleValue();
        while (iterator.hasNext()) {
            final double e = iterator.next().doubleValue();
            max = Math.max(max, e);
        }
        return max;
    }
    
    @SinceKotlin(version = "1.4")
    @Nullable
    public static final Float maxOrNull(@NotNull final Sequence<Float> $this$maxOrNull) {
        Intrinsics.checkNotNullParameter($this$maxOrNull, "<this>");
        final Iterator iterator = $this$maxOrNull.iterator();
        if (!iterator.hasNext()) {
            return null;
        }
        float max = iterator.next().floatValue();
        while (iterator.hasNext()) {
            final float e = iterator.next().floatValue();
            max = Math.max(max, e);
        }
        return max;
    }
    
    @SinceKotlin(version = "1.4")
    @Nullable
    public static final <T extends Comparable<? super T>> T maxOrNull(@NotNull final Sequence<? extends T> $this$maxOrNull) {
        Intrinsics.checkNotNullParameter($this$maxOrNull, "<this>");
        final Iterator iterator = $this$maxOrNull.iterator();
        if (!iterator.hasNext()) {
            return null;
        }
        Comparable max = iterator.next();
        while (iterator.hasNext()) {
            final Comparable e = iterator.next();
            if (max.compareTo(e) < 0) {
                max = e;
            }
        }
        return (T)max;
    }
    
    @SinceKotlin(version = "1.7")
    @JvmName(name = "maxWithOrThrow")
    public static final <T> T maxWithOrThrow(@NotNull final Sequence<? extends T> $this$maxWith, @NotNull final Comparator<? super T> comparator) {
        Intrinsics.checkNotNullParameter($this$maxWith, "<this>");
        Intrinsics.checkNotNullParameter(comparator, "comparator");
        final Iterator iterator = $this$maxWith.iterator();
        if (!iterator.hasNext()) {
            throw new NoSuchElementException();
        }
        Object max = iterator.next();
        while (iterator.hasNext()) {
            final Object e = iterator.next();
            if (comparator.compare((Object)max, (Object)e) < 0) {
                max = e;
            }
        }
        return (T)max;
    }
    
    @SinceKotlin(version = "1.4")
    @Nullable
    public static final <T> T maxWithOrNull(@NotNull final Sequence<? extends T> $this$maxWithOrNull, @NotNull final Comparator<? super T> comparator) {
        Intrinsics.checkNotNullParameter($this$maxWithOrNull, "<this>");
        Intrinsics.checkNotNullParameter(comparator, "comparator");
        final Iterator iterator = $this$maxWithOrNull.iterator();
        if (!iterator.hasNext()) {
            return null;
        }
        Object max = iterator.next();
        while (iterator.hasNext()) {
            final Object e = iterator.next();
            if (comparator.compare((Object)max, (Object)e) < 0) {
                max = e;
            }
        }
        return (T)max;
    }
    
    @SinceKotlin(version = "1.7")
    @JvmName(name = "minOrThrow")
    public static final double minOrThrow(@NotNull final Sequence<Double> $this$min) {
        Intrinsics.checkNotNullParameter($this$min, "<this>");
        final Iterator iterator = $this$min.iterator();
        if (!iterator.hasNext()) {
            throw new NoSuchElementException();
        }
        double min = iterator.next().doubleValue();
        while (iterator.hasNext()) {
            final double e = iterator.next().doubleValue();
            min = Math.min(min, e);
        }
        return min;
    }
    
    @SinceKotlin(version = "1.7")
    @JvmName(name = "minOrThrow")
    public static final float minOrThrow(@NotNull final Sequence<Float> $this$min) {
        Intrinsics.checkNotNullParameter($this$min, "<this>");
        final Iterator iterator = $this$min.iterator();
        if (!iterator.hasNext()) {
            throw new NoSuchElementException();
        }
        float min = iterator.next().floatValue();
        while (iterator.hasNext()) {
            final float e = iterator.next().floatValue();
            min = Math.min(min, e);
        }
        return min;
    }
    
    @SinceKotlin(version = "1.7")
    @JvmName(name = "minOrThrow")
    @NotNull
    public static final <T extends Comparable<? super T>> T minOrThrow(@NotNull final Sequence<? extends T> $this$min) {
        Intrinsics.checkNotNullParameter($this$min, "<this>");
        final Iterator iterator = $this$min.iterator();
        if (!iterator.hasNext()) {
            throw new NoSuchElementException();
        }
        Comparable min = iterator.next();
        while (iterator.hasNext()) {
            final Comparable e = iterator.next();
            if (min.compareTo(e) > 0) {
                min = e;
            }
        }
        return (T)min;
    }
    
    @SinceKotlin(version = "1.7")
    @JvmName(name = "minByOrThrow")
    public static final <T, R extends Comparable<? super R>> T minByOrThrow(@NotNull final Sequence<? extends T> $this$minBy, @NotNull final Function1<? super T, ? extends R> selector) {
        Intrinsics.checkNotNullParameter($this$minBy, "<this>");
        Intrinsics.checkNotNullParameter(selector, "selector");
        final int $i$f$minByOrThrow = 0;
        final Iterator iterator = $this$minBy.iterator();
        if (!iterator.hasNext()) {
            throw new NoSuchElementException();
        }
        Object minElem = iterator.next();
        if (!iterator.hasNext()) {
            return (T)minElem;
        }
        Comparable minValue = (Comparable)selector.invoke((Object)minElem);
        do {
            final Object e = iterator.next();
            final Comparable v = (Comparable)selector.invoke((Object)e);
            if (minValue.compareTo(v) > 0) {
                minElem = e;
                minValue = v;
            }
        } while (iterator.hasNext());
        return (T)minElem;
    }
    
    @SinceKotlin(version = "1.4")
    @Nullable
    public static final <T, R extends Comparable<? super R>> T minByOrNull(@NotNull final Sequence<? extends T> $this$minByOrNull, @NotNull final Function1<? super T, ? extends R> selector) {
        Intrinsics.checkNotNullParameter($this$minByOrNull, "<this>");
        Intrinsics.checkNotNullParameter(selector, "selector");
        final int $i$f$minByOrNull = 0;
        final Iterator iterator = $this$minByOrNull.iterator();
        if (!iterator.hasNext()) {
            return null;
        }
        Object minElem = iterator.next();
        if (!iterator.hasNext()) {
            return (T)minElem;
        }
        Comparable minValue = (Comparable)selector.invoke((Object)minElem);
        do {
            final Object e = iterator.next();
            final Comparable v = (Comparable)selector.invoke((Object)e);
            if (minValue.compareTo(v) > 0) {
                minElem = e;
                minValue = v;
            }
        } while (iterator.hasNext());
        return (T)minElem;
    }
    
    @SinceKotlin(version = "1.4")
    @OverloadResolutionByLambdaReturnType
    @InlineOnly
    private static final <T> double minOf(final Sequence<? extends T> $this$minOf, final Function1<? super T, Double> selector) {
        Intrinsics.checkNotNullParameter($this$minOf, "<this>");
        Intrinsics.checkNotNullParameter(selector, "selector");
        final Iterator iterator = $this$minOf.iterator();
        if (!iterator.hasNext()) {
            throw new NoSuchElementException();
        }
        double minValue = selector.invoke(iterator.next()).doubleValue();
        while (iterator.hasNext()) {
            final double v = selector.invoke(iterator.next()).doubleValue();
            minValue = Math.min(minValue, v);
        }
        return minValue;
    }
    
    @SinceKotlin(version = "1.4")
    @OverloadResolutionByLambdaReturnType
    @InlineOnly
    private static final <T> float minOf(final Sequence<? extends T> $this$minOf, final Function1<? super T, Float> selector) {
        Intrinsics.checkNotNullParameter($this$minOf, "<this>");
        Intrinsics.checkNotNullParameter(selector, "selector");
        final Iterator iterator = $this$minOf.iterator();
        if (!iterator.hasNext()) {
            throw new NoSuchElementException();
        }
        float minValue = selector.invoke(iterator.next()).floatValue();
        while (iterator.hasNext()) {
            final float v = selector.invoke(iterator.next()).floatValue();
            minValue = Math.min(minValue, v);
        }
        return minValue;
    }
    
    @SinceKotlin(version = "1.4")
    @OverloadResolutionByLambdaReturnType
    @InlineOnly
    private static final <T, R extends Comparable<? super R>> R minOf(final Sequence<? extends T> $this$minOf, final Function1<? super T, ? extends R> selector) {
        Intrinsics.checkNotNullParameter($this$minOf, "<this>");
        Intrinsics.checkNotNullParameter(selector, "selector");
        final Iterator iterator = $this$minOf.iterator();
        if (!iterator.hasNext()) {
            throw new NoSuchElementException();
        }
        Comparable minValue = (Comparable)selector.invoke(iterator.next());
        while (iterator.hasNext()) {
            final Comparable v = (Comparable)selector.invoke(iterator.next());
            if (minValue.compareTo(v) > 0) {
                minValue = v;
            }
        }
        return (R)minValue;
    }
    
    @SinceKotlin(version = "1.4")
    @OverloadResolutionByLambdaReturnType
    @InlineOnly
    private static final <T> Double minOfOrNull(final Sequence<? extends T> $this$minOfOrNull, final Function1<? super T, Double> selector) {
        Intrinsics.checkNotNullParameter($this$minOfOrNull, "<this>");
        Intrinsics.checkNotNullParameter(selector, "selector");
        final Iterator iterator = $this$minOfOrNull.iterator();
        if (!iterator.hasNext()) {
            return null;
        }
        double minValue = selector.invoke(iterator.next()).doubleValue();
        while (iterator.hasNext()) {
            final double v = selector.invoke(iterator.next()).doubleValue();
            minValue = Math.min(minValue, v);
        }
        return minValue;
    }
    
    @SinceKotlin(version = "1.4")
    @OverloadResolutionByLambdaReturnType
    @InlineOnly
    private static final <T> Float minOfOrNull(final Sequence<? extends T> $this$minOfOrNull, final Function1<? super T, Float> selector) {
        Intrinsics.checkNotNullParameter($this$minOfOrNull, "<this>");
        Intrinsics.checkNotNullParameter(selector, "selector");
        final Iterator iterator = $this$minOfOrNull.iterator();
        if (!iterator.hasNext()) {
            return null;
        }
        float minValue = selector.invoke(iterator.next()).floatValue();
        while (iterator.hasNext()) {
            final float v = selector.invoke(iterator.next()).floatValue();
            minValue = Math.min(minValue, v);
        }
        return minValue;
    }
    
    @SinceKotlin(version = "1.4")
    @OverloadResolutionByLambdaReturnType
    @InlineOnly
    private static final <T, R extends Comparable<? super R>> R minOfOrNull(final Sequence<? extends T> $this$minOfOrNull, final Function1<? super T, ? extends R> selector) {
        Intrinsics.checkNotNullParameter($this$minOfOrNull, "<this>");
        Intrinsics.checkNotNullParameter(selector, "selector");
        final Iterator iterator = $this$minOfOrNull.iterator();
        if (!iterator.hasNext()) {
            return null;
        }
        Comparable minValue = (Comparable)selector.invoke(iterator.next());
        while (iterator.hasNext()) {
            final Comparable v = (Comparable)selector.invoke(iterator.next());
            if (minValue.compareTo(v) > 0) {
                minValue = v;
            }
        }
        return (R)minValue;
    }
    
    @SinceKotlin(version = "1.4")
    @OverloadResolutionByLambdaReturnType
    @InlineOnly
    private static final <T, R> R minOfWith(final Sequence<? extends T> $this$minOfWith, final Comparator<? super R> comparator, final Function1<? super T, ? extends R> selector) {
        Intrinsics.checkNotNullParameter($this$minOfWith, "<this>");
        Intrinsics.checkNotNullParameter(comparator, "comparator");
        Intrinsics.checkNotNullParameter(selector, "selector");
        final Iterator iterator = $this$minOfWith.iterator();
        if (!iterator.hasNext()) {
            throw new NoSuchElementException();
        }
        Object minValue = selector.invoke(iterator.next());
        while (iterator.hasNext()) {
            final Object v = selector.invoke(iterator.next());
            if (comparator.compare((Object)minValue, (Object)v) > 0) {
                minValue = v;
            }
        }
        return (R)minValue;
    }
    
    @SinceKotlin(version = "1.4")
    @OverloadResolutionByLambdaReturnType
    @InlineOnly
    private static final <T, R> R minOfWithOrNull(final Sequence<? extends T> $this$minOfWithOrNull, final Comparator<? super R> comparator, final Function1<? super T, ? extends R> selector) {
        Intrinsics.checkNotNullParameter($this$minOfWithOrNull, "<this>");
        Intrinsics.checkNotNullParameter(comparator, "comparator");
        Intrinsics.checkNotNullParameter(selector, "selector");
        final Iterator iterator = $this$minOfWithOrNull.iterator();
        if (!iterator.hasNext()) {
            return null;
        }
        Object minValue = selector.invoke(iterator.next());
        while (iterator.hasNext()) {
            final Object v = selector.invoke(iterator.next());
            if (comparator.compare((Object)minValue, (Object)v) > 0) {
                minValue = v;
            }
        }
        return (R)minValue;
    }
    
    @SinceKotlin(version = "1.4")
    @Nullable
    public static final Double minOrNull(@NotNull final Sequence<Double> $this$minOrNull) {
        Intrinsics.checkNotNullParameter($this$minOrNull, "<this>");
        final Iterator iterator = $this$minOrNull.iterator();
        if (!iterator.hasNext()) {
            return null;
        }
        double min = iterator.next().doubleValue();
        while (iterator.hasNext()) {
            final double e = iterator.next().doubleValue();
            min = Math.min(min, e);
        }
        return min;
    }
    
    @SinceKotlin(version = "1.4")
    @Nullable
    public static final Float minOrNull(@NotNull final Sequence<Float> $this$minOrNull) {
        Intrinsics.checkNotNullParameter($this$minOrNull, "<this>");
        final Iterator iterator = $this$minOrNull.iterator();
        if (!iterator.hasNext()) {
            return null;
        }
        float min = iterator.next().floatValue();
        while (iterator.hasNext()) {
            final float e = iterator.next().floatValue();
            min = Math.min(min, e);
        }
        return min;
    }
    
    @SinceKotlin(version = "1.4")
    @Nullable
    public static final <T extends Comparable<? super T>> T minOrNull(@NotNull final Sequence<? extends T> $this$minOrNull) {
        Intrinsics.checkNotNullParameter($this$minOrNull, "<this>");
        final Iterator iterator = $this$minOrNull.iterator();
        if (!iterator.hasNext()) {
            return null;
        }
        Comparable min = iterator.next();
        while (iterator.hasNext()) {
            final Comparable e = iterator.next();
            if (min.compareTo(e) > 0) {
                min = e;
            }
        }
        return (T)min;
    }
    
    @SinceKotlin(version = "1.7")
    @JvmName(name = "minWithOrThrow")
    public static final <T> T minWithOrThrow(@NotNull final Sequence<? extends T> $this$minWith, @NotNull final Comparator<? super T> comparator) {
        Intrinsics.checkNotNullParameter($this$minWith, "<this>");
        Intrinsics.checkNotNullParameter(comparator, "comparator");
        final Iterator iterator = $this$minWith.iterator();
        if (!iterator.hasNext()) {
            throw new NoSuchElementException();
        }
        Object min = iterator.next();
        while (iterator.hasNext()) {
            final Object e = iterator.next();
            if (comparator.compare((Object)min, (Object)e) > 0) {
                min = e;
            }
        }
        return (T)min;
    }
    
    @SinceKotlin(version = "1.4")
    @Nullable
    public static final <T> T minWithOrNull(@NotNull final Sequence<? extends T> $this$minWithOrNull, @NotNull final Comparator<? super T> comparator) {
        Intrinsics.checkNotNullParameter($this$minWithOrNull, "<this>");
        Intrinsics.checkNotNullParameter(comparator, "comparator");
        final Iterator iterator = $this$minWithOrNull.iterator();
        if (!iterator.hasNext()) {
            return null;
        }
        Object min = iterator.next();
        while (iterator.hasNext()) {
            final Object e = iterator.next();
            if (comparator.compare((Object)min, (Object)e) > 0) {
                min = e;
            }
        }
        return (T)min;
    }
    
    public static final <T> boolean none(@NotNull final Sequence<? extends T> $this$none) {
        Intrinsics.checkNotNullParameter($this$none, "<this>");
        return !$this$none.iterator().hasNext();
    }
    
    public static final <T> boolean none(@NotNull final Sequence<? extends T> $this$none, @NotNull final Function1<? super T, Boolean> predicate) {
        Intrinsics.checkNotNullParameter($this$none, "<this>");
        Intrinsics.checkNotNullParameter(predicate, "predicate");
        final int $i$f$none = 0;
        for (final Object element : $this$none) {
            if (predicate.invoke((Object)element)) {
                return false;
            }
        }
        return true;
    }
    
    @SinceKotlin(version = "1.1")
    @NotNull
    public static final <T> Sequence<T> onEach(@NotNull final Sequence<? extends T> $this$onEach, @NotNull final Function1<? super T, Unit> action) {
        Intrinsics.checkNotNullParameter($this$onEach, "<this>");
        Intrinsics.checkNotNullParameter(action, "action");
        return map((Sequence<?>)$this$onEach, (Function1<? super Object, ? extends T>)new SequencesKt___SequencesKt$onEach.SequencesKt___SequencesKt$onEach$1((Function1)action));
    }
    
    @SinceKotlin(version = "1.4")
    @NotNull
    public static final <T> Sequence<T> onEachIndexed(@NotNull final Sequence<? extends T> $this$onEachIndexed, @NotNull final Function2<? super Integer, ? super T, Unit> action) {
        Intrinsics.checkNotNullParameter($this$onEachIndexed, "<this>");
        Intrinsics.checkNotNullParameter(action, "action");
        return mapIndexed((Sequence<?>)$this$onEachIndexed, (Function2<? super Integer, ? super Object, ? extends T>)new SequencesKt___SequencesKt$onEachIndexed.SequencesKt___SequencesKt$onEachIndexed$1((Function2)action));
    }
    
    public static final <S, T extends S> S reduce(@NotNull final Sequence<? extends T> $this$reduce, @NotNull final Function2<? super S, ? super T, ? extends S> operation) {
        Intrinsics.checkNotNullParameter($this$reduce, "<this>");
        Intrinsics.checkNotNullParameter(operation, "operation");
        final int $i$f$reduce = 0;
        final Iterator iterator = $this$reduce.iterator();
        if (!iterator.hasNext()) {
            throw new UnsupportedOperationException("Empty sequence can't be reduced.");
        }
        Object accumulator = iterator.next();
        while (iterator.hasNext()) {
            accumulator = operation.invoke((Object)accumulator, iterator.next());
        }
        return (S)accumulator;
    }
    
    public static final <S, T extends S> S reduceIndexed(@NotNull final Sequence<? extends T> $this$reduceIndexed, @NotNull final Function3<? super Integer, ? super S, ? super T, ? extends S> operation) {
        Intrinsics.checkNotNullParameter($this$reduceIndexed, "<this>");
        Intrinsics.checkNotNullParameter(operation, "operation");
        final int $i$f$reduceIndexed = 0;
        final Iterator iterator = $this$reduceIndexed.iterator();
        if (!iterator.hasNext()) {
            throw new UnsupportedOperationException("Empty sequence can't be reduced.");
        }
        int index = 1;
        Object accumulator = iterator.next();
        while (iterator.hasNext()) {
            final int i = index++;
            if (i < 0) {
                CollectionsKt.throwIndexOverflow();
            }
            accumulator = operation.invoke(Integer.valueOf(i), (Object)accumulator, iterator.next());
        }
        return (S)accumulator;
    }
    
    @SinceKotlin(version = "1.4")
    @Nullable
    public static final <S, T extends S> S reduceIndexedOrNull(@NotNull final Sequence<? extends T> $this$reduceIndexedOrNull, @NotNull final Function3<? super Integer, ? super S, ? super T, ? extends S> operation) {
        Intrinsics.checkNotNullParameter($this$reduceIndexedOrNull, "<this>");
        Intrinsics.checkNotNullParameter(operation, "operation");
        final int $i$f$reduceIndexedOrNull = 0;
        final Iterator iterator = $this$reduceIndexedOrNull.iterator();
        if (!iterator.hasNext()) {
            return null;
        }
        int index = 1;
        Object accumulator = iterator.next();
        while (iterator.hasNext()) {
            final int i = index++;
            if (i < 0) {
                CollectionsKt.throwIndexOverflow();
            }
            accumulator = operation.invoke(Integer.valueOf(i), (Object)accumulator, iterator.next());
        }
        return (S)accumulator;
    }
    
    @SinceKotlin(version = "1.4")
    @WasExperimental(markerClass = { ExperimentalStdlibApi.class })
    @Nullable
    public static final <S, T extends S> S reduceOrNull(@NotNull final Sequence<? extends T> $this$reduceOrNull, @NotNull final Function2<? super S, ? super T, ? extends S> operation) {
        Intrinsics.checkNotNullParameter($this$reduceOrNull, "<this>");
        Intrinsics.checkNotNullParameter(operation, "operation");
        final int $i$f$reduceOrNull = 0;
        final Iterator iterator = $this$reduceOrNull.iterator();
        if (!iterator.hasNext()) {
            return null;
        }
        Object accumulator = iterator.next();
        while (iterator.hasNext()) {
            accumulator = operation.invoke((Object)accumulator, iterator.next());
        }
        return (S)accumulator;
    }
    
    @SinceKotlin(version = "1.4")
    @NotNull
    public static final <T, R> Sequence<R> runningFold(@NotNull final Sequence<? extends T> $this$runningFold, final R initial, @NotNull final Function2<? super R, ? super T, ? extends R> operation) {
        Intrinsics.checkNotNullParameter($this$runningFold, "<this>");
        Intrinsics.checkNotNullParameter(operation, "operation");
        return SequencesKt__SequenceBuilderKt.sequence((Function2<? super SequenceScope<? super R>, ? super Continuation<? super Unit>, ?>)new SequencesKt___SequencesKt$runningFold.SequencesKt___SequencesKt$runningFold$1((Object)initial, (Sequence)$this$runningFold, (Function2)operation, (Continuation)null));
    }
    
    @SinceKotlin(version = "1.4")
    @NotNull
    public static final <T, R> Sequence<R> runningFoldIndexed(@NotNull final Sequence<? extends T> $this$runningFoldIndexed, final R initial, @NotNull final Function3<? super Integer, ? super R, ? super T, ? extends R> operation) {
        Intrinsics.checkNotNullParameter($this$runningFoldIndexed, "<this>");
        Intrinsics.checkNotNullParameter(operation, "operation");
        return SequencesKt__SequenceBuilderKt.sequence((Function2<? super SequenceScope<? super R>, ? super Continuation<? super Unit>, ?>)new SequencesKt___SequencesKt$runningFoldIndexed.SequencesKt___SequencesKt$runningFoldIndexed$1((Object)initial, (Sequence)$this$runningFoldIndexed, (Function3)operation, (Continuation)null));
    }
    
    @SinceKotlin(version = "1.4")
    @WasExperimental(markerClass = { ExperimentalStdlibApi.class })
    @NotNull
    public static final <S, T extends S> Sequence<S> runningReduce(@NotNull final Sequence<? extends T> $this$runningReduce, @NotNull final Function2<? super S, ? super T, ? extends S> operation) {
        Intrinsics.checkNotNullParameter($this$runningReduce, "<this>");
        Intrinsics.checkNotNullParameter(operation, "operation");
        return SequencesKt__SequenceBuilderKt.sequence((Function2<? super SequenceScope<? super S>, ? super Continuation<? super Unit>, ?>)new SequencesKt___SequencesKt$runningReduce.SequencesKt___SequencesKt$runningReduce$1((Sequence)$this$runningReduce, (Function2)operation, (Continuation)null));
    }
    
    @SinceKotlin(version = "1.4")
    @NotNull
    public static final <S, T extends S> Sequence<S> runningReduceIndexed(@NotNull final Sequence<? extends T> $this$runningReduceIndexed, @NotNull final Function3<? super Integer, ? super S, ? super T, ? extends S> operation) {
        Intrinsics.checkNotNullParameter($this$runningReduceIndexed, "<this>");
        Intrinsics.checkNotNullParameter(operation, "operation");
        return SequencesKt__SequenceBuilderKt.sequence((Function2<? super SequenceScope<? super S>, ? super Continuation<? super Unit>, ?>)new SequencesKt___SequencesKt$runningReduceIndexed.SequencesKt___SequencesKt$runningReduceIndexed$1((Sequence)$this$runningReduceIndexed, (Function3)operation, (Continuation)null));
    }
    
    @SinceKotlin(version = "1.4")
    @WasExperimental(markerClass = { ExperimentalStdlibApi.class })
    @NotNull
    public static final <T, R> Sequence<R> scan(@NotNull final Sequence<? extends T> $this$scan, final R initial, @NotNull final Function2<? super R, ? super T, ? extends R> operation) {
        Intrinsics.checkNotNullParameter($this$scan, "<this>");
        Intrinsics.checkNotNullParameter(operation, "operation");
        return (Sequence<R>)runningFold((Sequence<?>)$this$scan, (Object)initial, (Function2<? super Object, ? super Object, ?>)operation);
    }
    
    @SinceKotlin(version = "1.4")
    @WasExperimental(markerClass = { ExperimentalStdlibApi.class })
    @NotNull
    public static final <T, R> Sequence<R> scanIndexed(@NotNull final Sequence<? extends T> $this$scanIndexed, final R initial, @NotNull final Function3<? super Integer, ? super R, ? super T, ? extends R> operation) {
        Intrinsics.checkNotNullParameter($this$scanIndexed, "<this>");
        Intrinsics.checkNotNullParameter(operation, "operation");
        return (Sequence<R>)runningFoldIndexed((Sequence<?>)$this$scanIndexed, (Object)initial, (Function3<? super Integer, ? super Object, ? super Object, ?>)operation);
    }
    
    @Deprecated(message = "Use sumOf instead.", replaceWith = @ReplaceWith(expression = "this.sumOf(selector)", imports = {}))
    @DeprecatedSinceKotlin(warningSince = "1.5")
    @java.lang.Deprecated
    public static final <T> int sumBy(@NotNull final Sequence<? extends T> $this$sumBy, @NotNull final Function1<? super T, Integer> selector) {
        Intrinsics.checkNotNullParameter($this$sumBy, "<this>");
        Intrinsics.checkNotNullParameter(selector, "selector");
        final int $i$f$sumBy = 0;
        int sum = 0;
        for (final Object element : $this$sumBy) {
            sum += selector.invoke((Object)element).intValue();
        }
        return sum;
    }
    
    @Deprecated(message = "Use sumOf instead.", replaceWith = @ReplaceWith(expression = "this.sumOf(selector)", imports = {}))
    @DeprecatedSinceKotlin(warningSince = "1.5")
    @java.lang.Deprecated
    public static final <T> double sumByDouble(@NotNull final Sequence<? extends T> $this$sumByDouble, @NotNull final Function1<? super T, Double> selector) {
        Intrinsics.checkNotNullParameter($this$sumByDouble, "<this>");
        Intrinsics.checkNotNullParameter(selector, "selector");
        final int $i$f$sumByDouble = 0;
        double sum = 0.0;
        for (final Object element : $this$sumByDouble) {
            sum += selector.invoke((Object)element).doubleValue();
        }
        return sum;
    }
    
    @SinceKotlin(version = "1.4")
    @OverloadResolutionByLambdaReturnType
    @JvmName(name = "sumOfDouble")
    @InlineOnly
    private static final <T> double sumOfDouble(final Sequence<? extends T> $this$sumOf, final Function1<? super T, Double> selector) {
        Intrinsics.checkNotNullParameter($this$sumOf, "<this>");
        Intrinsics.checkNotNullParameter(selector, "selector");
        double sum = 0.0;
        for (final Object element : $this$sumOf) {
            sum += selector.invoke((Object)element).doubleValue();
        }
        return sum;
    }
    
    @SinceKotlin(version = "1.4")
    @OverloadResolutionByLambdaReturnType
    @JvmName(name = "sumOfInt")
    @InlineOnly
    private static final <T> int sumOfInt(final Sequence<? extends T> $this$sumOf, final Function1<? super T, Integer> selector) {
        Intrinsics.checkNotNullParameter($this$sumOf, "<this>");
        Intrinsics.checkNotNullParameter(selector, "selector");
        int sum = 0;
        for (final Object element : $this$sumOf) {
            sum += selector.invoke((Object)element).intValue();
        }
        return sum;
    }
    
    @SinceKotlin(version = "1.4")
    @OverloadResolutionByLambdaReturnType
    @JvmName(name = "sumOfLong")
    @InlineOnly
    private static final <T> long sumOfLong(final Sequence<? extends T> $this$sumOf, final Function1<? super T, Long> selector) {
        Intrinsics.checkNotNullParameter($this$sumOf, "<this>");
        Intrinsics.checkNotNullParameter(selector, "selector");
        long sum = 0L;
        for (final Object element : $this$sumOf) {
            sum += selector.invoke((Object)element).longValue();
        }
        return sum;
    }
    
    @SinceKotlin(version = "1.5")
    @OverloadResolutionByLambdaReturnType
    @JvmName(name = "sumOfUInt")
    @WasExperimental(markerClass = { ExperimentalUnsignedTypes.class })
    @InlineOnly
    private static final <T> int sumOfUInt(final Sequence<? extends T> $this$sumOf, final Function1<? super T, UInt> selector) {
        Intrinsics.checkNotNullParameter($this$sumOf, "<this>");
        Intrinsics.checkNotNullParameter(selector, "selector");
        int sum = UInt.constructor-impl(0);
        for (final Object element : $this$sumOf) {
            sum = UInt.constructor-impl(sum + selector.invoke((Object)element).unbox-impl());
        }
        return sum;
    }
    
    @SinceKotlin(version = "1.5")
    @OverloadResolutionByLambdaReturnType
    @JvmName(name = "sumOfULong")
    @WasExperimental(markerClass = { ExperimentalUnsignedTypes.class })
    @InlineOnly
    private static final <T> long sumOfULong(final Sequence<? extends T> $this$sumOf, final Function1<? super T, ULong> selector) {
        Intrinsics.checkNotNullParameter($this$sumOf, "<this>");
        Intrinsics.checkNotNullParameter(selector, "selector");
        long sum = ULong.constructor-impl(0L);
        for (final Object element : $this$sumOf) {
            sum = ULong.constructor-impl(sum + selector.invoke((Object)element).unbox-impl());
        }
        return sum;
    }
    
    @NotNull
    public static final <T> Sequence<T> requireNoNulls(@NotNull final Sequence<? extends T> $this$requireNoNulls) {
        Intrinsics.checkNotNullParameter($this$requireNoNulls, "<this>");
        return map((Sequence<?>)$this$requireNoNulls, (Function1<? super Object, ? extends T>)new SequencesKt___SequencesKt$requireNoNulls.SequencesKt___SequencesKt$requireNoNulls$1((Sequence)$this$requireNoNulls));
    }
    
    @SinceKotlin(version = "1.2")
    @NotNull
    public static final <T> Sequence<List<T>> chunked(@NotNull final Sequence<? extends T> $this$chunked, final int size) {
        Intrinsics.checkNotNullParameter($this$chunked, "<this>");
        return windowed($this$chunked, size, size, true);
    }
    
    @SinceKotlin(version = "1.2")
    @NotNull
    public static final <T, R> Sequence<R> chunked(@NotNull final Sequence<? extends T> $this$chunked, final int size, @NotNull final Function1<? super List<? extends T>, ? extends R> transform) {
        Intrinsics.checkNotNullParameter($this$chunked, "<this>");
        Intrinsics.checkNotNullParameter(transform, "transform");
        return windowed((Sequence<?>)$this$chunked, size, size, true, (Function1<? super List<?>, ? extends R>)transform);
    }
    
    @NotNull
    public static final <T> Sequence<T> minus(@NotNull final Sequence<? extends T> $this$minus, final T element) {
        Intrinsics.checkNotNullParameter($this$minus, "<this>");
        return (Sequence<T>)new SequencesKt___SequencesKt$minus.SequencesKt___SequencesKt$minus$1((Sequence)$this$minus, (Object)element);
    }
    
    @NotNull
    public static final <T> Sequence<T> minus(@NotNull final Sequence<? extends T> $this$minus, @NotNull final T[] elements) {
        Intrinsics.checkNotNullParameter($this$minus, "<this>");
        Intrinsics.checkNotNullParameter(elements, "elements");
        if (elements.length == 0) {
            return (Sequence<T>)$this$minus;
        }
        return (Sequence<T>)new SequencesKt___SequencesKt$minus.SequencesKt___SequencesKt$minus$2((Object[])elements, (Sequence)$this$minus);
    }
    
    @NotNull
    public static final <T> Sequence<T> minus(@NotNull final Sequence<? extends T> $this$minus, @NotNull final Iterable<? extends T> elements) {
        Intrinsics.checkNotNullParameter($this$minus, "<this>");
        Intrinsics.checkNotNullParameter(elements, "elements");
        return (Sequence<T>)new SequencesKt___SequencesKt$minus.SequencesKt___SequencesKt$minus$3((Iterable)elements, (Sequence)$this$minus);
    }
    
    @NotNull
    public static final <T> Sequence<T> minus(@NotNull final Sequence<? extends T> $this$minus, @NotNull final Sequence<? extends T> elements) {
        Intrinsics.checkNotNullParameter($this$minus, "<this>");
        Intrinsics.checkNotNullParameter(elements, "elements");
        return (Sequence<T>)new SequencesKt___SequencesKt$minus.SequencesKt___SequencesKt$minus$4((Sequence)elements, (Sequence)$this$minus);
    }
    
    @InlineOnly
    private static final <T> Sequence<T> minusElement(final Sequence<? extends T> $this$minusElement, final T element) {
        Intrinsics.checkNotNullParameter($this$minusElement, "<this>");
        return (Sequence<T>)minus($this$minusElement, (Object)element);
    }
    
    @NotNull
    public static final <T> Pair<List<T>, List<T>> partition(@NotNull final Sequence<? extends T> $this$partition, @NotNull final Function1<? super T, Boolean> predicate) {
        Intrinsics.checkNotNullParameter($this$partition, "<this>");
        Intrinsics.checkNotNullParameter(predicate, "predicate");
        final int $i$f$partition = 0;
        final ArrayList first = new ArrayList();
        final ArrayList second = new ArrayList();
        for (final Object element : $this$partition) {
            if (predicate.invoke((Object)element)) {
                first.add(element);
            }
            else {
                second.add(element);
            }
        }
        return new Pair<List<T>, List<T>>(first, second);
    }
    
    @NotNull
    public static final <T> Sequence<T> plus(@NotNull final Sequence<? extends T> $this$plus, final T element) {
        Intrinsics.checkNotNullParameter($this$plus, "<this>");
        return SequencesKt__SequencesKt.flatten((Sequence<? extends Sequence<? extends T>>)SequencesKt__SequencesKt.sequenceOf($this$plus, SequencesKt__SequencesKt.sequenceOf(element)));
    }
    
    @NotNull
    public static final <T> Sequence<T> plus(@NotNull final Sequence<? extends T> $this$plus, @NotNull final T[] elements) {
        Intrinsics.checkNotNullParameter($this$plus, "<this>");
        Intrinsics.checkNotNullParameter(elements, "elements");
        return plus($this$plus, (Iterable<? extends T>)ArraysKt___ArraysJvmKt.asList(elements));
    }
    
    @NotNull
    public static final <T> Sequence<T> plus(@NotNull final Sequence<? extends T> $this$plus, @NotNull final Iterable<? extends T> elements) {
        Intrinsics.checkNotNullParameter($this$plus, "<this>");
        Intrinsics.checkNotNullParameter(elements, "elements");
        return SequencesKt__SequencesKt.flatten((Sequence<? extends Sequence<? extends T>>)SequencesKt__SequencesKt.sequenceOf($this$plus, CollectionsKt___CollectionsKt.asSequence((Iterable<?>)elements)));
    }
    
    @NotNull
    public static final <T> Sequence<T> plus(@NotNull final Sequence<? extends T> $this$plus, @NotNull final Sequence<? extends T> elements) {
        Intrinsics.checkNotNullParameter($this$plus, "<this>");
        Intrinsics.checkNotNullParameter(elements, "elements");
        return SequencesKt__SequencesKt.flatten((Sequence<? extends Sequence<? extends T>>)SequencesKt__SequencesKt.sequenceOf($this$plus, elements));
    }
    
    @InlineOnly
    private static final <T> Sequence<T> plusElement(final Sequence<? extends T> $this$plusElement, final T element) {
        Intrinsics.checkNotNullParameter($this$plusElement, "<this>");
        return (Sequence<T>)plus($this$plusElement, (Object)element);
    }
    
    @SinceKotlin(version = "1.2")
    @NotNull
    public static final <T> Sequence<List<T>> windowed(@NotNull final Sequence<? extends T> $this$windowed, final int size, final int step, final boolean partialWindows) {
        Intrinsics.checkNotNullParameter($this$windowed, "<this>");
        return SlidingWindowKt.windowedSequence($this$windowed, size, step, partialWindows, false);
    }
    
    @SinceKotlin(version = "1.2")
    @NotNull
    public static final <T, R> Sequence<R> windowed(@NotNull final Sequence<? extends T> $this$windowed, final int size, final int step, final boolean partialWindows, @NotNull final Function1<? super List<? extends T>, ? extends R> transform) {
        Intrinsics.checkNotNullParameter($this$windowed, "<this>");
        Intrinsics.checkNotNullParameter(transform, "transform");
        return map((Sequence<?>)SlidingWindowKt.windowedSequence((Sequence<?>)$this$windowed, size, step, partialWindows, true), (Function1<? super Object, ? extends R>)transform);
    }
    
    @NotNull
    public static final <T, R> Sequence<Pair<T, R>> zip(@NotNull final Sequence<? extends T> $this$zip, @NotNull final Sequence<? extends R> other) {
        Intrinsics.checkNotNullParameter($this$zip, "<this>");
        Intrinsics.checkNotNullParameter(other, "other");
        return new MergingSequence<Object, Object, Pair<T, R>>($this$zip, other, (Function2<?, ?, ? extends Pair<T, R>>)SequencesKt___SequencesKt$zip.SequencesKt___SequencesKt$zip$1.INSTANCE);
    }
    
    @NotNull
    public static final <T, R, V> Sequence<V> zip(@NotNull final Sequence<? extends T> $this$zip, @NotNull final Sequence<? extends R> other, @NotNull final Function2<? super T, ? super R, ? extends V> transform) {
        Intrinsics.checkNotNullParameter($this$zip, "<this>");
        Intrinsics.checkNotNullParameter(other, "other");
        Intrinsics.checkNotNullParameter(transform, "transform");
        return new MergingSequence<Object, Object, V>($this$zip, other, transform);
    }
    
    @SinceKotlin(version = "1.2")
    @NotNull
    public static final <T> Sequence<Pair<T, T>> zipWithNext(@NotNull final Sequence<? extends T> $this$zipWithNext) {
        Intrinsics.checkNotNullParameter($this$zipWithNext, "<this>");
        return zipWithNext((Sequence<?>)$this$zipWithNext, (Function2<? super Object, ? super Object, ? extends Pair<T, T>>)SequencesKt___SequencesKt$zipWithNext.SequencesKt___SequencesKt$zipWithNext$1.INSTANCE);
    }
    
    @SinceKotlin(version = "1.2")
    @NotNull
    public static final <T, R> Sequence<R> zipWithNext(@NotNull final Sequence<? extends T> $this$zipWithNext, @NotNull final Function2<? super T, ? super T, ? extends R> transform) {
        Intrinsics.checkNotNullParameter($this$zipWithNext, "<this>");
        Intrinsics.checkNotNullParameter(transform, "transform");
        return SequencesKt__SequenceBuilderKt.sequence((Function2<? super SequenceScope<? super R>, ? super Continuation<? super Unit>, ?>)new SequencesKt___SequencesKt$zipWithNext.SequencesKt___SequencesKt$zipWithNext$2((Sequence)$this$zipWithNext, (Function2)transform, (Continuation)null));
    }
    
    @NotNull
    public static final <T, A extends Appendable> A joinTo(@NotNull final Sequence<? extends T> $this$joinTo, @NotNull final A buffer, @NotNull final CharSequence separator, @NotNull final CharSequence prefix, @NotNull final CharSequence postfix, final int limit, @NotNull final CharSequence truncated, @Nullable final Function1<? super T, ? extends CharSequence> transform) {
        Intrinsics.checkNotNullParameter($this$joinTo, "<this>");
        Intrinsics.checkNotNullParameter(buffer, "buffer");
        Intrinsics.checkNotNullParameter(separator, "separator");
        Intrinsics.checkNotNullParameter(prefix, "prefix");
        Intrinsics.checkNotNullParameter(postfix, "postfix");
        Intrinsics.checkNotNullParameter(truncated, "truncated");
        buffer.append(prefix);
        int count = 0;
        for (final Object element : $this$joinTo) {
            if (++count > 1) {
                buffer.append(separator);
            }
            if (limit >= 0 && count > limit) {
                break;
            }
            StringsKt__AppendableKt.appendElement(buffer, element, (Function1<? super Object, ? extends CharSequence>)transform);
        }
        if (limit >= 0 && count > limit) {
            buffer.append(truncated);
        }
        buffer.append(postfix);
        return buffer;
    }
    
    @NotNull
    public static final <T> String joinToString(@NotNull final Sequence<? extends T> $this$joinToString, @NotNull final CharSequence separator, @NotNull final CharSequence prefix, @NotNull final CharSequence postfix, final int limit, @NotNull final CharSequence truncated, @Nullable final Function1<? super T, ? extends CharSequence> transform) {
        Intrinsics.checkNotNullParameter($this$joinToString, "<this>");
        Intrinsics.checkNotNullParameter(separator, "separator");
        Intrinsics.checkNotNullParameter(prefix, "prefix");
        Intrinsics.checkNotNullParameter(postfix, "postfix");
        Intrinsics.checkNotNullParameter(truncated, "truncated");
        final String string = joinTo((Sequence<?>)$this$joinToString, (StringBuilder)new StringBuilder(), separator, prefix, postfix, limit, truncated, (Function1<? super Object, ? extends CharSequence>)transform).toString();
        Intrinsics.checkNotNullExpressionValue(string, "joinTo(StringBuilder(), \u2026ed, transform).toString()");
        return string;
    }
    
    @NotNull
    public static final <T> Iterable<T> asIterable(@NotNull final Sequence<? extends T> $this$asIterable) {
        Intrinsics.checkNotNullParameter($this$asIterable, "<this>");
        return new Iterable<T>($this$asIterable) {
            @NotNull
            @Override
            public Iterator<T> iterator() {
                final int n = 0;
                return this.$this_asIterable$inlined.iterator();
            }
        };
    }
    
    @InlineOnly
    private static final <T> Sequence<T> asSequence(final Sequence<? extends T> $this$asSequence) {
        Intrinsics.checkNotNullParameter($this$asSequence, "<this>");
        return (Sequence<T>)$this$asSequence;
    }
    
    @JvmName(name = "averageOfByte")
    public static final double averageOfByte(@NotNull final Sequence<Byte> $this$average) {
        Intrinsics.checkNotNullParameter($this$average, "<this>");
        double sum = 0.0;
        int count = 0;
        final Iterator<Byte> iterator = $this$average.iterator();
        while (iterator.hasNext()) {
            final byte element = iterator.next().byteValue();
            sum += element;
            if (++count < 0) {
                CollectionsKt.throwCountOverflow();
            }
        }
        return (count == 0) ? Double.NaN : (sum / count);
    }
    
    @JvmName(name = "averageOfShort")
    public static final double averageOfShort(@NotNull final Sequence<Short> $this$average) {
        Intrinsics.checkNotNullParameter($this$average, "<this>");
        double sum = 0.0;
        int count = 0;
        final Iterator<Short> iterator = $this$average.iterator();
        while (iterator.hasNext()) {
            final short element = iterator.next().shortValue();
            sum += element;
            if (++count < 0) {
                CollectionsKt.throwCountOverflow();
            }
        }
        return (count == 0) ? Double.NaN : (sum / count);
    }
    
    @JvmName(name = "averageOfInt")
    public static final double averageOfInt(@NotNull final Sequence<Integer> $this$average) {
        Intrinsics.checkNotNullParameter($this$average, "<this>");
        double sum = 0.0;
        int count = 0;
        final Iterator<Integer> iterator = $this$average.iterator();
        while (iterator.hasNext()) {
            final int element = iterator.next().intValue();
            sum += element;
            if (++count < 0) {
                CollectionsKt.throwCountOverflow();
            }
        }
        return (count == 0) ? Double.NaN : (sum / count);
    }
    
    @JvmName(name = "averageOfLong")
    public static final double averageOfLong(@NotNull final Sequence<Long> $this$average) {
        Intrinsics.checkNotNullParameter($this$average, "<this>");
        double sum = 0.0;
        int count = 0;
        final Iterator<Long> iterator = $this$average.iterator();
        while (iterator.hasNext()) {
            final long element = iterator.next().longValue();
            sum += element;
            if (++count < 0) {
                CollectionsKt.throwCountOverflow();
            }
        }
        return (count == 0) ? Double.NaN : (sum / count);
    }
    
    @JvmName(name = "averageOfFloat")
    public static final double averageOfFloat(@NotNull final Sequence<Float> $this$average) {
        Intrinsics.checkNotNullParameter($this$average, "<this>");
        double sum = 0.0;
        int count = 0;
        final Iterator<Float> iterator = $this$average.iterator();
        while (iterator.hasNext()) {
            final float element = iterator.next().floatValue();
            sum += element;
            if (++count < 0) {
                CollectionsKt.throwCountOverflow();
            }
        }
        return (count == 0) ? Double.NaN : (sum / count);
    }
    
    @JvmName(name = "averageOfDouble")
    public static final double averageOfDouble(@NotNull final Sequence<Double> $this$average) {
        Intrinsics.checkNotNullParameter($this$average, "<this>");
        double sum = 0.0;
        int count = 0;
        final Iterator<Double> iterator = $this$average.iterator();
        while (iterator.hasNext()) {
            final double element = iterator.next().doubleValue();
            sum += element;
            if (++count < 0) {
                CollectionsKt.throwCountOverflow();
            }
        }
        return (count == 0) ? Double.NaN : (sum / count);
    }
    
    @JvmName(name = "sumOfByte")
    public static final int sumOfByte(@NotNull final Sequence<Byte> $this$sum) {
        Intrinsics.checkNotNullParameter($this$sum, "<this>");
        int sum = 0;
        final Iterator<Byte> iterator = $this$sum.iterator();
        while (iterator.hasNext()) {
            final byte element = iterator.next().byteValue();
            sum += element;
        }
        return sum;
    }
    
    @JvmName(name = "sumOfShort")
    public static final int sumOfShort(@NotNull final Sequence<Short> $this$sum) {
        Intrinsics.checkNotNullParameter($this$sum, "<this>");
        int sum = 0;
        final Iterator<Short> iterator = $this$sum.iterator();
        while (iterator.hasNext()) {
            final short element = iterator.next().shortValue();
            sum += element;
        }
        return sum;
    }
    
    @JvmName(name = "sumOfInt")
    public static final int sumOfInt(@NotNull final Sequence<Integer> $this$sum) {
        Intrinsics.checkNotNullParameter($this$sum, "<this>");
        int sum = 0;
        final Iterator<Integer> iterator = $this$sum.iterator();
        while (iterator.hasNext()) {
            final int element = iterator.next().intValue();
            sum += element;
        }
        return sum;
    }
    
    @JvmName(name = "sumOfLong")
    public static final long sumOfLong(@NotNull final Sequence<Long> $this$sum) {
        Intrinsics.checkNotNullParameter($this$sum, "<this>");
        long sum = 0L;
        final Iterator<Long> iterator = $this$sum.iterator();
        while (iterator.hasNext()) {
            final long element = iterator.next().longValue();
            sum += element;
        }
        return sum;
    }
    
    @JvmName(name = "sumOfFloat")
    public static final float sumOfFloat(@NotNull final Sequence<Float> $this$sum) {
        Intrinsics.checkNotNullParameter($this$sum, "<this>");
        float sum = 0.0f;
        final Iterator<Float> iterator = $this$sum.iterator();
        while (iterator.hasNext()) {
            final float element = iterator.next().floatValue();
            sum += element;
        }
        return sum;
    }
    
    @JvmName(name = "sumOfDouble")
    public static final double sumOfDouble(@NotNull final Sequence<Double> $this$sum) {
        Intrinsics.checkNotNullParameter($this$sum, "<this>");
        double sum = 0.0;
        final Iterator<Double> iterator = $this$sum.iterator();
        while (iterator.hasNext()) {
            final double element = iterator.next().doubleValue();
            sum += element;
        }
        return sum;
    }
    
    public SequencesKt___SequencesKt() {
    }
}
