// 
// Decompiled by Procyon v0.5.36
// 

package kotlin.text;

import kotlin.collections.CharIterator;
import kotlin.jvm.internal.markers.KMappedMarker;
import kotlin.ranges.IntProgression;
import kotlin.collections.SlidingWindowKt;
import kotlin.sequences.Sequence;
import kotlin.ULong;
import kotlin.ExperimentalUnsignedTypes;
import kotlin.UInt;
import kotlin.DeprecatedSinceKotlin;
import kotlin.ReplaceWith;
import kotlin.Deprecated;
import java.util.Comparator;
import kotlin.collections.IntIterator;
import kotlin.Unit;
import kotlin.jvm.functions.Function3;
import kotlin.jvm.functions.Function0;
import kotlin.collections.IndexingIterable;
import kotlin.collections.IndexedValue;
import kotlin.collections.Grouping;
import kotlin.jvm.JvmName;
import kotlin.OverloadResolutionByLambdaReturnType;
import java.util.LinkedHashSet;
import java.util.Set;
import java.util.ArrayList;
import java.util.List;
import java.util.HashSet;
import java.util.Collection;
import java.util.LinkedHashMap;
import java.util.Map;
import kotlin.Pair;
import java.util.Iterator;
import kotlin.ranges.IntRange;
import kotlin.jvm.functions.Function2;
import kotlin.ExperimentalStdlibApi;
import kotlin.WasExperimental;
import kotlin.random.Random;
import org.jetbrains.annotations.Nullable;
import kotlin.SinceKotlin;
import java.util.NoSuchElementException;
import org.jetbrains.annotations.NotNull;
import kotlin.internal.InlineOnly;
import kotlin.jvm.internal.Intrinsics;
import kotlin.jvm.functions.Function1;
import kotlin.Metadata;

@Metadata(mv = { 1, 7, 1 }, k = 5, xi = 49, d1 = { "\u0000\u00f6\u0001\n\u0000\n\u0002\u0010\u000b\n\u0002\u0010\r\n\u0000\n\u0002\u0018\u0002\n\u0002\u0010\f\n\u0002\b\u0002\n\u0002\u0010\u001c\n\u0000\n\u0002\u0018\u0002\n\u0000\n\u0002\u0010$\n\u0002\b\u0003\n\u0002\u0018\u0002\n\u0002\b\u0005\n\u0002\u0010%\n\u0002\b\b\n\u0002\u0010 \n\u0002\u0010\u000e\n\u0000\n\u0002\u0010\b\n\u0002\b\u000f\n\u0002\u0018\u0002\n\u0002\u0018\u0002\n\u0002\b\u0003\n\u0002\u0018\u0002\n\u0002\u0018\u0002\n\u0002\b\n\n\u0002\u0010\u0000\n\u0002\b\b\n\u0002\u0010\u001f\n\u0002\b\n\n\u0002\u0018\u0002\n\u0002\b\u0004\n\u0002\u0010\u0002\n\u0002\b\u0006\n\u0002\u0010!\n\u0000\n\u0002\u0018\u0002\n\u0002\b\u000f\n\u0002\u0010\u000f\n\u0002\b\u0005\n\u0002\u0010\u0006\n\u0002\u0010\u0007\n\u0002\b\u0005\n\u0002\u0018\u0002\n\u0002\u0018\u0002\n\u0002\b\u001c\n\u0002\u0018\u0002\n\u0002\b\u0019\n\u0002\u0018\u0002\n\u0002\b\u0005\n\u0002\u0010\t\n\u0000\n\u0002\u0018\u0002\n\u0002\b\u0002\n\u0002\u0018\u0002\n\u0002\b\t\n\u0002\u0018\u0002\n\u0002\u0018\u0002\n\u0002\b\u0003\n\u0002\u0010\"\n\u0002\b\u0005\n\u0002\u0018\u0002\n\u0002\b\u0006\u001a$\u0010\u0000\u001a\u00020\u0001*\u00020\u00022\u0012\u0010\u0003\u001a\u000e\u0012\u0004\u0012\u00020\u0005\u0012\u0004\u0012\u00020\u00010\u0004H\u0086\b\u00f8\u0001\u0000\u001a\n\u0010\u0006\u001a\u00020\u0001*\u00020\u0002\u001a$\u0010\u0006\u001a\u00020\u0001*\u00020\u00022\u0012\u0010\u0003\u001a\u000e\u0012\u0004\u0012\u00020\u0005\u0012\u0004\u0012\u00020\u00010\u0004H\u0086\b\u00f8\u0001\u0000\u001a\u0010\u0010\u0007\u001a\b\u0012\u0004\u0012\u00020\u00050\b*\u00020\u0002\u001a\u0010\u0010\t\u001a\b\u0012\u0004\u0012\u00020\u00050\n*\u00020\u0002\u001aH\u0010\u000b\u001a\u000e\u0012\u0004\u0012\u0002H\r\u0012\u0004\u0012\u0002H\u000e0\f\"\u0004\b\u0000\u0010\r\"\u0004\b\u0001\u0010\u000e*\u00020\u00022\u001e\u0010\u000f\u001a\u001a\u0012\u0004\u0012\u00020\u0005\u0012\u0010\u0012\u000e\u0012\u0004\u0012\u0002H\r\u0012\u0004\u0012\u0002H\u000e0\u00100\u0004H\u0086\b\u00f8\u0001\u0000\u001a6\u0010\u0011\u001a\u000e\u0012\u0004\u0012\u0002H\r\u0012\u0004\u0012\u00020\u00050\f\"\u0004\b\u0000\u0010\r*\u00020\u00022\u0012\u0010\u0012\u001a\u000e\u0012\u0004\u0012\u00020\u0005\u0012\u0004\u0012\u0002H\r0\u0004H\u0086\b\u00f8\u0001\u0000\u001aP\u0010\u0011\u001a\u000e\u0012\u0004\u0012\u0002H\r\u0012\u0004\u0012\u0002H\u000e0\f\"\u0004\b\u0000\u0010\r\"\u0004\b\u0001\u0010\u000e*\u00020\u00022\u0012\u0010\u0012\u001a\u000e\u0012\u0004\u0012\u00020\u0005\u0012\u0004\u0012\u0002H\r0\u00042\u0012\u0010\u0013\u001a\u000e\u0012\u0004\u0012\u00020\u0005\u0012\u0004\u0012\u0002H\u000e0\u0004H\u0086\b\u00f8\u0001\u0000\u001aQ\u0010\u0014\u001a\u0002H\u0015\"\u0004\b\u0000\u0010\r\"\u0018\b\u0001\u0010\u0015*\u0012\u0012\u0006\b\u0000\u0012\u0002H\r\u0012\u0006\b\u0000\u0012\u00020\u00050\u0016*\u00020\u00022\u0006\u0010\u0017\u001a\u0002H\u00152\u0012\u0010\u0012\u001a\u000e\u0012\u0004\u0012\u00020\u0005\u0012\u0004\u0012\u0002H\r0\u0004H\u0086\b\u00f8\u0001\u0000¢\u0006\u0002\u0010\u0018\u001ak\u0010\u0014\u001a\u0002H\u0015\"\u0004\b\u0000\u0010\r\"\u0004\b\u0001\u0010\u000e\"\u0018\b\u0002\u0010\u0015*\u0012\u0012\u0006\b\u0000\u0012\u0002H\r\u0012\u0006\b\u0000\u0012\u0002H\u000e0\u0016*\u00020\u00022\u0006\u0010\u0017\u001a\u0002H\u00152\u0012\u0010\u0012\u001a\u000e\u0012\u0004\u0012\u00020\u0005\u0012\u0004\u0012\u0002H\r0\u00042\u0012\u0010\u0013\u001a\u000e\u0012\u0004\u0012\u00020\u0005\u0012\u0004\u0012\u0002H\u000e0\u0004H\u0086\b\u00f8\u0001\u0000¢\u0006\u0002\u0010\u0019\u001ac\u0010\u001a\u001a\u0002H\u0015\"\u0004\b\u0000\u0010\r\"\u0004\b\u0001\u0010\u000e\"\u0018\b\u0002\u0010\u0015*\u0012\u0012\u0006\b\u0000\u0012\u0002H\r\u0012\u0006\b\u0000\u0012\u0002H\u000e0\u0016*\u00020\u00022\u0006\u0010\u0017\u001a\u0002H\u00152\u001e\u0010\u000f\u001a\u001a\u0012\u0004\u0012\u00020\u0005\u0012\u0010\u0012\u000e\u0012\u0004\u0012\u0002H\r\u0012\u0004\u0012\u0002H\u000e0\u00100\u0004H\u0086\b\u00f8\u0001\u0000¢\u0006\u0002\u0010\u0018\u001a6\u0010\u001b\u001a\u000e\u0012\u0004\u0012\u00020\u0005\u0012\u0004\u0012\u0002H\u000e0\f\"\u0004\b\u0000\u0010\u000e*\u00020\u00022\u0012\u0010\u001c\u001a\u000e\u0012\u0004\u0012\u00020\u0005\u0012\u0004\u0012\u0002H\u000e0\u0004H\u0087\b\u00f8\u0001\u0000\u001aQ\u0010\u001d\u001a\u0002H\u0015\"\u0004\b\u0000\u0010\u000e\"\u0018\b\u0001\u0010\u0015*\u0012\u0012\u0006\b\u0000\u0012\u00020\u0005\u0012\u0006\b\u0000\u0012\u0002H\u000e0\u0016*\u00020\u00022\u0006\u0010\u0017\u001a\u0002H\u00152\u0012\u0010\u001c\u001a\u000e\u0012\u0004\u0012\u00020\u0005\u0012\u0004\u0012\u0002H\u000e0\u0004H\u0087\b\u00f8\u0001\u0000¢\u0006\u0002\u0010\u0018\u001a\u001a\u0010\u001e\u001a\b\u0012\u0004\u0012\u00020 0\u001f*\u00020\u00022\u0006\u0010!\u001a\u00020\"H\u0007\u001a4\u0010\u001e\u001a\b\u0012\u0004\u0012\u0002H#0\u001f\"\u0004\b\u0000\u0010#*\u00020\u00022\u0006\u0010!\u001a\u00020\"2\u0012\u0010\u000f\u001a\u000e\u0012\u0004\u0012\u00020\u0002\u0012\u0004\u0012\u0002H#0\u0004H\u0007\u001a\u001a\u0010$\u001a\b\u0012\u0004\u0012\u00020 0\n*\u00020\u00022\u0006\u0010!\u001a\u00020\"H\u0007\u001a4\u0010$\u001a\b\u0012\u0004\u0012\u0002H#0\n\"\u0004\b\u0000\u0010#*\u00020\u00022\u0006\u0010!\u001a\u00020\"2\u0012\u0010\u000f\u001a\u000e\u0012\u0004\u0012\u00020\u0002\u0012\u0004\u0012\u0002H#0\u0004H\u0007\u001a\r\u0010%\u001a\u00020\"*\u00020\u0002H\u0087\b\u001a$\u0010%\u001a\u00020\"*\u00020\u00022\u0012\u0010\u0003\u001a\u000e\u0012\u0004\u0012\u00020\u0005\u0012\u0004\u0012\u00020\u00010\u0004H\u0086\b\u00f8\u0001\u0000\u001a\u0012\u0010&\u001a\u00020\u0002*\u00020\u00022\u0006\u0010'\u001a\u00020\"\u001a\u0012\u0010&\u001a\u00020 *\u00020 2\u0006\u0010'\u001a\u00020\"\u001a\u0012\u0010(\u001a\u00020\u0002*\u00020\u00022\u0006\u0010'\u001a\u00020\"\u001a\u0012\u0010(\u001a\u00020 *\u00020 2\u0006\u0010'\u001a\u00020\"\u001a$\u0010)\u001a\u00020\u0002*\u00020\u00022\u0012\u0010\u0003\u001a\u000e\u0012\u0004\u0012\u00020\u0005\u0012\u0004\u0012\u00020\u00010\u0004H\u0086\b\u00f8\u0001\u0000\u001a$\u0010)\u001a\u00020 *\u00020 2\u0012\u0010\u0003\u001a\u000e\u0012\u0004\u0012\u00020\u0005\u0012\u0004\u0012\u00020\u00010\u0004H\u0086\b\u00f8\u0001\u0000\u001a$\u0010*\u001a\u00020\u0002*\u00020\u00022\u0012\u0010\u0003\u001a\u000e\u0012\u0004\u0012\u00020\u0005\u0012\u0004\u0012\u00020\u00010\u0004H\u0086\b\u00f8\u0001\u0000\u001a$\u0010*\u001a\u00020 *\u00020 2\u0012\u0010\u0003\u001a\u000e\u0012\u0004\u0012\u00020\u0005\u0012\u0004\u0012\u00020\u00010\u0004H\u0086\b\u00f8\u0001\u0000\u001a,\u0010+\u001a\u00020\u0005*\u00020\u00022\u0006\u0010,\u001a\u00020\"2\u0012\u0010-\u001a\u000e\u0012\u0004\u0012\u00020\"\u0012\u0004\u0012\u00020\u00050\u0004H\u0087\b\u00f8\u0001\u0000\u001a\u001c\u0010.\u001a\u0004\u0018\u00010\u0005*\u00020\u00022\u0006\u0010,\u001a\u00020\"H\u0087\b¢\u0006\u0002\u0010/\u001a$\u00100\u001a\u00020\u0002*\u00020\u00022\u0012\u0010\u0003\u001a\u000e\u0012\u0004\u0012\u00020\u0005\u0012\u0004\u0012\u00020\u00010\u0004H\u0086\b\u00f8\u0001\u0000\u001a$\u00100\u001a\u00020 *\u00020 2\u0012\u0010\u0003\u001a\u000e\u0012\u0004\u0012\u00020\u0005\u0012\u0004\u0012\u00020\u00010\u0004H\u0086\b\u00f8\u0001\u0000\u001a9\u00101\u001a\u00020\u0002*\u00020\u00022'\u0010\u0003\u001a#\u0012\u0013\u0012\u00110\"¢\u0006\f\b3\u0012\b\b4\u0012\u0004\b\b(,\u0012\u0004\u0012\u00020\u0005\u0012\u0004\u0012\u00020\u000102H\u0086\b\u00f8\u0001\u0000\u001a9\u00101\u001a\u00020 *\u00020 2'\u0010\u0003\u001a#\u0012\u0013\u0012\u00110\"¢\u0006\f\b3\u0012\b\b4\u0012\u0004\b\b(,\u0012\u0004\u0012\u00020\u0005\u0012\u0004\u0012\u00020\u000102H\u0086\b\u00f8\u0001\u0000\u001aT\u00105\u001a\u0002H6\"\f\b\u0000\u00106*\u000607j\u0002`8*\u00020\u00022\u0006\u0010\u0017\u001a\u0002H62'\u0010\u0003\u001a#\u0012\u0013\u0012\u00110\"¢\u0006\f\b3\u0012\b\b4\u0012\u0004\b\b(,\u0012\u0004\u0012\u00020\u0005\u0012\u0004\u0012\u00020\u000102H\u0086\b\u00f8\u0001\u0000¢\u0006\u0002\u00109\u001a$\u0010:\u001a\u00020\u0002*\u00020\u00022\u0012\u0010\u0003\u001a\u000e\u0012\u0004\u0012\u00020\u0005\u0012\u0004\u0012\u00020\u00010\u0004H\u0086\b\u00f8\u0001\u0000\u001a$\u0010:\u001a\u00020 *\u00020 2\u0012\u0010\u0003\u001a\u000e\u0012\u0004\u0012\u00020\u0005\u0012\u0004\u0012\u00020\u00010\u0004H\u0086\b\u00f8\u0001\u0000\u001a?\u0010;\u001a\u0002H6\"\f\b\u0000\u00106*\u000607j\u0002`8*\u00020\u00022\u0006\u0010\u0017\u001a\u0002H62\u0012\u0010\u0003\u001a\u000e\u0012\u0004\u0012\u00020\u0005\u0012\u0004\u0012\u00020\u00010\u0004H\u0086\b\u00f8\u0001\u0000¢\u0006\u0002\u0010<\u001a?\u0010=\u001a\u0002H6\"\f\b\u0000\u00106*\u000607j\u0002`8*\u00020\u00022\u0006\u0010\u0017\u001a\u0002H62\u0012\u0010\u0003\u001a\u000e\u0012\u0004\u0012\u00020\u0005\u0012\u0004\u0012\u00020\u00010\u0004H\u0086\b\u00f8\u0001\u0000¢\u0006\u0002\u0010<\u001a+\u0010>\u001a\u0004\u0018\u00010\u0005*\u00020\u00022\u0012\u0010\u0003\u001a\u000e\u0012\u0004\u0012\u00020\u0005\u0012\u0004\u0012\u00020\u00010\u0004H\u0087\b\u00f8\u0001\u0000¢\u0006\u0002\u0010?\u001a+\u0010@\u001a\u0004\u0018\u00010\u0005*\u00020\u00022\u0012\u0010\u0003\u001a\u000e\u0012\u0004\u0012\u00020\u0005\u0012\u0004\u0012\u00020\u00010\u0004H\u0087\b\u00f8\u0001\u0000¢\u0006\u0002\u0010?\u001a\n\u0010A\u001a\u00020\u0005*\u00020\u0002\u001a$\u0010A\u001a\u00020\u0005*\u00020\u00022\u0012\u0010\u0003\u001a\u000e\u0012\u0004\u0012\u00020\u0005\u0012\u0004\u0012\u00020\u00010\u0004H\u0086\b\u00f8\u0001\u0000\u001a5\u0010B\u001a\u0002H#\"\b\b\u0000\u0010#*\u00020C*\u00020\u00022\u0014\u0010\u000f\u001a\u0010\u0012\u0004\u0012\u00020\u0005\u0012\u0006\u0012\u0004\u0018\u0001H#0\u0004H\u0087\b\u00f8\u0001\u0000¢\u0006\u0002\u0010D\u001a7\u0010E\u001a\u0004\u0018\u0001H#\"\b\b\u0000\u0010#*\u00020C*\u00020\u00022\u0014\u0010\u000f\u001a\u0010\u0012\u0004\u0012\u00020\u0005\u0012\u0006\u0012\u0004\u0018\u0001H#0\u0004H\u0087\b\u00f8\u0001\u0000¢\u0006\u0002\u0010D\u001a\u0011\u0010F\u001a\u0004\u0018\u00010\u0005*\u00020\u0002¢\u0006\u0002\u0010G\u001a+\u0010F\u001a\u0004\u0018\u00010\u0005*\u00020\u00022\u0012\u0010\u0003\u001a\u000e\u0012\u0004\u0012\u00020\u0005\u0012\u0004\u0012\u00020\u00010\u0004H\u0086\b\u00f8\u0001\u0000¢\u0006\u0002\u0010?\u001a6\u0010H\u001a\b\u0012\u0004\u0012\u0002H#0\u001f\"\u0004\b\u0000\u0010#*\u00020\u00022\u0018\u0010\u000f\u001a\u0014\u0012\u0004\u0012\u00020\u0005\u0012\n\u0012\b\u0012\u0004\u0012\u0002H#0\b0\u0004H\u0086\b\u00f8\u0001\u0000\u001aP\u0010I\u001a\b\u0012\u0004\u0012\u0002H#0\u001f\"\u0004\b\u0000\u0010#*\u00020\u00022-\u0010\u000f\u001a)\u0012\u0013\u0012\u00110\"¢\u0006\f\b3\u0012\b\b4\u0012\u0004\b\b(,\u0012\u0004\u0012\u00020\u0005\u0012\n\u0012\b\u0012\u0004\u0012\u0002H#0\b02H\u0087\b\u00f8\u0001\u0000¢\u0006\u0002\bJ\u001af\u0010K\u001a\u0002H6\"\u0004\b\u0000\u0010#\"\u0010\b\u0001\u00106*\n\u0012\u0006\b\u0000\u0012\u0002H#0L*\u00020\u00022\u0006\u0010\u0017\u001a\u0002H62-\u0010\u000f\u001a)\u0012\u0013\u0012\u00110\"¢\u0006\f\b3\u0012\b\b4\u0012\u0004\b\b(,\u0012\u0004\u0012\u00020\u0005\u0012\n\u0012\b\u0012\u0004\u0012\u0002H#0\b02H\u0087\b\u00f8\u0001\u0000¢\u0006\u0004\bM\u0010N\u001aO\u0010O\u001a\u0002H6\"\u0004\b\u0000\u0010#\"\u0010\b\u0001\u00106*\n\u0012\u0006\b\u0000\u0012\u0002H#0L*\u00020\u00022\u0006\u0010\u0017\u001a\u0002H62\u0018\u0010\u000f\u001a\u0014\u0012\u0004\u0012\u00020\u0005\u0012\n\u0012\b\u0012\u0004\u0012\u0002H#0\b0\u0004H\u0086\b\u00f8\u0001\u0000¢\u0006\u0002\u0010P\u001aL\u0010Q\u001a\u0002H#\"\u0004\b\u0000\u0010#*\u00020\u00022\u0006\u0010R\u001a\u0002H#2'\u0010S\u001a#\u0012\u0013\u0012\u0011H#¢\u0006\f\b3\u0012\b\b4\u0012\u0004\b\b(T\u0012\u0004\u0012\u00020\u0005\u0012\u0004\u0012\u0002H#02H\u0086\b\u00f8\u0001\u0000¢\u0006\u0002\u0010U\u001aa\u0010V\u001a\u0002H#\"\u0004\b\u0000\u0010#*\u00020\u00022\u0006\u0010R\u001a\u0002H#2<\u0010S\u001a8\u0012\u0013\u0012\u00110\"¢\u0006\f\b3\u0012\b\b4\u0012\u0004\b\b(,\u0012\u0013\u0012\u0011H#¢\u0006\f\b3\u0012\b\b4\u0012\u0004\b\b(T\u0012\u0004\u0012\u00020\u0005\u0012\u0004\u0012\u0002H#0WH\u0086\b\u00f8\u0001\u0000¢\u0006\u0002\u0010X\u001aL\u0010Y\u001a\u0002H#\"\u0004\b\u0000\u0010#*\u00020\u00022\u0006\u0010R\u001a\u0002H#2'\u0010S\u001a#\u0012\u0004\u0012\u00020\u0005\u0012\u0013\u0012\u0011H#¢\u0006\f\b3\u0012\b\b4\u0012\u0004\b\b(T\u0012\u0004\u0012\u0002H#02H\u0086\b\u00f8\u0001\u0000¢\u0006\u0002\u0010U\u001aa\u0010Z\u001a\u0002H#\"\u0004\b\u0000\u0010#*\u00020\u00022\u0006\u0010R\u001a\u0002H#2<\u0010S\u001a8\u0012\u0013\u0012\u00110\"¢\u0006\f\b3\u0012\b\b4\u0012\u0004\b\b(,\u0012\u0004\u0012\u00020\u0005\u0012\u0013\u0012\u0011H#¢\u0006\f\b3\u0012\b\b4\u0012\u0004\b\b(T\u0012\u0004\u0012\u0002H#0WH\u0086\b\u00f8\u0001\u0000¢\u0006\u0002\u0010X\u001a$\u0010[\u001a\u00020\\*\u00020\u00022\u0012\u0010]\u001a\u000e\u0012\u0004\u0012\u00020\u0005\u0012\u0004\u0012\u00020\\0\u0004H\u0086\b\u00f8\u0001\u0000\u001a9\u0010^\u001a\u00020\\*\u00020\u00022'\u0010]\u001a#\u0012\u0013\u0012\u00110\"¢\u0006\f\b3\u0012\b\b4\u0012\u0004\b\b(,\u0012\u0004\u0012\u00020\u0005\u0012\u0004\u0012\u00020\\02H\u0086\b\u00f8\u0001\u0000\u001a,\u0010_\u001a\u00020\u0005*\u00020\u00022\u0006\u0010,\u001a\u00020\"2\u0012\u0010-\u001a\u000e\u0012\u0004\u0012\u00020\"\u0012\u0004\u0012\u00020\u00050\u0004H\u0087\b\u00f8\u0001\u0000\u001a\u0019\u0010`\u001a\u0004\u0018\u00010\u0005*\u00020\u00022\u0006\u0010,\u001a\u00020\"¢\u0006\u0002\u0010/\u001a<\u0010a\u001a\u0014\u0012\u0004\u0012\u0002H\r\u0012\n\u0012\b\u0012\u0004\u0012\u00020\u00050\u001f0\f\"\u0004\b\u0000\u0010\r*\u00020\u00022\u0012\u0010\u0012\u001a\u000e\u0012\u0004\u0012\u00020\u0005\u0012\u0004\u0012\u0002H\r0\u0004H\u0086\b\u00f8\u0001\u0000\u001aV\u0010a\u001a\u0014\u0012\u0004\u0012\u0002H\r\u0012\n\u0012\b\u0012\u0004\u0012\u0002H\u000e0\u001f0\f\"\u0004\b\u0000\u0010\r\"\u0004\b\u0001\u0010\u000e*\u00020\u00022\u0012\u0010\u0012\u001a\u000e\u0012\u0004\u0012\u00020\u0005\u0012\u0004\u0012\u0002H\r0\u00042\u0012\u0010\u0013\u001a\u000e\u0012\u0004\u0012\u00020\u0005\u0012\u0004\u0012\u0002H\u000e0\u0004H\u0086\b\u00f8\u0001\u0000\u001aU\u0010b\u001a\u0002H\u0015\"\u0004\b\u0000\u0010\r\"\u001c\b\u0001\u0010\u0015*\u0016\u0012\u0006\b\u0000\u0012\u0002H\r\u0012\n\u0012\b\u0012\u0004\u0012\u00020\u00050c0\u0016*\u00020\u00022\u0006\u0010\u0017\u001a\u0002H\u00152\u0012\u0010\u0012\u001a\u000e\u0012\u0004\u0012\u00020\u0005\u0012\u0004\u0012\u0002H\r0\u0004H\u0086\b\u00f8\u0001\u0000¢\u0006\u0002\u0010\u0018\u001ao\u0010b\u001a\u0002H\u0015\"\u0004\b\u0000\u0010\r\"\u0004\b\u0001\u0010\u000e\"\u001c\b\u0002\u0010\u0015*\u0016\u0012\u0006\b\u0000\u0012\u0002H\r\u0012\n\u0012\b\u0012\u0004\u0012\u0002H\u000e0c0\u0016*\u00020\u00022\u0006\u0010\u0017\u001a\u0002H\u00152\u0012\u0010\u0012\u001a\u000e\u0012\u0004\u0012\u00020\u0005\u0012\u0004\u0012\u0002H\r0\u00042\u0012\u0010\u0013\u001a\u000e\u0012\u0004\u0012\u00020\u0005\u0012\u0004\u0012\u0002H\u000e0\u0004H\u0086\b\u00f8\u0001\u0000¢\u0006\u0002\u0010\u0019\u001a8\u0010d\u001a\u000e\u0012\u0004\u0012\u00020\u0005\u0012\u0004\u0012\u0002H\r0e\"\u0004\b\u0000\u0010\r*\u00020\u00022\u0014\b\u0004\u0010\u0012\u001a\u000e\u0012\u0004\u0012\u00020\u0005\u0012\u0004\u0012\u0002H\r0\u0004H\u0087\b\u00f8\u0001\u0000\u001a$\u0010f\u001a\u00020\"*\u00020\u00022\u0012\u0010\u0003\u001a\u000e\u0012\u0004\u0012\u00020\u0005\u0012\u0004\u0012\u00020\u00010\u0004H\u0086\b\u00f8\u0001\u0000\u001a$\u0010g\u001a\u00020\"*\u00020\u00022\u0012\u0010\u0003\u001a\u000e\u0012\u0004\u0012\u00020\u0005\u0012\u0004\u0012\u00020\u00010\u0004H\u0086\b\u00f8\u0001\u0000\u001a\n\u0010h\u001a\u00020\u0005*\u00020\u0002\u001a$\u0010h\u001a\u00020\u0005*\u00020\u00022\u0012\u0010\u0003\u001a\u000e\u0012\u0004\u0012\u00020\u0005\u0012\u0004\u0012\u00020\u00010\u0004H\u0086\b\u00f8\u0001\u0000\u001a\u0011\u0010i\u001a\u0004\u0018\u00010\u0005*\u00020\u0002¢\u0006\u0002\u0010G\u001a+\u0010i\u001a\u0004\u0018\u00010\u0005*\u00020\u00022\u0012\u0010\u0003\u001a\u000e\u0012\u0004\u0012\u00020\u0005\u0012\u0004\u0012\u00020\u00010\u0004H\u0086\b\u00f8\u0001\u0000¢\u0006\u0002\u0010?\u001a0\u0010j\u001a\b\u0012\u0004\u0012\u0002H#0\u001f\"\u0004\b\u0000\u0010#*\u00020\u00022\u0012\u0010\u000f\u001a\u000e\u0012\u0004\u0012\u00020\u0005\u0012\u0004\u0012\u0002H#0\u0004H\u0086\b\u00f8\u0001\u0000\u001aE\u0010k\u001a\b\u0012\u0004\u0012\u0002H#0\u001f\"\u0004\b\u0000\u0010#*\u00020\u00022'\u0010\u000f\u001a#\u0012\u0013\u0012\u00110\"¢\u0006\f\b3\u0012\b\b4\u0012\u0004\b\b(,\u0012\u0004\u0012\u00020\u0005\u0012\u0004\u0012\u0002H#02H\u0086\b\u00f8\u0001\u0000\u001aK\u0010l\u001a\b\u0012\u0004\u0012\u0002H#0\u001f\"\b\b\u0000\u0010#*\u00020C*\u00020\u00022)\u0010\u000f\u001a%\u0012\u0013\u0012\u00110\"¢\u0006\f\b3\u0012\b\b4\u0012\u0004\b\b(,\u0012\u0004\u0012\u00020\u0005\u0012\u0006\u0012\u0004\u0018\u0001H#02H\u0086\b\u00f8\u0001\u0000\u001ad\u0010m\u001a\u0002H6\"\b\b\u0000\u0010#*\u00020C\"\u0010\b\u0001\u00106*\n\u0012\u0006\b\u0000\u0012\u0002H#0L*\u00020\u00022\u0006\u0010\u0017\u001a\u0002H62)\u0010\u000f\u001a%\u0012\u0013\u0012\u00110\"¢\u0006\f\b3\u0012\b\b4\u0012\u0004\b\b(,\u0012\u0004\u0012\u00020\u0005\u0012\u0006\u0012\u0004\u0018\u0001H#02H\u0086\b\u00f8\u0001\u0000¢\u0006\u0002\u0010N\u001a^\u0010n\u001a\u0002H6\"\u0004\b\u0000\u0010#\"\u0010\b\u0001\u00106*\n\u0012\u0006\b\u0000\u0012\u0002H#0L*\u00020\u00022\u0006\u0010\u0017\u001a\u0002H62'\u0010\u000f\u001a#\u0012\u0013\u0012\u00110\"¢\u0006\f\b3\u0012\b\b4\u0012\u0004\b\b(,\u0012\u0004\u0012\u00020\u0005\u0012\u0004\u0012\u0002H#02H\u0086\b\u00f8\u0001\u0000¢\u0006\u0002\u0010N\u001a6\u0010o\u001a\b\u0012\u0004\u0012\u0002H#0\u001f\"\b\b\u0000\u0010#*\u00020C*\u00020\u00022\u0014\u0010\u000f\u001a\u0010\u0012\u0004\u0012\u00020\u0005\u0012\u0006\u0012\u0004\u0018\u0001H#0\u0004H\u0086\b\u00f8\u0001\u0000\u001aO\u0010p\u001a\u0002H6\"\b\b\u0000\u0010#*\u00020C\"\u0010\b\u0001\u00106*\n\u0012\u0006\b\u0000\u0012\u0002H#0L*\u00020\u00022\u0006\u0010\u0017\u001a\u0002H62\u0014\u0010\u000f\u001a\u0010\u0012\u0004\u0012\u00020\u0005\u0012\u0006\u0012\u0004\u0018\u0001H#0\u0004H\u0086\b\u00f8\u0001\u0000¢\u0006\u0002\u0010P\u001aI\u0010q\u001a\u0002H6\"\u0004\b\u0000\u0010#\"\u0010\b\u0001\u00106*\n\u0012\u0006\b\u0000\u0012\u0002H#0L*\u00020\u00022\u0006\u0010\u0017\u001a\u0002H62\u0012\u0010\u000f\u001a\u000e\u0012\u0004\u0012\u00020\u0005\u0012\u0004\u0012\u0002H#0\u0004H\u0086\b\u00f8\u0001\u0000¢\u0006\u0002\u0010P\u001a\u0011\u0010r\u001a\u00020\u0005*\u00020\u0002H\u0007¢\u0006\u0002\bs\u001a9\u0010t\u001a\u00020\u0005\"\u000e\b\u0000\u0010#*\b\u0012\u0004\u0012\u0002H#0u*\u00020\u00022\u0012\u0010v\u001a\u000e\u0012\u0004\u0012\u00020\u0005\u0012\u0004\u0012\u0002H#0\u0004H\u0087\b\u00f8\u0001\u0000¢\u0006\u0002\bw\u001a;\u0010x\u001a\u0004\u0018\u00010\u0005\"\u000e\b\u0000\u0010#*\b\u0012\u0004\u0012\u0002H#0u*\u00020\u00022\u0012\u0010v\u001a\u000e\u0012\u0004\u0012\u00020\u0005\u0012\u0004\u0012\u0002H#0\u0004H\u0087\b\u00f8\u0001\u0000¢\u0006\u0002\u0010?\u001a9\u0010y\u001a\u0002H#\"\u000e\b\u0000\u0010#*\b\u0012\u0004\u0012\u0002H#0u*\u00020\u00022\u0012\u0010v\u001a\u000e\u0012\u0004\u0012\u00020\u0005\u0012\u0004\u0012\u0002H#0\u0004H\u0087\b\u00f8\u0001\u0000¢\u0006\u0002\u0010z\u001a$\u0010y\u001a\u00020{*\u00020\u00022\u0012\u0010v\u001a\u000e\u0012\u0004\u0012\u00020\u0005\u0012\u0004\u0012\u00020{0\u0004H\u0087\b\u00f8\u0001\u0000\u001a$\u0010y\u001a\u00020|*\u00020\u00022\u0012\u0010v\u001a\u000e\u0012\u0004\u0012\u00020\u0005\u0012\u0004\u0012\u00020|0\u0004H\u0087\b\u00f8\u0001\u0000\u001a;\u0010}\u001a\u0004\u0018\u0001H#\"\u000e\b\u0000\u0010#*\b\u0012\u0004\u0012\u0002H#0u*\u00020\u00022\u0012\u0010v\u001a\u000e\u0012\u0004\u0012\u00020\u0005\u0012\u0004\u0012\u0002H#0\u0004H\u0087\b\u00f8\u0001\u0000¢\u0006\u0002\u0010z\u001a+\u0010}\u001a\u0004\u0018\u00010{*\u00020\u00022\u0012\u0010v\u001a\u000e\u0012\u0004\u0012\u00020\u0005\u0012\u0004\u0012\u00020{0\u0004H\u0087\b\u00f8\u0001\u0000¢\u0006\u0002\u0010~\u001a+\u0010}\u001a\u0004\u0018\u00010|*\u00020\u00022\u0012\u0010v\u001a\u000e\u0012\u0004\u0012\u00020\u0005\u0012\u0004\u0012\u00020|0\u0004H\u0087\b\u00f8\u0001\u0000¢\u0006\u0002\u0010\u007f\u001aP\u0010\u0080\u0001\u001a\u0002H#\"\u0004\b\u0000\u0010#*\u00020\u00022\u001d\u0010\u0081\u0001\u001a\u0018\u0012\u0006\b\u0000\u0012\u0002H#0\u0082\u0001j\u000b\u0012\u0006\b\u0000\u0012\u0002H#`\u0083\u00012\u0012\u0010v\u001a\u000e\u0012\u0004\u0012\u00020\u0005\u0012\u0004\u0012\u0002H#0\u0004H\u0087\b\u00f8\u0001\u0000¢\u0006\u0003\u0010\u0084\u0001\u001aR\u0010\u0085\u0001\u001a\u0004\u0018\u0001H#\"\u0004\b\u0000\u0010#*\u00020\u00022\u001d\u0010\u0081\u0001\u001a\u0018\u0012\u0006\b\u0000\u0012\u0002H#0\u0082\u0001j\u000b\u0012\u0006\b\u0000\u0012\u0002H#`\u0083\u00012\u0012\u0010v\u001a\u000e\u0012\u0004\u0012\u00020\u0005\u0012\u0004\u0012\u0002H#0\u0004H\u0087\b\u00f8\u0001\u0000¢\u0006\u0003\u0010\u0084\u0001\u001a\u0014\u0010\u0086\u0001\u001a\u0004\u0018\u00010\u0005*\u00020\u0002H\u0007¢\u0006\u0002\u0010G\u001a2\u0010\u0087\u0001\u001a\u00020\u0005*\u00020\u00022\u001d\u0010\u0081\u0001\u001a\u0018\u0012\u0006\b\u0000\u0012\u00020\u00050\u0082\u0001j\u000b\u0012\u0006\b\u0000\u0012\u00020\u0005`\u0083\u0001H\u0007¢\u0006\u0003\b\u0088\u0001\u001a4\u0010\u0089\u0001\u001a\u0004\u0018\u00010\u0005*\u00020\u00022\u001d\u0010\u0081\u0001\u001a\u0018\u0012\u0006\b\u0000\u0012\u00020\u00050\u0082\u0001j\u000b\u0012\u0006\b\u0000\u0012\u00020\u0005`\u0083\u0001H\u0007¢\u0006\u0003\u0010\u008a\u0001\u001a\u0013\u0010\u008b\u0001\u001a\u00020\u0005*\u00020\u0002H\u0007¢\u0006\u0003\b\u008c\u0001\u001a;\u0010\u008d\u0001\u001a\u00020\u0005\"\u000e\b\u0000\u0010#*\b\u0012\u0004\u0012\u0002H#0u*\u00020\u00022\u0012\u0010v\u001a\u000e\u0012\u0004\u0012\u00020\u0005\u0012\u0004\u0012\u0002H#0\u0004H\u0087\b\u00f8\u0001\u0000¢\u0006\u0003\b\u008e\u0001\u001a<\u0010\u008f\u0001\u001a\u0004\u0018\u00010\u0005\"\u000e\b\u0000\u0010#*\b\u0012\u0004\u0012\u0002H#0u*\u00020\u00022\u0012\u0010v\u001a\u000e\u0012\u0004\u0012\u00020\u0005\u0012\u0004\u0012\u0002H#0\u0004H\u0087\b\u00f8\u0001\u0000¢\u0006\u0002\u0010?\u001a:\u0010\u0090\u0001\u001a\u0002H#\"\u000e\b\u0000\u0010#*\b\u0012\u0004\u0012\u0002H#0u*\u00020\u00022\u0012\u0010v\u001a\u000e\u0012\u0004\u0012\u00020\u0005\u0012\u0004\u0012\u0002H#0\u0004H\u0087\b\u00f8\u0001\u0000¢\u0006\u0002\u0010z\u001a%\u0010\u0090\u0001\u001a\u00020{*\u00020\u00022\u0012\u0010v\u001a\u000e\u0012\u0004\u0012\u00020\u0005\u0012\u0004\u0012\u00020{0\u0004H\u0087\b\u00f8\u0001\u0000\u001a%\u0010\u0090\u0001\u001a\u00020|*\u00020\u00022\u0012\u0010v\u001a\u000e\u0012\u0004\u0012\u00020\u0005\u0012\u0004\u0012\u00020|0\u0004H\u0087\b\u00f8\u0001\u0000\u001a<\u0010\u0091\u0001\u001a\u0004\u0018\u0001H#\"\u000e\b\u0000\u0010#*\b\u0012\u0004\u0012\u0002H#0u*\u00020\u00022\u0012\u0010v\u001a\u000e\u0012\u0004\u0012\u00020\u0005\u0012\u0004\u0012\u0002H#0\u0004H\u0087\b\u00f8\u0001\u0000¢\u0006\u0002\u0010z\u001a,\u0010\u0091\u0001\u001a\u0004\u0018\u00010{*\u00020\u00022\u0012\u0010v\u001a\u000e\u0012\u0004\u0012\u00020\u0005\u0012\u0004\u0012\u00020{0\u0004H\u0087\b\u00f8\u0001\u0000¢\u0006\u0002\u0010~\u001a,\u0010\u0091\u0001\u001a\u0004\u0018\u00010|*\u00020\u00022\u0012\u0010v\u001a\u000e\u0012\u0004\u0012\u00020\u0005\u0012\u0004\u0012\u00020|0\u0004H\u0087\b\u00f8\u0001\u0000¢\u0006\u0002\u0010\u007f\u001aP\u0010\u0092\u0001\u001a\u0002H#\"\u0004\b\u0000\u0010#*\u00020\u00022\u001d\u0010\u0081\u0001\u001a\u0018\u0012\u0006\b\u0000\u0012\u0002H#0\u0082\u0001j\u000b\u0012\u0006\b\u0000\u0012\u0002H#`\u0083\u00012\u0012\u0010v\u001a\u000e\u0012\u0004\u0012\u00020\u0005\u0012\u0004\u0012\u0002H#0\u0004H\u0087\b\u00f8\u0001\u0000¢\u0006\u0003\u0010\u0084\u0001\u001aR\u0010\u0093\u0001\u001a\u0004\u0018\u0001H#\"\u0004\b\u0000\u0010#*\u00020\u00022\u001d\u0010\u0081\u0001\u001a\u0018\u0012\u0006\b\u0000\u0012\u0002H#0\u0082\u0001j\u000b\u0012\u0006\b\u0000\u0012\u0002H#`\u0083\u00012\u0012\u0010v\u001a\u000e\u0012\u0004\u0012\u00020\u0005\u0012\u0004\u0012\u0002H#0\u0004H\u0087\b\u00f8\u0001\u0000¢\u0006\u0003\u0010\u0084\u0001\u001a\u0014\u0010\u0094\u0001\u001a\u0004\u0018\u00010\u0005*\u00020\u0002H\u0007¢\u0006\u0002\u0010G\u001a2\u0010\u0095\u0001\u001a\u00020\u0005*\u00020\u00022\u001d\u0010\u0081\u0001\u001a\u0018\u0012\u0006\b\u0000\u0012\u00020\u00050\u0082\u0001j\u000b\u0012\u0006\b\u0000\u0012\u00020\u0005`\u0083\u0001H\u0007¢\u0006\u0003\b\u0096\u0001\u001a4\u0010\u0097\u0001\u001a\u0004\u0018\u00010\u0005*\u00020\u00022\u001d\u0010\u0081\u0001\u001a\u0018\u0012\u0006\b\u0000\u0012\u00020\u00050\u0082\u0001j\u000b\u0012\u0006\b\u0000\u0012\u00020\u0005`\u0083\u0001H\u0007¢\u0006\u0003\u0010\u008a\u0001\u001a\u000b\u0010\u0098\u0001\u001a\u00020\u0001*\u00020\u0002\u001a%\u0010\u0098\u0001\u001a\u00020\u0001*\u00020\u00022\u0012\u0010\u0003\u001a\u000e\u0012\u0004\u0012\u00020\u0005\u0012\u0004\u0012\u00020\u00010\u0004H\u0086\b\u00f8\u0001\u0000\u001a8\u0010\u0099\u0001\u001a\u0003H\u009a\u0001\"\t\b\u0000\u0010\u009a\u0001*\u00020\u0002*\u0003H\u009a\u00012\u0012\u0010]\u001a\u000e\u0012\u0004\u0012\u00020\u0005\u0012\u0004\u0012\u00020\\0\u0004H\u0087\b\u00f8\u0001\u0000¢\u0006\u0003\u0010\u009b\u0001\u001aM\u0010\u009c\u0001\u001a\u0003H\u009a\u0001\"\t\b\u0000\u0010\u009a\u0001*\u00020\u0002*\u0003H\u009a\u00012'\u0010]\u001a#\u0012\u0013\u0012\u00110\"¢\u0006\f\b3\u0012\b\b4\u0012\u0004\b\b(,\u0012\u0004\u0012\u00020\u0005\u0012\u0004\u0012\u00020\\02H\u0087\b\u00f8\u0001\u0000¢\u0006\u0003\u0010\u009d\u0001\u001a1\u0010\u009e\u0001\u001a\u000e\u0012\u0004\u0012\u00020\u0002\u0012\u0004\u0012\u00020\u00020\u0010*\u00020\u00022\u0012\u0010\u0003\u001a\u000e\u0012\u0004\u0012\u00020\u0005\u0012\u0004\u0012\u00020\u00010\u0004H\u0086\b\u00f8\u0001\u0000\u001a1\u0010\u009e\u0001\u001a\u000e\u0012\u0004\u0012\u00020 \u0012\u0004\u0012\u00020 0\u0010*\u00020 2\u0012\u0010\u0003\u001a\u000e\u0012\u0004\u0012\u00020\u0005\u0012\u0004\u0012\u00020\u00010\u0004H\u0086\b\u00f8\u0001\u0000\u001a\u000e\u0010\u009f\u0001\u001a\u00020\u0005*\u00020\u0002H\u0087\b\u001a\u0017\u0010\u009f\u0001\u001a\u00020\u0005*\u00020\u00022\b\u0010\u009f\u0001\u001a\u00030 \u0001H\u0007\u001a\u0015\u0010¡\u0001\u001a\u0004\u0018\u00010\u0005*\u00020\u0002H\u0087\b¢\u0006\u0002\u0010G\u001a\u001f\u0010¡\u0001\u001a\u0004\u0018\u00010\u0005*\u00020\u00022\b\u0010\u009f\u0001\u001a\u00030 \u0001H\u0007¢\u0006\u0003\u0010¢\u0001\u001a:\u0010£\u0001\u001a\u00020\u0005*\u00020\u00022'\u0010S\u001a#\u0012\u0013\u0012\u00110\u0005¢\u0006\f\b3\u0012\b\b4\u0012\u0004\b\b(T\u0012\u0004\u0012\u00020\u0005\u0012\u0004\u0012\u00020\u000502H\u0086\b\u00f8\u0001\u0000\u001aO\u0010¤\u0001\u001a\u00020\u0005*\u00020\u00022<\u0010S\u001a8\u0012\u0013\u0012\u00110\"¢\u0006\f\b3\u0012\b\b4\u0012\u0004\b\b(,\u0012\u0013\u0012\u00110\u0005¢\u0006\f\b3\u0012\b\b4\u0012\u0004\b\b(T\u0012\u0004\u0012\u00020\u0005\u0012\u0004\u0012\u00020\u00050WH\u0086\b\u00f8\u0001\u0000\u001aW\u0010¥\u0001\u001a\u0004\u0018\u00010\u0005*\u00020\u00022<\u0010S\u001a8\u0012\u0013\u0012\u00110\"¢\u0006\f\b3\u0012\b\b4\u0012\u0004\b\b(,\u0012\u0013\u0012\u00110\u0005¢\u0006\f\b3\u0012\b\b4\u0012\u0004\b\b(T\u0012\u0004\u0012\u00020\u0005\u0012\u0004\u0012\u00020\u00050WH\u0087\b\u00f8\u0001\u0000¢\u0006\u0003\u0010¦\u0001\u001aB\u0010§\u0001\u001a\u0004\u0018\u00010\u0005*\u00020\u00022'\u0010S\u001a#\u0012\u0013\u0012\u00110\u0005¢\u0006\f\b3\u0012\b\b4\u0012\u0004\b\b(T\u0012\u0004\u0012\u00020\u0005\u0012\u0004\u0012\u00020\u000502H\u0087\b\u00f8\u0001\u0000¢\u0006\u0003\u0010¨\u0001\u001a:\u0010©\u0001\u001a\u00020\u0005*\u00020\u00022'\u0010S\u001a#\u0012\u0004\u0012\u00020\u0005\u0012\u0013\u0012\u00110\u0005¢\u0006\f\b3\u0012\b\b4\u0012\u0004\b\b(T\u0012\u0004\u0012\u00020\u000502H\u0086\b\u00f8\u0001\u0000\u001aO\u0010ª\u0001\u001a\u00020\u0005*\u00020\u00022<\u0010S\u001a8\u0012\u0013\u0012\u00110\"¢\u0006\f\b3\u0012\b\b4\u0012\u0004\b\b(,\u0012\u0004\u0012\u00020\u0005\u0012\u0013\u0012\u00110\u0005¢\u0006\f\b3\u0012\b\b4\u0012\u0004\b\b(T\u0012\u0004\u0012\u00020\u00050WH\u0086\b\u00f8\u0001\u0000\u001aW\u0010«\u0001\u001a\u0004\u0018\u00010\u0005*\u00020\u00022<\u0010S\u001a8\u0012\u0013\u0012\u00110\"¢\u0006\f\b3\u0012\b\b4\u0012\u0004\b\b(,\u0012\u0004\u0012\u00020\u0005\u0012\u0013\u0012\u00110\u0005¢\u0006\f\b3\u0012\b\b4\u0012\u0004\b\b(T\u0012\u0004\u0012\u00020\u00050WH\u0087\b\u00f8\u0001\u0000¢\u0006\u0003\u0010¦\u0001\u001aB\u0010¬\u0001\u001a\u0004\u0018\u00010\u0005*\u00020\u00022'\u0010S\u001a#\u0012\u0004\u0012\u00020\u0005\u0012\u0013\u0012\u00110\u0005¢\u0006\f\b3\u0012\b\b4\u0012\u0004\b\b(T\u0012\u0004\u0012\u00020\u000502H\u0087\b\u00f8\u0001\u0000¢\u0006\u0003\u0010¨\u0001\u001a\u000b\u0010\u00ad\u0001\u001a\u00020\u0002*\u00020\u0002\u001a\u000e\u0010\u00ad\u0001\u001a\u00020 *\u00020 H\u0087\b\u001aT\u0010®\u0001\u001a\b\u0012\u0004\u0012\u0002H#0\u001f\"\u0004\b\u0000\u0010#*\u00020\u00022\u0006\u0010R\u001a\u0002H#2'\u0010S\u001a#\u0012\u0013\u0012\u0011H#¢\u0006\f\b3\u0012\b\b4\u0012\u0004\b\b(T\u0012\u0004\u0012\u00020\u0005\u0012\u0004\u0012\u0002H#02H\u0087\b\u00f8\u0001\u0000¢\u0006\u0003\u0010¯\u0001\u001ai\u0010°\u0001\u001a\b\u0012\u0004\u0012\u0002H#0\u001f\"\u0004\b\u0000\u0010#*\u00020\u00022\u0006\u0010R\u001a\u0002H#2<\u0010S\u001a8\u0012\u0013\u0012\u00110\"¢\u0006\f\b3\u0012\b\b4\u0012\u0004\b\b(,\u0012\u0013\u0012\u0011H#¢\u0006\f\b3\u0012\b\b4\u0012\u0004\b\b(T\u0012\u0004\u0012\u00020\u0005\u0012\u0004\u0012\u0002H#0WH\u0087\b\u00f8\u0001\u0000¢\u0006\u0003\u0010±\u0001\u001a@\u0010²\u0001\u001a\b\u0012\u0004\u0012\u00020\u00050\u001f*\u00020\u00022'\u0010S\u001a#\u0012\u0013\u0012\u00110\u0005¢\u0006\f\b3\u0012\b\b4\u0012\u0004\b\b(T\u0012\u0004\u0012\u00020\u0005\u0012\u0004\u0012\u00020\u000502H\u0087\b\u00f8\u0001\u0000\u001aU\u0010³\u0001\u001a\b\u0012\u0004\u0012\u00020\u00050\u001f*\u00020\u00022<\u0010S\u001a8\u0012\u0013\u0012\u00110\"¢\u0006\f\b3\u0012\b\b4\u0012\u0004\b\b(,\u0012\u0013\u0012\u00110\u0005¢\u0006\f\b3\u0012\b\b4\u0012\u0004\b\b(T\u0012\u0004\u0012\u00020\u0005\u0012\u0004\u0012\u00020\u00050WH\u0087\b\u00f8\u0001\u0000\u001aT\u0010´\u0001\u001a\b\u0012\u0004\u0012\u0002H#0\u001f\"\u0004\b\u0000\u0010#*\u00020\u00022\u0006\u0010R\u001a\u0002H#2'\u0010S\u001a#\u0012\u0013\u0012\u0011H#¢\u0006\f\b3\u0012\b\b4\u0012\u0004\b\b(T\u0012\u0004\u0012\u00020\u0005\u0012\u0004\u0012\u0002H#02H\u0087\b\u00f8\u0001\u0000¢\u0006\u0003\u0010¯\u0001\u001ai\u0010µ\u0001\u001a\b\u0012\u0004\u0012\u0002H#0\u001f\"\u0004\b\u0000\u0010#*\u00020\u00022\u0006\u0010R\u001a\u0002H#2<\u0010S\u001a8\u0012\u0013\u0012\u00110\"¢\u0006\f\b3\u0012\b\b4\u0012\u0004\b\b(,\u0012\u0013\u0012\u0011H#¢\u0006\f\b3\u0012\b\b4\u0012\u0004\b\b(T\u0012\u0004\u0012\u00020\u0005\u0012\u0004\u0012\u0002H#0WH\u0087\b\u00f8\u0001\u0000¢\u0006\u0003\u0010±\u0001\u001a\u000b\u0010¶\u0001\u001a\u00020\u0005*\u00020\u0002\u001a%\u0010¶\u0001\u001a\u00020\u0005*\u00020\u00022\u0012\u0010\u0003\u001a\u000e\u0012\u0004\u0012\u00020\u0005\u0012\u0004\u0012\u00020\u00010\u0004H\u0086\b\u00f8\u0001\u0000\u001a\u0012\u0010·\u0001\u001a\u0004\u0018\u00010\u0005*\u00020\u0002¢\u0006\u0002\u0010G\u001a,\u0010·\u0001\u001a\u0004\u0018\u00010\u0005*\u00020\u00022\u0012\u0010\u0003\u001a\u000e\u0012\u0004\u0012\u00020\u0005\u0012\u0004\u0012\u00020\u00010\u0004H\u0086\b\u00f8\u0001\u0000¢\u0006\u0002\u0010?\u001a\u001a\u0010¸\u0001\u001a\u00020\u0002*\u00020\u00022\r\u0010¹\u0001\u001a\b\u0012\u0004\u0012\u00020\"0\b\u001a\u0015\u0010¸\u0001\u001a\u00020\u0002*\u00020\u00022\b\u0010¹\u0001\u001a\u00030º\u0001\u001a\u001d\u0010¸\u0001\u001a\u00020 *\u00020 2\r\u0010¹\u0001\u001a\b\u0012\u0004\u0012\u00020\"0\bH\u0087\b\u001a\u0015\u0010¸\u0001\u001a\u00020 *\u00020 2\b\u0010¹\u0001\u001a\u00030º\u0001\u001a%\u0010»\u0001\u001a\u00020\"*\u00020\u00022\u0012\u0010v\u001a\u000e\u0012\u0004\u0012\u00020\u0005\u0012\u0004\u0012\u00020\"0\u0004H\u0087\b\u00f8\u0001\u0000\u001a%\u0010¼\u0001\u001a\u00020{*\u00020\u00022\u0012\u0010v\u001a\u000e\u0012\u0004\u0012\u00020\u0005\u0012\u0004\u0012\u00020{0\u0004H\u0087\b\u00f8\u0001\u0000\u001a+\u0010½\u0001\u001a\u00020{*\u00020\u00022\u0012\u0010v\u001a\u000e\u0012\u0004\u0012\u00020\u0005\u0012\u0004\u0012\u00020{0\u0004H\u0087\b\u00f8\u0001\u0000¢\u0006\u0003\b¾\u0001\u001a+\u0010½\u0001\u001a\u00020\"*\u00020\u00022\u0012\u0010v\u001a\u000e\u0012\u0004\u0012\u00020\u0005\u0012\u0004\u0012\u00020\"0\u0004H\u0087\b\u00f8\u0001\u0000¢\u0006\u0003\b¿\u0001\u001a-\u0010½\u0001\u001a\u00030\u00c0\u0001*\u00020\u00022\u0013\u0010v\u001a\u000f\u0012\u0004\u0012\u00020\u0005\u0012\u0005\u0012\u00030\u00c0\u00010\u0004H\u0087\b\u00f8\u0001\u0000¢\u0006\u0003\b\u00c1\u0001\u001a3\u0010½\u0001\u001a\u00030\u00c2\u0001*\u00020\u00022\u0013\u0010v\u001a\u000f\u0012\u0004\u0012\u00020\u0005\u0012\u0005\u0012\u00030\u00c2\u00010\u0004H\u0087\b\u00f8\u0001\u0000\u00f8\u0001\u0001¢\u0006\u0006\b\u00c3\u0001\u0010\u00c4\u0001\u001a3\u0010½\u0001\u001a\u00030\u00c5\u0001*\u00020\u00022\u0013\u0010v\u001a\u000f\u0012\u0004\u0012\u00020\u0005\u0012\u0005\u0012\u00030\u00c5\u00010\u0004H\u0087\b\u00f8\u0001\u0000\u00f8\u0001\u0001¢\u0006\u0006\b\u00c6\u0001\u0010\u00c7\u0001\u001a\u0013\u0010\u00c8\u0001\u001a\u00020\u0002*\u00020\u00022\u0006\u0010'\u001a\u00020\"\u001a\u0013\u0010\u00c8\u0001\u001a\u00020 *\u00020 2\u0006\u0010'\u001a\u00020\"\u001a\u0013\u0010\u00c9\u0001\u001a\u00020\u0002*\u00020\u00022\u0006\u0010'\u001a\u00020\"\u001a\u0013\u0010\u00c9\u0001\u001a\u00020 *\u00020 2\u0006\u0010'\u001a\u00020\"\u001a%\u0010\u00ca\u0001\u001a\u00020\u0002*\u00020\u00022\u0012\u0010\u0003\u001a\u000e\u0012\u0004\u0012\u00020\u0005\u0012\u0004\u0012\u00020\u00010\u0004H\u0086\b\u00f8\u0001\u0000\u001a%\u0010\u00ca\u0001\u001a\u00020 *\u00020 2\u0012\u0010\u0003\u001a\u000e\u0012\u0004\u0012\u00020\u0005\u0012\u0004\u0012\u00020\u00010\u0004H\u0086\b\u00f8\u0001\u0000\u001a%\u0010\u00cb\u0001\u001a\u00020\u0002*\u00020\u00022\u0012\u0010\u0003\u001a\u000e\u0012\u0004\u0012\u00020\u0005\u0012\u0004\u0012\u00020\u00010\u0004H\u0086\b\u00f8\u0001\u0000\u001a%\u0010\u00cb\u0001\u001a\u00020 *\u00020 2\u0012\u0010\u0003\u001a\u000e\u0012\u0004\u0012\u00020\u0005\u0012\u0004\u0012\u00020\u00010\u0004H\u0086\b\u00f8\u0001\u0000\u001a+\u0010\u00cc\u0001\u001a\u0002H6\"\u0010\b\u0000\u00106*\n\u0012\u0006\b\u0000\u0012\u00020\u00050L*\u00020\u00022\u0006\u0010\u0017\u001a\u0002H6¢\u0006\u0003\u0010\u00cd\u0001\u001a\u001d\u0010\u00ce\u0001\u001a\u0014\u0012\u0004\u0012\u00020\u00050\u00cf\u0001j\t\u0012\u0004\u0012\u00020\u0005`\u00d0\u0001*\u00020\u0002\u001a\u0011\u0010\u00d1\u0001\u001a\b\u0012\u0004\u0012\u00020\u00050\u001f*\u00020\u0002\u001a\u0011\u0010\u00d2\u0001\u001a\b\u0012\u0004\u0012\u00020\u00050c*\u00020\u0002\u001a\u0012\u0010\u00d3\u0001\u001a\t\u0012\u0004\u0012\u00020\u00050\u00d4\u0001*\u00020\u0002\u001a1\u0010\u00d5\u0001\u001a\b\u0012\u0004\u0012\u00020 0\u001f*\u00020\u00022\u0006\u0010!\u001a\u00020\"2\t\b\u0002\u0010\u00d6\u0001\u001a\u00020\"2\t\b\u0002\u0010\u00d7\u0001\u001a\u00020\u0001H\u0007\u001aK\u0010\u00d5\u0001\u001a\b\u0012\u0004\u0012\u0002H#0\u001f\"\u0004\b\u0000\u0010#*\u00020\u00022\u0006\u0010!\u001a\u00020\"2\t\b\u0002\u0010\u00d6\u0001\u001a\u00020\"2\t\b\u0002\u0010\u00d7\u0001\u001a\u00020\u00012\u0012\u0010\u000f\u001a\u000e\u0012\u0004\u0012\u00020\u0002\u0012\u0004\u0012\u0002H#0\u0004H\u0007\u001a1\u0010\u00d8\u0001\u001a\b\u0012\u0004\u0012\u00020 0\n*\u00020\u00022\u0006\u0010!\u001a\u00020\"2\t\b\u0002\u0010\u00d6\u0001\u001a\u00020\"2\t\b\u0002\u0010\u00d7\u0001\u001a\u00020\u0001H\u0007\u001aK\u0010\u00d8\u0001\u001a\b\u0012\u0004\u0012\u0002H#0\n\"\u0004\b\u0000\u0010#*\u00020\u00022\u0006\u0010!\u001a\u00020\"2\t\b\u0002\u0010\u00d6\u0001\u001a\u00020\"2\t\b\u0002\u0010\u00d7\u0001\u001a\u00020\u00012\u0012\u0010\u000f\u001a\u000e\u0012\u0004\u0012\u00020\u0002\u0012\u0004\u0012\u0002H#0\u0004H\u0007\u001a\u0018\u0010\u00d9\u0001\u001a\u000f\u0012\u000b\u0012\t\u0012\u0004\u0012\u00020\u00050\u00da\u00010\b*\u00020\u0002\u001a)\u0010\u00db\u0001\u001a\u0014\u0012\u0010\u0012\u000e\u0012\u0004\u0012\u00020\u0005\u0012\u0004\u0012\u00020\u00050\u00100\u001f*\u00020\u00022\u0007\u0010\u00dc\u0001\u001a\u00020\u0002H\u0086\u0004\u001a`\u0010\u00db\u0001\u001a\b\u0012\u0004\u0012\u0002H\u000e0\u001f\"\u0004\b\u0000\u0010\u000e*\u00020\u00022\u0007\u0010\u00dc\u0001\u001a\u00020\u000228\u0010\u000f\u001a4\u0012\u0014\u0012\u00120\u0005¢\u0006\r\b3\u0012\t\b4\u0012\u0005\b\b(\u00dd\u0001\u0012\u0014\u0012\u00120\u0005¢\u0006\r\b3\u0012\t\b4\u0012\u0005\b\b(\u00de\u0001\u0012\u0004\u0012\u0002H\u000e02H\u0086\b\u00f8\u0001\u0000\u001a\u001f\u0010\u00df\u0001\u001a\u0014\u0012\u0010\u0012\u000e\u0012\u0004\u0012\u00020\u0005\u0012\u0004\u0012\u00020\u00050\u00100\u001f*\u00020\u0002H\u0007\u001aW\u0010\u00df\u0001\u001a\b\u0012\u0004\u0012\u0002H#0\u001f\"\u0004\b\u0000\u0010#*\u00020\u000228\u0010\u000f\u001a4\u0012\u0014\u0012\u00120\u0005¢\u0006\r\b3\u0012\t\b4\u0012\u0005\b\b(\u00dd\u0001\u0012\u0014\u0012\u00120\u0005¢\u0006\r\b3\u0012\t\b4\u0012\u0005\b\b(\u00de\u0001\u0012\u0004\u0012\u0002H#02H\u0087\b\u00f8\u0001\u0000\u0082\u0002\u000b\n\u0005\b\u009920\u0001\n\u0002\b\u0019¨\u0006\u00e0\u0001" }, d2 = { "all", "", "", "predicate", "Lkotlin/Function1;", "", "any", "asIterable", "", "asSequence", "Lkotlin/sequences/Sequence;", "associate", "", "K", "V", "transform", "Lkotlin/Pair;", "associateBy", "keySelector", "valueTransform", "associateByTo", "M", "", "destination", "(Ljava/lang/CharSequence;Ljava/util/Map;Lkotlin/jvm/functions/Function1;)Ljava/util/Map;", "(Ljava/lang/CharSequence;Ljava/util/Map;Lkotlin/jvm/functions/Function1;Lkotlin/jvm/functions/Function1;)Ljava/util/Map;", "associateTo", "associateWith", "valueSelector", "associateWithTo", "chunked", "", "", "size", "", "R", "chunkedSequence", "count", "drop", "n", "dropLast", "dropLastWhile", "dropWhile", "elementAtOrElse", "index", "defaultValue", "elementAtOrNull", "(Ljava/lang/CharSequence;I)Ljava/lang/Character;", "filter", "filterIndexed", "Lkotlin/Function2;", "Lkotlin/ParameterName;", "name", "filterIndexedTo", "C", "Ljava/lang/Appendable;", "Lkotlin/text/Appendable;", "(Ljava/lang/CharSequence;Ljava/lang/Appendable;Lkotlin/jvm/functions/Function2;)Ljava/lang/Appendable;", "filterNot", "filterNotTo", "(Ljava/lang/CharSequence;Ljava/lang/Appendable;Lkotlin/jvm/functions/Function1;)Ljava/lang/Appendable;", "filterTo", "find", "(Ljava/lang/CharSequence;Lkotlin/jvm/functions/Function1;)Ljava/lang/Character;", "findLast", "first", "firstNotNullOf", "", "(Ljava/lang/CharSequence;Lkotlin/jvm/functions/Function1;)Ljava/lang/Object;", "firstNotNullOfOrNull", "firstOrNull", "(Ljava/lang/CharSequence;)Ljava/lang/Character;", "flatMap", "flatMapIndexed", "flatMapIndexedIterable", "flatMapIndexedTo", "", "flatMapIndexedIterableTo", "(Ljava/lang/CharSequence;Ljava/util/Collection;Lkotlin/jvm/functions/Function2;)Ljava/util/Collection;", "flatMapTo", "(Ljava/lang/CharSequence;Ljava/util/Collection;Lkotlin/jvm/functions/Function1;)Ljava/util/Collection;", "fold", "initial", "operation", "acc", "(Ljava/lang/CharSequence;Ljava/lang/Object;Lkotlin/jvm/functions/Function2;)Ljava/lang/Object;", "foldIndexed", "Lkotlin/Function3;", "(Ljava/lang/CharSequence;Ljava/lang/Object;Lkotlin/jvm/functions/Function3;)Ljava/lang/Object;", "foldRight", "foldRightIndexed", "forEach", "", "action", "forEachIndexed", "getOrElse", "getOrNull", "groupBy", "groupByTo", "", "groupingBy", "Lkotlin/collections/Grouping;", "indexOfFirst", "indexOfLast", "last", "lastOrNull", "map", "mapIndexed", "mapIndexedNotNull", "mapIndexedNotNullTo", "mapIndexedTo", "mapNotNull", "mapNotNullTo", "mapTo", "max", "maxOrThrow", "maxBy", "", "selector", "maxByOrThrow", "maxByOrNull", "maxOf", "(Ljava/lang/CharSequence;Lkotlin/jvm/functions/Function1;)Ljava/lang/Comparable;", "", "", "maxOfOrNull", "(Ljava/lang/CharSequence;Lkotlin/jvm/functions/Function1;)Ljava/lang/Double;", "(Ljava/lang/CharSequence;Lkotlin/jvm/functions/Function1;)Ljava/lang/Float;", "maxOfWith", "comparator", "Ljava/util/Comparator;", "Lkotlin/Comparator;", "(Ljava/lang/CharSequence;Ljava/util/Comparator;Lkotlin/jvm/functions/Function1;)Ljava/lang/Object;", "maxOfWithOrNull", "maxOrNull", "maxWith", "maxWithOrThrow", "maxWithOrNull", "(Ljava/lang/CharSequence;Ljava/util/Comparator;)Ljava/lang/Character;", "min", "minOrThrow", "minBy", "minByOrThrow", "minByOrNull", "minOf", "minOfOrNull", "minOfWith", "minOfWithOrNull", "minOrNull", "minWith", "minWithOrThrow", "minWithOrNull", "none", "onEach", "S", "(Ljava/lang/CharSequence;Lkotlin/jvm/functions/Function1;)Ljava/lang/CharSequence;", "onEachIndexed", "(Ljava/lang/CharSequence;Lkotlin/jvm/functions/Function2;)Ljava/lang/CharSequence;", "partition", "random", "Lkotlin/random/Random;", "randomOrNull", "(Ljava/lang/CharSequence;Lkotlin/random/Random;)Ljava/lang/Character;", "reduce", "reduceIndexed", "reduceIndexedOrNull", "(Ljava/lang/CharSequence;Lkotlin/jvm/functions/Function3;)Ljava/lang/Character;", "reduceOrNull", "(Ljava/lang/CharSequence;Lkotlin/jvm/functions/Function2;)Ljava/lang/Character;", "reduceRight", "reduceRightIndexed", "reduceRightIndexedOrNull", "reduceRightOrNull", "reversed", "runningFold", "(Ljava/lang/CharSequence;Ljava/lang/Object;Lkotlin/jvm/functions/Function2;)Ljava/util/List;", "runningFoldIndexed", "(Ljava/lang/CharSequence;Ljava/lang/Object;Lkotlin/jvm/functions/Function3;)Ljava/util/List;", "runningReduce", "runningReduceIndexed", "scan", "scanIndexed", "single", "singleOrNull", "slice", "indices", "Lkotlin/ranges/IntRange;", "sumBy", "sumByDouble", "sumOf", "sumOfDouble", "sumOfInt", "", "sumOfLong", "Lkotlin/UInt;", "sumOfUInt", "(Ljava/lang/CharSequence;Lkotlin/jvm/functions/Function1;)I", "Lkotlin/ULong;", "sumOfULong", "(Ljava/lang/CharSequence;Lkotlin/jvm/functions/Function1;)J", "take", "takeLast", "takeLastWhile", "takeWhile", "toCollection", "(Ljava/lang/CharSequence;Ljava/util/Collection;)Ljava/util/Collection;", "toHashSet", "Ljava/util/HashSet;", "Lkotlin/collections/HashSet;", "toList", "toMutableList", "toSet", "", "windowed", "step", "partialWindows", "windowedSequence", "withIndex", "Lkotlin/collections/IndexedValue;", "zip", "other", "a", "b", "zipWithNext", "kotlin-stdlib" }, xs = "kotlin/text/StringsKt")
class StringsKt___StringsKt extends StringsKt___StringsJvmKt
{
    @InlineOnly
    private static final char elementAtOrElse(final CharSequence $this$elementAtOrElse, final int index, final Function1<? super Integer, Character> defaultValue) {
        Intrinsics.checkNotNullParameter($this$elementAtOrElse, "<this>");
        Intrinsics.checkNotNullParameter(defaultValue, "defaultValue");
        return (index >= 0 && index <= StringsKt__StringsKt.getLastIndex($this$elementAtOrElse)) ? $this$elementAtOrElse.charAt(index) : defaultValue.invoke(index);
    }
    
    @InlineOnly
    private static final Character elementAtOrNull(final CharSequence $this$elementAtOrNull, final int index) {
        Intrinsics.checkNotNullParameter($this$elementAtOrNull, "<this>");
        return getOrNull($this$elementAtOrNull, index);
    }
    
    @InlineOnly
    private static final Character find(final CharSequence $this$find, final Function1<? super Character, Boolean> predicate) {
        Intrinsics.checkNotNullParameter($this$find, "<this>");
        Intrinsics.checkNotNullParameter(predicate, "predicate");
        final CharSequence $this$firstOrNull$iv = $this$find;
        final int $i$f$firstOrNull = 0;
        for (int i = 0; i < $this$firstOrNull$iv.length(); ++i) {
            final char element$iv = $this$firstOrNull$iv.charAt(i);
            if (predicate.invoke(element$iv)) {
                return element$iv;
            }
        }
        return null;
    }
    
    @InlineOnly
    private static final Character findLast(final CharSequence $this$findLast, final Function1<? super Character, Boolean> predicate) {
        Intrinsics.checkNotNullParameter($this$findLast, "<this>");
        Intrinsics.checkNotNullParameter(predicate, "predicate");
        final CharSequence $this$lastOrNull$iv = $this$findLast;
        final int $i$f$lastOrNull = 0;
        int n = $this$lastOrNull$iv.length() - 1;
        if (0 <= n) {
            do {
                final int index$iv = n;
                --n;
                final char element$iv = $this$lastOrNull$iv.charAt(index$iv);
                if (predicate.invoke(element$iv)) {
                    return element$iv;
                }
            } while (0 <= n);
        }
        return null;
    }
    
    public static final char first(@NotNull final CharSequence $this$first) {
        Intrinsics.checkNotNullParameter($this$first, "<this>");
        if ($this$first.length() == 0) {
            throw new NoSuchElementException("Char sequence is empty.");
        }
        return $this$first.charAt(0);
    }
    
    public static final char first(@NotNull final CharSequence $this$first, @NotNull final Function1<? super Character, Boolean> predicate) {
        Intrinsics.checkNotNullParameter($this$first, "<this>");
        Intrinsics.checkNotNullParameter(predicate, "predicate");
        final int $i$f$first = 0;
        for (int i = 0; i < $this$first.length(); ++i) {
            final char element = $this$first.charAt(i);
            if (predicate.invoke(element)) {
                return element;
            }
        }
        throw new NoSuchElementException("Char sequence contains no character matching the predicate.");
    }
    
    @SinceKotlin(version = "1.5")
    @InlineOnly
    private static final <R> R firstNotNullOf(final CharSequence $this$firstNotNullOf, final Function1<? super Character, ? extends R> transform) {
        Intrinsics.checkNotNullParameter($this$firstNotNullOf, "<this>");
        Intrinsics.checkNotNullParameter(transform, "transform");
        int i = 0;
        while (true) {
            while (i < $this$firstNotNullOf.length()) {
                final Object invoke;
                final Object o;
                if ((o = (invoke = transform.invoke($this$firstNotNullOf.charAt(i)))) == null) {
                    ++i;
                }
                else {
                    if (o == null) {
                        throw new NoSuchElementException("No element of the char sequence was transformed to a non-null value.");
                    }
                    return (R)invoke;
                }
            }
            Object o;
            Object invoke = o = null;
            continue;
        }
    }
    
    @SinceKotlin(version = "1.5")
    @InlineOnly
    private static final <R> R firstNotNullOfOrNull(final CharSequence $this$firstNotNullOfOrNull, final Function1<? super Character, ? extends R> transform) {
        Intrinsics.checkNotNullParameter($this$firstNotNullOfOrNull, "<this>");
        Intrinsics.checkNotNullParameter(transform, "transform");
        for (int i = 0; i < $this$firstNotNullOfOrNull.length(); ++i) {
            final char element = $this$firstNotNullOfOrNull.charAt(i);
            final Object result = transform.invoke(element);
            if (result != null) {
                return (R)result;
            }
        }
        return null;
    }
    
    @Nullable
    public static final Character firstOrNull(@NotNull final CharSequence $this$firstOrNull) {
        Intrinsics.checkNotNullParameter($this$firstOrNull, "<this>");
        return ($this$firstOrNull.length() == 0) ? null : Character.valueOf($this$firstOrNull.charAt(0));
    }
    
    @Nullable
    public static final Character firstOrNull(@NotNull final CharSequence $this$firstOrNull, @NotNull final Function1<? super Character, Boolean> predicate) {
        Intrinsics.checkNotNullParameter($this$firstOrNull, "<this>");
        Intrinsics.checkNotNullParameter(predicate, "predicate");
        final int $i$f$firstOrNull = 0;
        for (int i = 0; i < $this$firstOrNull.length(); ++i) {
            final char element = $this$firstOrNull.charAt(i);
            if (predicate.invoke(element)) {
                return element;
            }
        }
        return null;
    }
    
    @InlineOnly
    private static final char getOrElse(final CharSequence $this$getOrElse, final int index, final Function1<? super Integer, Character> defaultValue) {
        Intrinsics.checkNotNullParameter($this$getOrElse, "<this>");
        Intrinsics.checkNotNullParameter(defaultValue, "defaultValue");
        return (index >= 0 && index <= StringsKt__StringsKt.getLastIndex($this$getOrElse)) ? $this$getOrElse.charAt(index) : defaultValue.invoke(index);
    }
    
    @Nullable
    public static final Character getOrNull(@NotNull final CharSequence $this$getOrNull, final int index) {
        Intrinsics.checkNotNullParameter($this$getOrNull, "<this>");
        return (index >= 0 && index <= StringsKt__StringsKt.getLastIndex($this$getOrNull)) ? Character.valueOf($this$getOrNull.charAt(index)) : null;
    }
    
    public static final int indexOfFirst(@NotNull final CharSequence $this$indexOfFirst, @NotNull final Function1<? super Character, Boolean> predicate) {
        Intrinsics.checkNotNullParameter($this$indexOfFirst, "<this>");
        Intrinsics.checkNotNullParameter(predicate, "predicate");
        final int $i$f$indexOfFirst = 0;
        for (int index = 0; index < $this$indexOfFirst.length(); ++index) {
            if (predicate.invoke($this$indexOfFirst.charAt(index))) {
                return index;
            }
        }
        return -1;
    }
    
    public static final int indexOfLast(@NotNull final CharSequence $this$indexOfLast, @NotNull final Function1<? super Character, Boolean> predicate) {
        Intrinsics.checkNotNullParameter($this$indexOfLast, "<this>");
        Intrinsics.checkNotNullParameter(predicate, "predicate");
        final int $i$f$indexOfLast = 0;
        int n = $this$indexOfLast.length() - 1;
        if (0 <= n) {
            do {
                final int index = n;
                --n;
                if (predicate.invoke($this$indexOfLast.charAt(index))) {
                    return index;
                }
            } while (0 <= n);
        }
        return -1;
    }
    
    public static final char last(@NotNull final CharSequence $this$last) {
        Intrinsics.checkNotNullParameter($this$last, "<this>");
        if ($this$last.length() == 0) {
            throw new NoSuchElementException("Char sequence is empty.");
        }
        return $this$last.charAt(StringsKt__StringsKt.getLastIndex($this$last));
    }
    
    public static final char last(@NotNull final CharSequence $this$last, @NotNull final Function1<? super Character, Boolean> predicate) {
        Intrinsics.checkNotNullParameter($this$last, "<this>");
        Intrinsics.checkNotNullParameter(predicate, "predicate");
        final int $i$f$last = 0;
        int n = $this$last.length() - 1;
        if (0 <= n) {
            do {
                final int index = n;
                --n;
                final char element = $this$last.charAt(index);
                if (predicate.invoke(element)) {
                    return element;
                }
            } while (0 <= n);
        }
        throw new NoSuchElementException("Char sequence contains no character matching the predicate.");
    }
    
    @Nullable
    public static final Character lastOrNull(@NotNull final CharSequence $this$lastOrNull) {
        Intrinsics.checkNotNullParameter($this$lastOrNull, "<this>");
        return ($this$lastOrNull.length() == 0) ? null : Character.valueOf($this$lastOrNull.charAt($this$lastOrNull.length() - 1));
    }
    
    @Nullable
    public static final Character lastOrNull(@NotNull final CharSequence $this$lastOrNull, @NotNull final Function1<? super Character, Boolean> predicate) {
        Intrinsics.checkNotNullParameter($this$lastOrNull, "<this>");
        Intrinsics.checkNotNullParameter(predicate, "predicate");
        final int $i$f$lastOrNull = 0;
        int n = $this$lastOrNull.length() - 1;
        if (0 <= n) {
            do {
                final int index = n;
                --n;
                final char element = $this$lastOrNull.charAt(index);
                if (predicate.invoke(element)) {
                    return element;
                }
            } while (0 <= n);
        }
        return null;
    }
    
    @SinceKotlin(version = "1.3")
    @InlineOnly
    private static final char random(final CharSequence $this$random) {
        Intrinsics.checkNotNullParameter($this$random, "<this>");
        return random($this$random, Random.Default);
    }
    
    @SinceKotlin(version = "1.3")
    public static final char random(@NotNull final CharSequence $this$random, @NotNull final Random random) {
        Intrinsics.checkNotNullParameter($this$random, "<this>");
        Intrinsics.checkNotNullParameter(random, "random");
        if ($this$random.length() == 0) {
            throw new NoSuchElementException("Char sequence is empty.");
        }
        return $this$random.charAt(random.nextInt($this$random.length()));
    }
    
    @SinceKotlin(version = "1.4")
    @WasExperimental(markerClass = { ExperimentalStdlibApi.class })
    @InlineOnly
    private static final Character randomOrNull(final CharSequence $this$randomOrNull) {
        Intrinsics.checkNotNullParameter($this$randomOrNull, "<this>");
        return randomOrNull($this$randomOrNull, Random.Default);
    }
    
    @SinceKotlin(version = "1.4")
    @WasExperimental(markerClass = { ExperimentalStdlibApi.class })
    @Nullable
    public static final Character randomOrNull(@NotNull final CharSequence $this$randomOrNull, @NotNull final Random random) {
        Intrinsics.checkNotNullParameter($this$randomOrNull, "<this>");
        Intrinsics.checkNotNullParameter(random, "random");
        if ($this$randomOrNull.length() == 0) {
            return null;
        }
        return $this$randomOrNull.charAt(random.nextInt($this$randomOrNull.length()));
    }
    
    public static final char single(@NotNull final CharSequence $this$single) {
        Intrinsics.checkNotNullParameter($this$single, "<this>");
        switch ($this$single.length()) {
            case 0: {
                throw new NoSuchElementException("Char sequence is empty.");
            }
            case 1: {
                return $this$single.charAt(0);
            }
            default: {
                throw new IllegalArgumentException("Char sequence has more than one element.");
            }
        }
    }
    
    public static final char single(@NotNull final CharSequence $this$single, @NotNull final Function1<? super Character, Boolean> predicate) {
        Intrinsics.checkNotNullParameter($this$single, "<this>");
        Intrinsics.checkNotNullParameter(predicate, "predicate");
        final int $i$f$single = 0;
        Character single = null;
        boolean found = false;
        for (int i = 0; i < $this$single.length(); ++i) {
            final char element = $this$single.charAt(i);
            if (predicate.invoke(element)) {
                if (found) {
                    throw new IllegalArgumentException("Char sequence contains more than one matching element.");
                }
                single = element;
                found = true;
            }
        }
        if (!found) {
            throw new NoSuchElementException("Char sequence contains no character matching the predicate.");
        }
        final Character object = single;
        Intrinsics.checkNotNull(object, "null cannot be cast to non-null type kotlin.Char");
        return object;
    }
    
    @Nullable
    public static final Character singleOrNull(@NotNull final CharSequence $this$singleOrNull) {
        Intrinsics.checkNotNullParameter($this$singleOrNull, "<this>");
        return ($this$singleOrNull.length() == 1) ? Character.valueOf($this$singleOrNull.charAt(0)) : null;
    }
    
    @Nullable
    public static final Character singleOrNull(@NotNull final CharSequence $this$singleOrNull, @NotNull final Function1<? super Character, Boolean> predicate) {
        Intrinsics.checkNotNullParameter($this$singleOrNull, "<this>");
        Intrinsics.checkNotNullParameter(predicate, "predicate");
        final int $i$f$singleOrNull = 0;
        Character single = null;
        boolean found = false;
        for (int i = 0; i < $this$singleOrNull.length(); ++i) {
            final char element = $this$singleOrNull.charAt(i);
            if (predicate.invoke(element)) {
                if (found) {
                    return null;
                }
                single = element;
                found = true;
            }
        }
        if (!found) {
            return null;
        }
        return single;
    }
    
    @NotNull
    public static final CharSequence drop(@NotNull final CharSequence $this$drop, final int n) {
        Intrinsics.checkNotNullParameter($this$drop, "<this>");
        if (n < 0) {
            final int n2 = 0;
            throw new IllegalArgumentException(("Requested character count " + n + " is less than zero.").toString());
        }
        return $this$drop.subSequence(RangesKt___RangesKt.coerceAtMost(n, $this$drop.length()), $this$drop.length());
    }
    
    @NotNull
    public static final String drop(@NotNull final String $this$drop, final int n) {
        Intrinsics.checkNotNullParameter($this$drop, "<this>");
        if (n < 0) {
            final int n2 = 0;
            throw new IllegalArgumentException(("Requested character count " + n + " is less than zero.").toString());
        }
        final String substring = $this$drop.substring(RangesKt___RangesKt.coerceAtMost(n, $this$drop.length()));
        Intrinsics.checkNotNullExpressionValue(substring, "this as java.lang.String).substring(startIndex)");
        return substring;
    }
    
    @NotNull
    public static final CharSequence dropLast(@NotNull final CharSequence $this$dropLast, final int n) {
        Intrinsics.checkNotNullParameter($this$dropLast, "<this>");
        if (n < 0) {
            final int n2 = 0;
            throw new IllegalArgumentException(("Requested character count " + n + " is less than zero.").toString());
        }
        return take($this$dropLast, RangesKt___RangesKt.coerceAtLeast($this$dropLast.length() - n, 0));
    }
    
    @NotNull
    public static final String dropLast(@NotNull final String $this$dropLast, final int n) {
        Intrinsics.checkNotNullParameter($this$dropLast, "<this>");
        if (n < 0) {
            final int n2 = 0;
            throw new IllegalArgumentException(("Requested character count " + n + " is less than zero.").toString());
        }
        return take($this$dropLast, RangesKt___RangesKt.coerceAtLeast($this$dropLast.length() - n, 0));
    }
    
    @NotNull
    public static final CharSequence dropLastWhile(@NotNull final CharSequence $this$dropLastWhile, @NotNull final Function1<? super Character, Boolean> predicate) {
        Intrinsics.checkNotNullParameter($this$dropLastWhile, "<this>");
        Intrinsics.checkNotNullParameter(predicate, "predicate");
        final int $i$f$dropLastWhile = 0;
        for (int index = StringsKt__StringsKt.getLastIndex($this$dropLastWhile); -1 < index; --index) {
            if (!predicate.invoke($this$dropLastWhile.charAt(index))) {
                return $this$dropLastWhile.subSequence(0, index + 1);
            }
        }
        return "";
    }
    
    @NotNull
    public static final String dropLastWhile(@NotNull final String $this$dropLastWhile, @NotNull final Function1<? super Character, Boolean> predicate) {
        Intrinsics.checkNotNullParameter($this$dropLastWhile, "<this>");
        Intrinsics.checkNotNullParameter(predicate, "predicate");
        final int $i$f$dropLastWhile = 0;
        for (int index = StringsKt__StringsKt.getLastIndex($this$dropLastWhile); -1 < index; --index) {
            if (!predicate.invoke($this$dropLastWhile.charAt(index))) {
                final String substring = $this$dropLastWhile.substring(0, index + 1);
                Intrinsics.checkNotNullExpressionValue(substring, "this as java.lang.String\u2026ing(startIndex, endIndex)");
                return substring;
            }
        }
        return "";
    }
    
    @NotNull
    public static final CharSequence dropWhile(@NotNull final CharSequence $this$dropWhile, @NotNull final Function1<? super Character, Boolean> predicate) {
        Intrinsics.checkNotNullParameter($this$dropWhile, "<this>");
        Intrinsics.checkNotNullParameter(predicate, "predicate");
        final int $i$f$dropWhile = 0;
        for (int index = 0; index < $this$dropWhile.length(); ++index) {
            if (!predicate.invoke($this$dropWhile.charAt(index))) {
                return $this$dropWhile.subSequence(index, $this$dropWhile.length());
            }
        }
        return "";
    }
    
    @NotNull
    public static final String dropWhile(@NotNull final String $this$dropWhile, @NotNull final Function1<? super Character, Boolean> predicate) {
        Intrinsics.checkNotNullParameter($this$dropWhile, "<this>");
        Intrinsics.checkNotNullParameter(predicate, "predicate");
        final int $i$f$dropWhile = 0;
        for (int index = 0; index < $this$dropWhile.length(); ++index) {
            if (!predicate.invoke($this$dropWhile.charAt(index))) {
                final String substring = $this$dropWhile.substring(index);
                Intrinsics.checkNotNullExpressionValue(substring, "this as java.lang.String).substring(startIndex)");
                return substring;
            }
        }
        return "";
    }
    
    @NotNull
    public static final CharSequence filter(@NotNull final CharSequence $this$filter, @NotNull final Function1<? super Character, Boolean> predicate) {
        // 
        // This method could not be decompiled.
        // 
        // Original Bytecode:
        // 
        //     1: ldc             "<this>"
        //     3: invokestatic    kotlin/jvm/internal/Intrinsics.checkNotNullParameter:(Ljava/lang/Object;Ljava/lang/String;)V
        //     6: aload_1         /* predicate */
        //     7: ldc             "predicate"
        //     9: invokestatic    kotlin/jvm/internal/Intrinsics.checkNotNullParameter:(Ljava/lang/Object;Ljava/lang/String;)V
        //    12: iconst_0       
        //    13: istore_2        /* $i$f$filter */
        //    14: aload_0         /* $this$filter */
        //    15: astore_3       
        //    16: new             Ljava/lang/StringBuilder;
        //    19: dup            
        //    20: invokespecial   java/lang/StringBuilder.<init>:()V
        //    23: checkcast       Ljava/lang/Appendable;
        //    26: astore          destination$iv
        //    28: iconst_0       
        //    29: istore          $i$f$filterTo
        //    31: iconst_0       
        //    32: istore          index$iv
        //    34: aload_3         /* $this$filterTo$iv */
        //    35: invokeinterface java/lang/CharSequence.length:()I
        //    40: istore          7
        //    42: iload           index$iv
        //    44: iload           7
        //    46: if_icmpge       95
        //    49: aload_3         /* $this$filterTo$iv */
        //    50: iload           index$iv
        //    52: invokeinterface java/lang/CharSequence.charAt:(I)C
        //    57: istore          element$iv
        //    59: aload_1         /* predicate */
        //    60: iload           element$iv
        //    62: invokestatic    java/lang/Character.valueOf:(C)Ljava/lang/Character;
        //    65: invokeinterface kotlin/jvm/functions/Function1.invoke:(Ljava/lang/Object;)Ljava/lang/Object;
        //    70: checkcast       Ljava/lang/Boolean;
        //    73: invokevirtual   java/lang/Boolean.booleanValue:()Z
        //    76: ifeq            89
        //    79: aload           destination$iv
        //    81: iload           element$iv
        //    83: invokeinterface java/lang/Appendable.append:(C)Ljava/lang/Appendable;
        //    88: pop            
        //    89: iinc            index$iv, 1
        //    92: goto            42
        //    95: aload           destination$iv
        //    97: checkcast       Ljava/lang/CharSequence;
        //   100: areturn        
        //    Signature:
        //  (Ljava/lang/CharSequence;Lkotlin/jvm/functions/Function1<-Ljava/lang/Character;Ljava/lang/Boolean;>;)Ljava/lang/CharSequence;
        //    StackMapTable: 00 03 FF 00 2A 00 08 07 00 1A 07 00 26 01 07 00 1A 07 01 12 01 01 01 00 00 FC 00 2E 01 FA 00 05
        // 
        // The error that occurred was:
        // 
        // java.lang.NullPointerException
        // 
        throw new IllegalStateException("An error occurred while decompiling this method.");
    }
    
    @NotNull
    public static final String filter(@NotNull final String $this$filter, @NotNull final Function1<? super Character, Boolean> predicate) {
        // 
        // This method could not be decompiled.
        // 
        // Original Bytecode:
        // 
        //     1: ldc             "<this>"
        //     3: invokestatic    kotlin/jvm/internal/Intrinsics.checkNotNullParameter:(Ljava/lang/Object;Ljava/lang/String;)V
        //     6: aload_1         /* predicate */
        //     7: ldc             "predicate"
        //     9: invokestatic    kotlin/jvm/internal/Intrinsics.checkNotNullParameter:(Ljava/lang/Object;Ljava/lang/String;)V
        //    12: iconst_0       
        //    13: istore_2        /* $i$f$filter */
        //    14: aload_0         /* $this$filter */
        //    15: checkcast       Ljava/lang/CharSequence;
        //    18: astore_3       
        //    19: new             Ljava/lang/StringBuilder;
        //    22: dup            
        //    23: invokespecial   java/lang/StringBuilder.<init>:()V
        //    26: checkcast       Ljava/lang/Appendable;
        //    29: astore          destination$iv
        //    31: iconst_0       
        //    32: istore          $i$f$filterTo
        //    34: iconst_0       
        //    35: istore          index$iv
        //    37: aload_3         /* $this$filterTo$iv */
        //    38: invokeinterface java/lang/CharSequence.length:()I
        //    43: istore          7
        //    45: iload           index$iv
        //    47: iload           7
        //    49: if_icmpge       98
        //    52: aload_3         /* $this$filterTo$iv */
        //    53: iload           index$iv
        //    55: invokeinterface java/lang/CharSequence.charAt:(I)C
        //    60: istore          element$iv
        //    62: aload_1         /* predicate */
        //    63: iload           element$iv
        //    65: invokestatic    java/lang/Character.valueOf:(C)Ljava/lang/Character;
        //    68: invokeinterface kotlin/jvm/functions/Function1.invoke:(Ljava/lang/Object;)Ljava/lang/Object;
        //    73: checkcast       Ljava/lang/Boolean;
        //    76: invokevirtual   java/lang/Boolean.booleanValue:()Z
        //    79: ifeq            92
        //    82: aload           destination$iv
        //    84: iload           element$iv
        //    86: invokeinterface java/lang/Appendable.append:(C)Ljava/lang/Appendable;
        //    91: pop            
        //    92: iinc            index$iv, 1
        //    95: goto            45
        //    98: aload           destination$iv
        //   100: checkcast       Ljava/lang/StringBuilder;
        //   103: invokevirtual   java/lang/StringBuilder.toString:()Ljava/lang/String;
        //   106: dup            
        //   107: ldc_w           "filterTo(StringBuilder(), predicate).toString()"
        //   110: invokestatic    kotlin/jvm/internal/Intrinsics.checkNotNullExpressionValue:(Ljava/lang/Object;Ljava/lang/String;)V
        //   113: areturn        
        //    Signature:
        //  (Ljava/lang/String;Lkotlin/jvm/functions/Function1<-Ljava/lang/Character;Ljava/lang/Boolean;>;)Ljava/lang/String;
        //    StackMapTable: 00 03 FF 00 2D 00 08 07 00 E5 07 00 26 01 07 00 1A 07 01 12 01 01 01 00 00 FC 00 2E 01 FA 00 05
        // 
        // The error that occurred was:
        // 
        // java.lang.NullPointerException
        // 
        throw new IllegalStateException("An error occurred while decompiling this method.");
    }
    
    @NotNull
    public static final CharSequence filterIndexed(@NotNull final CharSequence $this$filterIndexed, @NotNull final Function2<? super Integer, ? super Character, Boolean> predicate) {
        // 
        // This method could not be decompiled.
        // 
        // Original Bytecode:
        // 
        //     1: ldc             "<this>"
        //     3: invokestatic    kotlin/jvm/internal/Intrinsics.checkNotNullParameter:(Ljava/lang/Object;Ljava/lang/String;)V
        //     6: aload_1         /* predicate */
        //     7: ldc             "predicate"
        //     9: invokestatic    kotlin/jvm/internal/Intrinsics.checkNotNullParameter:(Ljava/lang/Object;Ljava/lang/String;)V
        //    12: iconst_0       
        //    13: istore_2        /* $i$f$filterIndexed */
        //    14: aload_0         /* $this$filterIndexed */
        //    15: astore_3       
        //    16: new             Ljava/lang/StringBuilder;
        //    19: dup            
        //    20: invokespecial   java/lang/StringBuilder.<init>:()V
        //    23: checkcast       Ljava/lang/Appendable;
        //    26: astore          destination$iv
        //    28: iconst_0       
        //    29: istore          $i$f$filterIndexedTo
        //    31: aload_3         /* $this$filterIndexedTo$iv */
        //    32: astore          $this$forEachIndexed$iv$iv
        //    34: iconst_0       
        //    35: istore          $i$f$forEachIndexed
        //    37: iconst_0       
        //    38: istore          index$iv$iv
        //    40: iconst_0       
        //    41: istore          9
        //    43: iload           9
        //    45: aload           $this$forEachIndexed$iv$iv
        //    47: invokeinterface java/lang/CharSequence.length:()I
        //    52: if_icmpge       123
        //    55: aload           $this$forEachIndexed$iv$iv
        //    57: iload           9
        //    59: invokeinterface java/lang/CharSequence.charAt:(I)C
        //    64: istore          item$iv$iv
        //    66: iload           index$iv$iv
        //    68: iinc            index$iv$iv, 1
        //    71: iload           item$iv$iv
        //    73: istore          11
        //    75: istore          index$iv
        //    77: iconst_0       
        //    78: istore          $i$a$-forEachIndexed-StringsKt___StringsKt$filterIndexedTo$1$iv
        //    80: aload_1         /* predicate */
        //    81: iload           index$iv
        //    83: invokestatic    java/lang/Integer.valueOf:(I)Ljava/lang/Integer;
        //    86: iload           element$iv
        //    88: invokestatic    java/lang/Character.valueOf:(C)Ljava/lang/Character;
        //    91: invokeinterface kotlin/jvm/functions/Function2.invoke:(Ljava/lang/Object;Ljava/lang/Object;)Ljava/lang/Object;
        //    96: checkcast       Ljava/lang/Boolean;
        //    99: invokevirtual   java/lang/Boolean.booleanValue:()Z
        //   102: ifeq            115
        //   105: aload           destination$iv
        //   107: iload           element$iv
        //   109: invokeinterface java/lang/Appendable.append:(C)Ljava/lang/Appendable;
        //   114: pop            
        //   115: nop            
        //   116: nop            
        //   117: iinc            9, 1
        //   120: goto            43
        //   123: nop            
        //   124: aload           destination$iv
        //   126: checkcast       Ljava/lang/CharSequence;
        //   129: areturn        
        //    Signature:
        //  (Ljava/lang/CharSequence;Lkotlin/jvm/functions/Function2<-Ljava/lang/Integer;-Ljava/lang/Character;Ljava/lang/Boolean;>;)Ljava/lang/CharSequence;
        //    StackMapTable: 00 03 FF 00 2B 00 0A 07 00 1A 07 01 22 01 07 00 1A 07 01 12 01 07 00 1A 01 01 01 00 00 FF 00 47 00 0E 07 00 1A 07 01 22 01 07 00 1A 07 01 12 01 07 00 1A 01 01 01 01 01 01 01 00 00 FF 00 07 00 0A 07 00 1A 07 01 22 01 07 00 1A 07 01 12 01 07 00 1A 01 01 01 00 00
        // 
        // The error that occurred was:
        // 
        // java.lang.NullPointerException
        // 
        throw new IllegalStateException("An error occurred while decompiling this method.");
    }
    
    @NotNull
    public static final String filterIndexed(@NotNull final String $this$filterIndexed, @NotNull final Function2<? super Integer, ? super Character, Boolean> predicate) {
        // 
        // This method could not be decompiled.
        // 
        // Original Bytecode:
        // 
        //     1: ldc             "<this>"
        //     3: invokestatic    kotlin/jvm/internal/Intrinsics.checkNotNullParameter:(Ljava/lang/Object;Ljava/lang/String;)V
        //     6: aload_1         /* predicate */
        //     7: ldc             "predicate"
        //     9: invokestatic    kotlin/jvm/internal/Intrinsics.checkNotNullParameter:(Ljava/lang/Object;Ljava/lang/String;)V
        //    12: iconst_0       
        //    13: istore_2        /* $i$f$filterIndexed */
        //    14: aload_0         /* $this$filterIndexed */
        //    15: checkcast       Ljava/lang/CharSequence;
        //    18: astore_3       
        //    19: new             Ljava/lang/StringBuilder;
        //    22: dup            
        //    23: invokespecial   java/lang/StringBuilder.<init>:()V
        //    26: checkcast       Ljava/lang/Appendable;
        //    29: astore          destination$iv
        //    31: iconst_0       
        //    32: istore          $i$f$filterIndexedTo
        //    34: aload_3         /* $this$filterIndexedTo$iv */
        //    35: astore          $this$forEachIndexed$iv$iv
        //    37: iconst_0       
        //    38: istore          $i$f$forEachIndexed
        //    40: iconst_0       
        //    41: istore          index$iv$iv
        //    43: iconst_0       
        //    44: istore          9
        //    46: iload           9
        //    48: aload           $this$forEachIndexed$iv$iv
        //    50: invokeinterface java/lang/CharSequence.length:()I
        //    55: if_icmpge       126
        //    58: aload           $this$forEachIndexed$iv$iv
        //    60: iload           9
        //    62: invokeinterface java/lang/CharSequence.charAt:(I)C
        //    67: istore          item$iv$iv
        //    69: iload           index$iv$iv
        //    71: iinc            index$iv$iv, 1
        //    74: iload           item$iv$iv
        //    76: istore          11
        //    78: istore          index$iv
        //    80: iconst_0       
        //    81: istore          $i$a$-forEachIndexed-StringsKt___StringsKt$filterIndexedTo$1$iv
        //    83: aload_1         /* predicate */
        //    84: iload           index$iv
        //    86: invokestatic    java/lang/Integer.valueOf:(I)Ljava/lang/Integer;
        //    89: iload           element$iv
        //    91: invokestatic    java/lang/Character.valueOf:(C)Ljava/lang/Character;
        //    94: invokeinterface kotlin/jvm/functions/Function2.invoke:(Ljava/lang/Object;Ljava/lang/Object;)Ljava/lang/Object;
        //    99: checkcast       Ljava/lang/Boolean;
        //   102: invokevirtual   java/lang/Boolean.booleanValue:()Z
        //   105: ifeq            118
        //   108: aload           destination$iv
        //   110: iload           element$iv
        //   112: invokeinterface java/lang/Appendable.append:(C)Ljava/lang/Appendable;
        //   117: pop            
        //   118: nop            
        //   119: nop            
        //   120: iinc            9, 1
        //   123: goto            46
        //   126: nop            
        //   127: aload           destination$iv
        //   129: checkcast       Ljava/lang/StringBuilder;
        //   132: invokevirtual   java/lang/StringBuilder.toString:()Ljava/lang/String;
        //   135: dup            
        //   136: ldc_w           "filterIndexedTo(StringBu\u2026(), predicate).toString()"
        //   139: invokestatic    kotlin/jvm/internal/Intrinsics.checkNotNullExpressionValue:(Ljava/lang/Object;Ljava/lang/String;)V
        //   142: areturn        
        //    Signature:
        //  (Ljava/lang/String;Lkotlin/jvm/functions/Function2<-Ljava/lang/Integer;-Ljava/lang/Character;Ljava/lang/Boolean;>;)Ljava/lang/String;
        //    StackMapTable: 00 03 FF 00 2E 00 0A 07 00 E5 07 01 22 01 07 00 1A 07 01 12 01 07 00 1A 01 01 01 00 00 FF 00 47 00 0E 07 00 E5 07 01 22 01 07 00 1A 07 01 12 01 07 00 1A 01 01 01 01 01 01 01 00 00 FF 00 07 00 0A 07 00 E5 07 01 22 01 07 00 1A 07 01 12 01 07 00 1A 01 01 01 00 00
        // 
        // The error that occurred was:
        // 
        // java.lang.NullPointerException
        // 
        throw new IllegalStateException("An error occurred while decompiling this method.");
    }
    
    @NotNull
    public static final <C extends Appendable> C filterIndexedTo(@NotNull final CharSequence $this$filterIndexedTo, @NotNull final C destination, @NotNull final Function2<? super Integer, ? super Character, Boolean> predicate) {
        // 
        // This method could not be decompiled.
        // 
        // Original Bytecode:
        // 
        //     1: ldc             "<this>"
        //     3: invokestatic    kotlin/jvm/internal/Intrinsics.checkNotNullParameter:(Ljava/lang/Object;Ljava/lang/String;)V
        //     6: aload_1         /* destination */
        //     7: ldc_w           "destination"
        //    10: invokestatic    kotlin/jvm/internal/Intrinsics.checkNotNullParameter:(Ljava/lang/Object;Ljava/lang/String;)V
        //    13: aload_2         /* predicate */
        //    14: ldc             "predicate"
        //    16: invokestatic    kotlin/jvm/internal/Intrinsics.checkNotNullParameter:(Ljava/lang/Object;Ljava/lang/String;)V
        //    19: iconst_0       
        //    20: istore_3        /* $i$f$filterIndexedTo */
        //    21: aload_0         /* $this$filterIndexedTo */
        //    22: astore          $this$forEachIndexed$iv
        //    24: iconst_0       
        //    25: istore          $i$f$forEachIndexed
        //    27: iconst_0       
        //    28: istore          index$iv
        //    30: iconst_0       
        //    31: istore          7
        //    33: iload           7
        //    35: aload           $this$forEachIndexed$iv
        //    37: invokeinterface java/lang/CharSequence.length:()I
        //    42: if_icmpge       112
        //    45: aload           $this$forEachIndexed$iv
        //    47: iload           7
        //    49: invokeinterface java/lang/CharSequence.charAt:(I)C
        //    54: istore          item$iv
        //    56: iload           index$iv
        //    58: iinc            index$iv, 1
        //    61: iload           item$iv
        //    63: istore          9
        //    65: istore          index
        //    67: iconst_0       
        //    68: istore          $i$a$-forEachIndexed-StringsKt___StringsKt$filterIndexedTo$1
        //    70: aload_2         /* predicate */
        //    71: iload           index
        //    73: invokestatic    java/lang/Integer.valueOf:(I)Ljava/lang/Integer;
        //    76: iload           element
        //    78: invokestatic    java/lang/Character.valueOf:(C)Ljava/lang/Character;
        //    81: invokeinterface kotlin/jvm/functions/Function2.invoke:(Ljava/lang/Object;Ljava/lang/Object;)Ljava/lang/Object;
        //    86: checkcast       Ljava/lang/Boolean;
        //    89: invokevirtual   java/lang/Boolean.booleanValue:()Z
        //    92: ifeq            104
        //    95: aload_1         /* destination */
        //    96: iload           element
        //    98: invokeinterface java/lang/Appendable.append:(C)Ljava/lang/Appendable;
        //   103: pop            
        //   104: nop            
        //   105: nop            
        //   106: iinc            7, 1
        //   109: goto            33
        //   112: nop            
        //   113: aload_1         /* destination */
        //   114: areturn        
        //    Signature:
        //  <C::Ljava/lang/Appendable;>(Ljava/lang/CharSequence;TC;Lkotlin/jvm/functions/Function2<-Ljava/lang/Integer;-Ljava/lang/Character;Ljava/lang/Boolean;>;)TC;
        //    StackMapTable: 00 03 FF 00 21 00 08 07 00 1A 07 01 12 07 01 22 01 07 00 1A 01 01 01 00 00 FF 00 46 00 0C 07 00 1A 07 01 12 07 01 22 01 07 00 1A 01 01 01 01 01 01 01 00 00 FF 00 07 00 08 07 00 1A 07 01 12 07 01 22 01 07 00 1A 01 01 01 00 00
        // 
        // The error that occurred was:
        // 
        // java.lang.NullPointerException
        // 
        throw new IllegalStateException("An error occurred while decompiling this method.");
    }
    
    @NotNull
    public static final CharSequence filterNot(@NotNull final CharSequence $this$filterNot, @NotNull final Function1<? super Character, Boolean> predicate) {
        // 
        // This method could not be decompiled.
        // 
        // Original Bytecode:
        // 
        //     1: ldc             "<this>"
        //     3: invokestatic    kotlin/jvm/internal/Intrinsics.checkNotNullParameter:(Ljava/lang/Object;Ljava/lang/String;)V
        //     6: aload_1         /* predicate */
        //     7: ldc             "predicate"
        //     9: invokestatic    kotlin/jvm/internal/Intrinsics.checkNotNullParameter:(Ljava/lang/Object;Ljava/lang/String;)V
        //    12: iconst_0       
        //    13: istore_2        /* $i$f$filterNot */
        //    14: aload_0         /* $this$filterNot */
        //    15: astore_3       
        //    16: new             Ljava/lang/StringBuilder;
        //    19: dup            
        //    20: invokespecial   java/lang/StringBuilder.<init>:()V
        //    23: checkcast       Ljava/lang/Appendable;
        //    26: astore          destination$iv
        //    28: iconst_0       
        //    29: istore          $i$f$filterNotTo
        //    31: iconst_0       
        //    32: istore          6
        //    34: iload           6
        //    36: aload_3         /* $this$filterNotTo$iv */
        //    37: invokeinterface java/lang/CharSequence.length:()I
        //    42: if_icmpge       91
        //    45: aload_3         /* $this$filterNotTo$iv */
        //    46: iload           6
        //    48: invokeinterface java/lang/CharSequence.charAt:(I)C
        //    53: istore          element$iv
        //    55: aload_1         /* predicate */
        //    56: iload           element$iv
        //    58: invokestatic    java/lang/Character.valueOf:(C)Ljava/lang/Character;
        //    61: invokeinterface kotlin/jvm/functions/Function1.invoke:(Ljava/lang/Object;)Ljava/lang/Object;
        //    66: checkcast       Ljava/lang/Boolean;
        //    69: invokevirtual   java/lang/Boolean.booleanValue:()Z
        //    72: ifne            85
        //    75: aload           destination$iv
        //    77: iload           element$iv
        //    79: invokeinterface java/lang/Appendable.append:(C)Ljava/lang/Appendable;
        //    84: pop            
        //    85: iinc            6, 1
        //    88: goto            34
        //    91: aload           destination$iv
        //    93: checkcast       Ljava/lang/CharSequence;
        //    96: areturn        
        //    Signature:
        //  (Ljava/lang/CharSequence;Lkotlin/jvm/functions/Function1<-Ljava/lang/Character;Ljava/lang/Boolean;>;)Ljava/lang/CharSequence;
        //    StackMapTable: 00 03 FF 00 22 00 07 07 00 1A 07 00 26 01 07 00 1A 07 01 12 01 01 00 00 FC 00 32 01 FA 00 05
        // 
        // The error that occurred was:
        // 
        // java.lang.NullPointerException
        // 
        throw new IllegalStateException("An error occurred while decompiling this method.");
    }
    
    @NotNull
    public static final String filterNot(@NotNull final String $this$filterNot, @NotNull final Function1<? super Character, Boolean> predicate) {
        // 
        // This method could not be decompiled.
        // 
        // Original Bytecode:
        // 
        //     1: ldc             "<this>"
        //     3: invokestatic    kotlin/jvm/internal/Intrinsics.checkNotNullParameter:(Ljava/lang/Object;Ljava/lang/String;)V
        //     6: aload_1         /* predicate */
        //     7: ldc             "predicate"
        //     9: invokestatic    kotlin/jvm/internal/Intrinsics.checkNotNullParameter:(Ljava/lang/Object;Ljava/lang/String;)V
        //    12: iconst_0       
        //    13: istore_2        /* $i$f$filterNot */
        //    14: aload_0         /* $this$filterNot */
        //    15: checkcast       Ljava/lang/CharSequence;
        //    18: astore_3       
        //    19: new             Ljava/lang/StringBuilder;
        //    22: dup            
        //    23: invokespecial   java/lang/StringBuilder.<init>:()V
        //    26: checkcast       Ljava/lang/Appendable;
        //    29: astore          destination$iv
        //    31: iconst_0       
        //    32: istore          $i$f$filterNotTo
        //    34: iconst_0       
        //    35: istore          6
        //    37: iload           6
        //    39: aload_3         /* $this$filterNotTo$iv */
        //    40: invokeinterface java/lang/CharSequence.length:()I
        //    45: if_icmpge       94
        //    48: aload_3         /* $this$filterNotTo$iv */
        //    49: iload           6
        //    51: invokeinterface java/lang/CharSequence.charAt:(I)C
        //    56: istore          element$iv
        //    58: aload_1         /* predicate */
        //    59: iload           element$iv
        //    61: invokestatic    java/lang/Character.valueOf:(C)Ljava/lang/Character;
        //    64: invokeinterface kotlin/jvm/functions/Function1.invoke:(Ljava/lang/Object;)Ljava/lang/Object;
        //    69: checkcast       Ljava/lang/Boolean;
        //    72: invokevirtual   java/lang/Boolean.booleanValue:()Z
        //    75: ifne            88
        //    78: aload           destination$iv
        //    80: iload           element$iv
        //    82: invokeinterface java/lang/Appendable.append:(C)Ljava/lang/Appendable;
        //    87: pop            
        //    88: iinc            6, 1
        //    91: goto            37
        //    94: aload           destination$iv
        //    96: checkcast       Ljava/lang/StringBuilder;
        //    99: invokevirtual   java/lang/StringBuilder.toString:()Ljava/lang/String;
        //   102: dup            
        //   103: ldc_w           "filterNotTo(StringBuilder(), predicate).toString()"
        //   106: invokestatic    kotlin/jvm/internal/Intrinsics.checkNotNullExpressionValue:(Ljava/lang/Object;Ljava/lang/String;)V
        //   109: areturn        
        //    Signature:
        //  (Ljava/lang/String;Lkotlin/jvm/functions/Function1<-Ljava/lang/Character;Ljava/lang/Boolean;>;)Ljava/lang/String;
        //    StackMapTable: 00 03 FF 00 25 00 07 07 00 E5 07 00 26 01 07 00 1A 07 01 12 01 01 00 00 FC 00 32 01 FA 00 05
        // 
        // The error that occurred was:
        // 
        // java.lang.NullPointerException
        // 
        throw new IllegalStateException("An error occurred while decompiling this method.");
    }
    
    @NotNull
    public static final <C extends Appendable> C filterNotTo(@NotNull final CharSequence $this$filterNotTo, @NotNull final C destination, @NotNull final Function1<? super Character, Boolean> predicate) {
        Intrinsics.checkNotNullParameter($this$filterNotTo, "<this>");
        Intrinsics.checkNotNullParameter(destination, "destination");
        Intrinsics.checkNotNullParameter(predicate, "predicate");
        final int $i$f$filterNotTo = 0;
        for (int i = 0; i < $this$filterNotTo.length(); ++i) {
            final char element = $this$filterNotTo.charAt(i);
            if (!predicate.invoke(element)) {
                destination.append(element);
            }
        }
        return destination;
    }
    
    @NotNull
    public static final <C extends Appendable> C filterTo(@NotNull final CharSequence $this$filterTo, @NotNull final C destination, @NotNull final Function1<? super Character, Boolean> predicate) {
        Intrinsics.checkNotNullParameter($this$filterTo, "<this>");
        Intrinsics.checkNotNullParameter(destination, "destination");
        Intrinsics.checkNotNullParameter(predicate, "predicate");
        final int $i$f$filterTo = 0;
        for (int index = 0; index < $this$filterTo.length(); ++index) {
            final char element = $this$filterTo.charAt(index);
            if (predicate.invoke(element)) {
                destination.append(element);
            }
        }
        return destination;
    }
    
    @NotNull
    public static final CharSequence slice(@NotNull final CharSequence $this$slice, @NotNull final IntRange indices) {
        Intrinsics.checkNotNullParameter($this$slice, "<this>");
        Intrinsics.checkNotNullParameter(indices, "indices");
        if (indices.isEmpty()) {
            return "";
        }
        return StringsKt__StringsKt.subSequence($this$slice, indices);
    }
    
    @NotNull
    public static final String slice(@NotNull final String $this$slice, @NotNull final IntRange indices) {
        Intrinsics.checkNotNullParameter($this$slice, "<this>");
        Intrinsics.checkNotNullParameter(indices, "indices");
        if (indices.isEmpty()) {
            return "";
        }
        return StringsKt__StringsKt.substring($this$slice, indices);
    }
    
    @NotNull
    public static final CharSequence slice(@NotNull final CharSequence $this$slice, @NotNull final Iterable<Integer> indices) {
        Intrinsics.checkNotNullParameter($this$slice, "<this>");
        Intrinsics.checkNotNullParameter(indices, "indices");
        final int size = CollectionsKt__IterablesKt.collectionSizeOrDefault((Iterable<?>)indices, 10);
        if (size == 0) {
            return "";
        }
        final StringBuilder result = new StringBuilder(size);
        final Iterator<? extends T> iterator = indices.iterator();
        while (iterator.hasNext()) {
            final int i = ((Number)iterator.next()).intValue();
            result.append($this$slice.charAt(i));
        }
        return result;
    }
    
    @InlineOnly
    private static final String slice(final String $this$slice, final Iterable<Integer> indices) {
        Intrinsics.checkNotNullParameter($this$slice, "<this>");
        Intrinsics.checkNotNullParameter(indices, "indices");
        return slice((CharSequence)$this$slice, indices).toString();
    }
    
    @NotNull
    public static final CharSequence take(@NotNull final CharSequence $this$take, final int n) {
        Intrinsics.checkNotNullParameter($this$take, "<this>");
        if (n < 0) {
            final int n2 = 0;
            throw new IllegalArgumentException(("Requested character count " + n + " is less than zero.").toString());
        }
        return $this$take.subSequence(0, RangesKt___RangesKt.coerceAtMost(n, $this$take.length()));
    }
    
    @NotNull
    public static final String take(@NotNull final String $this$take, final int n) {
        Intrinsics.checkNotNullParameter($this$take, "<this>");
        if (n < 0) {
            final int n2 = 0;
            throw new IllegalArgumentException(("Requested character count " + n + " is less than zero.").toString());
        }
        final String substring = $this$take.substring(0, RangesKt___RangesKt.coerceAtMost(n, $this$take.length()));
        Intrinsics.checkNotNullExpressionValue(substring, "this as java.lang.String\u2026ing(startIndex, endIndex)");
        return substring;
    }
    
    @NotNull
    public static final CharSequence takeLast(@NotNull final CharSequence $this$takeLast, final int n) {
        Intrinsics.checkNotNullParameter($this$takeLast, "<this>");
        if (n < 0) {
            final int n2 = 0;
            throw new IllegalArgumentException(("Requested character count " + n + " is less than zero.").toString());
        }
        final int length = $this$takeLast.length();
        return $this$takeLast.subSequence(length - RangesKt___RangesKt.coerceAtMost(n, length), length);
    }
    
    @NotNull
    public static final String takeLast(@NotNull final String $this$takeLast, final int n) {
        Intrinsics.checkNotNullParameter($this$takeLast, "<this>");
        if (n < 0) {
            final int n2 = 0;
            throw new IllegalArgumentException(("Requested character count " + n + " is less than zero.").toString());
        }
        final int length = $this$takeLast.length();
        final String substring = $this$takeLast.substring(length - RangesKt___RangesKt.coerceAtMost(n, length));
        Intrinsics.checkNotNullExpressionValue(substring, "this as java.lang.String).substring(startIndex)");
        return substring;
    }
    
    @NotNull
    public static final CharSequence takeLastWhile(@NotNull final CharSequence $this$takeLastWhile, @NotNull final Function1<? super Character, Boolean> predicate) {
        Intrinsics.checkNotNullParameter($this$takeLastWhile, "<this>");
        Intrinsics.checkNotNullParameter(predicate, "predicate");
        final int $i$f$takeLastWhile = 0;
        for (int index = StringsKt__StringsKt.getLastIndex($this$takeLastWhile); -1 < index; --index) {
            if (!predicate.invoke($this$takeLastWhile.charAt(index))) {
                return $this$takeLastWhile.subSequence(index + 1, $this$takeLastWhile.length());
            }
        }
        return $this$takeLastWhile.subSequence(0, $this$takeLastWhile.length());
    }
    
    @NotNull
    public static final String takeLastWhile(@NotNull final String $this$takeLastWhile, @NotNull final Function1<? super Character, Boolean> predicate) {
        Intrinsics.checkNotNullParameter($this$takeLastWhile, "<this>");
        Intrinsics.checkNotNullParameter(predicate, "predicate");
        final int $i$f$takeLastWhile = 0;
        for (int index = StringsKt__StringsKt.getLastIndex($this$takeLastWhile); -1 < index; --index) {
            if (!predicate.invoke($this$takeLastWhile.charAt(index))) {
                final String substring = $this$takeLastWhile.substring(index + 1);
                Intrinsics.checkNotNullExpressionValue(substring, "this as java.lang.String).substring(startIndex)");
                return substring;
            }
        }
        return $this$takeLastWhile;
    }
    
    @NotNull
    public static final CharSequence takeWhile(@NotNull final CharSequence $this$takeWhile, @NotNull final Function1<? super Character, Boolean> predicate) {
        Intrinsics.checkNotNullParameter($this$takeWhile, "<this>");
        Intrinsics.checkNotNullParameter(predicate, "predicate");
        final int $i$f$takeWhile = 0;
        for (int index = 0; index < $this$takeWhile.length(); ++index) {
            if (!predicate.invoke($this$takeWhile.charAt(index))) {
                return $this$takeWhile.subSequence(0, index);
            }
        }
        return $this$takeWhile.subSequence(0, $this$takeWhile.length());
    }
    
    @NotNull
    public static final String takeWhile(@NotNull final String $this$takeWhile, @NotNull final Function1<? super Character, Boolean> predicate) {
        Intrinsics.checkNotNullParameter($this$takeWhile, "<this>");
        Intrinsics.checkNotNullParameter(predicate, "predicate");
        final int $i$f$takeWhile = 0;
        for (int index = 0; index < $this$takeWhile.length(); ++index) {
            if (!predicate.invoke($this$takeWhile.charAt(index))) {
                final String substring = $this$takeWhile.substring(0, index);
                Intrinsics.checkNotNullExpressionValue(substring, "this as java.lang.String\u2026ing(startIndex, endIndex)");
                return substring;
            }
        }
        return $this$takeWhile;
    }
    
    @NotNull
    public static final CharSequence reversed(@NotNull final CharSequence $this$reversed) {
        Intrinsics.checkNotNullParameter($this$reversed, "<this>");
        final StringBuilder reverse = new StringBuilder($this$reversed).reverse();
        Intrinsics.checkNotNullExpressionValue(reverse, "StringBuilder(this).reverse()");
        return reverse;
    }
    
    @InlineOnly
    private static final String reversed(final String $this$reversed) {
        Intrinsics.checkNotNullParameter($this$reversed, "<this>");
        return reversed((CharSequence)$this$reversed).toString();
    }
    
    @NotNull
    public static final <K, V> Map<K, V> associate(@NotNull final CharSequence $this$associate, @NotNull final Function1<? super Character, ? extends Pair<? extends K, ? extends V>> transform) {
        // 
        // This method could not be decompiled.
        // 
        // Original Bytecode:
        // 
        //     1: ldc             "<this>"
        //     3: invokestatic    kotlin/jvm/internal/Intrinsics.checkNotNullParameter:(Ljava/lang/Object;Ljava/lang/String;)V
        //     6: aload_1         /* transform */
        //     7: ldc             "transform"
        //     9: invokestatic    kotlin/jvm/internal/Intrinsics.checkNotNullParameter:(Ljava/lang/Object;Ljava/lang/String;)V
        //    12: iconst_0       
        //    13: istore_2        /* $i$f$associate */
        //    14: aload_0         /* $this$associate */
        //    15: invokeinterface java/lang/CharSequence.length:()I
        //    20: invokestatic    kotlin/collections/MapsKt.mapCapacity:(I)I
        //    23: bipush          16
        //    25: invokestatic    kotlin/ranges/RangesKt.coerceAtLeast:(II)I
        //    28: istore_3        /* capacity */
        //    29: aload_0         /* $this$associate */
        //    30: astore          4
        //    32: new             Ljava/util/LinkedHashMap;
        //    35: dup            
        //    36: iload_3         /* capacity */
        //    37: invokespecial   java/util/LinkedHashMap.<init>:(I)V
        //    40: checkcast       Ljava/util/Map;
        //    43: astore          destination$iv
        //    45: iconst_0       
        //    46: istore          $i$f$associateTo
        //    48: iconst_0       
        //    49: istore          7
        //    51: iload           7
        //    53: aload           $this$associateTo$iv
        //    55: invokeinterface java/lang/CharSequence.length:()I
        //    60: if_icmpge       118
        //    63: aload           $this$associateTo$iv
        //    65: iload           7
        //    67: invokeinterface java/lang/CharSequence.charAt:(I)C
        //    72: istore          element$iv
        //    74: aload           destination$iv
        //    76: astore          9
        //    78: aload_1         /* transform */
        //    79: iload           element$iv
        //    81: invokestatic    java/lang/Character.valueOf:(C)Ljava/lang/Character;
        //    84: invokeinterface kotlin/jvm/functions/Function1.invoke:(Ljava/lang/Object;)Ljava/lang/Object;
        //    89: checkcast       Lkotlin/Pair;
        //    92: astore          10
        //    94: aload           9
        //    96: aload           10
        //    98: invokevirtual   kotlin/Pair.getFirst:()Ljava/lang/Object;
        //   101: aload           10
        //   103: invokevirtual   kotlin/Pair.getSecond:()Ljava/lang/Object;
        //   106: invokeinterface java/util/Map.put:(Ljava/lang/Object;Ljava/lang/Object;)Ljava/lang/Object;
        //   111: pop            
        //   112: iinc            7, 1
        //   115: goto            51
        //   118: aload           destination$iv
        //   120: areturn        
        //    Signature:
        //  <K:Ljava/lang/Object;V:Ljava/lang/Object;>(Ljava/lang/CharSequence;Lkotlin/jvm/functions/Function1<-Ljava/lang/Character;+Lkotlin/Pair<+TK;+TV;>;>;)Ljava/util/Map<TK;TV;>;
        //    StackMapTable: 00 02 FF 00 33 00 08 07 00 1A 07 00 26 01 01 07 00 1A 07 01 AC 01 01 00 00 FB 00 42
        // 
        // The error that occurred was:
        // 
        // java.lang.NullPointerException
        // 
        throw new IllegalStateException("An error occurred while decompiling this method.");
    }
    
    @NotNull
    public static final <K> Map<K, Character> associateBy(@NotNull final CharSequence $this$associateBy, @NotNull final Function1<? super Character, ? extends K> keySelector) {
        // 
        // This method could not be decompiled.
        // 
        // Original Bytecode:
        // 
        //     1: ldc             "<this>"
        //     3: invokestatic    kotlin/jvm/internal/Intrinsics.checkNotNullParameter:(Ljava/lang/Object;Ljava/lang/String;)V
        //     6: aload_1         /* keySelector */
        //     7: ldc_w           "keySelector"
        //    10: invokestatic    kotlin/jvm/internal/Intrinsics.checkNotNullParameter:(Ljava/lang/Object;Ljava/lang/String;)V
        //    13: iconst_0       
        //    14: istore_2        /* $i$f$associateBy */
        //    15: aload_0         /* $this$associateBy */
        //    16: invokeinterface java/lang/CharSequence.length:()I
        //    21: invokestatic    kotlin/collections/MapsKt.mapCapacity:(I)I
        //    24: bipush          16
        //    26: invokestatic    kotlin/ranges/RangesKt.coerceAtLeast:(II)I
        //    29: istore_3        /* capacity */
        //    30: aload_0         /* $this$associateBy */
        //    31: astore          4
        //    33: new             Ljava/util/LinkedHashMap;
        //    36: dup            
        //    37: iload_3         /* capacity */
        //    38: invokespecial   java/util/LinkedHashMap.<init>:(I)V
        //    41: checkcast       Ljava/util/Map;
        //    44: astore          destination$iv
        //    46: iconst_0       
        //    47: istore          $i$f$associateByTo
        //    49: iconst_0       
        //    50: istore          7
        //    52: iload           7
        //    54: aload           $this$associateByTo$iv
        //    56: invokeinterface java/lang/CharSequence.length:()I
        //    61: if_icmpge       105
        //    64: aload           $this$associateByTo$iv
        //    66: iload           7
        //    68: invokeinterface java/lang/CharSequence.charAt:(I)C
        //    73: istore          element$iv
        //    75: aload           destination$iv
        //    77: aload_1         /* keySelector */
        //    78: iload           element$iv
        //    80: invokestatic    java/lang/Character.valueOf:(C)Ljava/lang/Character;
        //    83: invokeinterface kotlin/jvm/functions/Function1.invoke:(Ljava/lang/Object;)Ljava/lang/Object;
        //    88: iload           element$iv
        //    90: invokestatic    java/lang/Character.valueOf:(C)Ljava/lang/Character;
        //    93: invokeinterface java/util/Map.put:(Ljava/lang/Object;Ljava/lang/Object;)Ljava/lang/Object;
        //    98: pop            
        //    99: iinc            7, 1
        //   102: goto            52
        //   105: aload           destination$iv
        //   107: areturn        
        //    Signature:
        //  <K:Ljava/lang/Object;>(Ljava/lang/CharSequence;Lkotlin/jvm/functions/Function1<-Ljava/lang/Character;+TK;>;)Ljava/util/Map<TK;Ljava/lang/Character;>;
        //    StackMapTable: 00 02 FF 00 34 00 08 07 00 1A 07 00 26 01 01 07 00 1A 07 01 AC 01 01 00 00 34
        // 
        // The error that occurred was:
        // 
        // java.lang.NullPointerException
        // 
        throw new IllegalStateException("An error occurred while decompiling this method.");
    }
    
    @NotNull
    public static final <K, V> Map<K, V> associateBy(@NotNull final CharSequence $this$associateBy, @NotNull final Function1<? super Character, ? extends K> keySelector, @NotNull final Function1<? super Character, ? extends V> valueTransform) {
        // 
        // This method could not be decompiled.
        // 
        // Original Bytecode:
        // 
        //     1: ldc             "<this>"
        //     3: invokestatic    kotlin/jvm/internal/Intrinsics.checkNotNullParameter:(Ljava/lang/Object;Ljava/lang/String;)V
        //     6: aload_1         /* keySelector */
        //     7: ldc_w           "keySelector"
        //    10: invokestatic    kotlin/jvm/internal/Intrinsics.checkNotNullParameter:(Ljava/lang/Object;Ljava/lang/String;)V
        //    13: aload_2         /* valueTransform */
        //    14: ldc_w           "valueTransform"
        //    17: invokestatic    kotlin/jvm/internal/Intrinsics.checkNotNullParameter:(Ljava/lang/Object;Ljava/lang/String;)V
        //    20: iconst_0       
        //    21: istore_3        /* $i$f$associateBy */
        //    22: aload_0         /* $this$associateBy */
        //    23: invokeinterface java/lang/CharSequence.length:()I
        //    28: invokestatic    kotlin/collections/MapsKt.mapCapacity:(I)I
        //    31: bipush          16
        //    33: invokestatic    kotlin/ranges/RangesKt.coerceAtLeast:(II)I
        //    36: istore          capacity
        //    38: aload_0         /* $this$associateBy */
        //    39: astore          5
        //    41: new             Ljava/util/LinkedHashMap;
        //    44: dup            
        //    45: iload           capacity
        //    47: invokespecial   java/util/LinkedHashMap.<init>:(I)V
        //    50: checkcast       Ljava/util/Map;
        //    53: astore          destination$iv
        //    55: iconst_0       
        //    56: istore          $i$f$associateByTo
        //    58: iconst_0       
        //    59: istore          8
        //    61: iload           8
        //    63: aload           $this$associateByTo$iv
        //    65: invokeinterface java/lang/CharSequence.length:()I
        //    70: if_icmpge       120
        //    73: aload           $this$associateByTo$iv
        //    75: iload           8
        //    77: invokeinterface java/lang/CharSequence.charAt:(I)C
        //    82: istore          element$iv
        //    84: aload           destination$iv
        //    86: aload_1         /* keySelector */
        //    87: iload           element$iv
        //    89: invokestatic    java/lang/Character.valueOf:(C)Ljava/lang/Character;
        //    92: invokeinterface kotlin/jvm/functions/Function1.invoke:(Ljava/lang/Object;)Ljava/lang/Object;
        //    97: aload_2         /* valueTransform */
        //    98: iload           element$iv
        //   100: invokestatic    java/lang/Character.valueOf:(C)Ljava/lang/Character;
        //   103: invokeinterface kotlin/jvm/functions/Function1.invoke:(Ljava/lang/Object;)Ljava/lang/Object;
        //   108: invokeinterface java/util/Map.put:(Ljava/lang/Object;Ljava/lang/Object;)Ljava/lang/Object;
        //   113: pop            
        //   114: iinc            8, 1
        //   117: goto            61
        //   120: aload           destination$iv
        //   122: areturn        
        //    Signature:
        //  <K:Ljava/lang/Object;V:Ljava/lang/Object;>(Ljava/lang/CharSequence;Lkotlin/jvm/functions/Function1<-Ljava/lang/Character;+TK;>;Lkotlin/jvm/functions/Function1<-Ljava/lang/Character;+TV;>;)Ljava/util/Map<TK;TV;>;
        //    StackMapTable: 00 02 FF 00 3D 00 09 07 00 1A 07 00 26 07 00 26 01 01 07 00 1A 07 01 AC 01 01 00 00 3A
        // 
        // The error that occurred was:
        // 
        // java.lang.NullPointerException
        // 
        throw new IllegalStateException("An error occurred while decompiling this method.");
    }
    
    @NotNull
    public static final <K, M extends Map<? super K, ? super Character>> M associateByTo(@NotNull final CharSequence $this$associateByTo, @NotNull final M destination, @NotNull final Function1<? super Character, ? extends K> keySelector) {
        Intrinsics.checkNotNullParameter($this$associateByTo, "<this>");
        Intrinsics.checkNotNullParameter(destination, "destination");
        Intrinsics.checkNotNullParameter(keySelector, "keySelector");
        final int $i$f$associateByTo = 0;
        for (int i = 0; i < $this$associateByTo.length(); ++i) {
            final char element = $this$associateByTo.charAt(i);
            ((Map<? super K, Character>)destination).put((Object)keySelector.invoke(element), Character.valueOf(element));
        }
        return destination;
    }
    
    @NotNull
    public static final <K, V, M extends Map<? super K, ? super V>> M associateByTo(@NotNull final CharSequence $this$associateByTo, @NotNull final M destination, @NotNull final Function1<? super Character, ? extends K> keySelector, @NotNull final Function1<? super Character, ? extends V> valueTransform) {
        Intrinsics.checkNotNullParameter($this$associateByTo, "<this>");
        Intrinsics.checkNotNullParameter(destination, "destination");
        Intrinsics.checkNotNullParameter(keySelector, "keySelector");
        Intrinsics.checkNotNullParameter(valueTransform, "valueTransform");
        final int $i$f$associateByTo = 0;
        for (int i = 0; i < $this$associateByTo.length(); ++i) {
            final char element = $this$associateByTo.charAt(i);
            destination.put((Object)keySelector.invoke(element), (Object)valueTransform.invoke(element));
        }
        return destination;
    }
    
    @NotNull
    public static final <K, V, M extends Map<? super K, ? super V>> M associateTo(@NotNull final CharSequence $this$associateTo, @NotNull final M destination, @NotNull final Function1<? super Character, ? extends Pair<? extends K, ? extends V>> transform) {
        Intrinsics.checkNotNullParameter($this$associateTo, "<this>");
        Intrinsics.checkNotNullParameter(destination, "destination");
        Intrinsics.checkNotNullParameter(transform, "transform");
        final int $i$f$associateTo = 0;
        for (int i = 0; i < $this$associateTo.length(); ++i) {
            final char element = $this$associateTo.charAt(i);
            final Pair pair = (Pair)transform.invoke(element);
            destination.put(pair.getFirst(), (Object)pair.getSecond());
        }
        return destination;
    }
    
    @SinceKotlin(version = "1.3")
    @NotNull
    public static final <V> Map<Character, V> associateWith(@NotNull final CharSequence $this$associateWith, @NotNull final Function1<? super Character, ? extends V> valueSelector) {
        Intrinsics.checkNotNullParameter($this$associateWith, "<this>");
        Intrinsics.checkNotNullParameter(valueSelector, "valueSelector");
        final int $i$f$associateWith = 0;
        final LinkedHashMap result = new LinkedHashMap(RangesKt___RangesKt.coerceAtLeast(MapsKt__MapsJVMKt.mapCapacity(RangesKt___RangesKt.coerceAtMost($this$associateWith.length(), 128)), 16));
        final CharSequence $this$associateWithTo$iv = $this$associateWith;
        final int $i$f$associateWithTo = 0;
        for (int i = 0; i < $this$associateWithTo$iv.length(); ++i) {
            final char element$iv = $this$associateWithTo$iv.charAt(i);
            result.put(element$iv, valueSelector.invoke(element$iv));
        }
        return (Map<Character, V>)result;
    }
    
    @SinceKotlin(version = "1.3")
    @NotNull
    public static final <V, M extends Map<? super Character, ? super V>> M associateWithTo(@NotNull final CharSequence $this$associateWithTo, @NotNull final M destination, @NotNull final Function1<? super Character, ? extends V> valueSelector) {
        Intrinsics.checkNotNullParameter($this$associateWithTo, "<this>");
        Intrinsics.checkNotNullParameter(destination, "destination");
        Intrinsics.checkNotNullParameter(valueSelector, "valueSelector");
        final int $i$f$associateWithTo = 0;
        for (int i = 0; i < $this$associateWithTo.length(); ++i) {
            final char element = $this$associateWithTo.charAt(i);
            ((Map<Character, ? super V>)destination).put(Character.valueOf(element), (Object)valueSelector.invoke(element));
        }
        return destination;
    }
    
    @NotNull
    public static final <C extends Collection<? super Character>> C toCollection(@NotNull final CharSequence $this$toCollection, @NotNull final C destination) {
        Intrinsics.checkNotNullParameter($this$toCollection, "<this>");
        Intrinsics.checkNotNullParameter(destination, "destination");
        for (int i = 0; i < $this$toCollection.length(); ++i) {
            final char item = $this$toCollection.charAt(i);
            ((Collection<Character>)destination).add(item);
        }
        return destination;
    }
    
    @NotNull
    public static final HashSet<Character> toHashSet(@NotNull final CharSequence $this$toHashSet) {
        Intrinsics.checkNotNullParameter($this$toHashSet, "<this>");
        return toCollection($this$toHashSet, (HashSet<Character>)new HashSet<Object>(MapsKt__MapsJVMKt.mapCapacity(RangesKt___RangesKt.coerceAtMost($this$toHashSet.length(), 128))));
    }
    
    @NotNull
    public static final List<Character> toList(@NotNull final CharSequence $this$toList) {
        Intrinsics.checkNotNullParameter($this$toList, "<this>");
        List<Character> list = null;
        switch ($this$toList.length()) {
            case 0: {
                list = CollectionsKt__CollectionsKt.emptyList();
                break;
            }
            case 1: {
                list = CollectionsKt__CollectionsJVMKt.listOf($this$toList.charAt(0));
                break;
            }
            default: {
                list = toMutableList($this$toList);
                break;
            }
        }
        return list;
    }
    
    @NotNull
    public static final List<Character> toMutableList(@NotNull final CharSequence $this$toMutableList) {
        Intrinsics.checkNotNullParameter($this$toMutableList, "<this>");
        return toCollection($this$toMutableList, (List<Character>)new ArrayList<Object>($this$toMutableList.length()));
    }
    
    @NotNull
    public static final Set<Character> toSet(@NotNull final CharSequence $this$toSet) {
        Intrinsics.checkNotNullParameter($this$toSet, "<this>");
        Set<Character> set = null;
        switch ($this$toSet.length()) {
            case 0: {
                set = SetsKt__SetsKt.emptySet();
                break;
            }
            case 1: {
                set = SetsKt__SetsJVMKt.setOf($this$toSet.charAt(0));
                break;
            }
            default: {
                set = toCollection($this$toSet, (LinkedHashSet<Character>)new LinkedHashSet<Object>(MapsKt__MapsJVMKt.mapCapacity(RangesKt___RangesKt.coerceAtMost($this$toSet.length(), 128))));
                break;
            }
        }
        return set;
    }
    
    @NotNull
    public static final <R> List<R> flatMap(@NotNull final CharSequence $this$flatMap, @NotNull final Function1<? super Character, ? extends Iterable<? extends R>> transform) {
        // 
        // This method could not be decompiled.
        // 
        // Original Bytecode:
        // 
        //     1: ldc             "<this>"
        //     3: invokestatic    kotlin/jvm/internal/Intrinsics.checkNotNullParameter:(Ljava/lang/Object;Ljava/lang/String;)V
        //     6: aload_1         /* transform */
        //     7: ldc             "transform"
        //     9: invokestatic    kotlin/jvm/internal/Intrinsics.checkNotNullParameter:(Ljava/lang/Object;Ljava/lang/String;)V
        //    12: iconst_0       
        //    13: istore_2        /* $i$f$flatMap */
        //    14: aload_0         /* $this$flatMap */
        //    15: astore_3       
        //    16: new             Ljava/util/ArrayList;
        //    19: dup            
        //    20: invokespecial   java/util/ArrayList.<init>:()V
        //    23: checkcast       Ljava/util/Collection;
        //    26: astore          destination$iv
        //    28: iconst_0       
        //    29: istore          $i$f$flatMapTo
        //    31: iconst_0       
        //    32: istore          6
        //    34: iload           6
        //    36: aload_3         /* $this$flatMapTo$iv */
        //    37: invokeinterface java/lang/CharSequence.length:()I
        //    42: if_icmpge       85
        //    45: aload_3         /* $this$flatMapTo$iv */
        //    46: iload           6
        //    48: invokeinterface java/lang/CharSequence.charAt:(I)C
        //    53: istore          element$iv
        //    55: aload_1         /* transform */
        //    56: iload           element$iv
        //    58: invokestatic    java/lang/Character.valueOf:(C)Ljava/lang/Character;
        //    61: invokeinterface kotlin/jvm/functions/Function1.invoke:(Ljava/lang/Object;)Ljava/lang/Object;
        //    66: checkcast       Ljava/lang/Iterable;
        //    69: astore          list$iv
        //    71: aload           destination$iv
        //    73: aload           list$iv
        //    75: invokestatic    kotlin/collections/CollectionsKt.addAll:(Ljava/util/Collection;Ljava/lang/Iterable;)Z
        //    78: pop            
        //    79: iinc            6, 1
        //    82: goto            34
        //    85: aload           destination$iv
        //    87: checkcast       Ljava/util/List;
        //    90: areturn        
        //    Signature:
        //  <R:Ljava/lang/Object;>(Ljava/lang/CharSequence;Lkotlin/jvm/functions/Function1<-Ljava/lang/Character;+Ljava/lang/Iterable<+TR;>;>;)Ljava/util/List<TR;>;
        //    StackMapTable: 00 02 FF 00 22 00 07 07 00 1A 07 00 26 01 07 00 1A 07 01 E3 01 01 00 00 32
        // 
        // The error that occurred was:
        // 
        // java.lang.NullPointerException
        // 
        throw new IllegalStateException("An error occurred while decompiling this method.");
    }
    
    @SinceKotlin(version = "1.4")
    @OverloadResolutionByLambdaReturnType
    @JvmName(name = "flatMapIndexedIterable")
    @InlineOnly
    private static final <R> List<R> flatMapIndexedIterable(final CharSequence $this$flatMapIndexed, final Function2<? super Integer, ? super Character, ? extends Iterable<? extends R>> transform) {
        Intrinsics.checkNotNullParameter($this$flatMapIndexed, "<this>");
        Intrinsics.checkNotNullParameter(transform, "transform");
        final ArrayList<Object> $this$addAll = new ArrayList<Object>();
        int n = 0;
        for (int i = 0; i < $this$flatMapIndexed.length(); ++i) {
            CollectionsKt__MutableCollectionsKt.addAll((Collection<? super Object>)$this$addAll, (Iterable<?>)transform.invoke(n++, $this$flatMapIndexed.charAt(i)));
        }
        return (List<R>)$this$addAll;
    }
    
    @SinceKotlin(version = "1.4")
    @OverloadResolutionByLambdaReturnType
    @JvmName(name = "flatMapIndexedIterableTo")
    @InlineOnly
    private static final <R, C extends Collection<? super R>> C flatMapIndexedIterableTo(final CharSequence $this$flatMapIndexedTo, final C destination, final Function2<? super Integer, ? super Character, ? extends Iterable<? extends R>> transform) {
        Intrinsics.checkNotNullParameter($this$flatMapIndexedTo, "<this>");
        Intrinsics.checkNotNullParameter(destination, "destination");
        Intrinsics.checkNotNullParameter(transform, "transform");
        int index = 0;
        for (int i = 0; i < $this$flatMapIndexedTo.length(); ++i) {
            final char element = $this$flatMapIndexedTo.charAt(i);
            final Iterable list = (Iterable)transform.invoke(index++, element);
            CollectionsKt__MutableCollectionsKt.addAll((Collection<? super Object>)destination, (Iterable<?>)list);
        }
        return destination;
    }
    
    @NotNull
    public static final <R, C extends Collection<? super R>> C flatMapTo(@NotNull final CharSequence $this$flatMapTo, @NotNull final C destination, @NotNull final Function1<? super Character, ? extends Iterable<? extends R>> transform) {
        Intrinsics.checkNotNullParameter($this$flatMapTo, "<this>");
        Intrinsics.checkNotNullParameter(destination, "destination");
        Intrinsics.checkNotNullParameter(transform, "transform");
        final int $i$f$flatMapTo = 0;
        for (int i = 0; i < $this$flatMapTo.length(); ++i) {
            final char element = $this$flatMapTo.charAt(i);
            final Iterable list = (Iterable)transform.invoke(element);
            CollectionsKt__MutableCollectionsKt.addAll((Collection<? super Object>)destination, (Iterable<?>)list);
        }
        return destination;
    }
    
    @NotNull
    public static final <K> Map<K, List<Character>> groupBy(@NotNull final CharSequence $this$groupBy, @NotNull final Function1<? super Character, ? extends K> keySelector) {
        // 
        // This method could not be decompiled.
        // 
        // Original Bytecode:
        // 
        //     1: ldc             "<this>"
        //     3: invokestatic    kotlin/jvm/internal/Intrinsics.checkNotNullParameter:(Ljava/lang/Object;Ljava/lang/String;)V
        //     6: aload_1         /* keySelector */
        //     7: ldc_w           "keySelector"
        //    10: invokestatic    kotlin/jvm/internal/Intrinsics.checkNotNullParameter:(Ljava/lang/Object;Ljava/lang/String;)V
        //    13: iconst_0       
        //    14: istore_2        /* $i$f$groupBy */
        //    15: aload_0         /* $this$groupBy */
        //    16: astore_3       
        //    17: new             Ljava/util/LinkedHashMap;
        //    20: dup            
        //    21: invokespecial   java/util/LinkedHashMap.<init>:()V
        //    24: checkcast       Ljava/util/Map;
        //    27: astore          destination$iv
        //    29: iconst_0       
        //    30: istore          $i$f$groupByTo
        //    32: iconst_0       
        //    33: istore          6
        //    35: iload           6
        //    37: aload_3         /* $this$groupByTo$iv */
        //    38: invokeinterface java/lang/CharSequence.length:()I
        //    43: if_icmpge       151
        //    46: aload_3         /* $this$groupByTo$iv */
        //    47: iload           6
        //    49: invokeinterface java/lang/CharSequence.charAt:(I)C
        //    54: istore          element$iv
        //    56: aload_1         /* keySelector */
        //    57: iload           element$iv
        //    59: invokestatic    java/lang/Character.valueOf:(C)Ljava/lang/Character;
        //    62: invokeinterface kotlin/jvm/functions/Function1.invoke:(Ljava/lang/Object;)Ljava/lang/Object;
        //    67: astore          key$iv
        //    69: aload           destination$iv
        //    71: astore          $this$getOrPut$iv$iv
        //    73: iconst_0       
        //    74: istore          $i$f$getOrPut
        //    76: aload           $this$getOrPut$iv$iv
        //    78: aload           key$iv
        //    80: invokeinterface java/util/Map.get:(Ljava/lang/Object;)Ljava/lang/Object;
        //    85: astore          value$iv$iv
        //    87: aload           value$iv$iv
        //    89: ifnonnull       124
        //    92: iconst_0       
        //    93: istore          $i$a$-getOrPut-StringsKt___StringsKt$groupByTo$list$1$iv
        //    95: new             Ljava/util/ArrayList;
        //    98: dup            
        //    99: invokespecial   java/util/ArrayList.<init>:()V
        //   102: checkcast       Ljava/util/List;
        //   105: astore          answer$iv$iv
        //   107: aload           $this$getOrPut$iv$iv
        //   109: aload           key$iv
        //   111: aload           answer$iv$iv
        //   113: invokeinterface java/util/Map.put:(Ljava/lang/Object;Ljava/lang/Object;)Ljava/lang/Object;
        //   118: pop            
        //   119: aload           answer$iv$iv
        //   121: goto            126
        //   124: aload           value$iv$iv
        //   126: nop            
        //   127: checkcast       Ljava/util/List;
        //   130: astore          list$iv
        //   132: aload           list$iv
        //   134: iload           element$iv
        //   136: invokestatic    java/lang/Character.valueOf:(C)Ljava/lang/Character;
        //   139: invokeinterface java/util/List.add:(Ljava/lang/Object;)Z
        //   144: pop            
        //   145: iinc            6, 1
        //   148: goto            35
        //   151: aload           destination$iv
        //   153: areturn        
        //    Signature:
        //  <K:Ljava/lang/Object;>(Ljava/lang/CharSequence;Lkotlin/jvm/functions/Function1<-Ljava/lang/Character;+TK;>;)Ljava/util/Map<TK;Ljava/util/List<Ljava/lang/Character;>;>;
        //    StackMapTable: 00 04 FF 00 23 00 07 07 00 1A 07 00 26 01 07 00 1A 07 01 AC 01 01 00 00 FF 00 58 00 0C 07 00 1A 07 00 26 01 07 00 1A 07 01 AC 01 01 01 07 00 76 07 01 AC 01 07 00 76 00 00 41 07 00 76 FF 00 18 00 07 07 00 1A 07 00 26 01 07 00 1A 07 01 AC 01 01 00 00
        // 
        // The error that occurred was:
        // 
        // java.lang.NullPointerException
        // 
        throw new IllegalStateException("An error occurred while decompiling this method.");
    }
    
    @NotNull
    public static final <K, V> Map<K, List<V>> groupBy(@NotNull final CharSequence $this$groupBy, @NotNull final Function1<? super Character, ? extends K> keySelector, @NotNull final Function1<? super Character, ? extends V> valueTransform) {
        // 
        // This method could not be decompiled.
        // 
        // Original Bytecode:
        // 
        //     1: ldc             "<this>"
        //     3: invokestatic    kotlin/jvm/internal/Intrinsics.checkNotNullParameter:(Ljava/lang/Object;Ljava/lang/String;)V
        //     6: aload_1         /* keySelector */
        //     7: ldc_w           "keySelector"
        //    10: invokestatic    kotlin/jvm/internal/Intrinsics.checkNotNullParameter:(Ljava/lang/Object;Ljava/lang/String;)V
        //    13: aload_2         /* valueTransform */
        //    14: ldc_w           "valueTransform"
        //    17: invokestatic    kotlin/jvm/internal/Intrinsics.checkNotNullParameter:(Ljava/lang/Object;Ljava/lang/String;)V
        //    20: iconst_0       
        //    21: istore_3        /* $i$f$groupBy */
        //    22: aload_0         /* $this$groupBy */
        //    23: astore          4
        //    25: new             Ljava/util/LinkedHashMap;
        //    28: dup            
        //    29: invokespecial   java/util/LinkedHashMap.<init>:()V
        //    32: checkcast       Ljava/util/Map;
        //    35: astore          destination$iv
        //    37: iconst_0       
        //    38: istore          $i$f$groupByTo
        //    40: iconst_0       
        //    41: istore          7
        //    43: iload           7
        //    45: aload           $this$groupByTo$iv
        //    47: invokeinterface java/lang/CharSequence.length:()I
        //    52: if_icmpge       167
        //    55: aload           $this$groupByTo$iv
        //    57: iload           7
        //    59: invokeinterface java/lang/CharSequence.charAt:(I)C
        //    64: istore          element$iv
        //    66: aload_1         /* keySelector */
        //    67: iload           element$iv
        //    69: invokestatic    java/lang/Character.valueOf:(C)Ljava/lang/Character;
        //    72: invokeinterface kotlin/jvm/functions/Function1.invoke:(Ljava/lang/Object;)Ljava/lang/Object;
        //    77: astore          key$iv
        //    79: aload           destination$iv
        //    81: astore          $this$getOrPut$iv$iv
        //    83: iconst_0       
        //    84: istore          $i$f$getOrPut
        //    86: aload           $this$getOrPut$iv$iv
        //    88: aload           key$iv
        //    90: invokeinterface java/util/Map.get:(Ljava/lang/Object;)Ljava/lang/Object;
        //    95: astore          value$iv$iv
        //    97: aload           value$iv$iv
        //    99: ifnonnull       134
        //   102: iconst_0       
        //   103: istore          $i$a$-getOrPut-StringsKt___StringsKt$groupByTo$list$2$iv
        //   105: new             Ljava/util/ArrayList;
        //   108: dup            
        //   109: invokespecial   java/util/ArrayList.<init>:()V
        //   112: checkcast       Ljava/util/List;
        //   115: astore          answer$iv$iv
        //   117: aload           $this$getOrPut$iv$iv
        //   119: aload           key$iv
        //   121: aload           answer$iv$iv
        //   123: invokeinterface java/util/Map.put:(Ljava/lang/Object;Ljava/lang/Object;)Ljava/lang/Object;
        //   128: pop            
        //   129: aload           answer$iv$iv
        //   131: goto            136
        //   134: aload           value$iv$iv
        //   136: nop            
        //   137: checkcast       Ljava/util/List;
        //   140: astore          list$iv
        //   142: aload           list$iv
        //   144: aload_2         /* valueTransform */
        //   145: iload           element$iv
        //   147: invokestatic    java/lang/Character.valueOf:(C)Ljava/lang/Character;
        //   150: invokeinterface kotlin/jvm/functions/Function1.invoke:(Ljava/lang/Object;)Ljava/lang/Object;
        //   155: invokeinterface java/util/List.add:(Ljava/lang/Object;)Z
        //   160: pop            
        //   161: iinc            7, 1
        //   164: goto            43
        //   167: aload           destination$iv
        //   169: areturn        
        //    Signature:
        //  <K:Ljava/lang/Object;V:Ljava/lang/Object;>(Ljava/lang/CharSequence;Lkotlin/jvm/functions/Function1<-Ljava/lang/Character;+TK;>;Lkotlin/jvm/functions/Function1<-Ljava/lang/Character;+TV;>;)Ljava/util/Map<TK;Ljava/util/List<TV;>;>;
        //    StackMapTable: 00 04 FF 00 2B 00 08 07 00 1A 07 00 26 07 00 26 01 07 00 1A 07 01 AC 01 01 00 00 FF 00 5A 00 0D 07 00 1A 07 00 26 07 00 26 01 07 00 1A 07 01 AC 01 01 01 07 00 76 07 01 AC 01 07 00 76 00 00 41 07 00 76 FF 00 1E 00 08 07 00 1A 07 00 26 07 00 26 01 07 00 1A 07 01 AC 01 01 00 00
        // 
        // The error that occurred was:
        // 
        // java.lang.NullPointerException
        // 
        throw new IllegalStateException("An error occurred while decompiling this method.");
    }
    
    @NotNull
    public static final <K, M extends Map<? super K, List<Character>>> M groupByTo(@NotNull final CharSequence $this$groupByTo, @NotNull final M destination, @NotNull final Function1<? super Character, ? extends K> keySelector) {
        Intrinsics.checkNotNullParameter($this$groupByTo, "<this>");
        Intrinsics.checkNotNullParameter(destination, "destination");
        Intrinsics.checkNotNullParameter(keySelector, "keySelector");
        final int $i$f$groupByTo = 0;
        for (int i = 0; i < $this$groupByTo.length(); ++i) {
            final char element = $this$groupByTo.charAt(i);
            final Object key = keySelector.invoke(element);
            final Map $this$getOrPut$iv = destination;
            final int $i$f$getOrPut = 0;
            final Object value$iv = $this$getOrPut$iv.get(key);
            Object o;
            if (value$iv == null) {
                final int n = 0;
                final Object answer$iv = new ArrayList<Object>();
                $this$getOrPut$iv.put(key, answer$iv);
                o = answer$iv;
            }
            else {
                o = value$iv;
            }
            final List list = (List)o;
            list.add(element);
        }
        return destination;
    }
    
    @NotNull
    public static final <K, V, M extends Map<? super K, List<V>>> M groupByTo(@NotNull final CharSequence $this$groupByTo, @NotNull final M destination, @NotNull final Function1<? super Character, ? extends K> keySelector, @NotNull final Function1<? super Character, ? extends V> valueTransform) {
        Intrinsics.checkNotNullParameter($this$groupByTo, "<this>");
        Intrinsics.checkNotNullParameter(destination, "destination");
        Intrinsics.checkNotNullParameter(keySelector, "keySelector");
        Intrinsics.checkNotNullParameter(valueTransform, "valueTransform");
        final int $i$f$groupByTo = 0;
        for (int i = 0; i < $this$groupByTo.length(); ++i) {
            final char element = $this$groupByTo.charAt(i);
            final Object key = keySelector.invoke(element);
            final Map $this$getOrPut$iv = destination;
            final int $i$f$getOrPut = 0;
            final Object value$iv = $this$getOrPut$iv.get(key);
            Object o;
            if (value$iv == null) {
                final int n = 0;
                final Object answer$iv = new ArrayList<Object>();
                $this$getOrPut$iv.put(key, answer$iv);
                o = answer$iv;
            }
            else {
                o = value$iv;
            }
            final List list = (List)o;
            list.add(valueTransform.invoke(element));
        }
        return destination;
    }
    
    @SinceKotlin(version = "1.1")
    @NotNull
    public static final <K> Grouping<Character, K> groupingBy(@NotNull final CharSequence $this$groupingBy, @NotNull final Function1<? super Character, ? extends K> keySelector) {
        Intrinsics.checkNotNullParameter($this$groupingBy, "<this>");
        Intrinsics.checkNotNullParameter(keySelector, "keySelector");
        final int $i$f$groupingBy = 0;
        return (Grouping<Character, K>)new StringsKt___StringsKt$groupingBy.StringsKt___StringsKt$groupingBy$1($this$groupingBy, (Function1)keySelector);
    }
    
    @NotNull
    public static final <R> List<R> map(@NotNull final CharSequence $this$map, @NotNull final Function1<? super Character, ? extends R> transform) {
        // 
        // This method could not be decompiled.
        // 
        // Original Bytecode:
        // 
        //     1: ldc             "<this>"
        //     3: invokestatic    kotlin/jvm/internal/Intrinsics.checkNotNullParameter:(Ljava/lang/Object;Ljava/lang/String;)V
        //     6: aload_1         /* transform */
        //     7: ldc             "transform"
        //     9: invokestatic    kotlin/jvm/internal/Intrinsics.checkNotNullParameter:(Ljava/lang/Object;Ljava/lang/String;)V
        //    12: iconst_0       
        //    13: istore_2        /* $i$f$map */
        //    14: aload_0         /* $this$map */
        //    15: astore_3       
        //    16: new             Ljava/util/ArrayList;
        //    19: dup            
        //    20: aload_0         /* $this$map */
        //    21: invokeinterface java/lang/CharSequence.length:()I
        //    26: invokespecial   java/util/ArrayList.<init>:(I)V
        //    29: checkcast       Ljava/util/Collection;
        //    32: astore          destination$iv
        //    34: iconst_0       
        //    35: istore          $i$f$mapTo
        //    37: iconst_0       
        //    38: istore          6
        //    40: iload           6
        //    42: aload_3         /* $this$mapTo$iv */
        //    43: invokeinterface java/lang/CharSequence.length:()I
        //    48: if_icmpge       86
        //    51: aload_3         /* $this$mapTo$iv */
        //    52: iload           6
        //    54: invokeinterface java/lang/CharSequence.charAt:(I)C
        //    59: istore          item$iv
        //    61: aload           destination$iv
        //    63: aload_1         /* transform */
        //    64: iload           item$iv
        //    66: invokestatic    java/lang/Character.valueOf:(C)Ljava/lang/Character;
        //    69: invokeinterface kotlin/jvm/functions/Function1.invoke:(Ljava/lang/Object;)Ljava/lang/Object;
        //    74: invokeinterface java/util/Collection.add:(Ljava/lang/Object;)Z
        //    79: pop            
        //    80: iinc            6, 1
        //    83: goto            40
        //    86: aload           destination$iv
        //    88: checkcast       Ljava/util/List;
        //    91: areturn        
        //    Signature:
        //  <R:Ljava/lang/Object;>(Ljava/lang/CharSequence;Lkotlin/jvm/functions/Function1<-Ljava/lang/Character;+TR;>;)Ljava/util/List<TR;>;
        //    StackMapTable: 00 02 FF 00 28 00 07 07 00 1A 07 00 26 01 07 00 1A 07 01 E3 01 01 00 00 2D
        // 
        // The error that occurred was:
        // 
        // java.lang.NullPointerException
        // 
        throw new IllegalStateException("An error occurred while decompiling this method.");
    }
    
    @NotNull
    public static final <R> List<R> mapIndexed(@NotNull final CharSequence $this$mapIndexed, @NotNull final Function2<? super Integer, ? super Character, ? extends R> transform) {
        // 
        // This method could not be decompiled.
        // 
        // Original Bytecode:
        // 
        //     1: ldc             "<this>"
        //     3: invokestatic    kotlin/jvm/internal/Intrinsics.checkNotNullParameter:(Ljava/lang/Object;Ljava/lang/String;)V
        //     6: aload_1         /* transform */
        //     7: ldc             "transform"
        //     9: invokestatic    kotlin/jvm/internal/Intrinsics.checkNotNullParameter:(Ljava/lang/Object;Ljava/lang/String;)V
        //    12: iconst_0       
        //    13: istore_2        /* $i$f$mapIndexed */
        //    14: aload_0         /* $this$mapIndexed */
        //    15: astore_3       
        //    16: new             Ljava/util/ArrayList;
        //    19: dup            
        //    20: aload_0         /* $this$mapIndexed */
        //    21: invokeinterface java/lang/CharSequence.length:()I
        //    26: invokespecial   java/util/ArrayList.<init>:(I)V
        //    29: checkcast       Ljava/util/Collection;
        //    32: astore          destination$iv
        //    34: iconst_0       
        //    35: istore          $i$f$mapIndexedTo
        //    37: iconst_0       
        //    38: istore          index$iv
        //    40: iconst_0       
        //    41: istore          7
        //    43: iload           7
        //    45: aload_3         /* $this$mapIndexedTo$iv */
        //    46: invokeinterface java/lang/CharSequence.length:()I
        //    51: if_icmpge       97
        //    54: aload_3         /* $this$mapIndexedTo$iv */
        //    55: iload           7
        //    57: invokeinterface java/lang/CharSequence.charAt:(I)C
        //    62: istore          item$iv
        //    64: aload           destination$iv
        //    66: aload_1         /* transform */
        //    67: iload           index$iv
        //    69: iinc            index$iv, 1
        //    72: invokestatic    java/lang/Integer.valueOf:(I)Ljava/lang/Integer;
        //    75: iload           item$iv
        //    77: invokestatic    java/lang/Character.valueOf:(C)Ljava/lang/Character;
        //    80: invokeinterface kotlin/jvm/functions/Function2.invoke:(Ljava/lang/Object;Ljava/lang/Object;)Ljava/lang/Object;
        //    85: invokeinterface java/util/Collection.add:(Ljava/lang/Object;)Z
        //    90: pop            
        //    91: iinc            7, 1
        //    94: goto            43
        //    97: aload           destination$iv
        //    99: checkcast       Ljava/util/List;
        //   102: areturn        
        //    Signature:
        //  <R:Ljava/lang/Object;>(Ljava/lang/CharSequence;Lkotlin/jvm/functions/Function2<-Ljava/lang/Integer;-Ljava/lang/Character;+TR;>;)Ljava/util/List<TR;>;
        //    StackMapTable: 00 02 FF 00 2B 00 08 07 00 1A 07 01 22 01 07 00 1A 07 01 E3 01 01 01 00 00 35
        // 
        // The error that occurred was:
        // 
        // java.lang.NullPointerException
        // 
        throw new IllegalStateException("An error occurred while decompiling this method.");
    }
    
    @NotNull
    public static final <R> List<R> mapIndexedNotNull(@NotNull final CharSequence $this$mapIndexedNotNull, @NotNull final Function2<? super Integer, ? super Character, ? extends R> transform) {
        // 
        // This method could not be decompiled.
        // 
        // Original Bytecode:
        // 
        //     1: ldc             "<this>"
        //     3: invokestatic    kotlin/jvm/internal/Intrinsics.checkNotNullParameter:(Ljava/lang/Object;Ljava/lang/String;)V
        //     6: aload_1         /* transform */
        //     7: ldc             "transform"
        //     9: invokestatic    kotlin/jvm/internal/Intrinsics.checkNotNullParameter:(Ljava/lang/Object;Ljava/lang/String;)V
        //    12: iconst_0       
        //    13: istore_2        /* $i$f$mapIndexedNotNull */
        //    14: aload_0         /* $this$mapIndexedNotNull */
        //    15: astore_3       
        //    16: new             Ljava/util/ArrayList;
        //    19: dup            
        //    20: invokespecial   java/util/ArrayList.<init>:()V
        //    23: checkcast       Ljava/util/Collection;
        //    26: astore          destination$iv
        //    28: iconst_0       
        //    29: istore          $i$f$mapIndexedNotNullTo
        //    31: aload_3         /* $this$mapIndexedNotNullTo$iv */
        //    32: astore          $this$forEachIndexed$iv$iv
        //    34: iconst_0       
        //    35: istore          $i$f$forEachIndexed
        //    37: iconst_0       
        //    38: istore          index$iv$iv
        //    40: iconst_0       
        //    41: istore          9
        //    43: iload           9
        //    45: aload           $this$forEachIndexed$iv$iv
        //    47: invokeinterface java/lang/CharSequence.length:()I
        //    52: if_icmpge       131
        //    55: aload           $this$forEachIndexed$iv$iv
        //    57: iload           9
        //    59: invokeinterface java/lang/CharSequence.charAt:(I)C
        //    64: istore          item$iv$iv
        //    66: iload           index$iv$iv
        //    68: iinc            index$iv$iv, 1
        //    71: iload           item$iv$iv
        //    73: istore          11
        //    75: istore          index$iv
        //    77: iconst_0       
        //    78: istore          $i$a$-forEachIndexed-StringsKt___StringsKt$mapIndexedNotNullTo$1$iv
        //    80: aload_1         /* transform */
        //    81: iload           index$iv
        //    83: invokestatic    java/lang/Integer.valueOf:(I)Ljava/lang/Integer;
        //    86: iload           element$iv
        //    88: invokestatic    java/lang/Character.valueOf:(C)Ljava/lang/Character;
        //    91: invokeinterface kotlin/jvm/functions/Function2.invoke:(Ljava/lang/Object;Ljava/lang/Object;)Ljava/lang/Object;
        //    96: dup            
        //    97: ifnull          122
        //   100: astore          14
        //   102: aload           14
        //   104: astore          it$iv
        //   106: iconst_0       
        //   107: istore          $i$a$-let-StringsKt___StringsKt$mapIndexedNotNullTo$1$1$iv
        //   109: aload           destination$iv
        //   111: aload           it$iv
        //   113: invokeinterface java/util/Collection.add:(Ljava/lang/Object;)Z
        //   118: pop            
        //   119: goto            124
        //   122: pop            
        //   123: nop            
        //   124: nop            
        //   125: iinc            9, 1
        //   128: goto            43
        //   131: nop            
        //   132: aload           destination$iv
        //   134: checkcast       Ljava/util/List;
        //   137: areturn        
        //    Signature:
        //  <R:Ljava/lang/Object;>(Ljava/lang/CharSequence;Lkotlin/jvm/functions/Function2<-Ljava/lang/Integer;-Ljava/lang/Character;+TR;>;)Ljava/util/List<TR;>;
        //    StackMapTable: 00 04 FF 00 2B 00 0A 07 00 1A 07 01 22 01 07 00 1A 07 01 E3 01 07 00 1A 01 01 01 00 00 FF 00 4E 00 0E 07 00 1A 07 01 22 01 07 00 1A 07 01 E3 01 07 00 1A 01 01 01 01 01 01 01 00 01 07 00 76 01 FF 00 06 00 0A 07 00 1A 07 01 22 01 07 00 1A 07 01 E3 01 07 00 1A 01 01 01 00 00
        // 
        // The error that occurred was:
        // 
        // java.lang.NullPointerException
        // 
        throw new IllegalStateException("An error occurred while decompiling this method.");
    }
    
    @NotNull
    public static final <R, C extends Collection<? super R>> C mapIndexedNotNullTo(@NotNull final CharSequence $this$mapIndexedNotNullTo, @NotNull final C destination, @NotNull final Function2<? super Integer, ? super Character, ? extends R> transform) {
        // 
        // This method could not be decompiled.
        // 
        // Original Bytecode:
        // 
        //     1: ldc             "<this>"
        //     3: invokestatic    kotlin/jvm/internal/Intrinsics.checkNotNullParameter:(Ljava/lang/Object;Ljava/lang/String;)V
        //     6: aload_1         /* destination */
        //     7: ldc_w           "destination"
        //    10: invokestatic    kotlin/jvm/internal/Intrinsics.checkNotNullParameter:(Ljava/lang/Object;Ljava/lang/String;)V
        //    13: aload_2         /* transform */
        //    14: ldc             "transform"
        //    16: invokestatic    kotlin/jvm/internal/Intrinsics.checkNotNullParameter:(Ljava/lang/Object;Ljava/lang/String;)V
        //    19: iconst_0       
        //    20: istore_3        /* $i$f$mapIndexedNotNullTo */
        //    21: aload_0         /* $this$mapIndexedNotNullTo */
        //    22: astore          $this$forEachIndexed$iv
        //    24: iconst_0       
        //    25: istore          $i$f$forEachIndexed
        //    27: iconst_0       
        //    28: istore          index$iv
        //    30: iconst_0       
        //    31: istore          7
        //    33: iload           7
        //    35: aload           $this$forEachIndexed$iv
        //    37: invokeinterface java/lang/CharSequence.length:()I
        //    42: if_icmpge       120
        //    45: aload           $this$forEachIndexed$iv
        //    47: iload           7
        //    49: invokeinterface java/lang/CharSequence.charAt:(I)C
        //    54: istore          item$iv
        //    56: iload           index$iv
        //    58: iinc            index$iv, 1
        //    61: iload           item$iv
        //    63: istore          9
        //    65: istore          index
        //    67: iconst_0       
        //    68: istore          $i$a$-forEachIndexed-StringsKt___StringsKt$mapIndexedNotNullTo$1
        //    70: aload_2         /* transform */
        //    71: iload           index
        //    73: invokestatic    java/lang/Integer.valueOf:(I)Ljava/lang/Integer;
        //    76: iload           element
        //    78: invokestatic    java/lang/Character.valueOf:(C)Ljava/lang/Character;
        //    81: invokeinterface kotlin/jvm/functions/Function2.invoke:(Ljava/lang/Object;Ljava/lang/Object;)Ljava/lang/Object;
        //    86: dup            
        //    87: ifnull          111
        //    90: astore          12
        //    92: aload           12
        //    94: astore          it
        //    96: iconst_0       
        //    97: istore          $i$a$-let-StringsKt___StringsKt$mapIndexedNotNullTo$1$1
        //    99: aload_1         /* destination */
        //   100: aload           it
        //   102: invokeinterface java/util/Collection.add:(Ljava/lang/Object;)Z
        //   107: pop            
        //   108: goto            113
        //   111: pop            
        //   112: nop            
        //   113: nop            
        //   114: iinc            7, 1
        //   117: goto            33
        //   120: nop            
        //   121: aload_1         /* destination */
        //   122: areturn        
        //    Signature:
        //  <R:Ljava/lang/Object;C::Ljava/util/Collection<-TR;>;>(Ljava/lang/CharSequence;TC;Lkotlin/jvm/functions/Function2<-Ljava/lang/Integer;-Ljava/lang/Character;+TR;>;)TC;
        //    StackMapTable: 00 04 FF 00 21 00 08 07 00 1A 07 01 E3 07 01 22 01 07 00 1A 01 01 01 00 00 FF 00 4D 00 0C 07 00 1A 07 01 E3 07 01 22 01 07 00 1A 01 01 01 01 01 01 01 00 01 07 00 76 01 FF 00 06 00 08 07 00 1A 07 01 E3 07 01 22 01 07 00 1A 01 01 01 00 00
        // 
        // The error that occurred was:
        // 
        // java.lang.NullPointerException
        // 
        throw new IllegalStateException("An error occurred while decompiling this method.");
    }
    
    @NotNull
    public static final <R, C extends Collection<? super R>> C mapIndexedTo(@NotNull final CharSequence $this$mapIndexedTo, @NotNull final C destination, @NotNull final Function2<? super Integer, ? super Character, ? extends R> transform) {
        Intrinsics.checkNotNullParameter($this$mapIndexedTo, "<this>");
        Intrinsics.checkNotNullParameter(destination, "destination");
        Intrinsics.checkNotNullParameter(transform, "transform");
        final int $i$f$mapIndexedTo = 0;
        int index = 0;
        for (int i = 0; i < $this$mapIndexedTo.length(); ++i) {
            final char item = $this$mapIndexedTo.charAt(i);
            destination.add((Object)transform.invoke(index++, item));
        }
        return destination;
    }
    
    @NotNull
    public static final <R> List<R> mapNotNull(@NotNull final CharSequence $this$mapNotNull, @NotNull final Function1<? super Character, ? extends R> transform) {
        // 
        // This method could not be decompiled.
        // 
        // Original Bytecode:
        // 
        //     1: ldc             "<this>"
        //     3: invokestatic    kotlin/jvm/internal/Intrinsics.checkNotNullParameter:(Ljava/lang/Object;Ljava/lang/String;)V
        //     6: aload_1         /* transform */
        //     7: ldc             "transform"
        //     9: invokestatic    kotlin/jvm/internal/Intrinsics.checkNotNullParameter:(Ljava/lang/Object;Ljava/lang/String;)V
        //    12: iconst_0       
        //    13: istore_2        /* $i$f$mapNotNull */
        //    14: aload_0         /* $this$mapNotNull */
        //    15: astore_3       
        //    16: new             Ljava/util/ArrayList;
        //    19: dup            
        //    20: invokespecial   java/util/ArrayList.<init>:()V
        //    23: checkcast       Ljava/util/Collection;
        //    26: astore          destination$iv
        //    28: iconst_0       
        //    29: istore          $i$f$mapNotNullTo
        //    31: aload_3         /* $this$mapNotNullTo$iv */
        //    32: astore          $this$forEach$iv$iv
        //    34: iconst_0       
        //    35: istore          $i$f$forEach
        //    37: iconst_0       
        //    38: istore          8
        //    40: iload           8
        //    42: aload           $this$forEach$iv$iv
        //    44: invokeinterface java/lang/CharSequence.length:()I
        //    49: if_icmpge       116
        //    52: aload           $this$forEach$iv$iv
        //    54: iload           8
        //    56: invokeinterface java/lang/CharSequence.charAt:(I)C
        //    61: istore          element$iv$iv
        //    63: iload           element$iv$iv
        //    65: istore          element$iv
        //    67: iconst_0       
        //    68: istore          $i$a$-forEach-StringsKt___StringsKt$mapNotNullTo$1$iv
        //    70: aload_1         /* transform */
        //    71: iload           element$iv
        //    73: invokestatic    java/lang/Character.valueOf:(C)Ljava/lang/Character;
        //    76: invokeinterface kotlin/jvm/functions/Function1.invoke:(Ljava/lang/Object;)Ljava/lang/Object;
        //    81: dup            
        //    82: ifnull          107
        //    85: astore          12
        //    87: aload           12
        //    89: astore          it$iv
        //    91: iconst_0       
        //    92: istore          $i$a$-let-StringsKt___StringsKt$mapNotNullTo$1$1$iv
        //    94: aload           destination$iv
        //    96: aload           it$iv
        //    98: invokeinterface java/util/Collection.add:(Ljava/lang/Object;)Z
        //   103: pop            
        //   104: goto            109
        //   107: pop            
        //   108: nop            
        //   109: nop            
        //   110: iinc            8, 1
        //   113: goto            40
        //   116: nop            
        //   117: aload           destination$iv
        //   119: checkcast       Ljava/util/List;
        //   122: areturn        
        //    Signature:
        //  <R:Ljava/lang/Object;>(Ljava/lang/CharSequence;Lkotlin/jvm/functions/Function1<-Ljava/lang/Character;+TR;>;)Ljava/util/List<TR;>;
        //    StackMapTable: 00 04 FF 00 28 00 09 07 00 1A 07 00 26 01 07 00 1A 07 01 E3 01 07 00 1A 01 01 00 00 FF 00 42 00 0C 07 00 1A 07 00 26 01 07 00 1A 07 01 E3 01 07 00 1A 01 01 01 01 01 00 01 07 00 76 01 F8 00 06
        // 
        // The error that occurred was:
        // 
        // java.lang.NullPointerException
        // 
        throw new IllegalStateException("An error occurred while decompiling this method.");
    }
    
    @NotNull
    public static final <R, C extends Collection<? super R>> C mapNotNullTo(@NotNull final CharSequence $this$mapNotNullTo, @NotNull final C destination, @NotNull final Function1<? super Character, ? extends R> transform) {
        Intrinsics.checkNotNullParameter($this$mapNotNullTo, "<this>");
        Intrinsics.checkNotNullParameter(destination, "destination");
        Intrinsics.checkNotNullParameter(transform, "transform");
        final int $i$f$mapNotNullTo = 0;
        final CharSequence $this$forEach$iv = $this$mapNotNullTo;
        final int $i$f$forEach = 0;
        for (int i = 0; i < $this$forEach$iv.length(); ++i) {
            final char element;
            final char element$iv = element = $this$forEach$iv.charAt(i);
            final int n = 0;
            final R invoke = (R)transform.invoke(element);
            if (invoke != null) {
                final Object it = invoke;
                final int n2 = 0;
                destination.add((Object)it);
            }
        }
        return destination;
    }
    
    @NotNull
    public static final <R, C extends Collection<? super R>> C mapTo(@NotNull final CharSequence $this$mapTo, @NotNull final C destination, @NotNull final Function1<? super Character, ? extends R> transform) {
        Intrinsics.checkNotNullParameter($this$mapTo, "<this>");
        Intrinsics.checkNotNullParameter(destination, "destination");
        Intrinsics.checkNotNullParameter(transform, "transform");
        final int $i$f$mapTo = 0;
        for (int i = 0; i < $this$mapTo.length(); ++i) {
            final char item = $this$mapTo.charAt(i);
            destination.add((Object)transform.invoke(item));
        }
        return destination;
    }
    
    @NotNull
    public static final Iterable<IndexedValue<Character>> withIndex(@NotNull final CharSequence $this$withIndex) {
        Intrinsics.checkNotNullParameter($this$withIndex, "<this>");
        return (Iterable<IndexedValue<Character>>)new IndexingIterable((Function0<? extends Iterator<?>>)new StringsKt___StringsKt$withIndex.StringsKt___StringsKt$withIndex$1($this$withIndex));
    }
    
    public static final boolean all(@NotNull final CharSequence $this$all, @NotNull final Function1<? super Character, Boolean> predicate) {
        Intrinsics.checkNotNullParameter($this$all, "<this>");
        Intrinsics.checkNotNullParameter(predicate, "predicate");
        final int $i$f$all = 0;
        for (int i = 0; i < $this$all.length(); ++i) {
            final char element = $this$all.charAt(i);
            if (!predicate.invoke(element)) {
                return false;
            }
        }
        return true;
    }
    
    public static final boolean any(@NotNull final CharSequence $this$any) {
        Intrinsics.checkNotNullParameter($this$any, "<this>");
        return $this$any.length() != 0;
    }
    
    public static final boolean any(@NotNull final CharSequence $this$any, @NotNull final Function1<? super Character, Boolean> predicate) {
        Intrinsics.checkNotNullParameter($this$any, "<this>");
        Intrinsics.checkNotNullParameter(predicate, "predicate");
        final int $i$f$any = 0;
        for (int i = 0; i < $this$any.length(); ++i) {
            final char element = $this$any.charAt(i);
            if (predicate.invoke(element)) {
                return true;
            }
        }
        return false;
    }
    
    @InlineOnly
    private static final int count(final CharSequence $this$count) {
        Intrinsics.checkNotNullParameter($this$count, "<this>");
        return $this$count.length();
    }
    
    public static final int count(@NotNull final CharSequence $this$count, @NotNull final Function1<? super Character, Boolean> predicate) {
        Intrinsics.checkNotNullParameter($this$count, "<this>");
        Intrinsics.checkNotNullParameter(predicate, "predicate");
        final int $i$f$count = 0;
        int count = 0;
        for (int i = 0; i < $this$count.length(); ++i) {
            final char element = $this$count.charAt(i);
            if (predicate.invoke(element)) {
                ++count;
            }
        }
        return count;
    }
    
    public static final <R> R fold(@NotNull final CharSequence $this$fold, final R initial, @NotNull final Function2<? super R, ? super Character, ? extends R> operation) {
        Intrinsics.checkNotNullParameter($this$fold, "<this>");
        Intrinsics.checkNotNullParameter(operation, "operation");
        final int $i$f$fold = 0;
        Object accumulator = initial;
        for (int i = 0; i < $this$fold.length(); ++i) {
            final char element = $this$fold.charAt(i);
            accumulator = operation.invoke((Object)accumulator, Character.valueOf(element));
        }
        return (R)accumulator;
    }
    
    public static final <R> R foldIndexed(@NotNull final CharSequence $this$foldIndexed, final R initial, @NotNull final Function3<? super Integer, ? super R, ? super Character, ? extends R> operation) {
        Intrinsics.checkNotNullParameter($this$foldIndexed, "<this>");
        Intrinsics.checkNotNullParameter(operation, "operation");
        final int $i$f$foldIndexed = 0;
        int index = 0;
        Object accumulator = initial;
        for (int i = 0; i < $this$foldIndexed.length(); ++i) {
            final char element = $this$foldIndexed.charAt(i);
            accumulator = operation.invoke(Integer.valueOf(index++), (Object)accumulator, Character.valueOf(element));
        }
        return (R)accumulator;
    }
    
    public static final <R> R foldRight(@NotNull final CharSequence $this$foldRight, final R initial, @NotNull final Function2<? super Character, ? super R, ? extends R> operation) {
        Intrinsics.checkNotNullParameter($this$foldRight, "<this>");
        Intrinsics.checkNotNullParameter(operation, "operation");
        final int $i$f$foldRight = 0;
        int index;
        Object accumulator;
        for (index = StringsKt__StringsKt.getLastIndex($this$foldRight), accumulator = initial; index >= 0; accumulator = operation.invoke(Character.valueOf($this$foldRight.charAt(index--)), (Object)accumulator)) {}
        return (R)accumulator;
    }
    
    public static final <R> R foldRightIndexed(@NotNull final CharSequence $this$foldRightIndexed, final R initial, @NotNull final Function3<? super Integer, ? super Character, ? super R, ? extends R> operation) {
        Intrinsics.checkNotNullParameter($this$foldRightIndexed, "<this>");
        Intrinsics.checkNotNullParameter(operation, "operation");
        final int $i$f$foldRightIndexed = 0;
        int index = StringsKt__StringsKt.getLastIndex($this$foldRightIndexed);
        Object accumulator = initial;
        while (index >= 0) {
            accumulator = operation.invoke(Integer.valueOf(index), Character.valueOf($this$foldRightIndexed.charAt(index)), (Object)accumulator);
            --index;
        }
        return (R)accumulator;
    }
    
    public static final void forEach(@NotNull final CharSequence $this$forEach, @NotNull final Function1<? super Character, Unit> action) {
        Intrinsics.checkNotNullParameter($this$forEach, "<this>");
        Intrinsics.checkNotNullParameter(action, "action");
        final int $i$f$forEach = 0;
        for (int i = 0; i < $this$forEach.length(); ++i) {
            final char element = $this$forEach.charAt(i);
            action.invoke(element);
        }
    }
    
    public static final void forEachIndexed(@NotNull final CharSequence $this$forEachIndexed, @NotNull final Function2<? super Integer, ? super Character, Unit> action) {
        Intrinsics.checkNotNullParameter($this$forEachIndexed, "<this>");
        Intrinsics.checkNotNullParameter(action, "action");
        final int $i$f$forEachIndexed = 0;
        int index = 0;
        for (int i = 0; i < $this$forEachIndexed.length(); ++i) {
            final char item = $this$forEachIndexed.charAt(i);
            action.invoke(index++, item);
        }
    }
    
    @SinceKotlin(version = "1.7")
    @JvmName(name = "maxOrThrow")
    public static final char maxOrThrow(@NotNull final CharSequence $this$max) {
        Intrinsics.checkNotNullParameter($this$max, "<this>");
        if ($this$max.length() == 0) {
            throw new NoSuchElementException();
        }
        char max = $this$max.charAt(0);
        final IntIterator iterator = new IntRange(1, StringsKt__StringsKt.getLastIndex($this$max)).iterator();
        while (iterator.hasNext()) {
            final int i = iterator.nextInt();
            final char e = $this$max.charAt(i);
            if (Intrinsics.compare(max, e) < 0) {
                max = e;
            }
        }
        return max;
    }
    
    @SinceKotlin(version = "1.7")
    @JvmName(name = "maxByOrThrow")
    public static final <R extends Comparable<? super R>> char maxByOrThrow(@NotNull final CharSequence $this$maxBy, @NotNull final Function1<? super Character, ? extends R> selector) {
        Intrinsics.checkNotNullParameter($this$maxBy, "<this>");
        Intrinsics.checkNotNullParameter(selector, "selector");
        final int $i$f$maxByOrThrow = 0;
        if ($this$maxBy.length() == 0) {
            throw new NoSuchElementException();
        }
        char maxElem = $this$maxBy.charAt(0);
        final int lastIndex = StringsKt__StringsKt.getLastIndex($this$maxBy);
        if (lastIndex == 0) {
            return maxElem;
        }
        Comparable maxValue = (Comparable)selector.invoke(maxElem);
        final IntIterator iterator = new IntRange(1, lastIndex).iterator();
        while (iterator.hasNext()) {
            final int i = iterator.nextInt();
            final char e = $this$maxBy.charAt(i);
            final Comparable v = (Comparable)selector.invoke(e);
            if (maxValue.compareTo(v) < 0) {
                maxElem = e;
                maxValue = v;
            }
        }
        return maxElem;
    }
    
    @SinceKotlin(version = "1.4")
    @Nullable
    public static final <R extends Comparable<? super R>> Character maxByOrNull(@NotNull final CharSequence $this$maxByOrNull, @NotNull final Function1<? super Character, ? extends R> selector) {
        Intrinsics.checkNotNullParameter($this$maxByOrNull, "<this>");
        Intrinsics.checkNotNullParameter(selector, "selector");
        final int $i$f$maxByOrNull = 0;
        if ($this$maxByOrNull.length() == 0) {
            return null;
        }
        char maxElem = $this$maxByOrNull.charAt(0);
        final int lastIndex = StringsKt__StringsKt.getLastIndex($this$maxByOrNull);
        if (lastIndex == 0) {
            return maxElem;
        }
        Comparable maxValue = (Comparable)selector.invoke(maxElem);
        final IntIterator iterator = new IntRange(1, lastIndex).iterator();
        while (iterator.hasNext()) {
            final int i = iterator.nextInt();
            final char e = $this$maxByOrNull.charAt(i);
            final Comparable v = (Comparable)selector.invoke(e);
            if (maxValue.compareTo(v) < 0) {
                maxElem = e;
                maxValue = v;
            }
        }
        return maxElem;
    }
    
    @SinceKotlin(version = "1.4")
    @OverloadResolutionByLambdaReturnType
    @InlineOnly
    private static final double maxOf(final CharSequence $this$maxOf, final Function1<? super Character, Double> selector) {
        Intrinsics.checkNotNullParameter($this$maxOf, "<this>");
        Intrinsics.checkNotNullParameter(selector, "selector");
        if ($this$maxOf.length() == 0) {
            throw new NoSuchElementException();
        }
        double maxValue = selector.invoke($this$maxOf.charAt(0)).doubleValue();
        final IntIterator iterator = new IntRange(1, StringsKt__StringsKt.getLastIndex($this$maxOf)).iterator();
        while (iterator.hasNext()) {
            final int i = iterator.nextInt();
            final double v = selector.invoke($this$maxOf.charAt(i)).doubleValue();
            maxValue = Math.max(maxValue, v);
        }
        return maxValue;
    }
    
    @SinceKotlin(version = "1.4")
    @OverloadResolutionByLambdaReturnType
    @InlineOnly
    private static final float maxOf(final CharSequence $this$maxOf, final Function1<? super Character, Float> selector) {
        Intrinsics.checkNotNullParameter($this$maxOf, "<this>");
        Intrinsics.checkNotNullParameter(selector, "selector");
        if ($this$maxOf.length() == 0) {
            throw new NoSuchElementException();
        }
        float maxValue = selector.invoke($this$maxOf.charAt(0)).floatValue();
        final IntIterator iterator = new IntRange(1, StringsKt__StringsKt.getLastIndex($this$maxOf)).iterator();
        while (iterator.hasNext()) {
            final int i = iterator.nextInt();
            final float v = selector.invoke($this$maxOf.charAt(i)).floatValue();
            maxValue = Math.max(maxValue, v);
        }
        return maxValue;
    }
    
    @SinceKotlin(version = "1.4")
    @OverloadResolutionByLambdaReturnType
    @InlineOnly
    private static final <R extends Comparable<? super R>> R maxOf(final CharSequence $this$maxOf, final Function1<? super Character, ? extends R> selector) {
        Intrinsics.checkNotNullParameter($this$maxOf, "<this>");
        Intrinsics.checkNotNullParameter(selector, "selector");
        if ($this$maxOf.length() == 0) {
            throw new NoSuchElementException();
        }
        Comparable maxValue = (Comparable)selector.invoke($this$maxOf.charAt(0));
        final IntIterator iterator = new IntRange(1, StringsKt__StringsKt.getLastIndex($this$maxOf)).iterator();
        while (iterator.hasNext()) {
            final int i = iterator.nextInt();
            final Comparable v = (Comparable)selector.invoke($this$maxOf.charAt(i));
            if (maxValue.compareTo(v) < 0) {
                maxValue = v;
            }
        }
        return (R)maxValue;
    }
    
    @SinceKotlin(version = "1.4")
    @OverloadResolutionByLambdaReturnType
    @InlineOnly
    private static final Double maxOfOrNull(final CharSequence $this$maxOfOrNull, final Function1<? super Character, Double> selector) {
        Intrinsics.checkNotNullParameter($this$maxOfOrNull, "<this>");
        Intrinsics.checkNotNullParameter(selector, "selector");
        if ($this$maxOfOrNull.length() == 0) {
            return null;
        }
        double maxValue = selector.invoke($this$maxOfOrNull.charAt(0)).doubleValue();
        final IntIterator iterator = new IntRange(1, StringsKt__StringsKt.getLastIndex($this$maxOfOrNull)).iterator();
        while (iterator.hasNext()) {
            final int i = iterator.nextInt();
            final double v = selector.invoke($this$maxOfOrNull.charAt(i)).doubleValue();
            maxValue = Math.max(maxValue, v);
        }
        return maxValue;
    }
    
    @SinceKotlin(version = "1.4")
    @OverloadResolutionByLambdaReturnType
    @InlineOnly
    private static final Float maxOfOrNull(final CharSequence $this$maxOfOrNull, final Function1<? super Character, Float> selector) {
        Intrinsics.checkNotNullParameter($this$maxOfOrNull, "<this>");
        Intrinsics.checkNotNullParameter(selector, "selector");
        if ($this$maxOfOrNull.length() == 0) {
            return null;
        }
        float maxValue = selector.invoke($this$maxOfOrNull.charAt(0)).floatValue();
        final IntIterator iterator = new IntRange(1, StringsKt__StringsKt.getLastIndex($this$maxOfOrNull)).iterator();
        while (iterator.hasNext()) {
            final int i = iterator.nextInt();
            final float v = selector.invoke($this$maxOfOrNull.charAt(i)).floatValue();
            maxValue = Math.max(maxValue, v);
        }
        return maxValue;
    }
    
    @SinceKotlin(version = "1.4")
    @OverloadResolutionByLambdaReturnType
    @InlineOnly
    private static final <R extends Comparable<? super R>> R maxOfOrNull(final CharSequence $this$maxOfOrNull, final Function1<? super Character, ? extends R> selector) {
        Intrinsics.checkNotNullParameter($this$maxOfOrNull, "<this>");
        Intrinsics.checkNotNullParameter(selector, "selector");
        if ($this$maxOfOrNull.length() == 0) {
            return null;
        }
        Comparable maxValue = (Comparable)selector.invoke($this$maxOfOrNull.charAt(0));
        final IntIterator iterator = new IntRange(1, StringsKt__StringsKt.getLastIndex($this$maxOfOrNull)).iterator();
        while (iterator.hasNext()) {
            final int i = iterator.nextInt();
            final Comparable v = (Comparable)selector.invoke($this$maxOfOrNull.charAt(i));
            if (maxValue.compareTo(v) < 0) {
                maxValue = v;
            }
        }
        return (R)maxValue;
    }
    
    @SinceKotlin(version = "1.4")
    @OverloadResolutionByLambdaReturnType
    @InlineOnly
    private static final <R> R maxOfWith(final CharSequence $this$maxOfWith, final Comparator<? super R> comparator, final Function1<? super Character, ? extends R> selector) {
        Intrinsics.checkNotNullParameter($this$maxOfWith, "<this>");
        Intrinsics.checkNotNullParameter(comparator, "comparator");
        Intrinsics.checkNotNullParameter(selector, "selector");
        if ($this$maxOfWith.length() == 0) {
            throw new NoSuchElementException();
        }
        Object maxValue = selector.invoke($this$maxOfWith.charAt(0));
        final IntIterator iterator = new IntRange(1, StringsKt__StringsKt.getLastIndex($this$maxOfWith)).iterator();
        while (iterator.hasNext()) {
            final int i = iterator.nextInt();
            final Object v = selector.invoke($this$maxOfWith.charAt(i));
            if (comparator.compare((Object)maxValue, (Object)v) < 0) {
                maxValue = v;
            }
        }
        return (R)maxValue;
    }
    
    @SinceKotlin(version = "1.4")
    @OverloadResolutionByLambdaReturnType
    @InlineOnly
    private static final <R> R maxOfWithOrNull(final CharSequence $this$maxOfWithOrNull, final Comparator<? super R> comparator, final Function1<? super Character, ? extends R> selector) {
        Intrinsics.checkNotNullParameter($this$maxOfWithOrNull, "<this>");
        Intrinsics.checkNotNullParameter(comparator, "comparator");
        Intrinsics.checkNotNullParameter(selector, "selector");
        if ($this$maxOfWithOrNull.length() == 0) {
            return null;
        }
        Object maxValue = selector.invoke($this$maxOfWithOrNull.charAt(0));
        final IntIterator iterator = new IntRange(1, StringsKt__StringsKt.getLastIndex($this$maxOfWithOrNull)).iterator();
        while (iterator.hasNext()) {
            final int i = iterator.nextInt();
            final Object v = selector.invoke($this$maxOfWithOrNull.charAt(i));
            if (comparator.compare((Object)maxValue, (Object)v) < 0) {
                maxValue = v;
            }
        }
        return (R)maxValue;
    }
    
    @SinceKotlin(version = "1.4")
    @Nullable
    public static final Character maxOrNull(@NotNull final CharSequence $this$maxOrNull) {
        Intrinsics.checkNotNullParameter($this$maxOrNull, "<this>");
        if ($this$maxOrNull.length() == 0) {
            return null;
        }
        char max = $this$maxOrNull.charAt(0);
        final IntIterator iterator = new IntRange(1, StringsKt__StringsKt.getLastIndex($this$maxOrNull)).iterator();
        while (iterator.hasNext()) {
            final int i = iterator.nextInt();
            final char e = $this$maxOrNull.charAt(i);
            if (Intrinsics.compare(max, e) < 0) {
                max = e;
            }
        }
        return max;
    }
    
    @SinceKotlin(version = "1.7")
    @JvmName(name = "maxWithOrThrow")
    public static final char maxWithOrThrow(@NotNull final CharSequence $this$maxWith, @NotNull final Comparator<? super Character> comparator) {
        Intrinsics.checkNotNullParameter($this$maxWith, "<this>");
        Intrinsics.checkNotNullParameter(comparator, "comparator");
        if ($this$maxWith.length() == 0) {
            throw new NoSuchElementException();
        }
        char max = $this$maxWith.charAt(0);
        final IntIterator iterator = new IntRange(1, StringsKt__StringsKt.getLastIndex($this$maxWith)).iterator();
        while (iterator.hasNext()) {
            final int i = iterator.nextInt();
            final char e = $this$maxWith.charAt(i);
            if (comparator.compare(max, e) < 0) {
                max = e;
            }
        }
        return max;
    }
    
    @SinceKotlin(version = "1.4")
    @Nullable
    public static final Character maxWithOrNull(@NotNull final CharSequence $this$maxWithOrNull, @NotNull final Comparator<? super Character> comparator) {
        Intrinsics.checkNotNullParameter($this$maxWithOrNull, "<this>");
        Intrinsics.checkNotNullParameter(comparator, "comparator");
        if ($this$maxWithOrNull.length() == 0) {
            return null;
        }
        char max = $this$maxWithOrNull.charAt(0);
        final IntIterator iterator = new IntRange(1, StringsKt__StringsKt.getLastIndex($this$maxWithOrNull)).iterator();
        while (iterator.hasNext()) {
            final int i = iterator.nextInt();
            final char e = $this$maxWithOrNull.charAt(i);
            if (comparator.compare(max, e) < 0) {
                max = e;
            }
        }
        return max;
    }
    
    @SinceKotlin(version = "1.7")
    @JvmName(name = "minOrThrow")
    public static final char minOrThrow(@NotNull final CharSequence $this$min) {
        Intrinsics.checkNotNullParameter($this$min, "<this>");
        if ($this$min.length() == 0) {
            throw new NoSuchElementException();
        }
        char min = $this$min.charAt(0);
        final IntIterator iterator = new IntRange(1, StringsKt__StringsKt.getLastIndex($this$min)).iterator();
        while (iterator.hasNext()) {
            final int i = iterator.nextInt();
            final char e = $this$min.charAt(i);
            if (Intrinsics.compare(min, e) > 0) {
                min = e;
            }
        }
        return min;
    }
    
    @SinceKotlin(version = "1.7")
    @JvmName(name = "minByOrThrow")
    public static final <R extends Comparable<? super R>> char minByOrThrow(@NotNull final CharSequence $this$minBy, @NotNull final Function1<? super Character, ? extends R> selector) {
        Intrinsics.checkNotNullParameter($this$minBy, "<this>");
        Intrinsics.checkNotNullParameter(selector, "selector");
        final int $i$f$minByOrThrow = 0;
        if ($this$minBy.length() == 0) {
            throw new NoSuchElementException();
        }
        char minElem = $this$minBy.charAt(0);
        final int lastIndex = StringsKt__StringsKt.getLastIndex($this$minBy);
        if (lastIndex == 0) {
            return minElem;
        }
        Comparable minValue = (Comparable)selector.invoke(minElem);
        final IntIterator iterator = new IntRange(1, lastIndex).iterator();
        while (iterator.hasNext()) {
            final int i = iterator.nextInt();
            final char e = $this$minBy.charAt(i);
            final Comparable v = (Comparable)selector.invoke(e);
            if (minValue.compareTo(v) > 0) {
                minElem = e;
                minValue = v;
            }
        }
        return minElem;
    }
    
    @SinceKotlin(version = "1.4")
    @Nullable
    public static final <R extends Comparable<? super R>> Character minByOrNull(@NotNull final CharSequence $this$minByOrNull, @NotNull final Function1<? super Character, ? extends R> selector) {
        Intrinsics.checkNotNullParameter($this$minByOrNull, "<this>");
        Intrinsics.checkNotNullParameter(selector, "selector");
        final int $i$f$minByOrNull = 0;
        if ($this$minByOrNull.length() == 0) {
            return null;
        }
        char minElem = $this$minByOrNull.charAt(0);
        final int lastIndex = StringsKt__StringsKt.getLastIndex($this$minByOrNull);
        if (lastIndex == 0) {
            return minElem;
        }
        Comparable minValue = (Comparable)selector.invoke(minElem);
        final IntIterator iterator = new IntRange(1, lastIndex).iterator();
        while (iterator.hasNext()) {
            final int i = iterator.nextInt();
            final char e = $this$minByOrNull.charAt(i);
            final Comparable v = (Comparable)selector.invoke(e);
            if (minValue.compareTo(v) > 0) {
                minElem = e;
                minValue = v;
            }
        }
        return minElem;
    }
    
    @SinceKotlin(version = "1.4")
    @OverloadResolutionByLambdaReturnType
    @InlineOnly
    private static final double minOf(final CharSequence $this$minOf, final Function1<? super Character, Double> selector) {
        Intrinsics.checkNotNullParameter($this$minOf, "<this>");
        Intrinsics.checkNotNullParameter(selector, "selector");
        if ($this$minOf.length() == 0) {
            throw new NoSuchElementException();
        }
        double minValue = selector.invoke($this$minOf.charAt(0)).doubleValue();
        final IntIterator iterator = new IntRange(1, StringsKt__StringsKt.getLastIndex($this$minOf)).iterator();
        while (iterator.hasNext()) {
            final int i = iterator.nextInt();
            final double v = selector.invoke($this$minOf.charAt(i)).doubleValue();
            minValue = Math.min(minValue, v);
        }
        return minValue;
    }
    
    @SinceKotlin(version = "1.4")
    @OverloadResolutionByLambdaReturnType
    @InlineOnly
    private static final float minOf(final CharSequence $this$minOf, final Function1<? super Character, Float> selector) {
        Intrinsics.checkNotNullParameter($this$minOf, "<this>");
        Intrinsics.checkNotNullParameter(selector, "selector");
        if ($this$minOf.length() == 0) {
            throw new NoSuchElementException();
        }
        float minValue = selector.invoke($this$minOf.charAt(0)).floatValue();
        final IntIterator iterator = new IntRange(1, StringsKt__StringsKt.getLastIndex($this$minOf)).iterator();
        while (iterator.hasNext()) {
            final int i = iterator.nextInt();
            final float v = selector.invoke($this$minOf.charAt(i)).floatValue();
            minValue = Math.min(minValue, v);
        }
        return minValue;
    }
    
    @SinceKotlin(version = "1.4")
    @OverloadResolutionByLambdaReturnType
    @InlineOnly
    private static final <R extends Comparable<? super R>> R minOf(final CharSequence $this$minOf, final Function1<? super Character, ? extends R> selector) {
        Intrinsics.checkNotNullParameter($this$minOf, "<this>");
        Intrinsics.checkNotNullParameter(selector, "selector");
        if ($this$minOf.length() == 0) {
            throw new NoSuchElementException();
        }
        Comparable minValue = (Comparable)selector.invoke($this$minOf.charAt(0));
        final IntIterator iterator = new IntRange(1, StringsKt__StringsKt.getLastIndex($this$minOf)).iterator();
        while (iterator.hasNext()) {
            final int i = iterator.nextInt();
            final Comparable v = (Comparable)selector.invoke($this$minOf.charAt(i));
            if (minValue.compareTo(v) > 0) {
                minValue = v;
            }
        }
        return (R)minValue;
    }
    
    @SinceKotlin(version = "1.4")
    @OverloadResolutionByLambdaReturnType
    @InlineOnly
    private static final Double minOfOrNull(final CharSequence $this$minOfOrNull, final Function1<? super Character, Double> selector) {
        Intrinsics.checkNotNullParameter($this$minOfOrNull, "<this>");
        Intrinsics.checkNotNullParameter(selector, "selector");
        if ($this$minOfOrNull.length() == 0) {
            return null;
        }
        double minValue = selector.invoke($this$minOfOrNull.charAt(0)).doubleValue();
        final IntIterator iterator = new IntRange(1, StringsKt__StringsKt.getLastIndex($this$minOfOrNull)).iterator();
        while (iterator.hasNext()) {
            final int i = iterator.nextInt();
            final double v = selector.invoke($this$minOfOrNull.charAt(i)).doubleValue();
            minValue = Math.min(minValue, v);
        }
        return minValue;
    }
    
    @SinceKotlin(version = "1.4")
    @OverloadResolutionByLambdaReturnType
    @InlineOnly
    private static final Float minOfOrNull(final CharSequence $this$minOfOrNull, final Function1<? super Character, Float> selector) {
        Intrinsics.checkNotNullParameter($this$minOfOrNull, "<this>");
        Intrinsics.checkNotNullParameter(selector, "selector");
        if ($this$minOfOrNull.length() == 0) {
            return null;
        }
        float minValue = selector.invoke($this$minOfOrNull.charAt(0)).floatValue();
        final IntIterator iterator = new IntRange(1, StringsKt__StringsKt.getLastIndex($this$minOfOrNull)).iterator();
        while (iterator.hasNext()) {
            final int i = iterator.nextInt();
            final float v = selector.invoke($this$minOfOrNull.charAt(i)).floatValue();
            minValue = Math.min(minValue, v);
        }
        return minValue;
    }
    
    @SinceKotlin(version = "1.4")
    @OverloadResolutionByLambdaReturnType
    @InlineOnly
    private static final <R extends Comparable<? super R>> R minOfOrNull(final CharSequence $this$minOfOrNull, final Function1<? super Character, ? extends R> selector) {
        Intrinsics.checkNotNullParameter($this$minOfOrNull, "<this>");
        Intrinsics.checkNotNullParameter(selector, "selector");
        if ($this$minOfOrNull.length() == 0) {
            return null;
        }
        Comparable minValue = (Comparable)selector.invoke($this$minOfOrNull.charAt(0));
        final IntIterator iterator = new IntRange(1, StringsKt__StringsKt.getLastIndex($this$minOfOrNull)).iterator();
        while (iterator.hasNext()) {
            final int i = iterator.nextInt();
            final Comparable v = (Comparable)selector.invoke($this$minOfOrNull.charAt(i));
            if (minValue.compareTo(v) > 0) {
                minValue = v;
            }
        }
        return (R)minValue;
    }
    
    @SinceKotlin(version = "1.4")
    @OverloadResolutionByLambdaReturnType
    @InlineOnly
    private static final <R> R minOfWith(final CharSequence $this$minOfWith, final Comparator<? super R> comparator, final Function1<? super Character, ? extends R> selector) {
        Intrinsics.checkNotNullParameter($this$minOfWith, "<this>");
        Intrinsics.checkNotNullParameter(comparator, "comparator");
        Intrinsics.checkNotNullParameter(selector, "selector");
        if ($this$minOfWith.length() == 0) {
            throw new NoSuchElementException();
        }
        Object minValue = selector.invoke($this$minOfWith.charAt(0));
        final IntIterator iterator = new IntRange(1, StringsKt__StringsKt.getLastIndex($this$minOfWith)).iterator();
        while (iterator.hasNext()) {
            final int i = iterator.nextInt();
            final Object v = selector.invoke($this$minOfWith.charAt(i));
            if (comparator.compare((Object)minValue, (Object)v) > 0) {
                minValue = v;
            }
        }
        return (R)minValue;
    }
    
    @SinceKotlin(version = "1.4")
    @OverloadResolutionByLambdaReturnType
    @InlineOnly
    private static final <R> R minOfWithOrNull(final CharSequence $this$minOfWithOrNull, final Comparator<? super R> comparator, final Function1<? super Character, ? extends R> selector) {
        Intrinsics.checkNotNullParameter($this$minOfWithOrNull, "<this>");
        Intrinsics.checkNotNullParameter(comparator, "comparator");
        Intrinsics.checkNotNullParameter(selector, "selector");
        if ($this$minOfWithOrNull.length() == 0) {
            return null;
        }
        Object minValue = selector.invoke($this$minOfWithOrNull.charAt(0));
        final IntIterator iterator = new IntRange(1, StringsKt__StringsKt.getLastIndex($this$minOfWithOrNull)).iterator();
        while (iterator.hasNext()) {
            final int i = iterator.nextInt();
            final Object v = selector.invoke($this$minOfWithOrNull.charAt(i));
            if (comparator.compare((Object)minValue, (Object)v) > 0) {
                minValue = v;
            }
        }
        return (R)minValue;
    }
    
    @SinceKotlin(version = "1.4")
    @Nullable
    public static final Character minOrNull(@NotNull final CharSequence $this$minOrNull) {
        Intrinsics.checkNotNullParameter($this$minOrNull, "<this>");
        if ($this$minOrNull.length() == 0) {
            return null;
        }
        char min = $this$minOrNull.charAt(0);
        final IntIterator iterator = new IntRange(1, StringsKt__StringsKt.getLastIndex($this$minOrNull)).iterator();
        while (iterator.hasNext()) {
            final int i = iterator.nextInt();
            final char e = $this$minOrNull.charAt(i);
            if (Intrinsics.compare(min, e) > 0) {
                min = e;
            }
        }
        return min;
    }
    
    @SinceKotlin(version = "1.7")
    @JvmName(name = "minWithOrThrow")
    public static final char minWithOrThrow(@NotNull final CharSequence $this$minWith, @NotNull final Comparator<? super Character> comparator) {
        Intrinsics.checkNotNullParameter($this$minWith, "<this>");
        Intrinsics.checkNotNullParameter(comparator, "comparator");
        if ($this$minWith.length() == 0) {
            throw new NoSuchElementException();
        }
        char min = $this$minWith.charAt(0);
        final IntIterator iterator = new IntRange(1, StringsKt__StringsKt.getLastIndex($this$minWith)).iterator();
        while (iterator.hasNext()) {
            final int i = iterator.nextInt();
            final char e = $this$minWith.charAt(i);
            if (comparator.compare(min, e) > 0) {
                min = e;
            }
        }
        return min;
    }
    
    @SinceKotlin(version = "1.4")
    @Nullable
    public static final Character minWithOrNull(@NotNull final CharSequence $this$minWithOrNull, @NotNull final Comparator<? super Character> comparator) {
        Intrinsics.checkNotNullParameter($this$minWithOrNull, "<this>");
        Intrinsics.checkNotNullParameter(comparator, "comparator");
        if ($this$minWithOrNull.length() == 0) {
            return null;
        }
        char min = $this$minWithOrNull.charAt(0);
        final IntIterator iterator = new IntRange(1, StringsKt__StringsKt.getLastIndex($this$minWithOrNull)).iterator();
        while (iterator.hasNext()) {
            final int i = iterator.nextInt();
            final char e = $this$minWithOrNull.charAt(i);
            if (comparator.compare(min, e) > 0) {
                min = e;
            }
        }
        return min;
    }
    
    public static final boolean none(@NotNull final CharSequence $this$none) {
        Intrinsics.checkNotNullParameter($this$none, "<this>");
        return $this$none.length() == 0;
    }
    
    public static final boolean none(@NotNull final CharSequence $this$none, @NotNull final Function1<? super Character, Boolean> predicate) {
        Intrinsics.checkNotNullParameter($this$none, "<this>");
        Intrinsics.checkNotNullParameter(predicate, "predicate");
        final int $i$f$none = 0;
        for (int i = 0; i < $this$none.length(); ++i) {
            final char element = $this$none.charAt(i);
            if (predicate.invoke(element)) {
                return false;
            }
        }
        return true;
    }
    
    @SinceKotlin(version = "1.1")
    @NotNull
    public static final <S extends CharSequence> S onEach(@NotNull final S $this$onEach, @NotNull final Function1<? super Character, Unit> action) {
        Intrinsics.checkNotNullParameter($this$onEach, "<this>");
        Intrinsics.checkNotNullParameter(action, "action");
        final int $i$f$onEach = 0;
        final CharSequence $this$onEach_u24lambda_u2415 = $this$onEach;
        final int n = 0;
        for (int i = 0; i < $this$onEach_u24lambda_u2415.length(); ++i) {
            final char element = $this$onEach_u24lambda_u2415.charAt(i);
            action.invoke(element);
        }
        return $this$onEach;
    }
    
    @SinceKotlin(version = "1.4")
    @NotNull
    public static final <S extends CharSequence> S onEachIndexed(@NotNull final S $this$onEachIndexed, @NotNull final Function2<? super Integer, ? super Character, Unit> action) {
        Intrinsics.checkNotNullParameter($this$onEachIndexed, "<this>");
        Intrinsics.checkNotNullParameter(action, "action");
        final int $i$f$onEachIndexed = 0;
        final CharSequence $this$onEachIndexed_u24lambda_u2416 = $this$onEachIndexed;
        final int n = 0;
        final CharSequence $this$forEachIndexed$iv = $this$onEachIndexed_u24lambda_u2416;
        final int $i$f$forEachIndexed = 0;
        int index$iv = 0;
        for (int i = 0; i < $this$forEachIndexed$iv.length(); ++i) {
            final char item$iv = $this$forEachIndexed$iv.charAt(i);
            action.invoke(index$iv++, item$iv);
        }
        return $this$onEachIndexed;
    }
    
    public static final char reduce(@NotNull final CharSequence $this$reduce, @NotNull final Function2<? super Character, ? super Character, Character> operation) {
        Intrinsics.checkNotNullParameter($this$reduce, "<this>");
        Intrinsics.checkNotNullParameter(operation, "operation");
        final int $i$f$reduce = 0;
        if ($this$reduce.length() == 0) {
            throw new UnsupportedOperationException("Empty char sequence can't be reduced.");
        }
        char accumulator = $this$reduce.charAt(0);
        final IntIterator iterator = new IntRange(1, StringsKt__StringsKt.getLastIndex($this$reduce)).iterator();
        while (iterator.hasNext()) {
            final int index = iterator.nextInt();
            accumulator = operation.invoke(accumulator, $this$reduce.charAt(index));
        }
        return accumulator;
    }
    
    public static final char reduceIndexed(@NotNull final CharSequence $this$reduceIndexed, @NotNull final Function3<? super Integer, ? super Character, ? super Character, Character> operation) {
        Intrinsics.checkNotNullParameter($this$reduceIndexed, "<this>");
        Intrinsics.checkNotNullParameter(operation, "operation");
        final int $i$f$reduceIndexed = 0;
        if ($this$reduceIndexed.length() == 0) {
            throw new UnsupportedOperationException("Empty char sequence can't be reduced.");
        }
        char accumulator = $this$reduceIndexed.charAt(0);
        final IntIterator iterator = new IntRange(1, StringsKt__StringsKt.getLastIndex($this$reduceIndexed)).iterator();
        while (iterator.hasNext()) {
            final int index = iterator.nextInt();
            accumulator = operation.invoke(index, accumulator, $this$reduceIndexed.charAt(index));
        }
        return accumulator;
    }
    
    @SinceKotlin(version = "1.4")
    @Nullable
    public static final Character reduceIndexedOrNull(@NotNull final CharSequence $this$reduceIndexedOrNull, @NotNull final Function3<? super Integer, ? super Character, ? super Character, Character> operation) {
        Intrinsics.checkNotNullParameter($this$reduceIndexedOrNull, "<this>");
        Intrinsics.checkNotNullParameter(operation, "operation");
        final int $i$f$reduceIndexedOrNull = 0;
        if ($this$reduceIndexedOrNull.length() == 0) {
            return null;
        }
        char accumulator = $this$reduceIndexedOrNull.charAt(0);
        final IntIterator iterator = new IntRange(1, StringsKt__StringsKt.getLastIndex($this$reduceIndexedOrNull)).iterator();
        while (iterator.hasNext()) {
            final int index = iterator.nextInt();
            accumulator = operation.invoke(index, accumulator, $this$reduceIndexedOrNull.charAt(index));
        }
        return accumulator;
    }
    
    @SinceKotlin(version = "1.4")
    @WasExperimental(markerClass = { ExperimentalStdlibApi.class })
    @Nullable
    public static final Character reduceOrNull(@NotNull final CharSequence $this$reduceOrNull, @NotNull final Function2<? super Character, ? super Character, Character> operation) {
        Intrinsics.checkNotNullParameter($this$reduceOrNull, "<this>");
        Intrinsics.checkNotNullParameter(operation, "operation");
        final int $i$f$reduceOrNull = 0;
        if ($this$reduceOrNull.length() == 0) {
            return null;
        }
        char accumulator = $this$reduceOrNull.charAt(0);
        final IntIterator iterator = new IntRange(1, StringsKt__StringsKt.getLastIndex($this$reduceOrNull)).iterator();
        while (iterator.hasNext()) {
            final int index = iterator.nextInt();
            accumulator = operation.invoke(accumulator, $this$reduceOrNull.charAt(index));
        }
        return accumulator;
    }
    
    public static final char reduceRight(@NotNull final CharSequence $this$reduceRight, @NotNull final Function2<? super Character, ? super Character, Character> operation) {
        Intrinsics.checkNotNullParameter($this$reduceRight, "<this>");
        Intrinsics.checkNotNullParameter(operation, "operation");
        final int $i$f$reduceRight = 0;
        int index = StringsKt__StringsKt.getLastIndex($this$reduceRight);
        if (index < 0) {
            throw new UnsupportedOperationException("Empty char sequence can't be reduced.");
        }
        char accumulator;
        for (accumulator = $this$reduceRight.charAt(index--); index >= 0; accumulator = operation.invoke($this$reduceRight.charAt(index--), accumulator)) {}
        return accumulator;
    }
    
    public static final char reduceRightIndexed(@NotNull final CharSequence $this$reduceRightIndexed, @NotNull final Function3<? super Integer, ? super Character, ? super Character, Character> operation) {
        Intrinsics.checkNotNullParameter($this$reduceRightIndexed, "<this>");
        Intrinsics.checkNotNullParameter(operation, "operation");
        final int $i$f$reduceRightIndexed = 0;
        int index = StringsKt__StringsKt.getLastIndex($this$reduceRightIndexed);
        if (index < 0) {
            throw new UnsupportedOperationException("Empty char sequence can't be reduced.");
        }
        char accumulator;
        for (accumulator = $this$reduceRightIndexed.charAt(index--); index >= 0; --index) {
            accumulator = operation.invoke(index, $this$reduceRightIndexed.charAt(index), accumulator);
        }
        return accumulator;
    }
    
    @SinceKotlin(version = "1.4")
    @Nullable
    public static final Character reduceRightIndexedOrNull(@NotNull final CharSequence $this$reduceRightIndexedOrNull, @NotNull final Function3<? super Integer, ? super Character, ? super Character, Character> operation) {
        Intrinsics.checkNotNullParameter($this$reduceRightIndexedOrNull, "<this>");
        Intrinsics.checkNotNullParameter(operation, "operation");
        final int $i$f$reduceRightIndexedOrNull = 0;
        int index = StringsKt__StringsKt.getLastIndex($this$reduceRightIndexedOrNull);
        if (index < 0) {
            return null;
        }
        char accumulator;
        for (accumulator = $this$reduceRightIndexedOrNull.charAt(index--); index >= 0; --index) {
            accumulator = operation.invoke(index, $this$reduceRightIndexedOrNull.charAt(index), accumulator);
        }
        return accumulator;
    }
    
    @SinceKotlin(version = "1.4")
    @WasExperimental(markerClass = { ExperimentalStdlibApi.class })
    @Nullable
    public static final Character reduceRightOrNull(@NotNull final CharSequence $this$reduceRightOrNull, @NotNull final Function2<? super Character, ? super Character, Character> operation) {
        Intrinsics.checkNotNullParameter($this$reduceRightOrNull, "<this>");
        Intrinsics.checkNotNullParameter(operation, "operation");
        final int $i$f$reduceRightOrNull = 0;
        int index = StringsKt__StringsKt.getLastIndex($this$reduceRightOrNull);
        if (index < 0) {
            return null;
        }
        char accumulator;
        for (accumulator = $this$reduceRightOrNull.charAt(index--); index >= 0; accumulator = operation.invoke($this$reduceRightOrNull.charAt(index--), accumulator)) {}
        return accumulator;
    }
    
    @SinceKotlin(version = "1.4")
    @NotNull
    public static final <R> List<R> runningFold(@NotNull final CharSequence $this$runningFold, final R initial, @NotNull final Function2<? super R, ? super Character, ? extends R> operation) {
        Intrinsics.checkNotNullParameter($this$runningFold, "<this>");
        Intrinsics.checkNotNullParameter(operation, "operation");
        final int $i$f$runningFold = 0;
        if ($this$runningFold.length() == 0) {
            return CollectionsKt__CollectionsJVMKt.listOf(initial);
        }
        final ArrayList $this$runningFold_u24lambda_u2417 = new ArrayList($this$runningFold.length() + 1);
        final int n = 0;
        $this$runningFold_u24lambda_u2417.add(initial);
        final ArrayList result = $this$runningFold_u24lambda_u2417;
        Object accumulator = initial;
        for (int i = 0; i < $this$runningFold.length(); ++i) {
            final char element = $this$runningFold.charAt(i);
            accumulator = operation.invoke((Object)accumulator, Character.valueOf(element));
            result.add(accumulator);
        }
        return (List<R>)result;
    }
    
    @SinceKotlin(version = "1.4")
    @NotNull
    public static final <R> List<R> runningFoldIndexed(@NotNull final CharSequence $this$runningFoldIndexed, final R initial, @NotNull final Function3<? super Integer, ? super R, ? super Character, ? extends R> operation) {
        Intrinsics.checkNotNullParameter($this$runningFoldIndexed, "<this>");
        Intrinsics.checkNotNullParameter(operation, "operation");
        final int $i$f$runningFoldIndexed = 0;
        if ($this$runningFoldIndexed.length() == 0) {
            return CollectionsKt__CollectionsJVMKt.listOf(initial);
        }
        final ArrayList $this$runningFoldIndexed_u24lambda_u2418 = new ArrayList($this$runningFoldIndexed.length() + 1);
        final int n = 0;
        $this$runningFoldIndexed_u24lambda_u2418.add(initial);
        final ArrayList result = $this$runningFoldIndexed_u24lambda_u2418;
        Object accumulator = initial;
        for (int index = 0; index < $this$runningFoldIndexed.length(); ++index) {
            accumulator = operation.invoke(Integer.valueOf(index), (Object)accumulator, Character.valueOf($this$runningFoldIndexed.charAt(index)));
            result.add(accumulator);
        }
        return (List<R>)result;
    }
    
    @SinceKotlin(version = "1.4")
    @NotNull
    public static final List<Character> runningReduce(@NotNull final CharSequence $this$runningReduce, @NotNull final Function2<? super Character, ? super Character, Character> operation) {
        Intrinsics.checkNotNullParameter($this$runningReduce, "<this>");
        Intrinsics.checkNotNullParameter(operation, "operation");
        final int $i$f$runningReduce = 0;
        if ($this$runningReduce.length() == 0) {
            return CollectionsKt__CollectionsKt.emptyList();
        }
        char accumulator = '\0';
        accumulator = $this$runningReduce.charAt(0);
        final ArrayList $this$runningReduce_u24lambda_u2419 = new ArrayList($this$runningReduce.length());
        final int n = 0;
        $this$runningReduce_u24lambda_u2419.add(accumulator);
        final ArrayList result = $this$runningReduce_u24lambda_u2419;
        for (int index = 1; index < $this$runningReduce.length(); ++index) {
            accumulator = operation.invoke(accumulator, $this$runningReduce.charAt(index));
            result.add(accumulator);
        }
        return (List<Character>)result;
    }
    
    @SinceKotlin(version = "1.4")
    @NotNull
    public static final List<Character> runningReduceIndexed(@NotNull final CharSequence $this$runningReduceIndexed, @NotNull final Function3<? super Integer, ? super Character, ? super Character, Character> operation) {
        Intrinsics.checkNotNullParameter($this$runningReduceIndexed, "<this>");
        Intrinsics.checkNotNullParameter(operation, "operation");
        final int $i$f$runningReduceIndexed = 0;
        if ($this$runningReduceIndexed.length() == 0) {
            return CollectionsKt__CollectionsKt.emptyList();
        }
        char accumulator = '\0';
        accumulator = $this$runningReduceIndexed.charAt(0);
        final ArrayList $this$runningReduceIndexed_u24lambda_u2420 = new ArrayList($this$runningReduceIndexed.length());
        final int n = 0;
        $this$runningReduceIndexed_u24lambda_u2420.add(accumulator);
        final ArrayList result = $this$runningReduceIndexed_u24lambda_u2420;
        for (int index = 1; index < $this$runningReduceIndexed.length(); ++index) {
            accumulator = operation.invoke(index, accumulator, $this$runningReduceIndexed.charAt(index));
            result.add(accumulator);
        }
        return (List<Character>)result;
    }
    
    @SinceKotlin(version = "1.4")
    @WasExperimental(markerClass = { ExperimentalStdlibApi.class })
    @NotNull
    public static final <R> List<R> scan(@NotNull final CharSequence $this$scan, final R initial, @NotNull final Function2<? super R, ? super Character, ? extends R> operation) {
        Intrinsics.checkNotNullParameter($this$scan, "<this>");
        Intrinsics.checkNotNullParameter(operation, "operation");
        final int $i$f$scan = 0;
        final CharSequence $this$runningFold$iv = $this$scan;
        final int $i$f$runningFold = 0;
        List<R> list;
        if ($this$runningFold$iv.length() == 0) {
            list = CollectionsKt__CollectionsJVMKt.listOf(initial);
        }
        else {
            final ArrayList $this$runningFold_u24lambda_u2417$iv = new ArrayList($this$runningFold$iv.length() + 1);
            final int n = 0;
            $this$runningFold_u24lambda_u2417$iv.add(initial);
            final ArrayList result$iv = $this$runningFold_u24lambda_u2417$iv;
            Object accumulator$iv = initial;
            for (int i = 0; i < $this$runningFold$iv.length(); ++i) {
                final char element$iv = $this$runningFold$iv.charAt(i);
                accumulator$iv = operation.invoke((Object)accumulator$iv, Character.valueOf(element$iv));
                result$iv.add(accumulator$iv);
            }
            list = (List<R>)result$iv;
        }
        return list;
    }
    
    @SinceKotlin(version = "1.4")
    @WasExperimental(markerClass = { ExperimentalStdlibApi.class })
    @NotNull
    public static final <R> List<R> scanIndexed(@NotNull final CharSequence $this$scanIndexed, final R initial, @NotNull final Function3<? super Integer, ? super R, ? super Character, ? extends R> operation) {
        Intrinsics.checkNotNullParameter($this$scanIndexed, "<this>");
        Intrinsics.checkNotNullParameter(operation, "operation");
        final int $i$f$scanIndexed = 0;
        final CharSequence $this$runningFoldIndexed$iv = $this$scanIndexed;
        final int $i$f$runningFoldIndexed = 0;
        List<R> list;
        if ($this$runningFoldIndexed$iv.length() == 0) {
            list = CollectionsKt__CollectionsJVMKt.listOf(initial);
        }
        else {
            final ArrayList $this$runningFoldIndexed_u24lambda_u2418$iv = new ArrayList($this$runningFoldIndexed$iv.length() + 1);
            final int n = 0;
            $this$runningFoldIndexed_u24lambda_u2418$iv.add(initial);
            final ArrayList result$iv = $this$runningFoldIndexed_u24lambda_u2418$iv;
            Object accumulator$iv = initial;
            for (int index$iv = 0; index$iv < $this$runningFoldIndexed$iv.length(); ++index$iv) {
                accumulator$iv = operation.invoke(Integer.valueOf(index$iv), (Object)accumulator$iv, Character.valueOf($this$runningFoldIndexed$iv.charAt(index$iv)));
                result$iv.add(accumulator$iv);
            }
            list = (List<R>)result$iv;
        }
        return list;
    }
    
    @Deprecated(message = "Use sumOf instead.", replaceWith = @ReplaceWith(expression = "this.sumOf(selector)", imports = {}))
    @DeprecatedSinceKotlin(warningSince = "1.5")
    @java.lang.Deprecated
    public static final int sumBy(@NotNull final CharSequence $this$sumBy, @NotNull final Function1<? super Character, Integer> selector) {
        Intrinsics.checkNotNullParameter($this$sumBy, "<this>");
        Intrinsics.checkNotNullParameter(selector, "selector");
        final int $i$f$sumBy = 0;
        int sum = 0;
        for (int i = 0; i < $this$sumBy.length(); ++i) {
            final char element = $this$sumBy.charAt(i);
            sum += selector.invoke(element).intValue();
        }
        return sum;
    }
    
    @Deprecated(message = "Use sumOf instead.", replaceWith = @ReplaceWith(expression = "this.sumOf(selector)", imports = {}))
    @DeprecatedSinceKotlin(warningSince = "1.5")
    @java.lang.Deprecated
    public static final double sumByDouble(@NotNull final CharSequence $this$sumByDouble, @NotNull final Function1<? super Character, Double> selector) {
        Intrinsics.checkNotNullParameter($this$sumByDouble, "<this>");
        Intrinsics.checkNotNullParameter(selector, "selector");
        final int $i$f$sumByDouble = 0;
        double sum = 0.0;
        for (int i = 0; i < $this$sumByDouble.length(); ++i) {
            final char element = $this$sumByDouble.charAt(i);
            sum += selector.invoke(element).doubleValue();
        }
        return sum;
    }
    
    @SinceKotlin(version = "1.4")
    @OverloadResolutionByLambdaReturnType
    @JvmName(name = "sumOfDouble")
    @InlineOnly
    private static final double sumOfDouble(final CharSequence $this$sumOf, final Function1<? super Character, Double> selector) {
        Intrinsics.checkNotNullParameter($this$sumOf, "<this>");
        Intrinsics.checkNotNullParameter(selector, "selector");
        double sum = 0.0;
        for (int i = 0; i < $this$sumOf.length(); ++i) {
            final char element = $this$sumOf.charAt(i);
            sum += selector.invoke(element).doubleValue();
        }
        return sum;
    }
    
    @SinceKotlin(version = "1.4")
    @OverloadResolutionByLambdaReturnType
    @JvmName(name = "sumOfInt")
    @InlineOnly
    private static final int sumOfInt(final CharSequence $this$sumOf, final Function1<? super Character, Integer> selector) {
        Intrinsics.checkNotNullParameter($this$sumOf, "<this>");
        Intrinsics.checkNotNullParameter(selector, "selector");
        int sum = 0;
        for (int i = 0; i < $this$sumOf.length(); ++i) {
            final char element = $this$sumOf.charAt(i);
            sum += selector.invoke(element).intValue();
        }
        return sum;
    }
    
    @SinceKotlin(version = "1.4")
    @OverloadResolutionByLambdaReturnType
    @JvmName(name = "sumOfLong")
    @InlineOnly
    private static final long sumOfLong(final CharSequence $this$sumOf, final Function1<? super Character, Long> selector) {
        Intrinsics.checkNotNullParameter($this$sumOf, "<this>");
        Intrinsics.checkNotNullParameter(selector, "selector");
        long sum = 0L;
        for (int i = 0; i < $this$sumOf.length(); ++i) {
            final char element = $this$sumOf.charAt(i);
            sum += selector.invoke(element).longValue();
        }
        return sum;
    }
    
    @SinceKotlin(version = "1.5")
    @OverloadResolutionByLambdaReturnType
    @JvmName(name = "sumOfUInt")
    @WasExperimental(markerClass = { ExperimentalUnsignedTypes.class })
    @InlineOnly
    private static final int sumOfUInt(final CharSequence $this$sumOf, final Function1<? super Character, UInt> selector) {
        Intrinsics.checkNotNullParameter($this$sumOf, "<this>");
        Intrinsics.checkNotNullParameter(selector, "selector");
        int sum = UInt.constructor-impl(0);
        for (int i = 0; i < $this$sumOf.length(); ++i) {
            final char element = $this$sumOf.charAt(i);
            sum = UInt.constructor-impl(sum + selector.invoke(element).unbox-impl());
        }
        return sum;
    }
    
    @SinceKotlin(version = "1.5")
    @OverloadResolutionByLambdaReturnType
    @JvmName(name = "sumOfULong")
    @WasExperimental(markerClass = { ExperimentalUnsignedTypes.class })
    @InlineOnly
    private static final long sumOfULong(final CharSequence $this$sumOf, final Function1<? super Character, ULong> selector) {
        Intrinsics.checkNotNullParameter($this$sumOf, "<this>");
        Intrinsics.checkNotNullParameter(selector, "selector");
        long sum = ULong.constructor-impl(0L);
        for (int i = 0; i < $this$sumOf.length(); ++i) {
            final char element = $this$sumOf.charAt(i);
            sum = ULong.constructor-impl(sum + selector.invoke(element).unbox-impl());
        }
        return sum;
    }
    
    @SinceKotlin(version = "1.2")
    @NotNull
    public static final List<String> chunked(@NotNull final CharSequence $this$chunked, final int size) {
        Intrinsics.checkNotNullParameter($this$chunked, "<this>");
        return windowed($this$chunked, size, size, true);
    }
    
    @SinceKotlin(version = "1.2")
    @NotNull
    public static final <R> List<R> chunked(@NotNull final CharSequence $this$chunked, final int size, @NotNull final Function1<? super CharSequence, ? extends R> transform) {
        Intrinsics.checkNotNullParameter($this$chunked, "<this>");
        Intrinsics.checkNotNullParameter(transform, "transform");
        return windowed($this$chunked, size, size, true, transform);
    }
    
    @SinceKotlin(version = "1.2")
    @NotNull
    public static final Sequence<String> chunkedSequence(@NotNull final CharSequence $this$chunkedSequence, final int size) {
        Intrinsics.checkNotNullParameter($this$chunkedSequence, "<this>");
        return chunkedSequence($this$chunkedSequence, size, (Function1<? super CharSequence, ? extends String>)StringsKt___StringsKt$chunkedSequence.StringsKt___StringsKt$chunkedSequence$1.INSTANCE);
    }
    
    @SinceKotlin(version = "1.2")
    @NotNull
    public static final <R> Sequence<R> chunkedSequence(@NotNull final CharSequence $this$chunkedSequence, final int size, @NotNull final Function1<? super CharSequence, ? extends R> transform) {
        Intrinsics.checkNotNullParameter($this$chunkedSequence, "<this>");
        Intrinsics.checkNotNullParameter(transform, "transform");
        return windowedSequence($this$chunkedSequence, size, size, true, transform);
    }
    
    @NotNull
    public static final Pair<CharSequence, CharSequence> partition(@NotNull final CharSequence $this$partition, @NotNull final Function1<? super Character, Boolean> predicate) {
        Intrinsics.checkNotNullParameter($this$partition, "<this>");
        Intrinsics.checkNotNullParameter(predicate, "predicate");
        final int $i$f$partition = 0;
        final StringBuilder first = new StringBuilder();
        final StringBuilder second = new StringBuilder();
        for (int i = 0; i < $this$partition.length(); ++i) {
            final char element = $this$partition.charAt(i);
            if (predicate.invoke(element)) {
                first.append(element);
            }
            else {
                second.append(element);
            }
        }
        return new Pair<CharSequence, CharSequence>(first, second);
    }
    
    @NotNull
    public static final Pair<String, String> partition(@NotNull final String $this$partition, @NotNull final Function1<? super Character, Boolean> predicate) {
        Intrinsics.checkNotNullParameter($this$partition, "<this>");
        Intrinsics.checkNotNullParameter(predicate, "predicate");
        final int $i$f$partition = 0;
        final StringBuilder first = new StringBuilder();
        final StringBuilder second = new StringBuilder();
        for (int i = 0; i < $this$partition.length(); ++i) {
            final char element = $this$partition.charAt(i);
            if (predicate.invoke(element)) {
                first.append(element);
            }
            else {
                second.append(element);
            }
        }
        final String string = first.toString();
        Intrinsics.checkNotNullExpressionValue(string, "first.toString()");
        final String string2 = second.toString();
        Intrinsics.checkNotNullExpressionValue(string2, "second.toString()");
        return new Pair<String, String>(string, string2);
    }
    
    @SinceKotlin(version = "1.2")
    @NotNull
    public static final List<String> windowed(@NotNull final CharSequence $this$windowed, final int size, final int step, final boolean partialWindows) {
        Intrinsics.checkNotNullParameter($this$windowed, "<this>");
        return windowed($this$windowed, size, step, partialWindows, (Function1<? super CharSequence, ? extends String>)StringsKt___StringsKt$windowed.StringsKt___StringsKt$windowed$1.INSTANCE);
    }
    
    @SinceKotlin(version = "1.2")
    @NotNull
    public static final <R> List<R> windowed(@NotNull final CharSequence $this$windowed, final int size, final int step, final boolean partialWindows, @NotNull final Function1<? super CharSequence, ? extends R> transform) {
        Intrinsics.checkNotNullParameter($this$windowed, "<this>");
        Intrinsics.checkNotNullParameter(transform, "transform");
        SlidingWindowKt.checkWindowSizeStep(size, step);
        final int thisSize = $this$windowed.length();
        final int resultCapacity = thisSize / step + ((thisSize % step != 0) ? 1 : 0);
        final ArrayList result = new ArrayList(resultCapacity);
        for (int index = 0; 0 <= index && index < thisSize; index += step) {
            final int end = index + size;
            int n;
            if (end < 0 || end > thisSize) {
                if (!partialWindows) {
                    break;
                }
                n = thisSize;
            }
            else {
                n = end;
            }
            final int coercedEnd = n;
            result.add(transform.invoke($this$windowed.subSequence(index, coercedEnd)));
        }
        return (List<R>)result;
    }
    
    @SinceKotlin(version = "1.2")
    @NotNull
    public static final Sequence<String> windowedSequence(@NotNull final CharSequence $this$windowedSequence, final int size, final int step, final boolean partialWindows) {
        Intrinsics.checkNotNullParameter($this$windowedSequence, "<this>");
        return windowedSequence($this$windowedSequence, size, step, partialWindows, (Function1<? super CharSequence, ? extends String>)StringsKt___StringsKt$windowedSequence.StringsKt___StringsKt$windowedSequence$1.INSTANCE);
    }
    
    @SinceKotlin(version = "1.2")
    @NotNull
    public static final <R> Sequence<R> windowedSequence(@NotNull final CharSequence $this$windowedSequence, final int size, final int step, final boolean partialWindows, @NotNull final Function1<? super CharSequence, ? extends R> transform) {
        Intrinsics.checkNotNullParameter($this$windowedSequence, "<this>");
        Intrinsics.checkNotNullParameter(transform, "transform");
        SlidingWindowKt.checkWindowSizeStep(size, step);
        final IntProgression windows = RangesKt___RangesKt.step(partialWindows ? StringsKt__StringsKt.getIndices($this$windowedSequence) : RangesKt___RangesKt.until(0, $this$windowedSequence.length() - size + 1), step);
        return SequencesKt___SequencesKt.map(CollectionsKt___CollectionsKt.asSequence((Iterable<?>)windows), (Function1<? super Object, ? extends R>)new StringsKt___StringsKt$windowedSequence.StringsKt___StringsKt$windowedSequence$2(size, $this$windowedSequence, (Function1)transform));
    }
    
    @NotNull
    public static final List<Pair<Character, Character>> zip(@NotNull final CharSequence $this$zip, @NotNull final CharSequence other) {
        // 
        // This method could not be decompiled.
        // 
        // Original Bytecode:
        // 
        //     1: ldc             "<this>"
        //     3: invokestatic    kotlin/jvm/internal/Intrinsics.checkNotNullParameter:(Ljava/lang/Object;Ljava/lang/String;)V
        //     6: aload_1         /* other */
        //     7: ldc_w           "other"
        //    10: invokestatic    kotlin/jvm/internal/Intrinsics.checkNotNullParameter:(Ljava/lang/Object;Ljava/lang/String;)V
        //    13: aload_0         /* $this$zip */
        //    14: astore_2        /* $this$zip$iv */
        //    15: iconst_0       
        //    16: istore_3        /* $i$f$zip */
        //    17: aload_2         /* $this$zip$iv */
        //    18: invokeinterface java/lang/CharSequence.length:()I
        //    23: aload_1         /* other */
        //    24: invokeinterface java/lang/CharSequence.length:()I
        //    29: invokestatic    java/lang/Math.min:(II)I
        //    32: istore          length$iv
        //    34: new             Ljava/util/ArrayList;
        //    37: dup            
        //    38: iload           length$iv
        //    40: invokespecial   java/util/ArrayList.<init>:(I)V
        //    43: astore          list$iv
        //    45: iconst_0       
        //    46: istore          i$iv
        //    48: iload           i$iv
        //    50: iload           length$iv
        //    52: if_icmpge       108
        //    55: aload           list$iv
        //    57: aload_2         /* $this$zip$iv */
        //    58: iload           i$iv
        //    60: invokeinterface java/lang/CharSequence.charAt:(I)C
        //    65: aload_1         /* other */
        //    66: iload           i$iv
        //    68: invokeinterface java/lang/CharSequence.charAt:(I)C
        //    73: istore          7
        //    75: istore          8
        //    77: astore          10
        //    79: iconst_0       
        //    80: istore          $i$a$-zip-StringsKt___StringsKt$zip$1
        //    82: iload           c1
        //    84: invokestatic    java/lang/Character.valueOf:(C)Ljava/lang/Character;
        //    87: iload           c2
        //    89: invokestatic    java/lang/Character.valueOf:(C)Ljava/lang/Character;
        //    92: invokestatic    kotlin/TuplesKt.to:(Ljava/lang/Object;Ljava/lang/Object;)Lkotlin/Pair;
        //    95: aload           10
        //    97: swap           
        //    98: invokevirtual   java/util/ArrayList.add:(Ljava/lang/Object;)Z
        //   101: pop            
        //   102: iinc            i$iv, 1
        //   105: goto            48
        //   108: aload           list$iv
        //   110: checkcast       Ljava/util/List;
        //   113: areturn        
        //    Signature:
        //  (Ljava/lang/CharSequence;Ljava/lang/CharSequence;)Ljava/util/List<Lkotlin/Pair<Ljava/lang/Character;Ljava/lang/Character;>;>;
        //    StackMapTable: 00 02 FF 00 30 00 07 07 00 1A 07 00 1A 07 00 1A 01 01 07 02 06 01 00 00 3B
        // 
        // The error that occurred was:
        // 
        // java.lang.NullPointerException
        // 
        throw new IllegalStateException("An error occurred while decompiling this method.");
    }
    
    @NotNull
    public static final <V> List<V> zip(@NotNull final CharSequence $this$zip, @NotNull final CharSequence other, @NotNull final Function2<? super Character, ? super Character, ? extends V> transform) {
        Intrinsics.checkNotNullParameter($this$zip, "<this>");
        Intrinsics.checkNotNullParameter(other, "other");
        Intrinsics.checkNotNullParameter(transform, "transform");
        final int $i$f$zip = 0;
        final int length = Math.min($this$zip.length(), other.length());
        final ArrayList list = new ArrayList(length);
        for (int i = 0; i < length; ++i) {
            list.add(transform.invoke($this$zip.charAt(i), other.charAt(i)));
        }
        return (List<V>)list;
    }
    
    @SinceKotlin(version = "1.2")
    @NotNull
    public static final List<Pair<Character, Character>> zipWithNext(@NotNull final CharSequence $this$zipWithNext) {
        // 
        // This method could not be decompiled.
        // 
        // Original Bytecode:
        // 
        //     1: ldc             "<this>"
        //     3: invokestatic    kotlin/jvm/internal/Intrinsics.checkNotNullParameter:(Ljava/lang/Object;Ljava/lang/String;)V
        //     6: aload_0         /* $this$zipWithNext */
        //     7: astore_1        /* $this$zipWithNext$iv */
        //     8: iconst_0       
        //     9: istore_2        /* $i$f$zipWithNext */
        //    10: aload_1         /* $this$zipWithNext$iv */
        //    11: invokeinterface java/lang/CharSequence.length:()I
        //    16: iconst_1       
        //    17: isub           
        //    18: istore_3        /* size$iv */
        //    19: iload_3         /* size$iv */
        //    20: iconst_1       
        //    21: if_icmpge       30
        //    24: invokestatic    kotlin/collections/CollectionsKt.emptyList:()Ljava/util/List;
        //    27: goto            109
        //    30: new             Ljava/util/ArrayList;
        //    33: dup            
        //    34: iload_3         /* size$iv */
        //    35: invokespecial   java/util/ArrayList.<init>:(I)V
        //    38: astore          result$iv
        //    40: iconst_0       
        //    41: istore          index$iv
        //    43: iload           index$iv
        //    45: iload_3         /* size$iv */
        //    46: if_icmpge       104
        //    49: aload           result$iv
        //    51: aload_1         /* $this$zipWithNext$iv */
        //    52: iload           index$iv
        //    54: invokeinterface java/lang/CharSequence.charAt:(I)C
        //    59: aload_1         /* $this$zipWithNext$iv */
        //    60: iload           index$iv
        //    62: iconst_1       
        //    63: iadd           
        //    64: invokeinterface java/lang/CharSequence.charAt:(I)C
        //    69: istore          6
        //    71: istore          7
        //    73: astore          9
        //    75: iconst_0       
        //    76: istore          $i$a$-zipWithNext-StringsKt___StringsKt$zipWithNext$1
        //    78: iload           a
        //    80: invokestatic    java/lang/Character.valueOf:(C)Ljava/lang/Character;
        //    83: iload           b
        //    85: invokestatic    java/lang/Character.valueOf:(C)Ljava/lang/Character;
        //    88: invokestatic    kotlin/TuplesKt.to:(Ljava/lang/Object;Ljava/lang/Object;)Lkotlin/Pair;
        //    91: aload           9
        //    93: swap           
        //    94: invokevirtual   java/util/ArrayList.add:(Ljava/lang/Object;)Z
        //    97: pop            
        //    98: iinc            index$iv, 1
        //   101: goto            43
        //   104: aload           result$iv
        //   106: checkcast       Ljava/util/List;
        //   109: areturn        
        //    Signature:
        //  (Ljava/lang/CharSequence;)Ljava/util/List<Lkotlin/Pair<Ljava/lang/Character;Ljava/lang/Character;>;>;
        //    StackMapTable: 00 04 FE 00 1E 07 00 1A 01 01 FD 00 0C 07 02 06 01 3C FF 00 04 00 04 07 00 1A 07 00 1A 01 01 00 01 07 02 04
        // 
        // The error that occurred was:
        // 
        // java.lang.NullPointerException
        // 
        throw new IllegalStateException("An error occurred while decompiling this method.");
    }
    
    @SinceKotlin(version = "1.2")
    @NotNull
    public static final <R> List<R> zipWithNext(@NotNull final CharSequence $this$zipWithNext, @NotNull final Function2<? super Character, ? super Character, ? extends R> transform) {
        Intrinsics.checkNotNullParameter($this$zipWithNext, "<this>");
        Intrinsics.checkNotNullParameter(transform, "transform");
        final int $i$f$zipWithNext = 0;
        final int size = $this$zipWithNext.length() - 1;
        if (size < 1) {
            return CollectionsKt__CollectionsKt.emptyList();
        }
        final ArrayList result = new ArrayList(size);
        for (int index = 0; index < size; ++index) {
            result.add(transform.invoke($this$zipWithNext.charAt(index), $this$zipWithNext.charAt(index + 1)));
        }
        return (List<R>)result;
    }
    
    @NotNull
    public static final Iterable<Character> asIterable(@NotNull final CharSequence $this$asIterable) {
        Intrinsics.checkNotNullParameter($this$asIterable, "<this>");
        if ($this$asIterable instanceof String && $this$asIterable.length() == 0) {
            return (Iterable<Character>)CollectionsKt__CollectionsKt.emptyList();
        }
        return new Iterable<Character>($this$asIterable) {
            @NotNull
            @Override
            public Iterator<Character> iterator() {
                final int n = 0;
                return StringsKt__StringsKt.iterator(this.$this_asIterable$inlined);
            }
        };
    }
    
    @NotNull
    public static final Sequence<Character> asSequence(@NotNull final CharSequence $this$asSequence) {
        Intrinsics.checkNotNullParameter($this$asSequence, "<this>");
        if ($this$asSequence instanceof String && $this$asSequence.length() == 0) {
            return SequencesKt__SequencesKt.emptySequence();
        }
        return new Sequence<Character>($this$asSequence) {
            @NotNull
            @Override
            public Iterator<Character> iterator() {
                final int n = 0;
                return StringsKt__StringsKt.iterator(this.$this_asSequence$inlined);
            }
        };
    }
    
    public StringsKt___StringsKt() {
    }
}
